Workbook

Sheet Início
A1: ROADMAP DE CURSOS & APRENDIZADO
A2: Pós-graduação · Concursos · Livros · Cursos de IA · Renda Extra — Sage Dreams · Calm & Natural
B5: NAVEGAÇÃO · CLIQUE PARA ABRIR
B6: Dashboard | E6: Roadmap | H6: Metas de Estudo | K6: Diário de Estudo
B7: Visão executiva, vencimentos urgentes e gráficos | E7: Linha do tempo de 12 meses (Gantt) | H7: Metas de horas, ritmo e mapa de calor | K7: Registro de cada sessão de estudo
B9: Pós-graduação | E9: Concurso | H9: Livros | K9: Cursos IA
B10: MBAs, especializações e extensões | E10: Preparatórios, banca e data da prova | H10: Biblioteca, páginas lidas e notas | K10: Inteligência artificial e automação
B12: Renda Extra | E12: Listas
B13: Cursos de renda e resultado mensal | E13: Listas das setas e prazo de alerta
B16: COMO USAR EM 6 PASSOS
B17: 1 | C17: Abra a aba da categoria e substitua a linha 10 (exemplo) pelo seu primeiro curso. Cada aba comporta 40 itens.
B18: 2 | C18: Preencha instituição, datas (compra, início, término previsto e vencimento do acesso), valor, login e senha.
B19: 3 | C19: Informe o total de aulas, disciplinas ou páginas e atualize o quanto já concluiu — o % de andamento é automático.
B20: 4 | C20: Escolha Status, Prioridade e Certificado pela seta da célula. Vencimento em branco = acesso vitalício.
B21: 5 | C21: Registre cada sessão no Diário de Estudo (linha 7 em diante, com o mesmo nome do curso) e defina metas em Metas de Estudo.
B22: 6 | C22: Acompanhe no Dashboard: previsão de término, risco de perder o acesso, custo por hora e ROI da renda extra — tudo automático.
B24: LEGENDA
B25: Célula branca | D25: Campo para preencher.
B26: Célula cinza-areia | D26: Fórmula automática — não edite nem apague.
B27: Em andamento | D27: Status em andamento · barra do Roadmap em verde-sálvia.
B28: Concluído | D28: Status concluído · barra do Roadmap em verde-escuro.
B29: ▲ A vencer | D29: Acesso com vencimento dentro do prazo de alerta (padrão 30 dias, editável em Listas).
B30: ■ Vencido | D30: Acesso expirado — priorize ou renove.
B32: IMPORTANTE
B33: • Previsão de término usa seu ritmo real desde a data de início; sem nenhuma aula/página concluída aparece “Sem ritmo”. “■ Estoura o acesso” = previsão depois do vencimento.
B34: • Não edite as células cinza-areia nem a aba Apoio: elas alimentam o Dashboard, o Roadmap e as Metas.
B35: • Segurança: planilha não é cofre. Prefira um gerenciador de senhas, use a coluna Senha só como lembrete e não compartilhe este arquivo.
B36: • As linhas de exemplo (cursos e diário) entram nos totais até serem substituídas ou apagadas. As metas de horas iniciais (20/20/8/15/10) são sugestões — ajuste em Metas de Estudo.
B37: • Mais de 40 itens? Copie uma linha inteira e use “Inserir células copiadas” ENTRE as linhas do meio da tabela, para fórmulas e gráficos acompanharem.

Sheet Dashboard
A1: DASHBOARD · ROADMAP DE APRENDIZADO
A2: Visão executiva de todas as categorias — tudo atualiza sozinho | K2: ← Voltar ao Início
B5: TOTAL DE ITENS | D5: EM ANDAMENTO | F5: CONCLUÍDOS | H5: INVESTIMENTO TOTAL | J5: PROGRESSO MÉDIO | L5: CERTIFICADOS EMITIDOS
B6: =C20 -> 5 | D6: =E20 -> 5 | F6: =F20 -> 0 | H6: =H20 -> 14933.9 | J6: =I20 -> 0.24944444 | L6: =M20 -> 0
B9: HORAS ESTUDADAS | D9: CUSTO MÉDIO POR HORA | F9: EM RISCO DE PERDER ACESSO | H9: ATRASADOS VS PLANO | J9: ROI · RENDA EXTRA | L9: PAYBACK MÉDIO (MESES)
B10: ='Diário de Estudo'!D5 -> 4.5 | D10: =IFERROR((SUMIF('Pós-graduação'!O10:O49,">0",'Pós-graduação'!F10:F49)+SUMIF(Concurso!Q10:Q49,">0",Concurso!H10:H49)+SUMIF(Livros!N10:N49,">0",Livros!H10:H49)+SUMIF('Cursos IA'!O10:O49,">0",'Cursos IA'!F10:F49)+SUMIF('Renda Extra'!O10:O49,">0",'Renda Extra'!F10:F49))/(SUM('Pós-graduação'!O10:O49)+SUM(Concurso!Q10:Q49)+SUM(Livros!N10:N49)+SUM('Cursos IA'!O10:O49)+SUM('Renda Extra'!O10:O49)),0) -> 2921.5333 | F10: =COUNTIF('Pós-graduação'!R10:R49,"*Estoura o acesso")+COUNTIF(Concurso!T10:T49,"*Estoura o acesso")+COUNTIF('Cursos IA'!R10:R49,"*Estoura o acesso")+COUNTIF('Renda Extra'!R10:R49,"*Estoura o acesso") -> 0 | H10: =COUNTIF('Pós-graduação'!R10:R49,"*Atrasado vs plano")+COUNTIF(Concurso!T10:T49,"*Atrasado vs plano")+COUNTIF(Livros!Q10:Q49,"*Atrasado vs plano")+COUNTIF('Cursos IA'!R10:R49,"*Atrasado vs plano")+COUNTIF('Renda Extra'!R10:R49,"*Atrasado vs plano") -> 1 | J10: =IFERROR((SUM('Renda Extra'!X10:X49)-SUM('Renda Extra'!F10:F49))/SUM('Renda Extra'!F10:F49),0) -> -0.39393939 | L10: =IFERROR(AVERAGE('Renda Extra'!Z10:Z49),"—") -> 0.975
B12: Atualizado em: | C12: =TODAY() -> 46298
B13: RESUMO POR CATEGORIA
B14: Categoria | C14: Itens | D14: Não iniciado | E14: Em andamento | F14: Concluído | G14: Pausado | H14: Investimento (R$) | I14: % médio | J14: Progresso | K14: A vencer | L14: Vencidos | M14: Certificados
B15: Pós-graduação | C15: =COUNTA('Pós-graduação'!B10:B49) -> 1 | D15: =COUNTIF('Pós-graduação'!S10:S49,D$14) -> 0 | E15: =COUNTIF('Pós-graduação'!S10:S49,E$14) -> 1 | F15: =COUNTIF('Pós-graduação'!S10:S49,F$14) -> 0 | G15: =COUNTIF('Pós-graduação'!S10:S49,G$14) -> 0 | H15: =SUM('Pós-graduação'!F10:F49) -> 12600 | I15: =IFERROR(AVERAGE('Pós-graduação'!N10:N49),0) -> 0.1 | J15: =REPT("█",MIN(10,ROUND(I15*10,0)))&REPT("░",10-MIN(10,ROUND(I15*10,0))) -> █░░░░░░░░░ | K15: =COUNTIF('Pós-graduação'!K10:K49,"*A vencer") -> 0 | L15: =COUNTIF('Pós-graduação'!K10:K49,"*Vencido") -> 0 | M15: =COUNTIF('Pós-graduação'!U10:U49,"Emitido") -> 0
B16: Concurso | C16: =COUNTA(Concurso!B10:B49) -> 1 | D16: =COUNTIF(Concurso!U10:U49,D$14) -> 0 | E16: =COUNTIF(Concurso!U10:U49,E$14) -> 1 | F16: =COUNTIF(Concurso!U10:U49,F$14) -> 0 | G16: =COUNTIF(Concurso!U10:U49,G$14) -> 0 | H16: =SUM(Concurso!H10:H49) -> 1490 | I16: =IFERROR(AVERAGE(Concurso!P10:P49),0) -> 0.25 | J16: =REPT("█",MIN(10,ROUND(I16*10,0)))&REPT("░",10-MIN(10,ROUND(I16*10,0))) -> ███░░░░░░░ | K16: =COUNTIF(Concurso!M10:M49,"*A vencer") -> 0 | L16: =COUNTIF(Concurso!M10:M49,"*Vencido") -> 0 | M16: =COUNTIF(Concurso!W10:W49,"Emitido") -> 0
B17: Livros | C17: =COUNTA(Livros!B10:B49) -> 1 | D17: =COUNTIF(Livros!R10:R49,D$14) -> 0 | E17: =COUNTIF(Livros!R10:R49,E$14) -> 1 | F17: =COUNTIF(Livros!R10:R49,F$14) -> 0 | G17: =COUNTIF(Livros!R10:R49,G$14) -> 0 | H17: =SUM(Livros!H10:H49) -> 49.9 | I17: =IFERROR(AVERAGE(Livros!M10:M49),0) -> 0.375 | J17: =REPT("█",MIN(10,ROUND(I17*10,0)))&REPT("░",10-MIN(10,ROUND(I17*10,0))) -> ████░░░░░░ | K17: — | L17: — | M17: —
B18: Cursos IA | C18: =COUNTA('Cursos IA'!B10:B49) -> 1 | D18: =COUNTIF('Cursos IA'!S10:S49,D$14) -> 0 | E18: =COUNTIF('Cursos IA'!S10:S49,E$14) -> 1 | F18: =COUNTIF('Cursos IA'!S10:S49,F$14) -> 0 | G18: =COUNTIF('Cursos IA'!S10:S49,G$14) -> 0 | H18: =SUM('Cursos IA'!F10:F49) -> 497 | I18: =IFERROR(AVERAGE('Cursos IA'!N10:N49),0) -> 0.3 | J18: =REPT("█",MIN(10,ROUND(I18*10,0)))&REPT("░",10-MIN(10,ROUND(I18*10,0))) -> ███░░░░░░░ | K18: =COUNTIF('Cursos IA'!K10:K49,"*A vencer") -> 0 | L18: =COUNTIF('Cursos IA'!K10:K49,"*Vencido") -> 0 | M18: =COUNTIF('Cursos IA'!U10:U49,"Emitido") -> 0
B19: Renda Extra | C19: =COUNTA('Renda Extra'!B10:B49) -> 1 | D19: =COUNTIF('Renda Extra'!S10:S49,D$14) -> 0 | E19: =COUNTIF('Renda Extra'!S10:S49,E$14) -> 1 | F19: =COUNTIF('Renda Extra'!S10:S49,F$14) -> 0 | G19: =COUNTIF('Renda Extra'!S10:S49,G$14) -> 0 | H19: =SUM('Renda Extra'!F10:F49) -> 297 | I19: =IFERROR(AVERAGE('Renda Extra'!N10:N49),0) -> 0.22222222 | J19: =REPT("█",MIN(10,ROUND(I19*10,0)))&REPT("░",10-MIN(10,ROUND(I19*10,0))) -> ██░░░░░░░░ | K19: =COUNTIF('Renda Extra'!K10:K49,"*A vencer") -> 0 | L19: =COUNTIF('Renda Extra'!K10:K49,"*Vencido") -> 0 | M19: =COUNTIF('Renda Extra'!U10:U49,"Emitido") -> 0
B20: TOTAL | C20: =SUM(C15:C19) -> 5 | D20: =SUM(D15:D19) -> 0 | E20: =SUM(E15:E19) -> 5 | F20: =SUM(F15:F19) -> 0 | G20: =SUM(G15:G19) -> 0 | H20: =SUM(H15:H19) -> 14933.9 | I20: =IFERROR(SUMPRODUCT(C15:C19,I15:I19)/C20,0) -> 0.24944444 | J20: =REPT("█",MIN(10,ROUND(I20*10,0)))&REPT("░",10-MIN(10,ROUND(I20*10,0))) -> ██░░░░░░░░ | K20: =SUM(K15:K19) -> 0 | L20: =SUM(L15:L19) -> 0 | M20: =SUM(M15:M19) -> 0
B22: VENCIMENTOS DE ACESSO · MAIS URGENTES PRIMEIRO | H22: METAS DE ESTUDO DO MÊS | M22: ='Metas de Estudo'!E5 -> 46296
B23: Categoria | C23: Item | F23: Vence em | G23: Dias | H23: Categoria | J23: Meta (h) | K23: Realizado | L23: % meta | M23: Progresso
B24: =IF(Apoio!$L$5="","",INDEX(Apoio!$A$5:$A$164,Apoio!$L$5)) -> Concurso | C24: =IF(Apoio!$L$5="","",INDEX(Apoio!$B$5:$B$164,Apoio!$L$5)) -> Curso Preparatório Completo (exemplo) | F24: =IF(Apoio!$L$5="","",INDEX(Apoio!$C$5:$C$164,Apoio!$L$5)) -> 46568 | G24: =IF(Apoio!$L$5="","",INDEX(Apoio!$D$5:$D$164,Apoio!$L$5)) -> 270 | H24: ='Metas de Estudo'!B13 -> Pós-graduação | J24: ='Metas de Estudo'!C13 -> 20 | K24: ='Metas de Estudo'!D13 -> 2 | L24: ='Metas de Estudo'!E13 -> 0.1 | M24: ='Metas de Estudo'!F13 -> █░░░░░░░░░
B25: =IF(Apoio!$L$6="","",INDEX(Apoio!$A$5:$A$164,Apoio!$L$6)) -> Renda Extra | C25: =IF(Apoio!$L$6="","",INDEX(Apoio!$B$5:$B$164,Apoio!$L$6)) -> Marketing de Afiliados do Zero (exemplo) | F25: =IF(Apoio!$L$6="","",INDEX(Apoio!$C$5:$C$164,Apoio!$L$6)) -> 46631 | G25: =IF(Apoio!$L$6="","",INDEX(Apoio!$D$5:$D$164,Apoio!$L$6)) -> 333 | H25: ='Metas de Estudo'!B14 -> Concurso | J25: ='Metas de Estudo'!C14 -> 20 | K25: ='Metas de Estudo'!D14 -> 0 | L25: ='Metas de Estudo'!E14 -> 0 | M25: ='Metas de Estudo'!F14 -> ░░░░░░░░░░
B26: =IF(Apoio!$L$7="","",INDEX(Apoio!$A$5:$A$164,Apoio!$L$7)) -> Cursos IA | C26: =IF(Apoio!$L$7="","",INDEX(Apoio!$B$5:$B$164,Apoio!$L$7)) -> Agentes de IA na Prática (exemplo) | F26: =IF(Apoio!$L$7="","",INDEX(Apoio!$C$5:$C$164,Apoio!$L$7)) -> 46642 | G26: =IF(Apoio!$L$7="","",INDEX(Apoio!$D$5:$D$164,Apoio!$L$7)) -> 344 | H26: ='Metas de Estudo'!B15 -> Livros | J26: ='Metas de Estudo'!C15 -> 8 | K26: ='Metas de Estudo'!D15 -> 1 | L26: ='Metas de Estudo'!E15 -> 0.125 | M26: ='Metas de Estudo'!F15 -> █░░░░░░░░░
B27: =IF(Apoio!$L$8="","",INDEX(Apoio!$A$5:$A$164,Apoio!$L$8)) -> Pós-graduação | C27: =IF(Apoio!$L$8="","",INDEX(Apoio!$B$5:$B$164,Apoio!$L$8)) -> MBA em Inteligência Artificial (exemplo) | F27: =IF(Apoio!$L$8="","",INDEX(Apoio!$C$5:$C$164,Apoio!$L$8)) -> 46997 | G27: =IF(Apoio!$L$8="","",INDEX(Apoio!$D$5:$D$164,Apoio!$L$8)) -> 699 | H27: ='Metas de Estudo'!B16 -> Cursos IA | J27: ='Metas de Estudo'!C16 -> 15 | K27: ='Metas de Estudo'!D16 -> 1.5 | L27: ='Metas de Estudo'!E16 -> 0.1 | M27: ='Metas de Estudo'!F16 -> █░░░░░░░░░
B28: =IF(Apoio!$L$9="","",INDEX(Apoio!$A$5:$A$164,Apoio!$L$9)) | C28: =IF(Apoio!$L$9="","",INDEX(Apoio!$B$5:$B$164,Apoio!$L$9)) | F28: =IF(Apoio!$L$9="","",INDEX(Apoio!$C$5:$C$164,Apoio!$L$9)) | G28: =IF(Apoio!$L$9="","",INDEX(Apoio!$D$5:$D$164,Apoio!$L$9)) | H28: ='Metas de Estudo'!B17 -> Renda Extra | J28: ='Metas de Estudo'!C17 -> 10 | K28: ='Metas de Estudo'!D17 -> 0 | L28: ='Metas de Estudo'!E17 -> 0 | M28: ='Metas de Estudo'!F17 -> ░░░░░░░░░░
B29: =IF(Apoio!$L$10="","",INDEX(Apoio!$A$5:$A$164,Apoio!$L$10)) | C29: =IF(Apoio!$L$10="","",INDEX(Apoio!$B$5:$B$164,Apoio!$L$10)) | F29: =IF(Apoio!$L$10="","",INDEX(Apoio!$C$5:$C$164,Apoio!$L$10)) | G29: =IF(Apoio!$L$10="","",INDEX(Apoio!$D$5:$D$164,Apoio!$L$10)) | H29: Dias estudados | J29: ='Metas de Estudo'!G8 -> 3
B30: =IF(Apoio!$L$11="","",INDEX(Apoio!$A$5:$A$164,Apoio!$L$11)) | C30: =IF(Apoio!$L$11="","",INDEX(Apoio!$B$5:$B$164,Apoio!$L$11)) | F30: =IF(Apoio!$L$11="","",INDEX(Apoio!$C$5:$C$164,Apoio!$L$11)) | G30: =IF(Apoio!$L$11="","",INDEX(Apoio!$D$5:$D$164,Apoio!$L$11)) | H30: Média por dia | J30: =IFERROR('Metas de Estudo'!D18/'Metas de Estudo'!G8,0) -> 1.5
B31: =IF(Apoio!$L$12="","",INDEX(Apoio!$A$5:$A$164,Apoio!$L$12)) | C31: =IF(Apoio!$L$12="","",INDEX(Apoio!$B$5:$B$164,Apoio!$L$12)) | F31: =IF(Apoio!$L$12="","",INDEX(Apoio!$C$5:$C$164,Apoio!$L$12)) | G31: =IF(Apoio!$L$12="","",INDEX(Apoio!$D$5:$D$164,Apoio!$L$12)) | H31: Total do mês | J31: ='Metas de Estudo'!D18 -> 4.5
B33: RISCO: PREVISÃO DE TÉRMINO DEPOIS DO VENCIMENTO | H33: ROI · CURSOS DE RENDA EXTRA
B34: Categoria | C34: Item | F34: Previsão | G34: Folga (dias) | H34: Curso | J34: Investido | K34: Receita acum. | L34: ROI | M34: Payback (m)
B35: =IF(Apoio!$N$5="","",INDEX(Apoio!$A$5:$A$164,Apoio!$N$5)) | C35: =IF(Apoio!$N$5="","Nenhum curso em risco — bom ritmo!",INDEX(Apoio!$B$5:$B$164,Apoio!$N$5)) -> Nenhum curso em risco — bom ritmo! | F35: =IF(Apoio!$N$5="","",INDEX(Apoio!$F$5:$F$164,Apoio!$N$5)) | G35: =IF(Apoio!$N$5="","",INDEX(Apoio!$G$5:$G$164,Apoio!$N$5)) | H35: =IF('Renda Extra'!$B10="","",'Renda Extra'!$B10) -> Marketing de Afiliados do Zero (exemplo) | J35: =IF($H35="","",'Renda Extra'!$F10) -> 297 | K35: =IF($H35="","",N('Renda Extra'!$X10)) -> 180 | L35: =IF($H35="","",'Renda Extra'!$Y10) -> -0.39393939 | M35: =IF($H35="","",'Renda Extra'!$Z10) -> 0.975
B36: =IF(Apoio!$N$6="","",INDEX(Apoio!$A$5:$A$164,Apoio!$N$6)) | C36: =IF(Apoio!$N$6="","",INDEX(Apoio!$B$5:$B$164,Apoio!$N$6)) | F36: =IF(Apoio!$N$6="","",INDEX(Apoio!$F$5:$F$164,Apoio!$N$6)) | G36: =IF(Apoio!$N$6="","",INDEX(Apoio!$G$5:$G$164,Apoio!$N$6)) | H36: =IF('Renda Extra'!$B11="","",'Renda Extra'!$B11) | J36: =IF($H36="","",'Renda Extra'!$F11) | K36: =IF($H36="","",N('Renda Extra'!$X11)) | L36: =IF($H36="","",'Renda Extra'!$Y11) | M36: =IF($H36="","",'Renda Extra'!$Z11)
B37: =IF(Apoio!$N$7="","",INDEX(Apoio!$A$5:$A$164,Apoio!$N$7)) | C37: =IF(Apoio!$N$7="","",INDEX(Apoio!$B$5:$B$164,Apoio!$N$7)) | F37: =IF(Apoio!$N$7="","",INDEX(Apoio!$F$5:$F$164,Apoio!$N$7)) | G37: =IF(Apoio!$N$7="","",INDEX(Apoio!$G$5:$G$164,Apoio!$N$7)) | H37: =IF('Renda Extra'!$B12="","",'Renda Extra'!$B12) | J37: =IF($H37="","",'Renda Extra'!$F12) | K37: =IF($H37="","",N('Renda Extra'!$X12)) | L37: =IF($H37="","",'Renda Extra'!$Y12) | M37: =IF($H37="","",'Renda Extra'!$Z12)
B38: =IF(Apoio!$N$8="","",INDEX(Apoio!$A$5:$A$164,Apoio!$N$8)) | C38: =IF(Apoio!$N$8="","",INDEX(Apoio!$B$5:$B$164,Apoio!$N$8)) | F38: =IF(Apoio!$N$8="","",INDEX(Apoio!$F$5:$F$164,Apoio!$N$8)) | G38: =IF(Apoio!$N$8="","",INDEX(Apoio!$G$5:$G$164,Apoio!$N$8)) | H38: =IF('Renda Extra'!$B13="","",'Renda Extra'!$B13) | J38: =IF($H38="","",'Renda Extra'!$F13) | K38: =IF($H38="","",N('Renda Extra'!$X13)) | L38: =IF($H38="","",'Renda Extra'!$Y13) | M38: =IF($H38="","",'Renda Extra'!$Z13)
B39: =IF(Apoio!$N$9="","",INDEX(Apoio!$A$5:$A$164,Apoio!$N$9)) | C39: =IF(Apoio!$N$9="","",INDEX(Apoio!$B$5:$B$164,Apoio!$N$9)) | F39: =IF(Apoio!$N$9="","",INDEX(Apoio!$F$5:$F$164,Apoio!$N$9)) | G39: =IF(Apoio!$N$9="","",INDEX(Apoio!$G$5:$G$164,Apoio!$N$9)) | H39: =IF('Renda Extra'!$B14="","",'Renda Extra'!$B14) | J39: =IF($H39="","",'Renda Extra'!$F14) | K39: =IF($H39="","",N('Renda Extra'!$X14)) | L39: =IF($H39="","",'Renda Extra'!$Y14) | M39: =IF($H39="","",'Renda Extra'!$Z14)
B76: “A vencer” usa o prazo de Listas (H6). Previsão de término = ritmo real (itens concluídos ÷ dias desde o início). Custo por hora = valor pago ÷ horas do Diário (use o mesmo nome do curso).

Sheet Roadmap
A1: ROADMAP · LINHA DO TEMPO
A2: Barras = início → término previsto (cor pelo status) · ▼ = mês do vencimento do acesso | Q2: ← Voltar ao Início
A5: Mês inicial: | B5: 46296 | C5: ← altere para deslocar a janela de 12 meses · mostra os 12 primeiros itens de cada aba
A7: Categoria | B7: Item | C7: Status | D7: Início | E7: Término | F7: Vence acesso | G7: % Andam. | H7: =$B$5 -> 46296 | I7: =EDATE(H7,1) -> 46327 | J7: =EDATE(I7,1) -> 46357 | K7: =EDATE(J7,1) -> 46388 | L7: =EDATE(K7,1) -> 46419 | M7: =EDATE(L7,1) -> 46447 | N7: =EDATE(M7,1) -> 46478 | O7: =EDATE(N7,1) -> 46508 | P7: =EDATE(O7,1) -> 46539 | ... S7: =EDATE(R7,1) -> 46631
A8: PÓS-GRADUAÇÃO
A9: =IF($B9="","","Pós-graduação") -> Pós-graduação | B9: =IF('Pós-graduação'!B10="","",'Pós-graduação'!B10) -> MBA em Inteligência Artificial (exemplo) | C9: =IF($B9="","",IF('Pós-graduação'!S10="","",'Pós-graduação'!S10)) -> Em andamento | D9: =IF($B9="","",IF('Pós-graduação'!G10="","",'Pós-graduação'!G10)) -> 46266 | E9: =IF($B9="","",IF('Pós-graduação'!H10<>"",'Pós-graduação'!H10,IF('Pós-graduação'!I10<>"",'Pós-graduação'!I10,""))) -> 46813 | F9: =IF($B9="","",IF('Pós-graduação'!I10="","",'Pós-graduação'!I10)) -> 46997 | G9: =IF($B9="","",'Pós-graduação'!N10) -> 0.1 | H9: =IF(OR($B9="",$F9=""),"",IF(AND($F9>=H$7,$F9<EDATE(H$7,1)),"▼","")) | I9: =IF(OR($B9="",$F9=""),"",IF(AND($F9>=I$7,$F9<EDATE(I$7,1)),"▼","")) | J9: =IF(OR($B9="",$F9=""),"",IF(AND($F9>=J$7,$F9<EDATE(J$7,1)),"▼","")) | K9: =IF(OR($B9="",$F9=""),"",IF(AND($F9>=K$7,$F9<EDATE(K$7,1)),"▼","")) | L9: =IF(OR($B9="",$F9=""),"",IF(AND($F9>=L$7,$F9<EDATE(L$7,1)),"▼","")) | M9: =IF(OR($B9="",$F9=""),"",IF(AND($F9>=M$7,$F9<EDATE(M$7,1)),"▼","")) | N9: =IF(OR($B9="",$F9=""),"",IF(AND($F9>=N$7,$F9<EDATE(N$7,1)),"▼","")) | O9: =IF(OR($B9="",$F9=""),"",IF(AND($F9>=O$7,$F9<EDATE(O$7,1)),"▼","")) | ... S9: =IF(OR($B9="",$F9=""),"",IF(AND($F9>=S$7,$F9<EDATE(S$7,1)),"▼",""))
A10: =IF($B10="","","Pós-graduação") | B10: =IF('Pós-graduação'!B11="","",'Pós-graduação'!B11) | C10: =IF($B10="","",IF('Pós-graduação'!S11="","",'Pós-graduação'!S11)) | D10: =IF($B10="","",IF('Pós-graduação'!G11="","",'Pós-graduação'!G11)) | E10: =IF($B10="","",IF('Pós-graduação'!H11<>"",'Pós-graduação'!H11,IF('Pós-graduação'!I11<>"",'Pós-graduação'!I11,""))) | F10: =IF($B10="","",IF('Pós-graduação'!I11="","",'Pós-graduação'!I11)) | G10: =IF($B10="","",'Pós-graduação'!N11) | H10: =IF(OR($B10="",$F10=""),"",IF(AND($F10>=H$7,$F10<EDATE(H$7,1)),"▼","")) | I10: =IF(OR($B10="",$F10=""),"",IF(AND($F10>=I$7,$F10<EDATE(I$7,1)),"▼","")) | J10: =IF(OR($B10="",$F10=""),"",IF(AND($F10>=J$7,$F10<EDATE(J$7,1)),"▼","")) | K10: =IF(OR($B10="",$F10=""),"",IF(AND($F10>=K$7,$F10<EDATE(K$7,1)),"▼","")) | L10: =IF(OR($B10="",$F10=""),"",IF(AND($F10>=L$7,$F10<EDATE(L$7,1)),"▼","")) | M10: =IF(OR($B10="",$F10=""),"",IF(AND($F10>=M$7,$F10<EDATE(M$7,1)),"▼","")) | N10: =IF(OR($B10="",$F10=""),"",IF(AND($F10>=N$7,$F10<EDATE(N$7,1)),"▼","")) | O10: =IF(OR($B10="",$F10=""),"",IF(AND($F10>=O$7,$F10<EDATE(O$7,1)),"▼","")) | ... S10: =IF(OR($B10="",$F10=""),"",IF(AND($F10>=S$7,$F10<EDATE(S$7,1)),"▼",""))
A11: =IF($B11="","","Pós-graduação") | B11: =IF('Pós-graduação'!B12="","",'Pós-graduação'!B12) | C11: =IF($B11="","",IF('Pós-graduação'!S12="","",'Pós-graduação'!S12)) | D11: =IF($B11="","",IF('Pós-graduação'!G12="","",'Pós-graduação'!G12)) | E11: =IF($B11="","",IF('Pós-graduação'!H12<>"",'Pós-graduação'!H12,IF('Pós-graduação'!I12<>"",'Pós-graduação'!I12,""))) | F11: =IF($B11="","",IF('Pós-graduação'!I12="","",'Pós-graduação'!I12)) | G11: =IF($B11="","",'Pós-graduação'!N12) | H11: =IF(OR($B11="",$F11=""),"",IF(AND($F11>=H$7,$F11<EDATE(H$7,1)),"▼","")) | I11: =IF(OR($B11="",$F11=""),"",IF(AND($F11>=I$7,$F11<EDATE(I$7,1)),"▼","")) | J11: =IF(OR($B11="",$F11=""),"",IF(AND($F11>=J$7,$F11<EDATE(J$7,1)),"▼","")) | K11: =IF(OR($B11="",$F11=""),"",IF(AND($F11>=K$7,$F11<EDATE(K$7,1)),"▼","")) | L11: =IF(OR($B11="",$F11=""),"",IF(AND($F11>=L$7,$F11<EDATE(L$7,1)),"▼","")) | M11: =IF(OR($B11="",$F11=""),"",IF(AND($F11>=M$7,$F11<EDATE(M$7,1)),"▼","")) | N11: =IF(OR($B11="",$F11=""),"",IF(AND($F11>=N$7,$F11<EDATE(N$7,1)),"▼","")) | O11: =IF(OR($B11="",$F11=""),"",IF(AND($F11>=O$7,$F11<EDATE(O$7,1)),"▼","")) | ... S11: =IF(OR($B11="",$F11=""),"",IF(AND($F11>=S$7,$F11<EDATE(S$7,1)),"▼",""))
A12: =IF($B12="","","Pós-graduação") | B12: =IF('Pós-graduação'!B13="","",'Pós-graduação'!B13) | C12: =IF($B12="","",IF('Pós-graduação'!S13="","",'Pós-graduação'!S13)) | D12: =IF($B12="","",IF('Pós-graduação'!G13="","",'Pós-graduação'!G13)) | E12: =IF($B12="","",IF('Pós-graduação'!H13<>"",'Pós-graduação'!H13,IF('Pós-graduação'!I13<>"",'Pós-graduação'!I13,""))) | F12: =IF($B12="","",IF('Pós-graduação'!I13="","",'Pós-graduação'!I13)) | G12: =IF($B12="","",'Pós-graduação'!N13) | H12: =IF(OR($B12="",$F12=""),"",IF(AND($F12>=H$7,$F12<EDATE(H$7,1)),"▼","")) | I12: =IF(OR($B12="",$F12=""),"",IF(AND($F12>=I$7,$F12<EDATE(I$7,1)),"▼","")) | J12: =IF(OR($B12="",$F12=""),"",IF(AND($F12>=J$7,$F12<EDATE(J$7,1)),"▼","")) | K12: =IF(OR($B12="",$F12=""),"",IF(AND($F12>=K$7,$F12<EDATE(K$7,1)),"▼","")) | L12: =IF(OR($B12="",$F12=""),"",IF(AND($F12>=L$7,$F12<EDATE(L$7,1)),"▼","")) | M12: =IF(OR($B12="",$F12=""),"",IF(AND($F12>=M$7,$F12<EDATE(M$7,1)),"▼","")) | N12: =IF(OR($B12="",$F12=""),"",IF(AND($F12>=N$7,$F12<EDATE(N$7,1)),"▼","")) | O12: =IF(OR($B12="",$F12=""),"",IF(AND($F12>=O$7,$F12<EDATE(O$7,1)),"▼","")) | ... S12: =IF(OR($B12="",$F12=""),"",IF(AND($F12>=S$7,$F12<EDATE(S$7,1)),"▼",""))
A13: =IF($B13="","","Pós-graduação") | B13: =IF('Pós-graduação'!B14="","",'Pós-graduação'!B14) | C13: =IF($B13="","",IF('Pós-graduação'!S14="","",'Pós-graduação'!S14)) | D13: =IF($B13="","",IF('Pós-graduação'!G14="","",'Pós-graduação'!G14)) | E13: =IF($B13="","",IF('Pós-graduação'!H14<>"",'Pós-graduação'!H14,IF('Pós-graduação'!I14<>"",'Pós-graduação'!I14,""))) | F13: =IF($B13="","",IF('Pós-graduação'!I14="","",'Pós-graduação'!I14)) | G13: =IF($B13="","",'Pós-graduação'!N14) | H13: =IF(OR($B13="",$F13=""),"",IF(AND($F13>=H$7,$F13<EDATE(H$7,1)),"▼","")) | I13: =IF(OR($B13="",$F13=""),"",IF(AND($F13>=I$7,$F13<EDATE(I$7,1)),"▼","")) | J13: =IF(OR($B13="",$F13=""),"",IF(AND($F13>=J$7,$F13<EDATE(J$7,1)),"▼","")) | K13: =IF(OR($B13="",$F13=""),"",IF(AND($F13>=K$7,$F13<EDATE(K$7,1)),"▼","")) | L13: =IF(OR($B13="",$F13=""),"",IF(AND($F13>=L$7,$F13<EDATE(L$7,1)),"▼","")) | M13: =IF(OR($B13="",$F13=""),"",IF(AND($F13>=M$7,$F13<EDATE(M$7,1)),"▼","")) | N13: =IF(OR($B13="",$F13=""),"",IF(AND($F13>=N$7,$F13<EDATE(N$7,1)),"▼","")) | O13: =IF(OR($B13="",$F13=""),"",IF(AND($F13>=O$7,$F13<EDATE(O$7,1)),"▼","")) | ... S13: =IF(OR($B13="",$F13=""),"",IF(AND($F13>=S$7,$F13<EDATE(S$7,1)),"▼",""))
A14: =IF($B14="","","Pós-graduação") | B14: =IF('Pós-graduação'!B15="","",'Pós-graduação'!B15) | C14: =IF($B14="","",IF('Pós-graduação'!S15="","",'Pós-graduação'!S15)) | D14: =IF($B14="","",IF('Pós-graduação'!G15="","",'Pós-graduação'!G15)) | E14: =IF($B14="","",IF('Pós-graduação'!H15<>"",'Pós-graduação'!H15,IF('Pós-graduação'!I15<>"",'Pós-graduação'!I15,""))) | F14: =IF($B14="","",IF('Pós-graduação'!I15="","",'Pós-graduação'!I15)) | G14: =IF($B14="","",'Pós-graduação'!N15) | H14: =IF(OR($B14="",$F14=""),"",IF(AND($F14>=H$7,$F14<EDATE(H$7,1)),"▼","")) | I14: =IF(OR($B14="",$F14=""),"",IF(AND($F14>=I$7,$F14<EDATE(I$7,1)),"▼","")) | J14: =IF(OR($B14="",$F14=""),"",IF(AND($F14>=J$7,$F14<EDATE(J$7,1)),"▼","")) | K14: =IF(OR($B14="",$F14=""),"",IF(AND($F14>=K$7,$F14<EDATE(K$7,1)),"▼","")) | L14: =IF(OR($B14="",$F14=""),"",IF(AND($F14>=L$7,$F14<EDATE(L$7,1)),"▼","")) | M14: =IF(OR($B14="",$F14=""),"",IF(AND($F14>=M$7,$F14<EDATE(M$7,1)),"▼","")) | N14: =IF(OR($B14="",$F14=""),"",IF(AND($F14>=N$7,$F14<EDATE(N$7,1)),"▼","")) | O14: =IF(OR($B14="",$F14=""),"",IF(AND($F14>=O$7,$F14<EDATE(O$7,1)),"▼","")) | ... S14: =IF(OR($B14="",$F14=""),"",IF(AND($F14>=S$7,$F14<EDATE(S$7,1)),"▼",""))
A15: =IF($B15="","","Pós-graduação") | B15: =IF('Pós-graduação'!B16="","",'Pós-graduação'!B16) | C15: =IF($B15="","",IF('Pós-graduação'!S16="","",'Pós-graduação'!S16)) | D15: =IF($B15="","",IF('Pós-graduação'!G16="","",'Pós-graduação'!G16)) | E15: =IF($B15="","",IF('Pós-graduação'!H16<>"",'Pós-graduação'!H16,IF('Pós-graduação'!I16<>"",'Pós-graduação'!I16,""))) | F15: =IF($B15="","",IF('Pós-graduação'!I16="","",'Pós-graduação'!I16)) | G15: =IF($B15="","",'Pós-graduação'!N16) | H15: =IF(OR($B15="",$F15=""),"",IF(AND($F15>=H$7,$F15<EDATE(H$7,1)),"▼","")) | I15: =IF(OR($B15="",$F15=""),"",IF(AND($F15>=I$7,$F15<EDATE(I$7,1)),"▼","")) | J15: =IF(OR($B15="",$F15=""),"",IF(AND($F15>=J$7,$F15<EDATE(J$7,1)),"▼","")) | K15: =IF(OR($B15="",$F15=""),"",IF(AND($F15>=K$7,$F15<EDATE(K$7,1)),"▼","")) | L15: =IF(OR($B15="",$F15=""),"",IF(AND($F15>=L$7,$F15<EDATE(L$7,1)),"▼","")) | M15: =IF(OR($B15="",$F15=""),"",IF(AND($F15>=M$7,$F15<EDATE(M$7,1)),"▼","")) | N15: =IF(OR($B15="",$F15=""),"",IF(AND($F15>=N$7,$F15<EDATE(N$7,1)),"▼","")) | O15: =IF(OR($B15="",$F15=""),"",IF(AND($F15>=O$7,$F15<EDATE(O$7,1)),"▼","")) | ... S15: =IF(OR($B15="",$F15=""),"",IF(AND($F15>=S$7,$F15<EDATE(S$7,1)),"▼",""))
A16: =IF($B16="","","Pós-graduação") | B16: =IF('Pós-graduação'!B17="","",'Pós-graduação'!B17) | C16: =IF($B16="","",IF('Pós-graduação'!S17="","",'Pós-graduação'!S17)) | D16: =IF($B16="","",IF('Pós-graduação'!G17="","",'Pós-graduação'!G17)) | E16: =IF($B16="","",IF('Pós-graduação'!H17<>"",'Pós-graduação'!H17,IF('Pós-graduação'!I17<>"",'Pós-graduação'!I17,""))) | F16: =IF($B16="","",IF('Pós-graduação'!I17="","",'Pós-graduação'!I17)) | G16: =IF($B16="","",'Pós-graduação'!N17) | H16: =IF(OR($B16="",$F16=""),"",IF(AND($F16>=H$7,$F16<EDATE(H$7,1)),"▼","")) | I16: =IF(OR($B16="",$F16=""),"",IF(AND($F16>=I$7,$F16<EDATE(I$7,1)),"▼","")) | J16: =IF(OR($B16="",$F16=""),"",IF(AND($F16>=J$7,$F16<EDATE(J$7,1)),"▼","")) | K16: =IF(OR($B16="",$F16=""),"",IF(AND($F16>=K$7,$F16<EDATE(K$7,1)),"▼","")) | L16: =IF(OR($B16="",$F16=""),"",IF(AND($F16>=L$7,$F16<EDATE(L$7,1)),"▼","")) | M16: =IF(OR($B16="",$F16=""),"",IF(AND($F16>=M$7,$F16<EDATE(M$7,1)),"▼","")) | N16: =IF(OR($B16="",$F16=""),"",IF(AND($F16>=N$7,$F16<EDATE(N$7,1)),"▼","")) | O16: =IF(OR($B16="",$F16=""),"",IF(AND($F16>=O$7,$F16<EDATE(O$7,1)),"▼","")) | ... S16: =IF(OR($B16="",$F16=""),"",IF(AND($F16>=S$7,$F16<EDATE(S$7,1)),"▼",""))
A17: =IF($B17="","","Pós-graduação") | B17: =IF('Pós-graduação'!B18="","",'Pós-graduação'!B18) | C17: =IF($B17="","",IF('Pós-graduação'!S18="","",'Pós-graduação'!S18)) | D17: =IF($B17="","",IF('Pós-graduação'!G18="","",'Pós-graduação'!G18)) | E17: =IF($B17="","",IF('Pós-graduação'!H18<>"",'Pós-graduação'!H18,IF('Pós-graduação'!I18<>"",'Pós-graduação'!I18,""))) | F17: =IF($B17="","",IF('Pós-graduação'!I18="","",'Pós-graduação'!I18)) | G17: =IF($B17="","",'Pós-graduação'!N18) | H17: =IF(OR($B17="",$F17=""),"",IF(AND($F17>=H$7,$F17<EDATE(H$7,1)),"▼","")) | I17: =IF(OR($B17="",$F17=""),"",IF(AND($F17>=I$7,$F17<EDATE(I$7,1)),"▼","")) | J17: =IF(OR($B17="",$F17=""),"",IF(AND($F17>=J$7,$F17<EDATE(J$7,1)),"▼","")) | K17: =IF(OR($B17="",$F17=""),"",IF(AND($F17>=K$7,$F17<EDATE(K$7,1)),"▼","")) | L17: =IF(OR($B17="",$F17=""),"",IF(AND($F17>=L$7,$F17<EDATE(L$7,1)),"▼","")) | M17: =IF(OR($B17="",$F17=""),"",IF(AND($F17>=M$7,$F17<EDATE(M$7,1)),"▼","")) | N17: =IF(OR($B17="",$F17=""),"",IF(AND($F17>=N$7,$F17<EDATE(N$7,1)),"▼","")) | O17: =IF(OR($B17="",$F17=""),"",IF(AND($F17>=O$7,$F17<EDATE(O$7,1)),"▼","")) | ... S17: =IF(OR($B17="",$F17=""),"",IF(AND($F17>=S$7,$F17<EDATE(S$7,1)),"▼",""))
A18: =IF($B18="","","Pós-graduação") | B18: =IF('Pós-graduação'!B19="","",'Pós-graduação'!B19) | C18: =IF($B18="","",IF('Pós-graduação'!S19="","",'Pós-graduação'!S19)) | D18: =IF($B18="","",IF('Pós-graduação'!G19="","",'Pós-graduação'!G19)) | E18: =IF($B18="","",IF('Pós-graduação'!H19<>"",'Pós-graduação'!H19,IF('Pós-graduação'!I19<>"",'Pós-graduação'!I19,""))) | F18: =IF($B18="","",IF('Pós-graduação'!I19="","",'Pós-graduação'!I19)) | G18: =IF($B18="","",'Pós-graduação'!N19) | H18: =IF(OR($B18="",$F18=""),"",IF(AND($F18>=H$7,$F18<EDATE(H$7,1)),"▼","")) | I18: =IF(OR($B18="",$F18=""),"",IF(AND($F18>=I$7,$F18<EDATE(I$7,1)),"▼","")) | J18: =IF(OR($B18="",$F18=""),"",IF(AND($F18>=J$7,$F18<EDATE(J$7,1)),"▼","")) | K18: =IF(OR($B18="",$F18=""),"",IF(AND($F18>=K$7,$F18<EDATE(K$7,1)),"▼","")) | L18: =IF(OR($B18="",$F18=""),"",IF(AND($F18>=L$7,$F18<EDATE(L$7,1)),"▼","")) | M18: =IF(OR($B18="",$F18=""),"",IF(AND($F18>=M$7,$F18<EDATE(M$7,1)),"▼","")) | N18: =IF(OR($B18="",$F18=""),"",IF(AND($F18>=N$7,$F18<EDATE(N$7,1)),"▼","")) | O18: =IF(OR($B18="",$F18=""),"",IF(AND($F18>=O$7,$F18<EDATE(O$7,1)),"▼","")) | ... S18: =IF(OR($B18="",$F18=""),"",IF(AND($F18>=S$7,$F18<EDATE(S$7,1)),"▼",""))
A19: =IF($B19="","","Pós-graduação") | B19: =IF('Pós-graduação'!B20="","",'Pós-graduação'!B20) | C19: =IF($B19="","",IF('Pós-graduação'!S20="","",'Pós-graduação'!S20)) | D19: =IF($B19="","",IF('Pós-graduação'!G20="","",'Pós-graduação'!G20)) | E19: =IF($B19="","",IF('Pós-graduação'!H20<>"",'Pós-graduação'!H20,IF('Pós-graduação'!I20<>"",'Pós-graduação'!I20,""))) | F19: =IF($B19="","",IF('Pós-graduação'!I20="","",'Pós-graduação'!I20)) | G19: =IF($B19="","",'Pós-graduação'!N20) | H19: =IF(OR($B19="",$F19=""),"",IF(AND($F19>=H$7,$F19<EDATE(H$7,1)),"▼","")) | I19: =IF(OR($B19="",$F19=""),"",IF(AND($F19>=I$7,$F19<EDATE(I$7,1)),"▼","")) | J19: =IF(OR($B19="",$F19=""),"",IF(AND($F19>=J$7,$F19<EDATE(J$7,1)),"▼","")) | K19: =IF(OR($B19="",$F19=""),"",IF(AND($F19>=K$7,$F19<EDATE(K$7,1)),"▼","")) | L19: =IF(OR($B19="",$F19=""),"",IF(AND($F19>=L$7,$F19<EDATE(L$7,1)),"▼","")) | M19: =IF(OR($B19="",$F19=""),"",IF(AND($F19>=M$7,$F19<EDATE(M$7,1)),"▼","")) | N19: =IF(OR($B19="",$F19=""),"",IF(AND($F19>=N$7,$F19<EDATE(N$7,1)),"▼","")) | O19: =IF(OR($B19="",$F19=""),"",IF(AND($F19>=O$7,$F19<EDATE(O$7,1)),"▼","")) | ... S19: =IF(OR($B19="",$F19=""),"",IF(AND($F19>=S$7,$F19<EDATE(S$7,1)),"▼",""))
A20: =IF($B20="","","Pós-graduação") | B20: =IF('Pós-graduação'!B21="","",'Pós-graduação'!B21) | C20: =IF($B20="","",IF('Pós-graduação'!S21="","",'Pós-graduação'!S21)) | D20: =IF($B20="","",IF('Pós-graduação'!G21="","",'Pós-graduação'!G21)) | E20: =IF($B20="","",IF('Pós-graduação'!H21<>"",'Pós-graduação'!H21,IF('Pós-graduação'!I21<>"",'Pós-graduação'!I21,""))) | F20: =IF($B20="","",IF('Pós-graduação'!I21="","",'Pós-graduação'!I21)) | G20: =IF($B20="","",'Pós-graduação'!N21) | H20: =IF(OR($B20="",$F20=""),"",IF(AND($F20>=H$7,$F20<EDATE(H$7,1)),"▼","")) | I20: =IF(OR($B20="",$F20=""),"",IF(AND($F20>=I$7,$F20<EDATE(I$7,1)),"▼","")) | J20: =IF(OR($B20="",$F20=""),"",IF(AND($F20>=J$7,$F20<EDATE(J$7,1)),"▼","")) | K20: =IF(OR($B20="",$F20=""),"",IF(AND($F20>=K$7,$F20<EDATE(K$7,1)),"▼","")) | L20: =IF(OR($B20="",$F20=""),"",IF(AND($F20>=L$7,$F20<EDATE(L$7,1)),"▼","")) | M20: =IF(OR($B20="",$F20=""),"",IF(AND($F20>=M$7,$F20<EDATE(M$7,1)),"▼","")) | N20: =IF(OR($B20="",$F20=""),"",IF(AND($F20>=N$7,$F20<EDATE(N$7,1)),"▼","")) | O20: =IF(OR($B20="",$F20=""),"",IF(AND($F20>=O$7,$F20<EDATE(O$7,1)),"▼","")) | ... S20: =IF(OR($B20="",$F20=""),"",IF(AND($F20>=S$7,$F20<EDATE(S$7,1)),"▼",""))
A21: CONCURSO
A22: =IF($B22="","","Concurso") -> Concurso | B22: =IF(Concurso!B10="","",Concurso!B10) -> Curso Preparatório Completo (exemplo) | C22: =IF($B22="","",IF(Concurso!U10="","",Concurso!U10)) -> Em andamento | D22: =IF($B22="","",IF(Concurso!I10="","",Concurso!I10)) -> 46280 | E22: =IF($B22="","",IF(Concurso!J10<>"",Concurso!J10,IF(Concurso!K10<>"",Concurso!K10,""))) -> 46446 | F22: =IF($B22="","",IF(Concurso!K10="","",Concurso!K10)) -> 46568 | G22: =IF($B22="","",Concurso!P10) -> 0.25 | H22: =IF(OR($B22="",$F22=""),"",IF(AND($F22>=H$7,$F22<EDATE(H$7,1)),"▼","")) | I22: =IF(OR($B22="",$F22=""),"",IF(AND($F22>=I$7,$F22<EDATE(I$7,1)),"▼","")) | J22: =IF(OR($B22="",$F22=""),"",IF(AND($F22>=J$7,$F22<EDATE(J$7,1)),"▼","")) | K22: =IF(OR($B22="",$F22=""),"",IF(AND($F22>=K$7,$F22<EDATE(K$7,1)),"▼","")) | L22: =IF(OR($B22="",$F22=""),"",IF(AND($F22>=L$7,$F22<EDATE(L$7,1)),"▼","")) | M22: =IF(OR($B22="",$F22=""),"",IF(AND($F22>=M$7,$F22<EDATE(M$7,1)),"▼","")) | N22: =IF(OR($B22="",$F22=""),"",IF(AND($F22>=N$7,$F22<EDATE(N$7,1)),"▼","")) | O22: =IF(OR($B22="",$F22=""),"",IF(AND($F22>=O$7,$F22<EDATE(O$7,1)),"▼","")) | ... S22: =IF(OR($B22="",$F22=""),"",IF(AND($F22>=S$7,$F22<EDATE(S$7,1)),"▼",""))
A23: =IF($B23="","","Concurso") | B23: =IF(Concurso!B11="","",Concurso!B11) | C23: =IF($B23="","",IF(Concurso!U11="","",Concurso!U11)) | D23: =IF($B23="","",IF(Concurso!I11="","",Concurso!I11)) | E23: =IF($B23="","",IF(Concurso!J11<>"",Concurso!J11,IF(Concurso!K11<>"",Concurso!K11,""))) | F23: =IF($B23="","",IF(Concurso!K11="","",Concurso!K11)) | G23: =IF($B23="","",Concurso!P11) | H23: =IF(OR($B23="",$F23=""),"",IF(AND($F23>=H$7,$F23<EDATE(H$7,1)),"▼","")) | I23: =IF(OR($B23="",$F23=""),"",IF(AND($F23>=I$7,$F23<EDATE(I$7,1)),"▼","")) | J23: =IF(OR($B23="",$F23=""),"",IF(AND($F23>=J$7,$F23<EDATE(J$7,1)),"▼","")) | K23: =IF(OR($B23="",$F23=""),"",IF(AND($F23>=K$7,$F23<EDATE(K$7,1)),"▼","")) | L23: =IF(OR($B23="",$F23=""),"",IF(AND($F23>=L$7,$F23<EDATE(L$7,1)),"▼","")) | M23: =IF(OR($B23="",$F23=""),"",IF(AND($F23>=M$7,$F23<EDATE(M$7,1)),"▼","")) | N23: =IF(OR($B23="",$F23=""),"",IF(AND($F23>=N$7,$F23<EDATE(N$7,1)),"▼","")) | O23: =IF(OR($B23="",$F23=""),"",IF(AND($F23>=O$7,$F23<EDATE(O$7,1)),"▼","")) | ... S23: =IF(OR($B23="",$F23=""),"",IF(AND($F23>=S$7,$F23<EDATE(S$7,1)),"▼",""))
A24: =IF($B24="","","Concurso") | B24: =IF(Concurso!B12="","",Concurso!B12) | C24: =IF($B24="","",IF(Concurso!U12="","",Concurso!U12)) | D24: =IF($B24="","",IF(Concurso!I12="","",Concurso!I12)) | E24: =IF($B24="","",IF(Concurso!J12<>"",Concurso!J12,IF(Concurso!K12<>"",Concurso!K12,""))) | F24: =IF($B24="","",IF(Concurso!K12="","",Concurso!K12)) | G24: =IF($B24="","",Concurso!P12) | H24: =IF(OR($B24="",$F24=""),"",IF(AND($F24>=H$7,$F24<EDATE(H$7,1)),"▼","")) | I24: =IF(OR($B24="",$F24=""),"",IF(AND($F24>=I$7,$F24<EDATE(I$7,1)),"▼","")) | J24: =IF(OR($B24="",$F24=""),"",IF(AND($F24>=J$7,$F24<EDATE(J$7,1)),"▼","")) | K24: =IF(OR($B24="",$F24=""),"",IF(AND($F24>=K$7,$F24<EDATE(K$7,1)),"▼","")) | L24: =IF(OR($B24="",$F24=""),"",IF(AND($F24>=L$7,$F24<EDATE(L$7,1)),"▼","")) | M24: =IF(OR($B24="",$F24=""),"",IF(AND($F24>=M$7,$F24<EDATE(M$7,1)),"▼","")) | N24: =IF(OR($B24="",$F24=""),"",IF(AND($F24>=N$7,$F24<EDATE(N$7,1)),"▼","")) | O24: =IF(OR($B24="",$F24=""),"",IF(AND($F24>=O$7,$F24<EDATE(O$7,1)),"▼","")) | ... S24: =IF(OR($B24="",$F24=""),"",IF(AND($F24>=S$7,$F24<EDATE(S$7,1)),"▼",""))
A25: =IF($B25="","","Concurso") | B25: =IF(Concurso!B13="","",Concurso!B13) | C25: =IF($B25="","",IF(Concurso!U13="","",Concurso!U13)) | D25: =IF($B25="","",IF(Concurso!I13="","",Concurso!I13)) | E25: =IF($B25="","",IF(Concurso!J13<>"",Concurso!J13,IF(Concurso!K13<>"",Concurso!K13,""))) | F25: =IF($B25="","",IF(Concurso!K13="","",Concurso!K13)) | G25: =IF($B25="","",Concurso!P13) | H25: =IF(OR($B25="",$F25=""),"",IF(AND($F25>=H$7,$F25<EDATE(H$7,1)),"▼","")) | I25: =IF(OR($B25="",$F25=""),"",IF(AND($F25>=I$7,$F25<EDATE(I$7,1)),"▼","")) | J25: =IF(OR($B25="",$F25=""),"",IF(AND($F25>=J$7,$F25<EDATE(J$7,1)),"▼","")) | K25: =IF(OR($B25="",$F25=""),"",IF(AND($F25>=K$7,$F25<EDATE(K$7,1)),"▼","")) | L25: =IF(OR($B25="",$F25=""),"",IF(AND($F25>=L$7,$F25<EDATE(L$7,1)),"▼","")) | M25: =IF(OR($B25="",$F25=""),"",IF(AND($F25>=M$7,$F25<EDATE(M$7,1)),"▼","")) | N25: =IF(OR($B25="",$F25=""),"",IF(AND($F25>=N$7,$F25<EDATE(N$7,1)),"▼","")) | O25: =IF(OR($B25="",$F25=""),"",IF(AND($F25>=O$7,$F25<EDATE(O$7,1)),"▼","")) | ... S25: =IF(OR($B25="",$F25=""),"",IF(AND($F25>=S$7,$F25<EDATE(S$7,1)),"▼",""))
A26: =IF($B26="","","Concurso") | B26: =IF(Concurso!B14="","",Concurso!B14) | C26: =IF($B26="","",IF(Concurso!U14="","",Concurso!U14)) | D26: =IF($B26="","",IF(Concurso!I14="","",Concurso!I14)) | E26: =IF($B26="","",IF(Concurso!J14<>"",Concurso!J14,IF(Concurso!K14<>"",Concurso!K14,""))) | F26: =IF($B26="","",IF(Concurso!K14="","",Concurso!K14)) | G26: =IF($B26="","",Concurso!P14) | H26: =IF(OR($B26="",$F26=""),"",IF(AND($F26>=H$7,$F26<EDATE(H$7,1)),"▼","")) | I26: =IF(OR($B26="",$F26=""),"",IF(AND($F26>=I$7,$F26<EDATE(I$7,1)),"▼","")) | J26: =IF(OR($B26="",$F26=""),"",IF(AND($F26>=J$7,$F26<EDATE(J$7,1)),"▼","")) | K26: =IF(OR($B26="",$F26=""),"",IF(AND($F26>=K$7,$F26<EDATE(K$7,1)),"▼","")) | L26: =IF(OR($B26="",$F26=""),"",IF(AND($F26>=L$7,$F26<EDATE(L$7,1)),"▼","")) | M26: =IF(OR($B26="",$F26=""),"",IF(AND($F26>=M$7,$F26<EDATE(M$7,1)),"▼","")) | N26: =IF(OR($B26="",$F26=""),"",IF(AND($F26>=N$7,$F26<EDATE(N$7,1)),"▼","")) | O26: =IF(OR($B26="",$F26=""),"",IF(AND($F26>=O$7,$F26<EDATE(O$7,1)),"▼","")) | ... S26: =IF(OR($B26="",$F26=""),"",IF(AND($F26>=S$7,$F26<EDATE(S$7,1)),"▼",""))
A27: =IF($B27="","","Concurso") | B27: =IF(Concurso!B15="","",Concurso!B15) | C27: =IF($B27="","",IF(Concurso!U15="","",Concurso!U15)) | D27: =IF($B27="","",IF(Concurso!I15="","",Concurso!I15)) | E27: =IF($B27="","",IF(Concurso!J15<>"",Concurso!J15,IF(Concurso!K15<>"",Concurso!K15,""))) | F27: =IF($B27="","",IF(Concurso!K15="","",Concurso!K15)) | G27: =IF($B27="","",Concurso!P15) | H27: =IF(OR($B27="",$F27=""),"",IF(AND($F27>=H$7,$F27<EDATE(H$7,1)),"▼","")) | I27: =IF(OR($B27="",$F27=""),"",IF(AND($F27>=I$7,$F27<EDATE(I$7,1)),"▼","")) | J27: =IF(OR($B27="",$F27=""),"",IF(AND($F27>=J$7,$F27<EDATE(J$7,1)),"▼","")) | K27: =IF(OR($B27="",$F27=""),"",IF(AND($F27>=K$7,$F27<EDATE(K$7,1)),"▼","")) | L27: =IF(OR($B27="",$F27=""),"",IF(AND($F27>=L$7,$F27<EDATE(L$7,1)),"▼","")) | M27: =IF(OR($B27="",$F27=""),"",IF(AND($F27>=M$7,$F27<EDATE(M$7,1)),"▼","")) | N27: =IF(OR($B27="",$F27=""),"",IF(AND($F27>=N$7,$F27<EDATE(N$7,1)),"▼","")) | O27: =IF(OR($B27="",$F27=""),"",IF(AND($F27>=O$7,$F27<EDATE(O$7,1)),"▼","")) | ... S27: =IF(OR($B27="",$F27=""),"",IF(AND($F27>=S$7,$F27<EDATE(S$7,1)),"▼",""))
A28: =IF($B28="","","Concurso") | B28: =IF(Concurso!B16="","",Concurso!B16) | C28: =IF($B28="","",IF(Concurso!U16="","",Concurso!U16)) | D28: =IF($B28="","",IF(Concurso!I16="","",Concurso!I16)) | E28: =IF($B28="","",IF(Concurso!J16<>"",Concurso!J16,IF(Concurso!K16<>"",Concurso!K16,""))) | F28: =IF($B28="","",IF(Concurso!K16="","",Concurso!K16)) | G28: =IF($B28="","",Concurso!P16) | H28: =IF(OR($B28="",$F28=""),"",IF(AND($F28>=H$7,$F28<EDATE(H$7,1)),"▼","")) | I28: =IF(OR($B28="",$F28=""),"",IF(AND($F28>=I$7,$F28<EDATE(I$7,1)),"▼","")) | J28: =IF(OR($B28="",$F28=""),"",IF(AND($F28>=J$7,$F28<EDATE(J$7,1)),"▼","")) | K28: =IF(OR($B28="",$F28=""),"",IF(AND($F28>=K$7,$F28<EDATE(K$7,1)),"▼","")) | L28: =IF(OR($B28="",$F28=""),"",IF(AND($F28>=L$7,$F28<EDATE(L$7,1)),"▼","")) | M28: =IF(OR($B28="",$F28=""),"",IF(AND($F28>=M$7,$F28<EDATE(M$7,1)),"▼","")) | N28: =IF(OR($B28="",$F28=""),"",IF(AND($F28>=N$7,$F28<EDATE(N$7,1)),"▼","")) | O28: =IF(OR($B28="",$F28=""),"",IF(AND($F28>=O$7,$F28<EDATE(O$7,1)),"▼","")) | ... S28: =IF(OR($B28="",$F28=""),"",IF(AND($F28>=S$7,$F28<EDATE(S$7,1)),"▼",""))
A29: =IF($B29="","","Concurso") | B29: =IF(Concurso!B17="","",Concurso!B17) | C29: =IF($B29="","",IF(Concurso!U17="","",Concurso!U17)) | D29: =IF($B29="","",IF(Concurso!I17="","",Concurso!I17)) | E29: =IF($B29="","",IF(Concurso!J17<>"",Concurso!J17,IF(Concurso!K17<>"",Concurso!K17,""))) | F29: =IF($B29="","",IF(Concurso!K17="","",Concurso!K17)) | G29: =IF($B29="","",Concurso!P17) | H29: =IF(OR($B29="",$F29=""),"",IF(AND($F29>=H$7,$F29<EDATE(H$7,1)),"▼","")) | I29: =IF(OR($B29="",$F29=""),"",IF(AND($F29>=I$7,$F29<EDATE(I$7,1)),"▼","")) | J29: =IF(OR($B29="",$F29=""),"",IF(AND($F29>=J$7,$F29<EDATE(J$7,1)),"▼","")) | K29: =IF(OR($B29="",$F29=""),"",IF(AND($F29>=K$7,$F29<EDATE(K$7,1)),"▼","")) | L29: =IF(OR($B29="",$F29=""),"",IF(AND($F29>=L$7,$F29<EDATE(L$7,1)),"▼","")) | M29: =IF(OR($B29="",$F29=""),"",IF(AND($F29>=M$7,$F29<EDATE(M$7,1)),"▼","")) | N29: =IF(OR($B29="",$F29=""),"",IF(AND($F29>=N$7,$F29<EDATE(N$7,1)),"▼","")) | O29: =IF(OR($B29="",$F29=""),"",IF(AND($F29>=O$7,$F29<EDATE(O$7,1)),"▼","")) | ... S29: =IF(OR($B29="",$F29=""),"",IF(AND($F29>=S$7,$F29<EDATE(S$7,1)),"▼",""))
A30: =IF($B30="","","Concurso") | B30: =IF(Concurso!B18="","",Concurso!B18) | C30: =IF($B30="","",IF(Concurso!U18="","",Concurso!U18)) | D30: =IF($B30="","",IF(Concurso!I18="","",Concurso!I18)) | E30: =IF($B30="","",IF(Concurso!J18<>"",Concurso!J18,IF(Concurso!K18<>"",Concurso!K18,""))) | F30: =IF($B30="","",IF(Concurso!K18="","",Concurso!K18)) | G30: =IF($B30="","",Concurso!P18) | H30: =IF(OR($B30="",$F30=""),"",IF(AND($F30>=H$7,$F30<EDATE(H$7,1)),"▼","")) | I30: =IF(OR($B30="",$F30=""),"",IF(AND($F30>=I$7,$F30<EDATE(I$7,1)),"▼","")) | J30: =IF(OR($B30="",$F30=""),"",IF(AND($F30>=J$7,$F30<EDATE(J$7,1)),"▼","")) | K30: =IF(OR($B30="",$F30=""),"",IF(AND($F30>=K$7,$F30<EDATE(K$7,1)),"▼","")) | L30: =IF(OR($B30="",$F30=""),"",IF(AND($F30>=L$7,$F30<EDATE(L$7,1)),"▼","")) | M30: =IF(OR($B30="",$F30=""),"",IF(AND($F30>=M$7,$F30<EDATE(M$7,1)),"▼","")) | N30: =IF(OR($B30="",$F30=""),"",IF(AND($F30>=N$7,$F30<EDATE(N$7,1)),"▼","")) | O30: =IF(OR($B30="",$F30=""),"",IF(AND($F30>=O$7,$F30<EDATE(O$7,1)),"▼","")) | ... S30: =IF(OR($B30="",$F30=""),"",IF(AND($F30>=S$7,$F30<EDATE(S$7,1)),"▼",""))
A31: =IF($B31="","","Concurso") | B31: =IF(Concurso!B19="","",Concurso!B19) | C31: =IF($B31="","",IF(Concurso!U19="","",Concurso!U19)) | D31: =IF($B31="","",IF(Concurso!I19="","",Concurso!I19)) | E31: =IF($B31="","",IF(Concurso!J19<>"",Concurso!J19,IF(Concurso!K19<>"",Concurso!K19,""))) | F31: =IF($B31="","",IF(Concurso!K19="","",Concurso!K19)) | G31: =IF($B31="","",Concurso!P19) | H31: =IF(OR($B31="",$F31=""),"",IF(AND($F31>=H$7,$F31<EDATE(H$7,1)),"▼","")) | I31: =IF(OR($B31="",$F31=""),"",IF(AND($F31>=I$7,$F31<EDATE(I$7,1)),"▼","")) | J31: =IF(OR($B31="",$F31=""),"",IF(AND($F31>=J$7,$F31<EDATE(J$7,1)),"▼","")) | K31: =IF(OR($B31="",$F31=""),"",IF(AND($F31>=K$7,$F31<EDATE(K$7,1)),"▼","")) | L31: =IF(OR($B31="",$F31=""),"",IF(AND($F31>=L$7,$F31<EDATE(L$7,1)),"▼","")) | M31: =IF(OR($B31="",$F31=""),"",IF(AND($F31>=M$7,$F31<EDATE(M$7,1)),"▼","")) | N31: =IF(OR($B31="",$F31=""),"",IF(AND($F31>=N$7,$F31<EDATE(N$7,1)),"▼","")) | O31: =IF(OR($B31="",$F31=""),"",IF(AND($F31>=O$7,$F31<EDATE(O$7,1)),"▼","")) | ... S31: =IF(OR($B31="",$F31=""),"",IF(AND($F31>=S$7,$F31<EDATE(S$7,1)),"▼",""))
A32: =IF($B32="","","Concurso") | B32: =IF(Concurso!B20="","",Concurso!B20) | C32: =IF($B32="","",IF(Concurso!U20="","",Concurso!U20)) | D32: =IF($B32="","",IF(Concurso!I20="","",Concurso!I20)) | E32: =IF($B32="","",IF(Concurso!J20<>"",Concurso!J20,IF(Concurso!K20<>"",Concurso!K20,""))) | F32: =IF($B32="","",IF(Concurso!K20="","",Concurso!K20)) | G32: =IF($B32="","",Concurso!P20) | H32: =IF(OR($B32="",$F32=""),"",IF(AND($F32>=H$7,$F32<EDATE(H$7,1)),"▼","")) | I32: =IF(OR($B32="",$F32=""),"",IF(AND($F32>=I$7,$F32<EDATE(I$7,1)),"▼","")) | J32: =IF(OR($B32="",$F32=""),"",IF(AND($F32>=J$7,$F32<EDATE(J$7,1)),"▼","")) | K32: =IF(OR($B32="",$F32=""),"",IF(AND($F32>=K$7,$F32<EDATE(K$7,1)),"▼","")) | L32: =IF(OR($B32="",$F32=""),"",IF(AND($F32>=L$7,$F32<EDATE(L$7,1)),"▼","")) | M32: =IF(OR($B32="",$F32=""),"",IF(AND($F32>=M$7,$F32<EDATE(M$7,1)),"▼","")) | N32: =IF(OR($B32="",$F32=""),"",IF(AND($F32>=N$7,$F32<EDATE(N$7,1)),"▼","")) | O32: =IF(OR($B32="",$F32=""),"",IF(AND($F32>=O$7,$F32<EDATE(O$7,1)),"▼","")) | ... S32: =IF(OR($B32="",$F32=""),"",IF(AND($F32>=S$7,$F32<EDATE(S$7,1)),"▼",""))
A33: =IF($B33="","","Concurso") | B33: =IF(Concurso!B21="","",Concurso!B21) | C33: =IF($B33="","",IF(Concurso!U21="","",Concurso!U21)) | D33: =IF($B33="","",IF(Concurso!I21="","",Concurso!I21)) | E33: =IF($B33="","",IF(Concurso!J21<>"",Concurso!J21,IF(Concurso!K21<>"",Concurso!K21,""))) | F33: =IF($B33="","",IF(Concurso!K21="","",Concurso!K21)) | G33: =IF($B33="","",Concurso!P21) | H33: =IF(OR($B33="",$F33=""),"",IF(AND($F33>=H$7,$F33<EDATE(H$7,1)),"▼","")) | I33: =IF(OR($B33="",$F33=""),"",IF(AND($F33>=I$7,$F33<EDATE(I$7,1)),"▼","")) | J33: =IF(OR($B33="",$F33=""),"",IF(AND($F33>=J$7,$F33<EDATE(J$7,1)),"▼","")) | K33: =IF(OR($B33="",$F33=""),"",IF(AND($F33>=K$7,$F33<EDATE(K$7,1)),"▼","")) | L33: =IF(OR($B33="",$F33=""),"",IF(AND($F33>=L$7,$F33<EDATE(L$7,1)),"▼","")) | M33: =IF(OR($B33="",$F33=""),"",IF(AND($F33>=M$7,$F33<EDATE(M$7,1)),"▼","")) | N33: =IF(OR($B33="",$F33=""),"",IF(AND($F33>=N$7,$F33<EDATE(N$7,1)),"▼","")) | O33: =IF(OR($B33="",$F33=""),"",IF(AND($F33>=O$7,$F33<EDATE(O$7,1)),"▼","")) | ... S33: =IF(OR($B33="",$F33=""),"",IF(AND($F33>=S$7,$F33<EDATE(S$7,1)),"▼",""))
A34: LIVROS
A35: =IF($B35="","","Livros") -> Livros | B35: =IF(Livros!B10="","",Livros!B10) -> Hábitos Atômicos (exemplo) | C35: =IF($B35="","",IF(Livros!R10="","",Livros!R10)) -> Em andamento | D35: =IF($B35="","",IF(Livros!I10="","",Livros!I10)) -> 46290 | E35: =IF($B35="","",IF(Livros!J10="","",Livros!J10)) -> 46341 | F35: ="" | G35: =IF($B35="","",Livros!M10) -> 0.375 | H35: =IF(OR($B35="",$F35=""),"",IF(AND($F35>=H$7,$F35<EDATE(H$7,1)),"▼","")) | I35: =IF(OR($B35="",$F35=""),"",IF(AND($F35>=I$7,$F35<EDATE(I$7,1)),"▼","")) | J35: =IF(OR($B35="",$F35=""),"",IF(AND($F35>=J$7,$F35<EDATE(J$7,1)),"▼","")) | K35: =IF(OR($B35="",$F35=""),"",IF(AND($F35>=K$7,$F35<EDATE(K$7,1)),"▼","")) | L35: =IF(OR($B35="",$F35=""),"",IF(AND($F35>=L$7,$F35<EDATE(L$7,1)),"▼","")) | M35: =IF(OR($B35="",$F35=""),"",IF(AND($F35>=M$7,$F35<EDATE(M$7,1)),"▼","")) | N35: =IF(OR($B35="",$F35=""),"",IF(AND($F35>=N$7,$F35<EDATE(N$7,1)),"▼","")) | O35: =IF(OR($B35="",$F35=""),"",IF(AND($F35>=O$7,$F35<EDATE(O$7,1)),"▼","")) | ... S35: =IF(OR($B35="",$F35=""),"",IF(AND($F35>=S$7,$F35<EDATE(S$7,1)),"▼",""))
A36: =IF($B36="","","Livros") | B36: =IF(Livros!B11="","",Livros!B11) | C36: =IF($B36="","",IF(Livros!R11="","",Livros!R11)) | D36: =IF($B36="","",IF(Livros!I11="","",Livros!I11)) | E36: =IF($B36="","",IF(Livros!J11="","",Livros!J11)) | F36: ="" | G36: =IF($B36="","",Livros!M11) | H36: =IF(OR($B36="",$F36=""),"",IF(AND($F36>=H$7,$F36<EDATE(H$7,1)),"▼","")) | I36: =IF(OR($B36="",$F36=""),"",IF(AND($F36>=I$7,$F36<EDATE(I$7,1)),"▼","")) | J36: =IF(OR($B36="",$F36=""),"",IF(AND($F36>=J$7,$F36<EDATE(J$7,1)),"▼","")) | K36: =IF(OR($B36="",$F36=""),"",IF(AND($F36>=K$7,$F36<EDATE(K$7,1)),"▼","")) | L36: =IF(OR($B36="",$F36=""),"",IF(AND($F36>=L$7,$F36<EDATE(L$7,1)),"▼","")) | M36: =IF(OR($B36="",$F36=""),"",IF(AND($F36>=M$7,$F36<EDATE(M$7,1)),"▼","")) | N36: =IF(OR($B36="",$F36=""),"",IF(AND($F36>=N$7,$F36<EDATE(N$7,1)),"▼","")) | O36: =IF(OR($B36="",$F36=""),"",IF(AND($F36>=O$7,$F36<EDATE(O$7,1)),"▼","")) | ... S36: =IF(OR($B36="",$F36=""),"",IF(AND($F36>=S$7,$F36<EDATE(S$7,1)),"▼",""))
A37: =IF($B37="","","Livros") | B37: =IF(Livros!B12="","",Livros!B12) | C37: =IF($B37="","",IF(Livros!R12="","",Livros!R12)) | D37: =IF($B37="","",IF(Livros!I12="","",Livros!I12)) | E37: =IF($B37="","",IF(Livros!J12="","",Livros!J12)) | F37: ="" | G37: =IF($B37="","",Livros!M12) | H37: =IF(OR($B37="",$F37=""),"",IF(AND($F37>=H$7,$F37<EDATE(H$7,1)),"▼","")) | I37: =IF(OR($B37="",$F37=""),"",IF(AND($F37>=I$7,$F37<EDATE(I$7,1)),"▼","")) | J37: =IF(OR($B37="",$F37=""),"",IF(AND($F37>=J$7,$F37<EDATE(J$7,1)),"▼","")) | K37: =IF(OR($B37="",$F37=""),"",IF(AND($F37>=K$7,$F37<EDATE(K$7,1)),"▼","")) | L37: =IF(OR($B37="",$F37=""),"",IF(AND($F37>=L$7,$F37<EDATE(L$7,1)),"▼","")) | M37: =IF(OR($B37="",$F37=""),"",IF(AND($F37>=M$7,$F37<EDATE(M$7,1)),"▼","")) | N37: =IF(OR($B37="",$F37=""),"",IF(AND($F37>=N$7,$F37<EDATE(N$7,1)),"▼","")) | O37: =IF(OR($B37="",$F37=""),"",IF(AND($F37>=O$7,$F37<EDATE(O$7,1)),"▼","")) | ... S37: =IF(OR($B37="",$F37=""),"",IF(AND($F37>=S$7,$F37<EDATE(S$7,1)),"▼",""))
A38: =IF($B38="","","Livros") | B38: =IF(Livros!B13="","",Livros!B13) | C38: =IF($B38="","",IF(Livros!R13="","",Livros!R13)) | D38: =IF($B38="","",IF(Livros!I13="","",Livros!I13)) | E38: =IF($B38="","",IF(Livros!J13="","",Livros!J13)) | F38: ="" | G38: =IF($B38="","",Livros!M13) | H38: =IF(OR($B38="",$F38=""),"",IF(AND($F38>=H$7,$F38<EDATE(H$7,1)),"▼","")) | I38: =IF(OR($B38="",$F38=""),"",IF(AND($F38>=I$7,$F38<EDATE(I$7,1)),"▼","")) | J38: =IF(OR($B38="",$F38=""),"",IF(AND($F38>=J$7,$F38<EDATE(J$7,1)),"▼","")) | K38: =IF(OR($B38="",$F38=""),"",IF(AND($F38>=K$7,$F38<EDATE(K$7,1)),"▼","")) | L38: =IF(OR($B38="",$F38=""),"",IF(AND($F38>=L$7,$F38<EDATE(L$7,1)),"▼","")) | M38: =IF(OR($B38="",$F38=""),"",IF(AND($F38>=M$7,$F38<EDATE(M$7,1)),"▼","")) | N38: =IF(OR($B38="",$F38=""),"",IF(AND($F38>=N$7,$F38<EDATE(N$7,1)),"▼","")) | O38: =IF(OR($B38="",$F38=""),"",IF(AND($F38>=O$7,$F38<EDATE(O$7,1)),"▼","")) | ... S38: =IF(OR($B38="",$F38=""),"",IF(AND($F38>=S$7,$F38<EDATE(S$7,1)),"▼",""))
A39: =IF($B39="","","Livros") | B39: =IF(Livros!B14="","",Livros!B14) | C39: =IF($B39="","",IF(Livros!R14="","",Livros!R14)) | D39: =IF($B39="","",IF(Livros!I14="","",Livros!I14)) | E39: =IF($B39="","",IF(Livros!J14="","",Livros!J14)) | F39: ="" | G39: =IF($B39="","",Livros!M14) | H39: =IF(OR($B39="",$F39=""),"",IF(AND($F39>=H$7,$F39<EDATE(H$7,1)),"▼","")) | I39: =IF(OR($B39="",$F39=""),"",IF(AND($F39>=I$7,$F39<EDATE(I$7,1)),"▼","")) | J39: =IF(OR($B39="",$F39=""),"",IF(AND($F39>=J$7,$F39<EDATE(J$7,1)),"▼","")) | K39: =IF(OR($B39="",$F39=""),"",IF(AND($F39>=K$7,$F39<EDATE(K$7,1)),"▼","")) | L39: =IF(OR($B39="",$F39=""),"",IF(AND($F39>=L$7,$F39<EDATE(L$7,1)),"▼","")) | M39: =IF(OR($B39="",$F39=""),"",IF(AND($F39>=M$7,$F39<EDATE(M$7,1)),"▼","")) | N39: =IF(OR($B39="",$F39=""),"",IF(AND($F39>=N$7,$F39<EDATE(N$7,1)),"▼","")) | O39: =IF(OR($B39="",$F39=""),"",IF(AND($F39>=O$7,$F39<EDATE(O$7,1)),"▼","")) | ... S39: =IF(OR($B39="",$F39=""),"",IF(AND($F39>=S$7,$F39<EDATE(S$7,1)),"▼",""))
A40: =IF($B40="","","Livros") | B40: =IF(Livros!B15="","",Livros!B15) | C40: =IF($B40="","",IF(Livros!R15="","",Livros!R15)) | D40: =IF($B40="","",IF(Livros!I15="","",Livros!I15)) | E40: =IF($B40="","",IF(Livros!J15="","",Livros!J15)) | F40: ="" | G40: =IF($B40="","",Livros!M15) | H40: =IF(OR($B40="",$F40=""),"",IF(AND($F40>=H$7,$F40<EDATE(H$7,1)),"▼","")) | I40: =IF(OR($B40="",$F40=""),"",IF(AND($F40>=I$7,$F40<EDATE(I$7,1)),"▼","")) | J40: =IF(OR($B40="",$F40=""),"",IF(AND($F40>=J$7,$F40<EDATE(J$7,1)),"▼","")) | K40: =IF(OR($B40="",$F40=""),"",IF(AND($F40>=K$7,$F40<EDATE(K$7,1)),"▼","")) | L40: =IF(OR($B40="",$F40=""),"",IF(AND($F40>=L$7,$F40<EDATE(L$7,1)),"▼","")) | M40: =IF(OR($B40="",$F40=""),"",IF(AND($F40>=M$7,$F40<EDATE(M$7,1)),"▼","")) | N40: =IF(OR($B40="",$F40=""),"",IF(AND($F40>=N$7,$F40<EDATE(N$7,1)),"▼","")) | O40: =IF(OR($B40="",$F40=""),"",IF(AND($F40>=O$7,$F40<EDATE(O$7,1)),"▼","")) | ... S40: =IF(OR($B40="",$F40=""),"",IF(AND($F40>=S$7,$F40<EDATE(S$7,1)),"▼",""))
A41: =IF($B41="","","Livros") | B41: =IF(Livros!B16="","",Livros!B16) | C41: =IF($B41="","",IF(Livros!R16="","",Livros!R16)) | D41: =IF($B41="","",IF(Livros!I16="","",Livros!I16)) | E41: =IF($B41="","",IF(Livros!J16="","",Livros!J16)) | F41: ="" | G41: =IF($B41="","",Livros!M16) | H41: =IF(OR($B41="",$F41=""),"",IF(AND($F41>=H$7,$F41<EDATE(H$7,1)),"▼","")) | I41: =IF(OR($B41="",$F41=""),"",IF(AND($F41>=I$7,$F41<EDATE(I$7,1)),"▼","")) | J41: =IF(OR($B41="",$F41=""),"",IF(AND($F41>=J$7,$F41<EDATE(J$7,1)),"▼","")) | K41: =IF(OR($B41="",$F41=""),"",IF(AND($F41>=K$7,$F41<EDATE(K$7,1)),"▼","")) | L41: =IF(OR($B41="",$F41=""),"",IF(AND($F41>=L$7,$F41<EDATE(L$7,1)),"▼","")) | M41: =IF(OR($B41="",$F41=""),"",IF(AND($F41>=M$7,$F41<EDATE(M$7,1)),"▼","")) | N41: =IF(OR($B41="",$F41=""),"",IF(AND($F41>=N$7,$F41<EDATE(N$7,1)),"▼","")) | O41: =IF(OR($B41="",$F41=""),"",IF(AND($F41>=O$7,$F41<EDATE(O$7,1)),"▼","")) | ... S41: =IF(OR($B41="",$F41=""),"",IF(AND($F41>=S$7,$F41<EDATE(S$7,1)),"▼",""))
A42: =IF($B42="","","Livros") | B42: =IF(Livros!B17="","",Livros!B17) | C42: =IF($B42="","",IF(Livros!R17="","",Livros!R17)) | D42: =IF($B42="","",IF(Livros!I17="","",Livros!I17)) | E42: =IF($B42="","",IF(Livros!J17="","",Livros!J17)) | F42: ="" | G42: =IF($B42="","",Livros!M17) | H42: =IF(OR($B42="",$F42=""),"",IF(AND($F42>=H$7,$F42<EDATE(H$7,1)),"▼","")) | I42: =IF(OR($B42="",$F42=""),"",IF(AND($F42>=I$7,$F42<EDATE(I$7,1)),"▼","")) | J42: =IF(OR($B42="",$F42=""),"",IF(AND($F42>=J$7,$F42<EDATE(J$7,1)),"▼","")) | K42: =IF(OR($B42="",$F42=""),"",IF(AND($F42>=K$7,$F42<EDATE(K$7,1)),"▼","")) | L42: =IF(OR($B42="",$F42=""),"",IF(AND($F42>=L$7,$F42<EDATE(L$7,1)),"▼","")) | M42: =IF(OR($B42="",$F42=""),"",IF(AND($F42>=M$7,$F42<EDATE(M$7,1)),"▼","")) | N42: =IF(OR($B42="",$F42=""),"",IF(AND($F42>=N$7,$F42<EDATE(N$7,1)),"▼","")) | O42: =IF(OR($B42="",$F42=""),"",IF(AND($F42>=O$7,$F42<EDATE(O$7,1)),"▼","")) | ... S42: =IF(OR($B42="",$F42=""),"",IF(AND($F42>=S$7,$F42<EDATE(S$7,1)),"▼",""))
A43: =IF($B43="","","Livros") | B43: =IF(Livros!B18="","",Livros!B18) | C43: =IF($B43="","",IF(Livros!R18="","",Livros!R18)) | D43: =IF($B43="","",IF(Livros!I18="","",Livros!I18)) | E43: =IF($B43="","",IF(Livros!J18="","",Livros!J18)) | F43: ="" | G43: =IF($B43="","",Livros!M18) | H43: =IF(OR($B43="",$F43=""),"",IF(AND($F43>=H$7,$F43<EDATE(H$7,1)),"▼","")) | I43: =IF(OR($B43="",$F43=""),"",IF(AND($F43>=I$7,$F43<EDATE(I$7,1)),"▼","")) | J43: =IF(OR($B43="",$F43=""),"",IF(AND($F43>=J$7,$F43<EDATE(J$7,1)),"▼","")) | K43: =IF(OR($B43="",$F43=""),"",IF(AND($F43>=K$7,$F43<EDATE(K$7,1)),"▼","")) | L43: =IF(OR($B43="",$F43=""),"",IF(AND($F43>=L$7,$F43<EDATE(L$7,1)),"▼","")) | M43: =IF(OR($B43="",$F43=""),"",IF(AND($F43>=M$7,$F43<EDATE(M$7,1)),"▼","")) | N43: =IF(OR($B43="",$F43=""),"",IF(AND($F43>=N$7,$F43<EDATE(N$7,1)),"▼","")) | O43: =IF(OR($B43="",$F43=""),"",IF(AND($F43>=O$7,$F43<EDATE(O$7,1)),"▼","")) | ... S43: =IF(OR($B43="",$F43=""),"",IF(AND($F43>=S$7,$F43<EDATE(S$7,1)),"▼",""))
A44: =IF($B44="","","Livros") | B44: =IF(Livros!B19="","",Livros!B19) | C44: =IF($B44="","",IF(Livros!R19="","",Livros!R19)) | D44: =IF($B44="","",IF(Livros!I19="","",Livros!I19)) | E44: =IF($B44="","",IF(Livros!J19="","",Livros!J19)) | F44: ="" | G44: =IF($B44="","",Livros!M19) | H44: =IF(OR($B44="",$F44=""),"",IF(AND($F44>=H$7,$F44<EDATE(H$7,1)),"▼","")) | I44: =IF(OR($B44="",$F44=""),"",IF(AND($F44>=I$7,$F44<EDATE(I$7,1)),"▼","")) | J44: =IF(OR($B44="",$F44=""),"",IF(AND($F44>=J$7,$F44<EDATE(J$7,1)),"▼","")) | K44: =IF(OR($B44="",$F44=""),"",IF(AND($F44>=K$7,$F44<EDATE(K$7,1)),"▼","")) | L44: =IF(OR($B44="",$F44=""),"",IF(AND($F44>=L$7,$F44<EDATE(L$7,1)),"▼","")) | M44: =IF(OR($B44="",$F44=""),"",IF(AND($F44>=M$7,$F44<EDATE(M$7,1)),"▼","")) | N44: =IF(OR($B44="",$F44=""),"",IF(AND($F44>=N$7,$F44<EDATE(N$7,1)),"▼","")) | O44: =IF(OR($B44="",$F44=""),"",IF(AND($F44>=O$7,$F44<EDATE(O$7,1)),"▼","")) | ... S44: =IF(OR($B44="",$F44=""),"",IF(AND($F44>=S$7,$F44<EDATE(S$7,1)),"▼",""))
A45: =IF($B45="","","Livros") | B45: =IF(Livros!B20="","",Livros!B20) | C45: =IF($B45="","",IF(Livros!R20="","",Livros!R20)) | D45: =IF($B45="","",IF(Livros!I20="","",Livros!I20)) | E45: =IF($B45="","",IF(Livros!J20="","",Livros!J20)) | F45: ="" | G45: =IF($B45="","",Livros!M20) | H45: =IF(OR($B45="",$F45=""),"",IF(AND($F45>=H$7,$F45<EDATE(H$7,1)),"▼","")) | I45: =IF(OR($B45="",$F45=""),"",IF(AND($F45>=I$7,$F45<EDATE(I$7,1)),"▼","")) | J45: =IF(OR($B45="",$F45=""),"",IF(AND($F45>=J$7,$F45<EDATE(J$7,1)),"▼","")) | K45: =IF(OR($B45="",$F45=""),"",IF(AND($F45>=K$7,$F45<EDATE(K$7,1)),"▼","")) | L45: =IF(OR($B45="",$F45=""),"",IF(AND($F45>=L$7,$F45<EDATE(L$7,1)),"▼","")) | M45: =IF(OR($B45="",$F45=""),"",IF(AND($F45>=M$7,$F45<EDATE(M$7,1)),"▼","")) | N45: =IF(OR($B45="",$F45=""),"",IF(AND($F45>=N$7,$F45<EDATE(N$7,1)),"▼","")) | O45: =IF(OR($B45="",$F45=""),"",IF(AND($F45>=O$7,$F45<EDATE(O$7,1)),"▼","")) | ... S45: =IF(OR($B45="",$F45=""),"",IF(AND($F45>=S$7,$F45<EDATE(S$7,1)),"▼",""))
A46: =IF($B46="","","Livros") | B46: =IF(Livros!B21="","",Livros!B21) | C46: =IF($B46="","",IF(Livros!R21="","",Livros!R21)) | D46: =IF($B46="","",IF(Livros!I21="","",Livros!I21)) | E46: =IF($B46="","",IF(Livros!J21="","",Livros!J21)) | F46: ="" | G46: =IF($B46="","",Livros!M21) | H46: =IF(OR($B46="",$F46=""),"",IF(AND($F46>=H$7,$F46<EDATE(H$7,1)),"▼","")) | I46: =IF(OR($B46="",$F46=""),"",IF(AND($F46>=I$7,$F46<EDATE(I$7,1)),"▼","")) | J46: =IF(OR($B46="",$F46=""),"",IF(AND($F46>=J$7,$F46<EDATE(J$7,1)),"▼","")) | K46: =IF(OR($B46="",$F46=""),"",IF(AND($F46>=K$7,$F46<EDATE(K$7,1)),"▼","")) | L46: =IF(OR($B46="",$F46=""),"",IF(AND($F46>=L$7,$F46<EDATE(L$7,1)),"▼","")) | M46: =IF(OR($B46="",$F46=""),"",IF(AND($F46>=M$7,$F46<EDATE(M$7,1)),"▼","")) | N46: =IF(OR($B46="",$F46=""),"",IF(AND($F46>=N$7,$F46<EDATE(N$7,1)),"▼","")) | O46: =IF(OR($B46="",$F46=""),"",IF(AND($F46>=O$7,$F46<EDATE(O$7,1)),"▼","")) | ... S46: =IF(OR($B46="",$F46=""),"",IF(AND($F46>=S$7,$F46<EDATE(S$7,1)),"▼",""))
A47: CURSOS IA
A48: =IF($B48="","","Cursos IA") -> Cursos IA | B48: =IF('Cursos IA'!B10="","",'Cursos IA'!B10) -> Agentes de IA na Prática (exemplo) | C48: =IF($B48="","",IF('Cursos IA'!S10="","",'Cursos IA'!S10)) -> Em andamento | D48: =IF($B48="","",IF('Cursos IA'!G10="","",'Cursos IA'!G10)) -> 46285 | E48: =IF($B48="","",IF('Cursos IA'!H10<>"",'Cursos IA'!H10,IF('Cursos IA'!I10<>"",'Cursos IA'!I10,""))) -> 46376 | F48: =IF($B48="","",IF('Cursos IA'!I10="","",'Cursos IA'!I10)) -> 46642 | G48: =IF($B48="","",'Cursos IA'!N10) -> 0.3 | H48: =IF(OR($B48="",$F48=""),"",IF(AND($F48>=H$7,$F48<EDATE(H$7,1)),"▼","")) | I48: =IF(OR($B48="",$F48=""),"",IF(AND($F48>=I$7,$F48<EDATE(I$7,1)),"▼","")) | J48: =IF(OR($B48="",$F48=""),"",IF(AND($F48>=J$7,$F48<EDATE(J$7,1)),"▼","")) | K48: =IF(OR($B48="",$F48=""),"",IF(AND($F48>=K$7,$F48<EDATE(K$7,1)),"▼","")) | L48: =IF(OR($B48="",$F48=""),"",IF(AND($F48>=L$7,$F48<EDATE(L$7,1)),"▼","")) | M48: =IF(OR($B48="",$F48=""),"",IF(AND($F48>=M$7,$F48<EDATE(M$7,1)),"▼","")) | N48: =IF(OR($B48="",$F48=""),"",IF(AND($F48>=N$7,$F48<EDATE(N$7,1)),"▼","")) | O48: =IF(OR($B48="",$F48=""),"",IF(AND($F48>=O$7,$F48<EDATE(O$7,1)),"▼","")) | ... S48: =IF(OR($B48="",$F48=""),"",IF(AND($F48>=S$7,$F48<EDATE(S$7,1)),"▼","")) -> ▼
A49: =IF($B49="","","Cursos IA") | B49: =IF('Cursos IA'!B11="","",'Cursos IA'!B11) | C49: =IF($B49="","",IF('Cursos IA'!S11="","",'Cursos IA'!S11)) | D49: =IF($B49="","",IF('Cursos IA'!G11="","",'Cursos IA'!G11)) | E49: =IF($B49="","",IF('Cursos IA'!H11<>"",'Cursos IA'!H11,IF('Cursos IA'!I11<>"",'Cursos IA'!I11,""))) | F49: =IF($B49="","",IF('Cursos IA'!I11="","",'Cursos IA'!I11)) | G49: =IF($B49="","",'Cursos IA'!N11) | H49: =IF(OR($B49="",$F49=""),"",IF(AND($F49>=H$7,$F49<EDATE(H$7,1)),"▼","")) | I49: =IF(OR($B49="",$F49=""),"",IF(AND($F49>=I$7,$F49<EDATE(I$7,1)),"▼","")) | J49: =IF(OR($B49="",$F49=""),"",IF(AND($F49>=J$7,$F49<EDATE(J$7,1)),"▼","")) | K49: =IF(OR($B49="",$F49=""),"",IF(AND($F49>=K$7,$F49<EDATE(K$7,1)),"▼","")) | L49: =IF(OR($B49="",$F49=""),"",IF(AND($F49>=L$7,$F49<EDATE(L$7,1)),"▼","")) | M49: =IF(OR($B49="",$F49=""),"",IF(AND($F49>=M$7,$F49<EDATE(M$7,1)),"▼","")) | N49: =IF(OR($B49="",$F49=""),"",IF(AND($F49>=N$7,$F49<EDATE(N$7,1)),"▼","")) | O49: =IF(OR($B49="",$F49=""),"",IF(AND($F49>=O$7,$F49<EDATE(O$7,1)),"▼","")) | ... S49: =IF(OR($B49="",$F49=""),"",IF(AND($F49>=S$7,$F49<EDATE(S$7,1)),"▼",""))
A50: =IF($B50="","","Cursos IA") | B50: =IF('Cursos IA'!B12="","",'Cursos IA'!B12) | C50: =IF($B50="","",IF('Cursos IA'!S12="","",'Cursos IA'!S12)) | D50: =IF($B50="","",IF('Cursos IA'!G12="","",'Cursos IA'!G12)) | E50: =IF($B50="","",IF('Cursos IA'!H12<>"",'Cursos IA'!H12,IF('Cursos IA'!I12<>"",'Cursos IA'!I12,""))) | F50: =IF($B50="","",IF('Cursos IA'!I12="","",'Cursos IA'!I12)) | G50: =IF($B50="","",'Cursos IA'!N12) | H50: =IF(OR($B50="",$F50=""),"",IF(AND($F50>=H$7,$F50<EDATE(H$7,1)),"▼","")) | I50: =IF(OR($B50="",$F50=""),"",IF(AND($F50>=I$7,$F50<EDATE(I$7,1)),"▼","")) | J50: =IF(OR($B50="",$F50=""),"",IF(AND($F50>=J$7,$F50<EDATE(J$7,1)),"▼","")) | K50: =IF(OR($B50="",$F50=""),"",IF(AND($F50>=K$7,$F50<EDATE(K$7,1)),"▼","")) | L50: =IF(OR($B50="",$F50=""),"",IF(AND($F50>=L$7,$F50<EDATE(L$7,1)),"▼","")) | M50: =IF(OR($B50="",$F50=""),"",IF(AND($F50>=M$7,$F50<EDATE(M$7,1)),"▼","")) | N50: =IF(OR($B50="",$F50=""),"",IF(AND($F50>=N$7,$F50<EDATE(N$7,1)),"▼","")) | O50: =IF(OR($B50="",$F50=""),"",IF(AND($F50>=O$7,$F50<EDATE(O$7,1)),"▼","")) | ... S50: =IF(OR($B50="",$F50=""),"",IF(AND($F50>=S$7,$F50<EDATE(S$7,1)),"▼",""))
A51: =IF($B51="","","Cursos IA") | B51: =IF('Cursos IA'!B13="","",'Cursos IA'!B13) | C51: =IF($B51="","",IF('Cursos IA'!S13="","",'Cursos IA'!S13)) | D51: =IF($B51="","",IF('Cursos IA'!G13="","",'Cursos IA'!G13)) | E51: =IF($B51="","",IF('Cursos IA'!H13<>"",'Cursos IA'!H13,IF('Cursos IA'!I13<>"",'Cursos IA'!I13,""))) | F51: =IF($B51="","",IF('Cursos IA'!I13="","",'Cursos IA'!I13)) | G51: =IF($B51="","",'Cursos IA'!N13) | H51: =IF(OR($B51="",$F51=""),"",IF(AND($F51>=H$7,$F51<EDATE(H$7,1)),"▼","")) | I51: =IF(OR($B51="",$F51=""),"",IF(AND($F51>=I$7,$F51<EDATE(I$7,1)),"▼","")) | J51: =IF(OR($B51="",$F51=""),"",IF(AND($F51>=J$7,$F51<EDATE(J$7,1)),"▼","")) | K51: =IF(OR($B51="",$F51=""),"",IF(AND($F51>=K$7,$F51<EDATE(K$7,1)),"▼","")) | L51: =IF(OR($B51="",$F51=""),"",IF(AND($F51>=L$7,$F51<EDATE(L$7,1)),"▼","")) | M51: =IF(OR($B51="",$F51=""),"",IF(AND($F51>=M$7,$F51<EDATE(M$7,1)),"▼","")) | N51: =IF(OR($B51="",$F51=""),"",IF(AND($F51>=N$7,$F51<EDATE(N$7,1)),"▼","")) | O51: =IF(OR($B51="",$F51=""),"",IF(AND($F51>=O$7,$F51<EDATE(O$7,1)),"▼","")) | ... S51: =IF(OR($B51="",$F51=""),"",IF(AND($F51>=S$7,$F51<EDATE(S$7,1)),"▼",""))
A52: =IF($B52="","","Cursos IA") | B52: =IF('Cursos IA'!B14="","",'Cursos IA'!B14) | C52: =IF($B52="","",IF('Cursos IA'!S14="","",'Cursos IA'!S14)) | D52: =IF($B52="","",IF('Cursos IA'!G14="","",'Cursos IA'!G14)) | E52: =IF($B52="","",IF('Cursos IA'!H14<>"",'Cursos IA'!H14,IF('Cursos IA'!I14<>"",'Cursos IA'!I14,""))) | F52: =IF($B52="","",IF('Cursos IA'!I14="","",'Cursos IA'!I14)) | G52: =IF($B52="","",'Cursos IA'!N14) | H52: =IF(OR($B52="",$F52=""),"",IF(AND($F52>=H$7,$F52<EDATE(H$7,1)),"▼","")) | I52: =IF(OR($B52="",$F52=""),"",IF(AND($F52>=I$7,$F52<EDATE(I$7,1)),"▼","")) | J52: =IF(OR($B52="",$F52=""),"",IF(AND($F52>=J$7,$F52<EDATE(J$7,1)),"▼","")) | K52: =IF(OR($B52="",$F52=""),"",IF(AND($F52>=K$7,$F52<EDATE(K$7,1)),"▼","")) | L52: =IF(OR($B52="",$F52=""),"",IF(AND($F52>=L$7,$F52<EDATE(L$7,1)),"▼","")) | M52: =IF(OR($B52="",$F52=""),"",IF(AND($F52>=M$7,$F52<EDATE(M$7,1)),"▼","")) | N52: =IF(OR($B52="",$F52=""),"",IF(AND($F52>=N$7,$F52<EDATE(N$7,1)),"▼","")) | O52: =IF(OR($B52="",$F52=""),"",IF(AND($F52>=O$7,$F52<EDATE(O$7,1)),"▼","")) | ... S52: =IF(OR($B52="",$F52=""),"",IF(AND($F52>=S$7,$F52<EDATE(S$7,1)),"▼",""))
A53: =IF($B53="","","Cursos IA") | B53: =IF('Cursos IA'!B15="","",'Cursos IA'!B15) | C53: =IF($B53="","",IF('Cursos IA'!S15="","",'Cursos IA'!S15)) | D53: =IF($B53="","",IF('Cursos IA'!G15="","",'Cursos IA'!G15)) | E53: =IF($B53="","",IF('Cursos IA'!H15<>"",'Cursos IA'!H15,IF('Cursos IA'!I15<>"",'Cursos IA'!I15,""))) | F53: =IF($B53="","",IF('Cursos IA'!I15="","",'Cursos IA'!I15)) | G53: =IF($B53="","",'Cursos IA'!N15) | H53: =IF(OR($B53="",$F53=""),"",IF(AND($F53>=H$7,$F53<EDATE(H$7,1)),"▼","")) | I53: =IF(OR($B53="",$F53=""),"",IF(AND($F53>=I$7,$F53<EDATE(I$7,1)),"▼","")) | J53: =IF(OR($B53="",$F53=""),"",IF(AND($F53>=J$7,$F53<EDATE(J$7,1)),"▼","")) | K53: =IF(OR($B53="",$F53=""),"",IF(AND($F53>=K$7,$F53<EDATE(K$7,1)),"▼","")) | L53: =IF(OR($B53="",$F53=""),"",IF(AND($F53>=L$7,$F53<EDATE(L$7,1)),"▼","")) | M53: =IF(OR($B53="",$F53=""),"",IF(AND($F53>=M$7,$F53<EDATE(M$7,1)),"▼","")) | N53: =IF(OR($B53="",$F53=""),"",IF(AND($F53>=N$7,$F53<EDATE(N$7,1)),"▼","")) | O53: =IF(OR($B53="",$F53=""),"",IF(AND($F53>=O$7,$F53<EDATE(O$7,1)),"▼","")) | ... S53: =IF(OR($B53="",$F53=""),"",IF(AND($F53>=S$7,$F53<EDATE(S$7,1)),"▼",""))
A54: =IF($B54="","","Cursos IA") | B54: =IF('Cursos IA'!B16="","",'Cursos IA'!B16) | C54: =IF($B54="","",IF('Cursos IA'!S16="","",'Cursos IA'!S16)) | D54: =IF($B54="","",IF('Cursos IA'!G16="","",'Cursos IA'!G16)) | E54: =IF($B54="","",IF('Cursos IA'!H16<>"",'Cursos IA'!H16,IF('Cursos IA'!I16<>"",'Cursos IA'!I16,""))) | F54: =IF($B54="","",IF('Cursos IA'!I16="","",'Cursos IA'!I16)) | G54: =IF($B54="","",'Cursos IA'!N16) | H54: =IF(OR($B54="",$F54=""),"",IF(AND($F54>=H$7,$F54<EDATE(H$7,1)),"▼","")) | I54: =IF(OR($B54="",$F54=""),"",IF(AND($F54>=I$7,$F54<EDATE(I$7,1)),"▼","")) | J54: =IF(OR($B54="",$F54=""),"",IF(AND($F54>=J$7,$F54<EDATE(J$7,1)),"▼","")) | K54: =IF(OR($B54="",$F54=""),"",IF(AND($F54>=K$7,$F54<EDATE(K$7,1)),"▼","")) | L54: =IF(OR($B54="",$F54=""),"",IF(AND($F54>=L$7,$F54<EDATE(L$7,1)),"▼","")) | M54: =IF(OR($B54="",$F54=""),"",IF(AND($F54>=M$7,$F54<EDATE(M$7,1)),"▼","")) | N54: =IF(OR($B54="",$F54=""),"",IF(AND($F54>=N$7,$F54<EDATE(N$7,1)),"▼","")) | O54: =IF(OR($B54="",$F54=""),"",IF(AND($F54>=O$7,$F54<EDATE(O$7,1)),"▼","")) | ... S54: =IF(OR($B54="",$F54=""),"",IF(AND($F54>=S$7,$F54<EDATE(S$7,1)),"▼",""))
A55: =IF($B55="","","Cursos IA") | B55: =IF('Cursos IA'!B17="","",'Cursos IA'!B17) | C55: =IF($B55="","",IF('Cursos IA'!S17="","",'Cursos IA'!S17)) | D55: =IF($B55="","",IF('Cursos IA'!G17="","",'Cursos IA'!G17)) | E55: =IF($B55="","",IF('Cursos IA'!H17<>"",'Cursos IA'!H17,IF('Cursos IA'!I17<>"",'Cursos IA'!I17,""))) | F55: =IF($B55="","",IF('Cursos IA'!I17="","",'Cursos IA'!I17)) | G55: =IF($B55="","",'Cursos IA'!N17) | H55: =IF(OR($B55="",$F55=""),"",IF(AND($F55>=H$7,$F55<EDATE(H$7,1)),"▼","")) | I55: =IF(OR($B55="",$F55=""),"",IF(AND($F55>=I$7,$F55<EDATE(I$7,1)),"▼","")) | J55: =IF(OR($B55="",$F55=""),"",IF(AND($F55>=J$7,$F55<EDATE(J$7,1)),"▼","")) | K55: =IF(OR($B55="",$F55=""),"",IF(AND($F55>=K$7,$F55<EDATE(K$7,1)),"▼","")) | L55: =IF(OR($B55="",$F55=""),"",IF(AND($F55>=L$7,$F55<EDATE(L$7,1)),"▼","")) | M55: =IF(OR($B55="",$F55=""),"",IF(AND($F55>=M$7,$F55<EDATE(M$7,1)),"▼","")) | N55: =IF(OR($B55="",$F55=""),"",IF(AND($F55>=N$7,$F55<EDATE(N$7,1)),"▼","")) | O55: =IF(OR($B55="",$F55=""),"",IF(AND($F55>=O$7,$F55<EDATE(O$7,1)),"▼","")) | ... S55: =IF(OR($B55="",$F55=""),"",IF(AND($F55>=S$7,$F55<EDATE(S$7,1)),"▼",""))
A56: =IF($B56="","","Cursos IA") | B56: =IF('Cursos IA'!B18="","",'Cursos IA'!B18) | C56: =IF($B56="","",IF('Cursos IA'!S18="","",'Cursos IA'!S18)) | D56: =IF($B56="","",IF('Cursos IA'!G18="","",'Cursos IA'!G18)) | E56: =IF($B56="","",IF('Cursos IA'!H18<>"",'Cursos IA'!H18,IF('Cursos IA'!I18<>"",'Cursos IA'!I18,""))) | F56: =IF($B56="","",IF('Cursos IA'!I18="","",'Cursos IA'!I18)) | G56: =IF($B56="","",'Cursos IA'!N18) | H56: =IF(OR($B56="",$F56=""),"",IF(AND($F56>=H$7,$F56<EDATE(H$7,1)),"▼","")) | I56: =IF(OR($B56="",$F56=""),"",IF(AND($F56>=I$7,$F56<EDATE(I$7,1)),"▼","")) | J56: =IF(OR($B56="",$F56=""),"",IF(AND($F56>=J$7,$F56<EDATE(J$7,1)),"▼","")) | K56: =IF(OR($B56="",$F56=""),"",IF(AND($F56>=K$7,$F56<EDATE(K$7,1)),"▼","")) | L56: =IF(OR($B56="",$F56=""),"",IF(AND($F56>=L$7,$F56<EDATE(L$7,1)),"▼","")) | M56: =IF(OR($B56="",$F56=""),"",IF(AND($F56>=M$7,$F56<EDATE(M$7,1)),"▼","")) | N56: =IF(OR($B56="",$F56=""),"",IF(AND($F56>=N$7,$F56<EDATE(N$7,1)),"▼","")) | O56: =IF(OR($B56="",$F56=""),"",IF(AND($F56>=O$7,$F56<EDATE(O$7,1)),"▼","")) | ... S56: =IF(OR($B56="",$F56=""),"",IF(AND($F56>=S$7,$F56<EDATE(S$7,1)),"▼",""))
A57: =IF($B57="","","Cursos IA") | B57: =IF('Cursos IA'!B19="","",'Cursos IA'!B19) | C57: =IF($B57="","",IF('Cursos IA'!S19="","",'Cursos IA'!S19)) | D57: =IF($B57="","",IF('Cursos IA'!G19="","",'Cursos IA'!G19)) | E57: =IF($B57="","",IF('Cursos IA'!H19<>"",'Cursos IA'!H19,IF('Cursos IA'!I19<>"",'Cursos IA'!I19,""))) | F57: =IF($B57="","",IF('Cursos IA'!I19="","",'Cursos IA'!I19)) | G57: =IF($B57="","",'Cursos IA'!N19) | H57: =IF(OR($B57="",$F57=""),"",IF(AND($F57>=H$7,$F57<EDATE(H$7,1)),"▼","")) | I57: =IF(OR($B57="",$F57=""),"",IF(AND($F57>=I$7,$F57<EDATE(I$7,1)),"▼","")) | J57: =IF(OR($B57="",$F57=""),"",IF(AND($F57>=J$7,$F57<EDATE(J$7,1)),"▼","")) | K57: =IF(OR($B57="",$F57=""),"",IF(AND($F57>=K$7,$F57<EDATE(K$7,1)),"▼","")) | L57: =IF(OR($B57="",$F57=""),"",IF(AND($F57>=L$7,$F57<EDATE(L$7,1)),"▼","")) | M57: =IF(OR($B57="",$F57=""),"",IF(AND($F57>=M$7,$F57<EDATE(M$7,1)),"▼","")) | N57: =IF(OR($B57="",$F57=""),"",IF(AND($F57>=N$7,$F57<EDATE(N$7,1)),"▼","")) | O57: =IF(OR($B57="",$F57=""),"",IF(AND($F57>=O$7,$F57<EDATE(O$7,1)),"▼","")) | ... S57: =IF(OR($B57="",$F57=""),"",IF(AND($F57>=S$7,$F57<EDATE(S$7,1)),"▼",""))
A58: =IF($B58="","","Cursos IA") | B58: =IF('Cursos IA'!B20="","",'Cursos IA'!B20) | C58: =IF($B58="","",IF('Cursos IA'!S20="","",'Cursos IA'!S20)) | D58: =IF($B58="","",IF('Cursos IA'!G20="","",'Cursos IA'!G20)) | E58: =IF($B58="","",IF('Cursos IA'!H20<>"",'Cursos IA'!H20,IF('Cursos IA'!I20<>"",'Cursos IA'!I20,""))) | F58: =IF($B58="","",IF('Cursos IA'!I20="","",'Cursos IA'!I20)) | G58: =IF($B58="","",'Cursos IA'!N20) | H58: =IF(OR($B58="",$F58=""),"",IF(AND($F58>=H$7,$F58<EDATE(H$7,1)),"▼","")) | I58: =IF(OR($B58="",$F58=""),"",IF(AND($F58>=I$7,$F58<EDATE(I$7,1)),"▼","")) | J58: =IF(OR($B58="",$F58=""),"",IF(AND($F58>=J$7,$F58<EDATE(J$7,1)),"▼","")) | K58: =IF(OR($B58="",$F58=""),"",IF(AND($F58>=K$7,$F58<EDATE(K$7,1)),"▼","")) | L58: =IF(OR($B58="",$F58=""),"",IF(AND($F58>=L$7,$F58<EDATE(L$7,1)),"▼","")) | M58: =IF(OR($B58="",$F58=""),"",IF(AND($F58>=M$7,$F58<EDATE(M$7,1)),"▼","")) | N58: =IF(OR($B58="",$F58=""),"",IF(AND($F58>=N$7,$F58<EDATE(N$7,1)),"▼","")) | O58: =IF(OR($B58="",$F58=""),"",IF(AND($F58>=O$7,$F58<EDATE(O$7,1)),"▼","")) | ... S58: =IF(OR($B58="",$F58=""),"",IF(AND($F58>=S$7,$F58<EDATE(S$7,1)),"▼",""))
A59: =IF($B59="","","Cursos IA") | B59: =IF('Cursos IA'!B21="","",'Cursos IA'!B21) | C59: =IF($B59="","",IF('Cursos IA'!S21="","",'Cursos IA'!S21)) | D59: =IF($B59="","",IF('Cursos IA'!G21="","",'Cursos IA'!G21)) | E59: =IF($B59="","",IF('Cursos IA'!H21<>"",'Cursos IA'!H21,IF('Cursos IA'!I21<>"",'Cursos IA'!I21,""))) | F59: =IF($B59="","",IF('Cursos IA'!I21="","",'Cursos IA'!I21)) | G59: =IF($B59="","",'Cursos IA'!N21) | H59: =IF(OR($B59="",$F59=""),"",IF(AND($F59>=H$7,$F59<EDATE(H$7,1)),"▼","")) | I59: =IF(OR($B59="",$F59=""),"",IF(AND($F59>=I$7,$F59<EDATE(I$7,1)),"▼","")) | J59: =IF(OR($B59="",$F59=""),"",IF(AND($F59>=J$7,$F59<EDATE(J$7,1)),"▼","")) | K59: =IF(OR($B59="",$F59=""),"",IF(AND($F59>=K$7,$F59<EDATE(K$7,1)),"▼","")) | L59: =IF(OR($B59="",$F59=""),"",IF(AND($F59>=L$7,$F59<EDATE(L$7,1)),"▼","")) | M59: =IF(OR($B59="",$F59=""),"",IF(AND($F59>=M$7,$F59<EDATE(M$7,1)),"▼","")) | N59: =IF(OR($B59="",$F59=""),"",IF(AND($F59>=N$7,$F59<EDATE(N$7,1)),"▼","")) | O59: =IF(OR($B59="",$F59=""),"",IF(AND($F59>=O$7,$F59<EDATE(O$7,1)),"▼","")) | ... S59: =IF(OR($B59="",$F59=""),"",IF(AND($F59>=S$7,$F59<EDATE(S$7,1)),"▼",""))
A60: RENDA EXTRA
A61: =IF($B61="","","Renda Extra") -> Renda Extra | B61: =IF('Renda Extra'!B10="","",'Renda Extra'!B10) -> Marketing de Afiliados do Zero (exemplo) | C61: =IF($B61="","",IF('Renda Extra'!S10="","",'Renda Extra'!S10)) -> Em andamento | D61: =IF($B61="","",IF('Renda Extra'!G10="","",'Renda Extra'!G10)) -> 46268 | E61: =IF($B61="","",IF('Renda Extra'!H10<>"",'Renda Extra'!H10,IF('Renda Extra'!I10<>"",'Renda Extra'!I10,""))) -> 46356 | F61: =IF($B61="","",IF('Renda Extra'!I10="","",'Renda Extra'!I10)) -> 46631 | G61: =IF($B61="","",'Renda Extra'!N10) -> 0.22222222 | H61: =IF(OR($B61="",$F61=""),"",IF(AND($F61>=H$7,$F61<EDATE(H$7,1)),"▼","")) | I61: =IF(OR($B61="",$F61=""),"",IF(AND($F61>=I$7,$F61<EDATE(I$7,1)),"▼","")) | J61: =IF(OR($B61="",$F61=""),"",IF(AND($F61>=J$7,$F61<EDATE(J$7,1)),"▼","")) | K61: =IF(OR($B61="",$F61=""),"",IF(AND($F61>=K$7,$F61<EDATE(K$7,1)),"▼","")) | L61: =IF(OR($B61="",$F61=""),"",IF(AND($F61>=L$7,$F61<EDATE(L$7,1)),"▼","")) | M61: =IF(OR($B61="",$F61=""),"",IF(AND($F61>=M$7,$F61<EDATE(M$7,1)),"▼","")) | N61: =IF(OR($B61="",$F61=""),"",IF(AND($F61>=N$7,$F61<EDATE(N$7,1)),"▼","")) | O61: =IF(OR($B61="",$F61=""),"",IF(AND($F61>=O$7,$F61<EDATE(O$7,1)),"▼","")) | ... S61: =IF(OR($B61="",$F61=""),"",IF(AND($F61>=S$7,$F61<EDATE(S$7,1)),"▼","")) -> ▼
A62: =IF($B62="","","Renda Extra") | B62: =IF('Renda Extra'!B11="","",'Renda Extra'!B11) | C62: =IF($B62="","",IF('Renda Extra'!S11="","",'Renda Extra'!S11)) | D62: =IF($B62="","",IF('Renda Extra'!G11="","",'Renda Extra'!G11)) | E62: =IF($B62="","",IF('Renda Extra'!H11<>"",'Renda Extra'!H11,IF('Renda Extra'!I11<>"",'Renda Extra'!I11,""))) | F62: =IF($B62="","",IF('Renda Extra'!I11="","",'Renda Extra'!I11)) | G62: =IF($B62="","",'Renda Extra'!N11) | H62: =IF(OR($B62="",$F62=""),"",IF(AND($F62>=H$7,$F62<EDATE(H$7,1)),"▼","")) | I62: =IF(OR($B62="",$F62=""),"",IF(AND($F62>=I$7,$F62<EDATE(I$7,1)),"▼","")) | J62: =IF(OR($B62="",$F62=""),"",IF(AND($F62>=J$7,$F62<EDATE(J$7,1)),"▼","")) | K62: =IF(OR($B62="",$F62=""),"",IF(AND($F62>=K$7,$F62<EDATE(K$7,1)),"▼","")) | L62: =IF(OR($B62="",$F62=""),"",IF(AND($F62>=L$7,$F62<EDATE(L$7,1)),"▼","")) | M62: =IF(OR($B62="",$F62=""),"",IF(AND($F62>=M$7,$F62<EDATE(M$7,1)),"▼","")) | N62: =IF(OR($B62="",$F62=""),"",IF(AND($F62>=N$7,$F62<EDATE(N$7,1)),"▼","")) | O62: =IF(OR($B62="",$F62=""),"",IF(AND($F62>=O$7,$F62<EDATE(O$7,1)),"▼","")) | ... S62: =IF(OR($B62="",$F62=""),"",IF(AND($F62>=S$7,$F62<EDATE(S$7,1)),"▼",""))
A63: =IF($B63="","","Renda Extra") | B63: =IF('Renda Extra'!B12="","",'Renda Extra'!B12) | C63: =IF($B63="","",IF('Renda Extra'!S12="","",'Renda Extra'!S12)) | D63: =IF($B63="","",IF('Renda Extra'!G12="","",'Renda Extra'!G12)) | E63: =IF($B63="","",IF('Renda Extra'!H12<>"",'Renda Extra'!H12,IF('Renda Extra'!I12<>"",'Renda Extra'!I12,""))) | F63: =IF($B63="","",IF('Renda Extra'!I12="","",'Renda Extra'!I12)) | G63: =IF($B63="","",'Renda Extra'!N12) | H63: =IF(OR($B63="",$F63=""),"",IF(AND($F63>=H$7,$F63<EDATE(H$7,1)),"▼","")) | I63: =IF(OR($B63="",$F63=""),"",IF(AND($F63>=I$7,$F63<EDATE(I$7,1)),"▼","")) | J63: =IF(OR($B63="",$F63=""),"",IF(AND($F63>=J$7,$F63<EDATE(J$7,1)),"▼","")) | K63: =IF(OR($B63="",$F63=""),"",IF(AND($F63>=K$7,$F63<EDATE(K$7,1)),"▼","")) | L63: =IF(OR($B63="",$F63=""),"",IF(AND($F63>=L$7,$F63<EDATE(L$7,1)),"▼","")) | M63: =IF(OR($B63="",$F63=""),"",IF(AND($F63>=M$7,$F63<EDATE(M$7,1)),"▼","")) | N63: =IF(OR($B63="",$F63=""),"",IF(AND($F63>=N$7,$F63<EDATE(N$7,1)),"▼","")) | O63: =IF(OR($B63="",$F63=""),"",IF(AND($F63>=O$7,$F63<EDATE(O$7,1)),"▼","")) | ... S63: =IF(OR($B63="",$F63=""),"",IF(AND($F63>=S$7,$F63<EDATE(S$7,1)),"▼",""))
A64: =IF($B64="","","Renda Extra") | B64: =IF('Renda Extra'!B13="","",'Renda Extra'!B13) | C64: =IF($B64="","",IF('Renda Extra'!S13="","",'Renda Extra'!S13)) | D64: =IF($B64="","",IF('Renda Extra'!G13="","",'Renda Extra'!G13)) | E64: =IF($B64="","",IF('Renda Extra'!H13<>"",'Renda Extra'!H13,IF('Renda Extra'!I13<>"",'Renda Extra'!I13,""))) | F64: =IF($B64="","",IF('Renda Extra'!I13="","",'Renda Extra'!I13)) | G64: =IF($B64="","",'Renda Extra'!N13) | H64: =IF(OR($B64="",$F64=""),"",IF(AND($F64>=H$7,$F64<EDATE(H$7,1)),"▼","")) | I64: =IF(OR($B64="",$F64=""),"",IF(AND($F64>=I$7,$F64<EDATE(I$7,1)),"▼","")) | J64: =IF(OR($B64="",$F64=""),"",IF(AND($F64>=J$7,$F64<EDATE(J$7,1)),"▼","")) | K64: =IF(OR($B64="",$F64=""),"",IF(AND($F64>=K$7,$F64<EDATE(K$7,1)),"▼","")) | L64: =IF(OR($B64="",$F64=""),"",IF(AND($F64>=L$7,$F64<EDATE(L$7,1)),"▼","")) | M64: =IF(OR($B64="",$F64=""),"",IF(AND($F64>=M$7,$F64<EDATE(M$7,1)),"▼","")) | N64: =IF(OR($B64="",$F64=""),"",IF(AND($F64>=N$7,$F64<EDATE(N$7,1)),"▼","")) | O64: =IF(OR($B64="",$F64=""),"",IF(AND($F64>=O$7,$F64<EDATE(O$7,1)),"▼","")) | ... S64: =IF(OR($B64="",$F64=""),"",IF(AND($F64>=S$7,$F64<EDATE(S$7,1)),"▼",""))
A65: =IF($B65="","","Renda Extra") | B65: =IF('Renda Extra'!B14="","",'Renda Extra'!B14) | C65: =IF($B65="","",IF('Renda Extra'!S14="","",'Renda Extra'!S14)) | D65: =IF($B65="","",IF('Renda Extra'!G14="","",'Renda Extra'!G14)) | E65: =IF($B65="","",IF('Renda Extra'!H14<>"",'Renda Extra'!H14,IF('Renda Extra'!I14<>"",'Renda Extra'!I14,""))) | F65: =IF($B65="","",IF('Renda Extra'!I14="","",'Renda Extra'!I14)) | G65: =IF($B65="","",'Renda Extra'!N14) | H65: =IF(OR($B65="",$F65=""),"",IF(AND($F65>=H$7,$F65<EDATE(H$7,1)),"▼","")) | I65: =IF(OR($B65="",$F65=""),"",IF(AND($F65>=I$7,$F65<EDATE(I$7,1)),"▼","")) | J65: =IF(OR($B65="",$F65=""),"",IF(AND($F65>=J$7,$F65<EDATE(J$7,1)),"▼","")) | K65: =IF(OR($B65="",$F65=""),"",IF(AND($F65>=K$7,$F65<EDATE(K$7,1)),"▼","")) | L65: =IF(OR($B65="",$F65=""),"",IF(AND($F65>=L$7,$F65<EDATE(L$7,1)),"▼","")) | M65: =IF(OR($B65="",$F65=""),"",IF(AND($F65>=M$7,$F65<EDATE(M$7,1)),"▼","")) | N65: =IF(OR($B65="",$F65=""),"",IF(AND($F65>=N$7,$F65<EDATE(N$7,1)),"▼","")) | O65: =IF(OR($B65="",$F65=""),"",IF(AND($F65>=O$7,$F65<EDATE(O$7,1)),"▼","")) | ... S65: =IF(OR($B65="",$F65=""),"",IF(AND($F65>=S$7,$F65<EDATE(S$7,1)),"▼",""))
A66: =IF($B66="","","Renda Extra") | B66: =IF('Renda Extra'!B15="","",'Renda Extra'!B15) | C66: =IF($B66="","",IF('Renda Extra'!S15="","",'Renda Extra'!S15)) | D66: =IF($B66="","",IF('Renda Extra'!G15="","",'Renda Extra'!G15)) | E66: =IF($B66="","",IF('Renda Extra'!H15<>"",'Renda Extra'!H15,IF('Renda Extra'!I15<>"",'Renda Extra'!I15,""))) | F66: =IF($B66="","",IF('Renda Extra'!I15="","",'Renda Extra'!I15)) | G66: =IF($B66="","",'Renda Extra'!N15) | H66: =IF(OR($B66="",$F66=""),"",IF(AND($F66>=H$7,$F66<EDATE(H$7,1)),"▼","")) | I66: =IF(OR($B66="",$F66=""),"",IF(AND($F66>=I$7,$F66<EDATE(I$7,1)),"▼","")) | J66: =IF(OR($B66="",$F66=""),"",IF(AND($F66>=J$7,$F66<EDATE(J$7,1)),"▼","")) | K66: =IF(OR($B66="",$F66=""),"",IF(AND($F66>=K$7,$F66<EDATE(K$7,1)),"▼","")) | L66: =IF(OR($B66="",$F66=""),"",IF(AND($F66>=L$7,$F66<EDATE(L$7,1)),"▼","")) | M66: =IF(OR($B66="",$F66=""),"",IF(AND($F66>=M$7,$F66<EDATE(M$7,1)),"▼","")) | N66: =IF(OR($B66="",$F66=""),"",IF(AND($F66>=N$7,$F66<EDATE(N$7,1)),"▼","")) | O66: =IF(OR($B66="",$F66=""),"",IF(AND($F66>=O$7,$F66<EDATE(O$7,1)),"▼","")) | ... S66: =IF(OR($B66="",$F66=""),"",IF(AND($F66>=S$7,$F66<EDATE(S$7,1)),"▼",""))
A67: =IF($B67="","","Renda Extra") | B67: =IF('Renda Extra'!B16="","",'Renda Extra'!B16) | C67: =IF($B67="","",IF('Renda Extra'!S16="","",'Renda Extra'!S16)) | D67: =IF($B67="","",IF('Renda Extra'!G16="","",'Renda Extra'!G16)) | E67: =IF($B67="","",IF('Renda Extra'!H16<>"",'Renda Extra'!H16,IF('Renda Extra'!I16<>"",'Renda Extra'!I16,""))) | F67: =IF($B67="","",IF('Renda Extra'!I16="","",'Renda Extra'!I16)) | G67: =IF($B67="","",'Renda Extra'!N16) | H67: =IF(OR($B67="",$F67=""),"",IF(AND($F67>=H$7,$F67<EDATE(H$7,1)),"▼","")) | I67: =IF(OR($B67="",$F67=""),"",IF(AND($F67>=I$7,$F67<EDATE(I$7,1)),"▼","")) | J67: =IF(OR($B67="",$F67=""),"",IF(AND($F67>=J$7,$F67<EDATE(J$7,1)),"▼","")) | K67: =IF(OR($B67="",$F67=""),"",IF(AND($F67>=K$7,$F67<EDATE(K$7,1)),"▼","")) | L67: =IF(OR($B67="",$F67=""),"",IF(AND($F67>=L$7,$F67<EDATE(L$7,1)),"▼","")) | M67: =IF(OR($B67="",$F67=""),"",IF(AND($F67>=M$7,$F67<EDATE(M$7,1)),"▼","")) | N67: =IF(OR($B67="",$F67=""),"",IF(AND($F67>=N$7,$F67<EDATE(N$7,1)),"▼","")) | O67: =IF(OR($B67="",$F67=""),"",IF(AND($F67>=O$7,$F67<EDATE(O$7,1)),"▼","")) | ... S67: =IF(OR($B67="",$F67=""),"",IF(AND($F67>=S$7,$F67<EDATE(S$7,1)),"▼",""))
A68: =IF($B68="","","Renda Extra") | B68: =IF('Renda Extra'!B17="","",'Renda Extra'!B17) | C68: =IF($B68="","",IF('Renda Extra'!S17="","",'Renda Extra'!S17)) | D68: =IF($B68="","",IF('Renda Extra'!G17="","",'Renda Extra'!G17)) | E68: =IF($B68="","",IF('Renda Extra'!H17<>"",'Renda Extra'!H17,IF('Renda Extra'!I17<>"",'Renda Extra'!I17,""))) | F68: =IF($B68="","",IF('Renda Extra'!I17="","",'Renda Extra'!I17)) | G68: =IF($B68="","",'Renda Extra'!N17) | H68: =IF(OR($B68="",$F68=""),"",IF(AND($F68>=H$7,$F68<EDATE(H$7,1)),"▼","")) | I68: =IF(OR($B68="",$F68=""),"",IF(AND($F68>=I$7,$F68<EDATE(I$7,1)),"▼","")) | J68: =IF(OR($B68="",$F68=""),"",IF(AND($F68>=J$7,$F68<EDATE(J$7,1)),"▼","")) | K68: =IF(OR($B68="",$F68=""),"",IF(AND($F68>=K$7,$F68<EDATE(K$7,1)),"▼","")) | L68: =IF(OR($B68="",$F68=""),"",IF(AND($F68>=L$7,$F68<EDATE(L$7,1)),"▼","")) | M68: =IF(OR($B68="",$F68=""),"",IF(AND($F68>=M$7,$F68<EDATE(M$7,1)),"▼","")) | N68: =IF(OR($B68="",$F68=""),"",IF(AND($F68>=N$7,$F68<EDATE(N$7,1)),"▼","")) | O68: =IF(OR($B68="",$F68=""),"",IF(AND($F68>=O$7,$F68<EDATE(O$7,1)),"▼","")) | ... S68: =IF(OR($B68="",$F68=""),"",IF(AND($F68>=S$7,$F68<EDATE(S$7,1)),"▼",""))
A69: =IF($B69="","","Renda Extra") | B69: =IF('Renda Extra'!B18="","",'Renda Extra'!B18) | C69: =IF($B69="","",IF('Renda Extra'!S18="","",'Renda Extra'!S18)) | D69: =IF($B69="","",IF('Renda Extra'!G18="","",'Renda Extra'!G18)) | E69: =IF($B69="","",IF('Renda Extra'!H18<>"",'Renda Extra'!H18,IF('Renda Extra'!I18<>"",'Renda Extra'!I18,""))) | F69: =IF($B69="","",IF('Renda Extra'!I18="","",'Renda Extra'!I18)) | G69: =IF($B69="","",'Renda Extra'!N18) | H69: =IF(OR($B69="",$F69=""),"",IF(AND($F69>=H$7,$F69<EDATE(H$7,1)),"▼","")) | I69: =IF(OR($B69="",$F69=""),"",IF(AND($F69>=I$7,$F69<EDATE(I$7,1)),"▼","")) | J69: =IF(OR($B69="",$F69=""),"",IF(AND($F69>=J$7,$F69<EDATE(J$7,1)),"▼","")) | K69: =IF(OR($B69="",$F69=""),"",IF(AND($F69>=K$7,$F69<EDATE(K$7,1)),"▼","")) | L69: =IF(OR($B69="",$F69=""),"",IF(AND($F69>=L$7,$F69<EDATE(L$7,1)),"▼","")) | M69: =IF(OR($B69="",$F69=""),"",IF(AND($F69>=M$7,$F69<EDATE(M$7,1)),"▼","")) | N69: =IF(OR($B69="",$F69=""),"",IF(AND($F69>=N$7,$F69<EDATE(N$7,1)),"▼","")) | O69: =IF(OR($B69="",$F69=""),"",IF(AND($F69>=O$7,$F69<EDATE(O$7,1)),"▼","")) | ... S69: =IF(OR($B69="",$F69=""),"",IF(AND($F69>=S$7,$F69<EDATE(S$7,1)),"▼",""))
A70: =IF($B70="","","Renda Extra") | B70: =IF('Renda Extra'!B19="","",'Renda Extra'!B19) | C70: =IF($B70="","",IF('Renda Extra'!S19="","",'Renda Extra'!S19)) | D70: =IF($B70="","",IF('Renda Extra'!G19="","",'Renda Extra'!G19)) | E70: =IF($B70="","",IF('Renda Extra'!H19<>"",'Renda Extra'!H19,IF('Renda Extra'!I19<>"",'Renda Extra'!I19,""))) | F70: =IF($B70="","",IF('Renda Extra'!I19="","",'Renda Extra'!I19)) | G70: =IF($B70="","",'Renda Extra'!N19) | H70: =IF(OR($B70="",$F70=""),"",IF(AND($F70>=H$7,$F70<EDATE(H$7,1)),"▼","")) | I70: =IF(OR($B70="",$F70=""),"",IF(AND($F70>=I$7,$F70<EDATE(I$7,1)),"▼","")) | J70: =IF(OR($B70="",$F70=""),"",IF(AND($F70>=J$7,$F70<EDATE(J$7,1)),"▼","")) | K70: =IF(OR($B70="",$F70=""),"",IF(AND($F70>=K$7,$F70<EDATE(K$7,1)),"▼","")) | L70: =IF(OR($B70="",$F70=""),"",IF(AND($F70>=L$7,$F70<EDATE(L$7,1)),"▼","")) | M70: =IF(OR($B70="",$F70=""),"",IF(AND($F70>=M$7,$F70<EDATE(M$7,1)),"▼","")) | N70: =IF(OR($B70="",$F70=""),"",IF(AND($F70>=N$7,$F70<EDATE(N$7,1)),"▼","")) | O70: =IF(OR($B70="",$F70=""),"",IF(AND($F70>=O$7,$F70<EDATE(O$7,1)),"▼","")) | ... S70: =IF(OR($B70="",$F70=""),"",IF(AND($F70>=S$7,$F70<EDATE(S$7,1)),"▼",""))
A71: =IF($B71="","","Renda Extra") | B71: =IF('Renda Extra'!B20="","",'Renda Extra'!B20) | C71: =IF($B71="","",IF('Renda Extra'!S20="","",'Renda Extra'!S20)) | D71: =IF($B71="","",IF('Renda Extra'!G20="","",'Renda Extra'!G20)) | E71: =IF($B71="","",IF('Renda Extra'!H20<>"",'Renda Extra'!H20,IF('Renda Extra'!I20<>"",'Renda Extra'!I20,""))) | F71: =IF($B71="","",IF('Renda Extra'!I20="","",'Renda Extra'!I20)) | G71: =IF($B71="","",'Renda Extra'!N20) | H71: =IF(OR($B71="",$F71=""),"",IF(AND($F71>=H$7,$F71<EDATE(H$7,1)),"▼","")) | I71: =IF(OR($B71="",$F71=""),"",IF(AND($F71>=I$7,$F71<EDATE(I$7,1)),"▼","")) | J71: =IF(OR($B71="",$F71=""),"",IF(AND($F71>=J$7,$F71<EDATE(J$7,1)),"▼","")) | K71: =IF(OR($B71="",$F71=""),"",IF(AND($F71>=K$7,$F71<EDATE(K$7,1)),"▼","")) | L71: =IF(OR($B71="",$F71=""),"",IF(AND($F71>=L$7,$F71<EDATE(L$7,1)),"▼","")) | M71: =IF(OR($B71="",$F71=""),"",IF(AND($F71>=M$7,$F71<EDATE(M$7,1)),"▼","")) | N71: =IF(OR($B71="",$F71=""),"",IF(AND($F71>=N$7,$F71<EDATE(N$7,1)),"▼","")) | O71: =IF(OR($B71="",$F71=""),"",IF(AND($F71>=O$7,$F71<EDATE(O$7,1)),"▼","")) | ... S71: =IF(OR($B71="",$F71=""),"",IF(AND($F71>=S$7,$F71<EDATE(S$7,1)),"▼",""))
A72: =IF($B72="","","Renda Extra") | B72: =IF('Renda Extra'!B21="","",'Renda Extra'!B21) | C72: =IF($B72="","",IF('Renda Extra'!S21="","",'Renda Extra'!S21)) | D72: =IF($B72="","",IF('Renda Extra'!G21="","",'Renda Extra'!G21)) | E72: =IF($B72="","",IF('Renda Extra'!H21<>"",'Renda Extra'!H21,IF('Renda Extra'!I21<>"",'Renda Extra'!I21,""))) | F72: =IF($B72="","",IF('Renda Extra'!I21="","",'Renda Extra'!I21)) | G72: =IF($B72="","",'Renda Extra'!N21) | H72: =IF(OR($B72="",$F72=""),"",IF(AND($F72>=H$7,$F72<EDATE(H$7,1)),"▼","")) | I72: =IF(OR($B72="",$F72=""),"",IF(AND($F72>=I$7,$F72<EDATE(I$7,1)),"▼","")) | J72: =IF(OR($B72="",$F72=""),"",IF(AND($F72>=J$7,$F72<EDATE(J$7,1)),"▼","")) | K72: =IF(OR($B72="",$F72=""),"",IF(AND($F72>=K$7,$F72<EDATE(K$7,1)),"▼","")) | L72: =IF(OR($B72="",$F72=""),"",IF(AND($F72>=L$7,$F72<EDATE(L$7,1)),"▼","")) | M72: =IF(OR($B72="",$F72=""),"",IF(AND($F72>=M$7,$F72<EDATE(M$7,1)),"▼","")) | N72: =IF(OR($B72="",$F72=""),"",IF(AND($F72>=N$7,$F72<EDATE(N$7,1)),"▼","")) | O72: =IF(OR($B72="",$F72=""),"",IF(AND($F72>=O$7,$F72<EDATE(O$7,1)),"▼","")) | ... S72: =IF(OR($B72="",$F72=""),"",IF(AND($F72>=S$7,$F72<EDATE(S$7,1)),"▼",""))

Sheet Metas de Estudo
A1: METAS DE ESTUDO
A2: Defina metas mensais de horas, acompanhe o ritmo e veja seu mapa de calor | N2: ← Voltar ao Início
B5: Mês de referência: | C5: 46296 | D5: 1º dia (auto): | E5: =DATE(YEAR($C$5),MONTH($C$5),1) -> 46296 | F5: % do mês decorrido: | G5: =MAX(0,MIN(1,(TODAY()-$E$5+1)/(EOMONTH($E$5,0)-$E$5+1))) -> 0.096774194 | H5: ← digite qualquer data do mês
B7: HORAS NO MÊS | D7: META DO MÊS | F7: % DA META | G7: DIAS ESTUDADOS
B8: =D18 -> 4.5 | D8: =C18 -> 73 | F8: =E18 -> 0.061643836 | G8: =COUNTIF(J14:P14,">0")+COUNTIF(J16:P16,">0")+COUNTIF(J18:P18,">0")+COUNTIF(J20:P20,">0")+COUNTIF(J22:P22,">0")+COUNTIF(J24:P24,">0") -> 3
B11: METAS POR CATEGORIA | J11: MAPA DE CALOR DO MÊS
B12: Categoria | C12: Meta (h) | D12: Realizado (h) | E12: % da meta | F12: Progresso | G12: Faltam (h) | H12: Ritmo | J12: Seg | K12: Ter | L12: Qua | M12: Qui | N12: Sex | O12: Sáb | P12: Dom
B13: =Listas!$E$6 -> Pós-graduação | C13: 20 | D13: =SUMIFS('Diário de Estudo'!$D$7:$D$506,'Diário de Estudo'!$B$7:$B$506,$B13,'Diário de Estudo'!$A$7:$A$506,">="&$E$5,'Diário de Estudo'!$A$7:$A$506,"<"&EDATE($E$5,1)) -> 2 | E13: =IF(C13=0,0,D13/C13) -> 0.1 | F13: =REPT("█",MIN(10,ROUND(E13*10,0)))&REPT("░",10-MIN(10,ROUND(E13*10,0))) -> █░░░░░░░░░ | G13: =MAX(0,C13-D13) -> 18 | H13: =IF(C13=0,"—",IF(D13>=C13,"Meta batida",IF(D13>=C13*$G$5,"No ritmo","Abaixo do ritmo"))) -> No ritmo | J13: =IF(MONTH($E$5-WEEKDAY($E$5,2)+1+0)=MONTH($E$5),$E$5-WEEKDAY($E$5,2)+1+0,"") | K13: =IF(MONTH($E$5-WEEKDAY($E$5,2)+1+1)=MONTH($E$5),$E$5-WEEKDAY($E$5,2)+1+1,"") | L13: =IF(MONTH($E$5-WEEKDAY($E$5,2)+1+2)=MONTH($E$5),$E$5-WEEKDAY($E$5,2)+1+2,"") | M13: =IF(MONTH($E$5-WEEKDAY($E$5,2)+1+3)=MONTH($E$5),$E$5-WEEKDAY($E$5,2)+1+3,"") -> 46296 | N13: =IF(MONTH($E$5-WEEKDAY($E$5,2)+1+4)=MONTH($E$5),$E$5-WEEKDAY($E$5,2)+1+4,"") -> 46297 | O13: =IF(MONTH($E$5-WEEKDAY($E$5,2)+1+5)=MONTH($E$5),$E$5-WEEKDAY($E$5,2)+1+5,"") -> 46298 | P13: =IF(MONTH($E$5-WEEKDAY($E$5,2)+1+6)=MONTH($E$5),$E$5-WEEKDAY($E$5,2)+1+6,"") -> 46299
B14: =Listas!$E$7 -> Concurso | C14: 20 | D14: =SUMIFS('Diário de Estudo'!$D$7:$D$506,'Diário de Estudo'!$B$7:$B$506,$B14,'Diário de Estudo'!$A$7:$A$506,">="&$E$5,'Diário de Estudo'!$A$7:$A$506,"<"&EDATE($E$5,1)) -> 0 | E14: =IF(C14=0,0,D14/C14) -> 0 | F14: =REPT("█",MIN(10,ROUND(E14*10,0)))&REPT("░",10-MIN(10,ROUND(E14*10,0))) -> ░░░░░░░░░░ | G14: =MAX(0,C14-D14) -> 20 | H14: =IF(C14=0,"—",IF(D14>=C14,"Meta batida",IF(D14>=C14*$G$5,"No ritmo","Abaixo do ritmo"))) -> Abaixo do ritmo | J14: =IF(J13="","",SUMIFS('Diário de Estudo'!$D$7:$D$506,'Diário de Estudo'!$A$7:$A$506,J13)) | K14: =IF(K13="","",SUMIFS('Diário de Estudo'!$D$7:$D$506,'Diário de Estudo'!$A$7:$A$506,K13)) | L14: =IF(L13="","",SUMIFS('Diário de Estudo'!$D$7:$D$506,'Diário de Estudo'!$A$7:$A$506,L13)) | M14: =IF(M13="","",SUMIFS('Diário de Estudo'!$D$7:$D$506,'Diário de Estudo'!$A$7:$A$506,M13)) -> 2 | N14: =IF(N13="","",SUMIFS('Diário de Estudo'!$D$7:$D$506,'Diário de Estudo'!$A$7:$A$506,N13)) -> 1.5 | O14: =IF(O13="","",SUMIFS('Diário de Estudo'!$D$7:$D$506,'Diário de Estudo'!$A$7:$A$506,O13)) -> 1 | P14: =IF(P13="","",SUMIFS('Diário de Estudo'!$D$7:$D$506,'Diário de Estudo'!$A$7:$A$506,P13)) -> 0
B15: =Listas!$E$8 -> Livros | C15: 8 | D15: =SUMIFS('Diário de Estudo'!$D$7:$D$506,'Diário de Estudo'!$B$7:$B$506,$B15,'Diário de Estudo'!$A$7:$A$506,">="&$E$5,'Diário de Estudo'!$A$7:$A$506,"<"&EDATE($E$5,1)) -> 1 | E15: =IF(C15=0,0,D15/C15) -> 0.125 | F15: =REPT("█",MIN(10,ROUND(E15*10,0)))&REPT("░",10-MIN(10,ROUND(E15*10,0))) -> █░░░░░░░░░ | G15: =MAX(0,C15-D15) -> 7 | H15: =IF(C15=0,"—",IF(D15>=C15,"Meta batida",IF(D15>=C15*$G$5,"No ritmo","Abaixo do ritmo"))) -> No ritmo | J15: =IF(MONTH($E$5-WEEKDAY($E$5,2)+1+7)=MONTH($E$5),$E$5-WEEKDAY($E$5,2)+1+7,"") -> 46300 | K15: =IF(MONTH($E$5-WEEKDAY($E$5,2)+1+8)=MONTH($E$5),$E$5-WEEKDAY($E$5,2)+1+8,"") -> 46301 | L15: =IF(MONTH($E$5-WEEKDAY($E$5,2)+1+9)=MONTH($E$5),$E$5-WEEKDAY($E$5,2)+1+9,"") -> 46302 | M15: =IF(MONTH($E$5-WEEKDAY($E$5,2)+1+10)=MONTH($E$5),$E$5-WEEKDAY($E$5,2)+1+10,"") -> 46303 | N15: =IF(MONTH($E$5-WEEKDAY($E$5,2)+1+11)=MONTH($E$5),$E$5-WEEKDAY($E$5,2)+1+11,"") -> 46304 | O15: =IF(MONTH($E$5-WEEKDAY($E$5,2)+1+12)=MONTH($E$5),$E$5-WEEKDAY($E$5,2)+1+12,"") -> 46305 | P15: =IF(MONTH($E$5-WEEKDAY($E$5,2)+1+13)=MONTH($E$5),$E$5-WEEKDAY($E$5,2)+1+13,"") -> 46306
B16: =Listas!$E$9 -> Cursos IA | C16: 15 | D16: =SUMIFS('Diário de Estudo'!$D$7:$D$506,'Diário de Estudo'!$B$7:$B$506,$B16,'Diário de Estudo'!$A$7:$A$506,">="&$E$5,'Diário de Estudo'!$A$7:$A$506,"<"&EDATE($E$5,1)) -> 1.5 | E16: =IF(C16=0,0,D16/C16) -> 0.1 | F16: =REPT("█",MIN(10,ROUND(E16*10,0)))&REPT("░",10-MIN(10,ROUND(E16*10,0))) -> █░░░░░░░░░ | G16: =MAX(0,C16-D16) -> 13.5 | H16: =IF(C16=0,"—",IF(D16>=C16,"Meta batida",IF(D16>=C16*$G$5,"No ritmo","Abaixo do ritmo"))) -> No ritmo | J16: =IF(J15="","",SUMIFS('Diário de Estudo'!$D$7:$D$506,'Diário de Estudo'!$A$7:$A$506,J15)) -> 0 | K16: =IF(K15="","",SUMIFS('Diário de Estudo'!$D$7:$D$506,'Diário de Estudo'!$A$7:$A$506,K15)) -> 0 | L16: =IF(L15="","",SUMIFS('Diário de Estudo'!$D$7:$D$506,'Diário de Estudo'!$A$7:$A$506,L15)) -> 0 | M16: =IF(M15="","",SUMIFS('Diário de Estudo'!$D$7:$D$506,'Diário de Estudo'!$A$7:$A$506,M15)) -> 0 | N16: =IF(N15="","",SUMIFS('Diário de Estudo'!$D$7:$D$506,'Diário de Estudo'!$A$7:$A$506,N15)) -> 0 | O16: =IF(O15="","",SUMIFS('Diário de Estudo'!$D$7:$D$506,'Diário de Estudo'!$A$7:$A$506,O15)) -> 0 | P16: =IF(P15="","",SUMIFS('Diário de Estudo'!$D$7:$D$506,'Diário de Estudo'!$A$7:$A$506,P15)) -> 0
B17: =Listas!$E$10 -> Renda Extra | C17: 10 | D17: =SUMIFS('Diário de Estudo'!$D$7:$D$506,'Diário de Estudo'!$B$7:$B$506,$B17,'Diário de Estudo'!$A$7:$A$506,">="&$E$5,'Diário de Estudo'!$A$7:$A$506,"<"&EDATE($E$5,1)) -> 0 | E17: =IF(C17=0,0,D17/C17) -> 0 | F17: =REPT("█",MIN(10,ROUND(E17*10,0)))&REPT("░",10-MIN(10,ROUND(E17*10,0))) -> ░░░░░░░░░░ | G17: =MAX(0,C17-D17) -> 10 | H17: =IF(C17=0,"—",IF(D17>=C17,"Meta batida",IF(D17>=C17*$G$5,"No ritmo","Abaixo do ritmo"))) -> Abaixo do ritmo | J17: =IF(MONTH($E$5-WEEKDAY($E$5,2)+1+14)=MONTH($E$5),$E$5-WEEKDAY($E$5,2)+1+14,"") -> 46307 | K17: =IF(MONTH($E$5-WEEKDAY($E$5,2)+1+15)=MONTH($E$5),$E$5-WEEKDAY($E$5,2)+1+15,"") -> 46308 | L17: =IF(MONTH($E$5-WEEKDAY($E$5,2)+1+16)=MONTH($E$5),$E$5-WEEKDAY($E$5,2)+1+16,"") -> 46309 | M17: =IF(MONTH($E$5-WEEKDAY($E$5,2)+1+17)=MONTH($E$5),$E$5-WEEKDAY($E$5,2)+1+17,"") -> 46310 | N17: =IF(MONTH($E$5-WEEKDAY($E$5,2)+1+18)=MONTH($E$5),$E$5-WEEKDAY($E$5,2)+1+18,"") -> 46311 | O17: =IF(MONTH($E$5-WEEKDAY($E$5,2)+1+19)=MONTH($E$5),$E$5-WEEKDAY($E$5,2)+1+19,"") -> 46312 | P17: =IF(MONTH($E$5-WEEKDAY($E$5,2)+1+20)=MONTH($E$5),$E$5-WEEKDAY($E$5,2)+1+20,"") -> 46313
B18: TOTAL | C18: =SUM(C13:C17) -> 73 | D18: =SUM(D13:D17) -> 4.5 | E18: =IF(C18=0,0,D18/C18) -> 0.061643836 | F18: =REPT("█",MIN(10,ROUND(E18*10,0)))&REPT("░",10-MIN(10,ROUND(E18*10,0))) -> █░░░░░░░░░ | G18: =MAX(0,C18-D18) -> 68.5 | H18: =IF(C18=0,"—",IF(D18>=C18,"Meta batida",IF(D18>=C18*$G$5,"No ritmo","Abaixo do ritmo"))) -> Abaixo do ritmo | J18: =IF(J17="","",SUMIFS('Diário de Estudo'!$D$7:$D$506,'Diário de Estudo'!$A$7:$A$506,J17)) -> 0 | K18: =IF(K17="","",SUMIFS('Diário de Estudo'!$D$7:$D$506,'Diário de Estudo'!$A$7:$A$506,K17)) -> 0 | L18: =IF(L17="","",SUMIFS('Diário de Estudo'!$D$7:$D$506,'Diário de Estudo'!$A$7:$A$506,L17)) -> 0 | M18: =IF(M17="","",SUMIFS('Diário de Estudo'!$D$7:$D$506,'Diário de Estudo'!$A$7:$A$506,M17)) -> 0 | N18: =IF(N17="","",SUMIFS('Diário de Estudo'!$D$7:$D$506,'Diário de Estudo'!$A$7:$A$506,N17)) -> 0 | O18: =IF(O17="","",SUMIFS('Diário de Estudo'!$D$7:$D$506,'Diário de Estudo'!$A$7:$A$506,O17)) -> 0 | P18: =IF(P17="","",SUMIFS('Diário de Estudo'!$D$7:$D$506,'Diário de Estudo'!$A$7:$A$506,P17)) -> 0
J19: =IF(MONTH($E$5-WEEKDAY($E$5,2)+1+21)=MONTH($E$5),$E$5-WEEKDAY($E$5,2)+1+21,"") -> 46314 | K19: =IF(MONTH($E$5-WEEKDAY($E$5,2)+1+22)=MONTH($E$5),$E$5-WEEKDAY($E$5,2)+1+22,"") -> 46315 | L19: =IF(MONTH($E$5-WEEKDAY($E$5,2)+1+23)=MONTH($E$5),$E$5-WEEKDAY($E$5,2)+1+23,"") -> 46316 | M19: =IF(MONTH($E$5-WEEKDAY($E$5,2)+1+24)=MONTH($E$5),$E$5-WEEKDAY($E$5,2)+1+24,"") -> 46317 | N19: =IF(MONTH($E$5-WEEKDAY($E$5,2)+1+25)=MONTH($E$5),$E$5-WEEKDAY($E$5,2)+1+25,"") -> 46318 | O19: =IF(MONTH($E$5-WEEKDAY($E$5,2)+1+26)=MONTH($E$5),$E$5-WEEKDAY($E$5,2)+1+26,"") -> 46319 | P19: =IF(MONTH($E$5-WEEKDAY($E$5,2)+1+27)=MONTH($E$5),$E$5-WEEKDAY($E$5,2)+1+27,"") -> 46320
J20: =IF(J19="","",SUMIFS('Diário de Estudo'!$D$7:$D$506,'Diário de Estudo'!$A$7:$A$506,J19)) -> 0 | K20: =IF(K19="","",SUMIFS('Diário de Estudo'!$D$7:$D$506,'Diário de Estudo'!$A$7:$A$506,K19)) -> 0 | L20: =IF(L19="","",SUMIFS('Diário de Estudo'!$D$7:$D$506,'Diário de Estudo'!$A$7:$A$506,L19)) -> 0 | M20: =IF(M19="","",SUMIFS('Diário de Estudo'!$D$7:$D$506,'Diário de Estudo'!$A$7:$A$506,M19)) -> 0 | N20: =IF(N19="","",SUMIFS('Diário de Estudo'!$D$7:$D$506,'Diário de Estudo'!$A$7:$A$506,N19)) -> 0 | O20: =IF(O19="","",SUMIFS('Diário de Estudo'!$D$7:$D$506,'Diário de Estudo'!$A$7:$A$506,O19)) -> 0 | P20: =IF(P19="","",SUMIFS('Diário de Estudo'!$D$7:$D$506,'Diário de Estudo'!$A$7:$A$506,P19)) -> 0
J21: =IF(MONTH($E$5-WEEKDAY($E$5,2)+1+28)=MONTH($E$5),$E$5-WEEKDAY($E$5,2)+1+28,"") -> 46321 | K21: =IF(MONTH($E$5-WEEKDAY($E$5,2)+1+29)=MONTH($E$5),$E$5-WEEKDAY($E$5,2)+1+29,"") -> 46322 | L21: =IF(MONTH($E$5-WEEKDAY($E$5,2)+1+30)=MONTH($E$5),$E$5-WEEKDAY($E$5,2)+1+30,"") -> 46323 | M21: =IF(MONTH($E$5-WEEKDAY($E$5,2)+1+31)=MONTH($E$5),$E$5-WEEKDAY($E$5,2)+1+31,"") -> 46324 | N21: =IF(MONTH($E$5-WEEKDAY($E$5,2)+1+32)=MONTH($E$5),$E$5-WEEKDAY($E$5,2)+1+32,"") -> 46325 | O21: =IF(MONTH($E$5-WEEKDAY($E$5,2)+1+33)=MONTH($E$5),$E$5-WEEKDAY($E$5,2)+1+33,"") -> 46326 | P21: =IF(MONTH($E$5-WEEKDAY($E$5,2)+1+34)=MONTH($E$5),$E$5-WEEKDAY($E$5,2)+1+34,"")
J22: =IF(J21="","",SUMIFS('Diário de Estudo'!$D$7:$D$506,'Diário de Estudo'!$A$7:$A$506,J21)) -> 0 | K22: =IF(K21="","",SUMIFS('Diário de Estudo'!$D$7:$D$506,'Diário de Estudo'!$A$7:$A$506,K21)) -> 0 | L22: =IF(L21="","",SUMIFS('Diário de Estudo'!$D$7:$D$506,'Diário de Estudo'!$A$7:$A$506,L21)) -> 0 | M22: =IF(M21="","",SUMIFS('Diário de Estudo'!$D$7:$D$506,'Diário de Estudo'!$A$7:$A$506,M21)) -> 0 | N22: =IF(N21="","",SUMIFS('Diário de Estudo'!$D$7:$D$506,'Diário de Estudo'!$A$7:$A$506,N21)) -> 0 | O22: =IF(O21="","",SUMIFS('Diário de Estudo'!$D$7:$D$506,'Diário de Estudo'!$A$7:$A$506,O21)) -> 0 | P22: =IF(P21="","",SUMIFS('Diário de Estudo'!$D$7:$D$506,'Diário de Estudo'!$A$7:$A$506,P21))
J23: =IF(MONTH($E$5-WEEKDAY($E$5,2)+1+35)=MONTH($E$5),$E$5-WEEKDAY($E$5,2)+1+35,"") | K23: =IF(MONTH($E$5-WEEKDAY($E$5,2)+1+36)=MONTH($E$5),$E$5-WEEKDAY($E$5,2)+1+36,"") | L23: =IF(MONTH($E$5-WEEKDAY($E$5,2)+1+37)=MONTH($E$5),$E$5-WEEKDAY($E$5,2)+1+37,"") | M23: =IF(MONTH($E$5-WEEKDAY($E$5,2)+1+38)=MONTH($E$5),$E$5-WEEKDAY($E$5,2)+1+38,"") | N23: =IF(MONTH($E$5-WEEKDAY($E$5,2)+1+39)=MONTH($E$5),$E$5-WEEKDAY($E$5,2)+1+39,"") | O23: =IF(MONTH($E$5-WEEKDAY($E$5,2)+1+40)=MONTH($E$5),$E$5-WEEKDAY($E$5,2)+1+40,"") | P23: =IF(MONTH($E$5-WEEKDAY($E$5,2)+1+41)=MONTH($E$5),$E$5-WEEKDAY($E$5,2)+1+41,"")
J24: =IF(J23="","",SUMIFS('Diário de Estudo'!$D$7:$D$506,'Diário de Estudo'!$A$7:$A$506,J23)) | K24: =IF(K23="","",SUMIFS('Diário de Estudo'!$D$7:$D$506,'Diário de Estudo'!$A$7:$A$506,K23)) | L24: =IF(L23="","",SUMIFS('Diário de Estudo'!$D$7:$D$506,'Diário de Estudo'!$A$7:$A$506,L23)) | M24: =IF(M23="","",SUMIFS('Diário de Estudo'!$D$7:$D$506,'Diário de Estudo'!$A$7:$A$506,M23)) | N24: =IF(N23="","",SUMIFS('Diário de Estudo'!$D$7:$D$506,'Diário de Estudo'!$A$7:$A$506,N23)) | O24: =IF(O23="","",SUMIFS('Diário de Estudo'!$D$7:$D$506,'Diário de Estudo'!$A$7:$A$506,O23)) | P24: =IF(P23="","",SUMIFS('Diário de Estudo'!$D$7:$D$506,'Diário de Estudo'!$A$7:$A$506,P23))
J25: Quanto mais escura a célula, mais horas estudadas no dia · dia de hoje em verde-escuro

Sheet Diário de Estudo
A1: DIÁRIO DE ESTUDO
A2: Registre cada sessão de estudo — alimenta as Metas, o mapa de calor e o Dashboard | D2: ← Voltar ao Início
A5: Use o mesmo nome do curso (escolha na seta) para calcular custo por hora · Linhas 7–9 = exemplo | D5: =SUM(D7:D506) -> 4.5 | E5: ← total de horas registradas
A6: Data | B6: Categoria | C6: Curso / Livro | D6: Horas | E6: Tema estudado | F6: Foco (1–5)
A7: 46296 | B7: Pós-graduação | C7: MBA em Inteligência Artificial (exemplo) | D7: 2 | E7: Introdução a machine learning | F7: 4
A8: 46297 | B8: Cursos IA | C8: Agentes de IA na Prática (exemplo) | D8: 1.5 | E8: Fluxos de automação | F8: 5
A9: 46298 | B9: Livros | C9: Hábitos Atômicos (exemplo) | D9: 1 | E9: Capítulos 5 a 7 | F9: 4

Sheet Pós-graduação
A1: PÓS-GRADUAÇÃO
A2: MBAs, especializações, mestrado e extensões · disciplinas, acesso, certificado e investimento | W2: ← Voltar ao Início
B5: ITENS | D5: EM ANDAMENTO | F5: CONCLUÍDOS | H5: INVESTIDO | J5: PROGRESSO MÉDIO | L5: ACESSOS A VENCER
B6: =COUNTA(B10:B49) -> 1 | D6: =COUNTIF(S10:S49,"Em andamento") -> 1 | F6: =COUNTIF(S10:S49,"Concluído") -> 0 | H6: =SUM(F10:F49) -> 12600 | J6: =IFERROR(AVERAGE(N10:N49),0) -> 0.1 | L6: =COUNTIF(K10:K49,"*A vencer") -> 0
A8: Células cinza = automáticas (não edite) · Linha 10 = exemplo: substitua ou apague · Use a seta das células Status, Prioridade e Certificado
A9: ID | B9: Curso / Pós-graduação | C9: Instituição | D9: Modalidade | E9: Data da compra | F9: Valor pago (R$) | G9: Data de início | H9: Término previsto | I9: Vencimento do acesso | J9: Dias p/ vencer | K9: Situação do acesso | L9: Disciplinas (total) | M9: Disciplinas concluídas | N9: % Andamento | O9: Horas estudadas | P9: Custo por hora (R$) | Q9: Previsão de término | R9: Risco de prazo | S9: Status | T9: Prioridade | U9: Certificado | V9: Login | W9: Senha | X9: Link de acesso | Y9: Observações
A10: =IF($B10="","","PG-"&TEXT(ROW()-9,"00")) -> PG-01 | B10: MBA em Inteligência Artificial (exemplo) | C10: Universidade Exemplo | D10: EAD | E10: 46244 | F10: 12600 | G10: 46266 | H10: 46813 | I10: 46997 | J10: =IF(OR($B10="",$I10=""),"",$I10-TODAY()) -> 699 | K10: =IF($B10="","",IF($I10="","∞ Vitalício",IF($J10<0,"■ Vencido",IF($J10<=Listas!$H$6,"▲ A vencer","● Ativo")))) -> ● Ativo | L10: 20 | M10: 2 | N10: =IF($B10="","",IF(N($L10)=0,0,MIN(1,N($M10)/$L10))) -> 0.1 | O10: =IF($B10="","",SUMIFS('Diário de Estudo'!$D$7:$D$506,'Diário de Estudo'!$C$7:$C$506,$B10)) -> 2 | P10: =IF($B10="","",IF(AND(N($O10)>0,N($F10)>0),$F10/$O10,"")) -> 6300 | Q10: =IF($B10="","",IF(OR(N($L10)=0,$G10=""),"",IF(N($M10)>=$L10,"Concluído",IF(OR(N($M10)<=0,TODAY()<=$G10),"Sem ritmo",TODAY()+ROUNDUP(($L10-$M10)/($M10/(TODAY()-$G10)),0))))) -> 46586 | R10: =IF($B10="","",IF(ISNUMBER($Q10),IF(AND(ISNUMBER($I10),$Q10>$I10),"■ Estoura o acesso",IF(AND(ISNUMBER($H10),$Q10>$H10),"▲ Atrasado vs plano","● No prazo")),IF($Q10="Concluído","◆ Concluído","—"))) -> ● No prazo | S10: Em andamento | T10: Alta | U10: Não emitido | V10: seu.email@exemplo.com | W10: (guarde no gerenciador de senhas) | X10: https://portal.exemplo.com | Y10: Linha de exemplo — substitua pelos seus dados.
A11: =IF($B11="","","PG-"&TEXT(ROW()-9,"00")) | J11: =IF(OR($B11="",$I11=""),"",$I11-TODAY()) | K11: =IF($B11="","",IF($I11="","∞ Vitalício",IF($J11<0,"■ Vencido",IF($J11<=Listas!$H$6,"▲ A vencer","● Ativo")))) | N11: =IF($B11="","",IF(N($L11)=0,0,MIN(1,N($M11)/$L11))) | O11: =IF($B11="","",SUMIFS('Diário de Estudo'!$D$7:$D$506,'Diário de Estudo'!$C$7:$C$506,$B11)) | P11: =IF($B11="","",IF(AND(N($O11)>0,N($F11)>0),$F11/$O11,"")) | Q11: =IF($B11="","",IF(OR(N($L11)=0,$G11=""),"",IF(N($M11)>=$L11,"Concluído",IF(OR(N($M11)<=0,TODAY()<=$G11),"Sem ritmo",TODAY()+ROUNDUP(($L11-$M11)/($M11/(TODAY()-$G11)),0))))) | R11: =IF($B11="","",IF(ISNUMBER($Q11),IF(AND(ISNUMBER($I11),$Q11>$I11),"■ Estoura o acesso",IF(AND(ISNUMBER($H11),$Q11>$H11),"▲ Atrasado vs plano","● No prazo")),IF($Q11="Concluído","◆ Concluído","—")))
A12: =IF($B12="","","PG-"&TEXT(ROW()-9,"00")) | J12: =IF(OR($B12="",$I12=""),"",$I12-TODAY()) | K12: =IF($B12="","",IF($I12="","∞ Vitalício",IF($J12<0,"■ Vencido",IF($J12<=Listas!$H$6,"▲ A vencer","● Ativo")))) | N12: =IF($B12="","",IF(N($L12)=0,0,MIN(1,N($M12)/$L12))) | O12: =IF($B12="","",SUMIFS('Diário de Estudo'!$D$7:$D$506,'Diário de Estudo'!$C$7:$C$506,$B12)) | P12: =IF($B12="","",IF(AND(N($O12)>0,N($F12)>0),$F12/$O12,"")) | Q12: =IF($B12="","",IF(OR(N($L12)=0,$G12=""),"",IF(N($M12)>=$L12,"Concluído",IF(OR(N($M12)<=0,TODAY()<=$G12),"Sem ritmo",TODAY()+ROUNDUP(($L12-$M12)/($M12/(TODAY()-$G12)),0))))) | R12: =IF($B12="","",IF(ISNUMBER($Q12),IF(AND(ISNUMBER($I12),$Q12>$I12),"■ Estoura o acesso",IF(AND(ISNUMBER($H12),$Q12>$H12),"▲ Atrasado vs plano","● No prazo")),IF($Q12="Concluído","◆ Concluído","—")))
A13: =IF($B13="","","PG-"&TEXT(ROW()-9,"00")) | J13: =IF(OR($B13="",$I13=""),"",$I13-TODAY()) | K13: =IF($B13="","",IF($I13="","∞ Vitalício",IF($J13<0,"■ Vencido",IF($J13<=Listas!$H$6,"▲ A vencer","● Ativo")))) | N13: =IF($B13="","",IF(N($L13)=0,0,MIN(1,N($M13)/$L13))) | O13: =IF($B13="","",SUMIFS('Diário de Estudo'!$D$7:$D$506,'Diário de Estudo'!$C$7:$C$506,$B13)) | P13: =IF($B13="","",IF(AND(N($O13)>0,N($F13)>0),$F13/$O13,"")) | Q13: =IF($B13="","",IF(OR(N($L13)=0,$G13=""),"",IF(N($M13)>=$L13,"Concluído",IF(OR(N($M13)<=0,TODAY()<=$G13),"Sem ritmo",TODAY()+ROUNDUP(($L13-$M13)/($M13/(TODAY()-$G13)),0))))) | R13: =IF($B13="","",IF(ISNUMBER($Q13),IF(AND(ISNUMBER($I13),$Q13>$I13),"■ Estoura o acesso",IF(AND(ISNUMBER($H13),$Q13>$H13),"▲ Atrasado vs plano","● No prazo")),IF($Q13="Concluído","◆ Concluído","—")))
A14: =IF($B14="","","PG-"&TEXT(ROW()-9,"00")) | J14: =IF(OR($B14="",$I14=""),"",$I14-TODAY()) | K14: =IF($B14="","",IF($I14="","∞ Vitalício",IF($J14<0,"■ Vencido",IF($J14<=Listas!$H$6,"▲ A vencer","● Ativo")))) | N14: =IF($B14="","",IF(N($L14)=0,0,MIN(1,N($M14)/$L14))) | O14: =IF($B14="","",SUMIFS('Diário de Estudo'!$D$7:$D$506,'Diário de Estudo'!$C$7:$C$506,$B14)) | P14: =IF($B14="","",IF(AND(N($O14)>0,N($F14)>0),$F14/$O14,"")) | Q14: =IF($B14="","",IF(OR(N($L14)=0,$G14=""),"",IF(N($M14)>=$L14,"Concluído",IF(OR(N($M14)<=0,TODAY()<=$G14),"Sem ritmo",TODAY()+ROUNDUP(($L14-$M14)/($M14/(TODAY()-$G14)),0))))) | R14: =IF($B14="","",IF(ISNUMBER($Q14),IF(AND(ISNUMBER($I14),$Q14>$I14),"■ Estoura o acesso",IF(AND(ISNUMBER($H14),$Q14>$H14),"▲ Atrasado vs plano","● No prazo")),IF($Q14="Concluído","◆ Concluído","—")))
A15: =IF($B15="","","PG-"&TEXT(ROW()-9,"00")) | J15: =IF(OR($B15="",$I15=""),"",$I15-TODAY()) | K15: =IF($B15="","",IF($I15="","∞ Vitalício",IF($J15<0,"■ Vencido",IF($J15<=Listas!$H$6,"▲ A vencer","● Ativo")))) | N15: =IF($B15="","",IF(N($L15)=0,0,MIN(1,N($M15)/$L15))) | O15: =IF($B15="","",SUMIFS('Diário de Estudo'!$D$7:$D$506,'Diário de Estudo'!$C$7:$C$506,$B15)) | P15: =IF($B15="","",IF(AND(N($O15)>0,N($F15)>0),$F15/$O15,"")) | Q15: =IF($B15="","",IF(OR(N($L15)=0,$G15=""),"",IF(N($M15)>=$L15,"Concluído",IF(OR(N($M15)<=0,TODAY()<=$G15),"Sem ritmo",TODAY()+ROUNDUP(($L15-$M15)/($M15/(TODAY()-$G15)),0))))) | R15: =IF($B15="","",IF(ISNUMBER($Q15),IF(AND(ISNUMBER($I15),$Q15>$I15),"■ Estoura o acesso",IF(AND(ISNUMBER($H15),$Q15>$H15),"▲ Atrasado vs plano","● No prazo")),IF($Q15="Concluído","◆ Concluído","—")))
A16: =IF($B16="","","PG-"&TEXT(ROW()-9,"00")) | J16: =IF(OR($B16="",$I16=""),"",$I16-TODAY()) | K16: =IF($B16="","",IF($I16="","∞ Vitalício",IF($J16<0,"■ Vencido",IF($J16<=Listas!$H$6,"▲ A vencer","● Ativo")))) | N16: =IF($B16="","",IF(N($L16)=0,0,MIN(1,N($M16)/$L16))) | O16: =IF($B16="","",SUMIFS('Diário de Estudo'!$D$7:$D$506,'Diário de Estudo'!$C$7:$C$506,$B16)) | P16: =IF($B16="","",IF(AND(N($O16)>0,N($F16)>0),$F16/$O16,"")) | Q16: =IF($B16="","",IF(OR(N($L16)=0,$G16=""),"",IF(N($M16)>=$L16,"Concluído",IF(OR(N($M16)<=0,TODAY()<=$G16),"Sem ritmo",TODAY()+ROUNDUP(($L16-$M16)/($M16/(TODAY()-$G16)),0))))) | R16: =IF($B16="","",IF(ISNUMBER($Q16),IF(AND(ISNUMBER($I16),$Q16>$I16),"■ Estoura o acesso",IF(AND(ISNUMBER($H16),$Q16>$H16),"▲ Atrasado vs plano","● No prazo")),IF($Q16="Concluído","◆ Concluído","—")))
A17: =IF($B17="","","PG-"&TEXT(ROW()-9,"00")) | J17: =IF(OR($B17="",$I17=""),"",$I17-TODAY()) | K17: =IF($B17="","",IF($I17="","∞ Vitalício",IF($J17<0,"■ Vencido",IF($J17<=Listas!$H$6,"▲ A vencer","● Ativo")))) | N17: =IF($B17="","",IF(N($L17)=0,0,MIN(1,N($M17)/$L17))) | O17: =IF($B17="","",SUMIFS('Diário de Estudo'!$D$7:$D$506,'Diário de Estudo'!$C$7:$C$506,$B17)) | P17: =IF($B17="","",IF(AND(N($O17)>0,N($F17)>0),$F17/$O17,"")) | Q17: =IF($B17="","",IF(OR(N($L17)=0,$G17=""),"",IF(N($M17)>=$L17,"Concluído",IF(OR(N($M17)<=0,TODAY()<=$G17),"Sem ritmo",TODAY()+ROUNDUP(($L17-$M17)/($M17/(TODAY()-$G17)),0))))) | R17: =IF($B17="","",IF(ISNUMBER($Q17),IF(AND(ISNUMBER($I17),$Q17>$I17),"■ Estoura o acesso",IF(AND(ISNUMBER($H17),$Q17>$H17),"▲ Atrasado vs plano","● No prazo")),IF($Q17="Concluído","◆ Concluído","—")))
A18: =IF($B18="","","PG-"&TEXT(ROW()-9,"00")) | J18: =IF(OR($B18="",$I18=""),"",$I18-TODAY()) | K18: =IF($B18="","",IF($I18="","∞ Vitalício",IF($J18<0,"■ Vencido",IF($J18<=Listas!$H$6,"▲ A vencer","● Ativo")))) | N18: =IF($B18="","",IF(N($L18)=0,0,MIN(1,N($M18)/$L18))) | O18: =IF($B18="","",SUMIFS('Diário de Estudo'!$D$7:$D$506,'Diário de Estudo'!$C$7:$C$506,$B18)) | P18: =IF($B18="","",IF(AND(N($O18)>0,N($F18)>0),$F18/$O18,"")) | Q18: =IF($B18="","",IF(OR(N($L18)=0,$G18=""),"",IF(N($M18)>=$L18,"Concluído",IF(OR(N($M18)<=0,TODAY()<=$G18),"Sem ritmo",TODAY()+ROUNDUP(($L18-$M18)/($M18/(TODAY()-$G18)),0))))) | R18: =IF($B18="","",IF(ISNUMBER($Q18),IF(AND(ISNUMBER($I18),$Q18>$I18),"■ Estoura o acesso",IF(AND(ISNUMBER($H18),$Q18>$H18),"▲ Atrasado vs plano","● No prazo")),IF($Q18="Concluído","◆ Concluído","—")))
A19: =IF($B19="","","PG-"&TEXT(ROW()-9,"00")) | J19: =IF(OR($B19="",$I19=""),"",$I19-TODAY()) | K19: =IF($B19="","",IF($I19="","∞ Vitalício",IF($J19<0,"■ Vencido",IF($J19<=Listas!$H$6,"▲ A vencer","● Ativo")))) | N19: =IF($B19="","",IF(N($L19)=0,0,MIN(1,N($M19)/$L19))) | O19: =IF($B19="","",SUMIFS('Diário de Estudo'!$D$7:$D$506,'Diário de Estudo'!$C$7:$C$506,$B19)) | P19: =IF($B19="","",IF(AND(N($O19)>0,N($F19)>0),$F19/$O19,"")) | Q19: =IF($B19="","",IF(OR(N($L19)=0,$G19=""),"",IF(N($M19)>=$L19,"Concluído",IF(OR(N($M19)<=0,TODAY()<=$G19),"Sem ritmo",TODAY()+ROUNDUP(($L19-$M19)/($M19/(TODAY()-$G19)),0))))) | R19: =IF($B19="","",IF(ISNUMBER($Q19),IF(AND(ISNUMBER($I19),$Q19>$I19),"■ Estoura o acesso",IF(AND(ISNUMBER($H19),$Q19>$H19),"▲ Atrasado vs plano","● No prazo")),IF($Q19="Concluído","◆ Concluído","—")))
A20: =IF($B20="","","PG-"&TEXT(ROW()-9,"00")) | J20: =IF(OR($B20="",$I20=""),"",$I20-TODAY()) | K20: =IF($B20="","",IF($I20="","∞ Vitalício",IF($J20<0,"■ Vencido",IF($J20<=Listas!$H$6,"▲ A vencer","● Ativo")))) | N20: =IF($B20="","",IF(N($L20)=0,0,MIN(1,N($M20)/$L20))) | O20: =IF($B20="","",SUMIFS('Diário de Estudo'!$D$7:$D$506,'Diário de Estudo'!$C$7:$C$506,$B20)) | P20: =IF($B20="","",IF(AND(N($O20)>0,N($F20)>0),$F20/$O20,"")) | Q20: =IF($B20="","",IF(OR(N($L20)=0,$G20=""),"",IF(N($M20)>=$L20,"Concluído",IF(OR(N($M20)<=0,TODAY()<=$G20),"Sem ritmo",TODAY()+ROUNDUP(($L20-$M20)/($M20/(TODAY()-$G20)),0))))) | R20: =IF($B20="","",IF(ISNUMBER($Q20),IF(AND(ISNUMBER($I20),$Q20>$I20),"■ Estoura o acesso",IF(AND(ISNUMBER($H20),$Q20>$H20),"▲ Atrasado vs plano","● No prazo")),IF($Q20="Concluído","◆ Concluído","—")))
A21: =IF($B21="","","PG-"&TEXT(ROW()-9,"00")) | J21: =IF(OR($B21="",$I21=""),"",$I21-TODAY()) | K21: =IF($B21="","",IF($I21="","∞ Vitalício",IF($J21<0,"■ Vencido",IF($J21<=Listas!$H$6,"▲ A vencer","● Ativo")))) | N21: =IF($B21="","",IF(N($L21)=0,0,MIN(1,N($M21)/$L21))) | O21: =IF($B21="","",SUMIFS('Diário de Estudo'!$D$7:$D$506,'Diário de Estudo'!$C$7:$C$506,$B21)) | P21: =IF($B21="","",IF(AND(N($O21)>0,N($F21)>0),$F21/$O21,"")) | Q21: =IF($B21="","",IF(OR(N($L21)=0,$G21=""),"",IF(N($M21)>=$L21,"Concluído",IF(OR(N($M21)<=0,TODAY()<=$G21),"Sem ritmo",TODAY()+ROUNDUP(($L21-$M21)/($M21/(TODAY()-$G21)),0))))) | R21: =IF($B21="","",IF(ISNUMBER($Q21),IF(AND(ISNUMBER($I21),$Q21>$I21),"■ Estoura o acesso",IF(AND(ISNUMBER($H21),$Q21>$H21),"▲ Atrasado vs plano","● No prazo")),IF($Q21="Concluído","◆ Concluído","—")))
A22: =IF($B22="","","PG-"&TEXT(ROW()-9,"00")) | J22: =IF(OR($B22="",$I22=""),"",$I22-TODAY()) | K22: =IF($B22="","",IF($I22="","∞ Vitalício",IF($J22<0,"■ Vencido",IF($J22<=Listas!$H$6,"▲ A vencer","● Ativo")))) | N22: =IF($B22="","",IF(N($L22)=0,0,MIN(1,N($M22)/$L22))) | O22: =IF($B22="","",SUMIFS('Diário de Estudo'!$D$7:$D$506,'Diário de Estudo'!$C$7:$C$506,$B22)) | P22: =IF($B22="","",IF(AND(N($O22)>0,N($F22)>0),$F22/$O22,"")) | Q22: =IF($B22="","",IF(OR(N($L22)=0,$G22=""),"",IF(N($M22)>=$L22,"Concluído",IF(OR(N($M22)<=0,TODAY()<=$G22),"Sem ritmo",TODAY()+ROUNDUP(($L22-$M22)/($M22/(TODAY()-$G22)),0))))) | R22: =IF($B22="","",IF(ISNUMBER($Q22),IF(AND(ISNUMBER($I22),$Q22>$I22),"■ Estoura o acesso",IF(AND(ISNUMBER($H22),$Q22>$H22),"▲ Atrasado vs plano","● No prazo")),IF($Q22="Concluído","◆ Concluído","—")))
... A49: =IF($B49="","","PG-"&TEXT(ROW()-9,"00")) | J49: =IF(OR($B49="",$I49=""),"",$I49-TODAY()) | K49: =IF($B49="","",IF($I49="","∞ Vitalício",IF($J49<0,"■ Vencido",IF($J49<=Listas!$H$6,"▲ A vencer","● Ativo")))) | N49: =IF($B49="","",IF(N($L49)=0,0,MIN(1,N($M49)/$L49))) | O49: =IF($B49="","",SUMIFS('Diário de Estudo'!$D$7:$D$506,'Diário de Estudo'!$C$7:$C$506,$B49)) | P49: =IF($B49="","",IF(AND(N($O49)>0,N($F49)>0),$F49/$O49,"")) | Q49: =IF($B49="","",IF(OR(N($L49)=0,$G49=""),"",IF(N($M49)>=$L49,"Concluído",IF(OR(N($M49)<=0,TODAY()<=$G49),"Sem ritmo",TODAY()+ROUNDUP(($L49-$M49)/($M49/(TODAY()-$G49)),0))))) | R49: =IF($B49="","",IF(ISNUMBER($Q49),IF(AND(ISNUMBER($I49),$Q49>$I49),"■ Estoura o acesso",IF(AND(ISNUMBER($H49),$Q49>$H49),"▲ Atrasado vs plano","● No prazo")),IF($Q49="Concluído","◆ Concluído","—")))

Sheet Concurso
A1: CONCURSOS PÚBLICOS
A2: Cursos preparatórios, bancos de questões e materiais · vincule cada curso ao concurso-alvo | Y2: ← Voltar ao Início
B5: ITENS | D5: EM ANDAMENTO | F5: CONCLUÍDOS | H5: INVESTIDO | J5: PROGRESSO MÉDIO | L5: ACESSOS A VENCER
B6: =COUNTA(B10:B49) -> 1 | D6: =COUNTIF(U10:U49,"Em andamento") -> 1 | F6: =COUNTIF(U10:U49,"Concluído") -> 0 | H6: =SUM(H10:H49) -> 1490 | J6: =IFERROR(AVERAGE(P10:P49),0) -> 0.25 | L6: =COUNTIF(M10:M49,"*A vencer") -> 0
A8: Células cinza = automáticas (não edite) · Linha 10 = exemplo: substitua ou apague · Use a seta das células Status, Prioridade e Certificado
A9: ID | B9: Curso / Material | C9: Plataforma / Instituição | D9: Concurso / Cargo alvo | E9: Banca | F9: Data da prova | G9: Data da compra | H9: Valor pago (R$) | I9: Data de início | J9: Término previsto | K9: Vencimento do acesso | L9: Dias p/ vencer | M9: Situação do acesso | N9: Aulas / Tópicos (total) | O9: Aulas / Tópicos concluídos | P9: % Andamento | Q9: Horas estudadas | R9: Custo por hora (R$) | S9: Previsão de término | T9: Risco de prazo | U9: Status | V9: Prioridade | W9: Certificado | X9: Login | Y9: Senha | Z9: Link de acesso | AA9: Observações
A10: =IF($B10="","","CO-"&TEXT(ROW()-9,"00")) -> CO-01 | B10: Curso Preparatório Completo (exemplo) | C10: Plataforma Exemplo | D10: Analista — Órgão Exemplo | E10: CEBRASPE | F10: 46460 | G10: 46270 | H10: 1490 | I10: 46280 | J10: 46446 | K10: 46568 | L10: =IF(OR($B10="",$K10=""),"",$K10-TODAY()) -> 270 | M10: =IF($B10="","",IF($K10="","∞ Vitalício",IF($L10<0,"■ Vencido",IF($L10<=Listas!$H$6,"▲ A vencer","● Ativo")))) -> ● Ativo | N10: 180 | O10: 45 | P10: =IF($B10="","",IF(N($N10)=0,0,MIN(1,N($O10)/$N10))) -> 0.25 | Q10: =IF($B10="","",SUMIFS('Diário de Estudo'!$D$7:$D$506,'Diário de Estudo'!$C$7:$C$506,$B10)) -> 0 | R10: =IF($B10="","",IF(AND(N($Q10)>0,N($H10)>0),$H10/$Q10,"")) | S10: =IF($B10="","",IF(OR(N($N10)=0,$I10=""),"",IF(N($O10)>=$N10,"Concluído",IF(OR(N($O10)<=0,TODAY()<=$I10),"Sem ritmo",TODAY()+ROUNDUP(($N10-$O10)/($O10/(TODAY()-$I10)),0))))) -> 46352 | T10: =IF($B10="","",IF(ISNUMBER($S10),IF(AND(ISNUMBER($K10),$S10>$K10),"■ Estoura o acesso",IF(AND(ISNUMBER($J10),$S10>$J10),"▲ Atrasado vs plano","● No prazo")),IF($S10="Concluído","◆ Concluído","—"))) -> ● No prazo | U10: Em andamento | V10: Alta | W10: Não se aplica | X10: seu.email@exemplo.com | Y10: (guarde no gerenciador de senhas) | Z10: https://plataforma.exemplo.com | AA10: Linha de exemplo — substitua pelos seus dados.
A11: =IF($B11="","","CO-"&TEXT(ROW()-9,"00")) | L11: =IF(OR($B11="",$K11=""),"",$K11-TODAY()) | M11: =IF($B11="","",IF($K11="","∞ Vitalício",IF($L11<0,"■ Vencido",IF($L11<=Listas!$H$6,"▲ A vencer","● Ativo")))) | P11: =IF($B11="","",IF(N($N11)=0,0,MIN(1,N($O11)/$N11))) | Q11: =IF($B11="","",SUMIFS('Diário de Estudo'!$D$7:$D$506,'Diário de Estudo'!$C$7:$C$506,$B11)) | R11: =IF($B11="","",IF(AND(N($Q11)>0,N($H11)>0),$H11/$Q11,"")) | S11: =IF($B11="","",IF(OR(N($N11)=0,$I11=""),"",IF(N($O11)>=$N11,"Concluído",IF(OR(N($O11)<=0,TODAY()<=$I11),"Sem ritmo",TODAY()+ROUNDUP(($N11-$O11)/($O11/(TODAY()-$I11)),0))))) | T11: =IF($B11="","",IF(ISNUMBER($S11),IF(AND(ISNUMBER($K11),$S11>$K11),"■ Estoura o acesso",IF(AND(ISNUMBER($J11),$S11>$J11),"▲ Atrasado vs plano","● No prazo")),IF($S11="Concluído","◆ Concluído","—")))
A12: =IF($B12="","","CO-"&TEXT(ROW()-9,"00")) | L12: =IF(OR($B12="",$K12=""),"",$K12-TODAY()) | M12: =IF($B12="","",IF($K12="","∞ Vitalício",IF($L12<0,"■ Vencido",IF($L12<=Listas!$H$6,"▲ A vencer","● Ativo")))) | P12: =IF($B12="","",IF(N($N12)=0,0,MIN(1,N($O12)/$N12))) | Q12: =IF($B12="","",SUMIFS('Diário de Estudo'!$D$7:$D$506,'Diário de Estudo'!$C$7:$C$506,$B12)) | R12: =IF($B12="","",IF(AND(N($Q12)>0,N($H12)>0),$H12/$Q12,"")) | S12: =IF($B12="","",IF(OR(N($N12)=0,$I12=""),"",IF(N($O12)>=$N12,"Concluído",IF(OR(N($O12)<=0,TODAY()<=$I12),"Sem ritmo",TODAY()+ROUNDUP(($N12-$O12)/($O12/(TODAY()-$I12)),0))))) | T12: =IF($B12="","",IF(ISNUMBER($S12),IF(AND(ISNUMBER($K12),$S12>$K12),"■ Estoura o acesso",IF(AND(ISNUMBER($J12),$S12>$J12),"▲ Atrasado vs plano","● No prazo")),IF($S12="Concluído","◆ Concluído","—")))
A13: =IF($B13="","","CO-"&TEXT(ROW()-9,"00")) | L13: =IF(OR($B13="",$K13=""),"",$K13-TODAY()) | M13: =IF($B13="","",IF($K13="","∞ Vitalício",IF($L13<0,"■ Vencido",IF($L13<=Listas!$H$6,"▲ A vencer","● Ativo")))) | P13: =IF($B13="","",IF(N($N13)=0,0,MIN(1,N($O13)/$N13))) | Q13: =IF($B13="","",SUMIFS('Diário de Estudo'!$D$7:$D$506,'Diário de Estudo'!$C$7:$C$506,$B13)) | R13: =IF($B13="","",IF(AND(N($Q13)>0,N($H13)>0),$H13/$Q13,"")) | S13: =IF($B13="","",IF(OR(N($N13)=0,$I13=""),"",IF(N($O13)>=$N13,"Concluído",IF(OR(N($O13)<=0,TODAY()<=$I13),"Sem ritmo",TODAY()+ROUNDUP(($N13-$O13)/($O13/(TODAY()-$I13)),0))))) | T13: =IF($B13="","",IF(ISNUMBER($S13),IF(AND(ISNUMBER($K13),$S13>$K13),"■ Estoura o acesso",IF(AND(ISNUMBER($J13),$S13>$J13),"▲ Atrasado vs plano","● No prazo")),IF($S13="Concluído","◆ Concluído","—")))
A14: =IF($B14="","","CO-"&TEXT(ROW()-9,"00")) | L14: =IF(OR($B14="",$K14=""),"",$K14-TODAY()) | M14: =IF($B14="","",IF($K14="","∞ Vitalício",IF($L14<0,"■ Vencido",IF($L14<=Listas!$H$6,"▲ A vencer","● Ativo")))) | P14: =IF($B14="","",IF(N($N14)=0,0,MIN(1,N($O14)/$N14))) | Q14: =IF($B14="","",SUMIFS('Diário de Estudo'!$D$7:$D$506,'Diário de Estudo'!$C$7:$C$506,$B14)) | R14: =IF($B14="","",IF(AND(N($Q14)>0,N($H14)>0),$H14/$Q14,"")) | S14: =IF($B14="","",IF(OR(N($N14)=0,$I14=""),"",IF(N($O14)>=$N14,"Concluído",IF(OR(N($O14)<=0,TODAY()<=$I14),"Sem ritmo",TODAY()+ROUNDUP(($N14-$O14)/($O14/(TODAY()-$I14)),0))))) | T14: =IF($B14="","",IF(ISNUMBER($S14),IF(AND(ISNUMBER($K14),$S14>$K14),"■ Estoura o acesso",IF(AND(ISNUMBER($J14),$S14>$J14),"▲ Atrasado vs plano","● No prazo")),IF($S14="Concluído","◆ Concluído","—")))
A15: =IF($B15="","","CO-"&TEXT(ROW()-9,"00")) | L15: =IF(OR($B15="",$K15=""),"",$K15-TODAY()) | M15: =IF($B15="","",IF($K15="","∞ Vitalício",IF($L15<0,"■ Vencido",IF($L15<=Listas!$H$6,"▲ A vencer","● Ativo")))) | P15: =IF($B15="","",IF(N($N15)=0,0,MIN(1,N($O15)/$N15))) | Q15: =IF($B15="","",SUMIFS('Diário de Estudo'!$D$7:$D$506,'Diário de Estudo'!$C$7:$C$506,$B15)) | R15: =IF($B15="","",IF(AND(N($Q15)>0,N($H15)>0),$H15/$Q15,"")) | S15: =IF($B15="","",IF(OR(N($N15)=0,$I15=""),"",IF(N($O15)>=$N15,"Concluído",IF(OR(N($O15)<=0,TODAY()<=$I15),"Sem ritmo",TODAY()+ROUNDUP(($N15-$O15)/($O15/(TODAY()-$I15)),0))))) | T15: =IF($B15="","",IF(ISNUMBER($S15),IF(AND(ISNUMBER($K15),$S15>$K15),"■ Estoura o acesso",IF(AND(ISNUMBER($J15),$S15>$J15),"▲ Atrasado vs plano","● No prazo")),IF($S15="Concluído","◆ Concluído","—")))
A16: =IF($B16="","","CO-"&TEXT(ROW()-9,"00")) | L16: =IF(OR($B16="",$K16=""),"",$K16-TODAY()) | M16: =IF($B16="","",IF($K16="","∞ Vitalício",IF($L16<0,"■ Vencido",IF($L16<=Listas!$H$6,"▲ A vencer","● Ativo")))) | P16: =IF($B16="","",IF(N($N16)=0,0,MIN(1,N($O16)/$N16))) | Q16: =IF($B16="","",SUMIFS('Diário de Estudo'!$D$7:$D$506,'Diário de Estudo'!$C$7:$C$506,$B16)) | R16: =IF($B16="","",IF(AND(N($Q16)>0,N($H16)>0),$H16/$Q16,"")) | S16: =IF($B16="","",IF(OR(N($N16)=0,$I16=""),"",IF(N($O16)>=$N16,"Concluído",IF(OR(N($O16)<=0,TODAY()<=$I16),"Sem ritmo",TODAY()+ROUNDUP(($N16-$O16)/($O16/(TODAY()-$I16)),0))))) | T16: =IF($B16="","",IF(ISNUMBER($S16),IF(AND(ISNUMBER($K16),$S16>$K16),"■ Estoura o acesso",IF(AND(ISNUMBER($J16),$S16>$J16),"▲ Atrasado vs plano","● No prazo")),IF($S16="Concluído","◆ Concluído","—")))
A17: =IF($B17="","","CO-"&TEXT(ROW()-9,"00")) | L17: =IF(OR($B17="",$K17=""),"",$K17-TODAY()) | M17: =IF($B17="","",IF($K17="","∞ Vitalício",IF($L17<0,"■ Vencido",IF($L17<=Listas!$H$6,"▲ A vencer","● Ativo")))) | P17: =IF($B17="","",IF(N($N17)=0,0,MIN(1,N($O17)/$N17))) | Q17: =IF($B17="","",SUMIFS('Diário de Estudo'!$D$7:$D$506,'Diário de Estudo'!$C$7:$C$506,$B17)) | R17: =IF($B17="","",IF(AND(N($Q17)>0,N($H17)>0),$H17/$Q17,"")) | S17: =IF($B17="","",IF(OR(N($N17)=0,$I17=""),"",IF(N($O17)>=$N17,"Concluído",IF(OR(N($O17)<=0,TODAY()<=$I17),"Sem ritmo",TODAY()+ROUNDUP(($N17-$O17)/($O17/(TODAY()-$I17)),0))))) | T17: =IF($B17="","",IF(ISNUMBER($S17),IF(AND(ISNUMBER($K17),$S17>$K17),"■ Estoura o acesso",IF(AND(ISNUMBER($J17),$S17>$J17),"▲ Atrasado vs plano","● No prazo")),IF($S17="Concluído","◆ Concluído","—")))
A18: =IF($B18="","","CO-"&TEXT(ROW()-9,"00")) | L18: =IF(OR($B18="",$K18=""),"",$K18-TODAY()) | M18: =IF($B18="","",IF($K18="","∞ Vitalício",IF($L18<0,"■ Vencido",IF($L18<=Listas!$H$6,"▲ A vencer","● Ativo")))) | P18: =IF($B18="","",IF(N($N18)=0,0,MIN(1,N($O18)/$N18))) | Q18: =IF($B18="","",SUMIFS('Diário de Estudo'!$D$7:$D$506,'Diário de Estudo'!$C$7:$C$506,$B18)) | R18: =IF($B18="","",IF(AND(N($Q18)>0,N($H18)>0),$H18/$Q18,"")) | S18: =IF($B18="","",IF(OR(N($N18)=0,$I18=""),"",IF(N($O18)>=$N18,"Concluído",IF(OR(N($O18)<=0,TODAY()<=$I18),"Sem ritmo",TODAY()+ROUNDUP(($N18-$O18)/($O18/(TODAY()-$I18)),0))))) | T18: =IF($B18="","",IF(ISNUMBER($S18),IF(AND(ISNUMBER($K18),$S18>$K18),"■ Estoura o acesso",IF(AND(ISNUMBER($J18),$S18>$J18),"▲ Atrasado vs plano","● No prazo")),IF($S18="Concluído","◆ Concluído","—")))
A19: =IF($B19="","","CO-"&TEXT(ROW()-9,"00")) | L19: =IF(OR($B19="",$K19=""),"",$K19-TODAY()) | M19: =IF($B19="","",IF($K19="","∞ Vitalício",IF($L19<0,"■ Vencido",IF($L19<=Listas!$H$6,"▲ A vencer","● Ativo")))) | P19: =IF($B19="","",IF(N($N19)=0,0,MIN(1,N($O19)/$N19))) | Q19: =IF($B19="","",SUMIFS('Diário de Estudo'!$D$7:$D$506,'Diário de Estudo'!$C$7:$C$506,$B19)) | R19: =IF($B19="","",IF(AND(N($Q19)>0,N($H19)>0),$H19/$Q19,"")) | S19: =IF($B19="","",IF(OR(N($N19)=0,$I19=""),"",IF(N($O19)>=$N19,"Concluído",IF(OR(N($O19)<=0,TODAY()<=$I19),"Sem ritmo",TODAY()+ROUNDUP(($N19-$O19)/($O19/(TODAY()-$I19)),0))))) | T19: =IF($B19="","",IF(ISNUMBER($S19),IF(AND(ISNUMBER($K19),$S19>$K19),"■ Estoura o acesso",IF(AND(ISNUMBER($J19),$S19>$J19),"▲ Atrasado vs plano","● No prazo")),IF($S19="Concluído","◆ Concluído","—")))
A20: =IF($B20="","","CO-"&TEXT(ROW()-9,"00")) | L20: =IF(OR($B20="",$K20=""),"",$K20-TODAY()) | M20: =IF($B20="","",IF($K20="","∞ Vitalício",IF($L20<0,"■ Vencido",IF($L20<=Listas!$H$6,"▲ A vencer","● Ativo")))) | P20: =IF($B20="","",IF(N($N20)=0,0,MIN(1,N($O20)/$N20))) | Q20: =IF($B20="","",SUMIFS('Diário de Estudo'!$D$7:$D$506,'Diário de Estudo'!$C$7:$C$506,$B20)) | R20: =IF($B20="","",IF(AND(N($Q20)>0,N($H20)>0),$H20/$Q20,"")) | S20: =IF($B20="","",IF(OR(N($N20)=0,$I20=""),"",IF(N($O20)>=$N20,"Concluído",IF(OR(N($O20)<=0,TODAY()<=$I20),"Sem ritmo",TODAY()+ROUNDUP(($N20-$O20)/($O20/(TODAY()-$I20)),0))))) | T20: =IF($B20="","",IF(ISNUMBER($S20),IF(AND(ISNUMBER($K20),$S20>$K20),"■ Estoura o acesso",IF(AND(ISNUMBER($J20),$S20>$J20),"▲ Atrasado vs plano","● No prazo")),IF($S20="Concluído","◆ Concluído","—")))
A21: =IF($B21="","","CO-"&TEXT(ROW()-9,"00")) | L21: =IF(OR($B21="",$K21=""),"",$K21-TODAY()) | M21: =IF($B21="","",IF($K21="","∞ Vitalício",IF($L21<0,"■ Vencido",IF($L21<=Listas!$H$6,"▲ A vencer","● Ativo")))) | P21: =IF($B21="","",IF(N($N21)=0,0,MIN(1,N($O21)/$N21))) | Q21: =IF($B21="","",SUMIFS('Diário de Estudo'!$D$7:$D$506,'Diário de Estudo'!$C$7:$C$506,$B21)) | R21: =IF($B21="","",IF(AND(N($Q21)>0,N($H21)>0),$H21/$Q21,"")) | S21: =IF($B21="","",IF(OR(N($N21)=0,$I21=""),"",IF(N($O21)>=$N21,"Concluído",IF(OR(N($O21)<=0,TODAY()<=$I21),"Sem ritmo",TODAY()+ROUNDUP(($N21-$O21)/($O21/(TODAY()-$I21)),0))))) | T21: =IF($B21="","",IF(ISNUMBER($S21),IF(AND(ISNUMBER($K21),$S21>$K21),"■ Estoura o acesso",IF(AND(ISNUMBER($J21),$S21>$J21),"▲ Atrasado vs plano","● No prazo")),IF($S21="Concluído","◆ Concluído","—")))
A22: =IF($B22="","","CO-"&TEXT(ROW()-9,"00")) | L22: =IF(OR($B22="",$K22=""),"",$K22-TODAY()) | M22: =IF($B22="","",IF($K22="","∞ Vitalício",IF($L22<0,"■ Vencido",IF($L22<=Listas!$H$6,"▲ A vencer","● Ativo")))) | P22: =IF($B22="","",IF(N($N22)=0,0,MIN(1,N($O22)/$N22))) | Q22: =IF($B22="","",SUMIFS('Diário de Estudo'!$D$7:$D$506,'Diário de Estudo'!$C$7:$C$506,$B22)) | R22: =IF($B22="","",IF(AND(N($Q22)>0,N($H22)>0),$H22/$Q22,"")) | S22: =IF($B22="","",IF(OR(N($N22)=0,$I22=""),"",IF(N($O22)>=$N22,"Concluído",IF(OR(N($O22)<=0,TODAY()<=$I22),"Sem ritmo",TODAY()+ROUNDUP(($N22-$O22)/($O22/(TODAY()-$I22)),0))))) | T22: =IF($B22="","",IF(ISNUMBER($S22),IF(AND(ISNUMBER($K22),$S22>$K22),"■ Estoura o acesso",IF(AND(ISNUMBER($J22),$S22>$J22),"▲ Atrasado vs plano","● No prazo")),IF($S22="Concluído","◆ Concluído","—")))
... A49: =IF($B49="","","CO-"&TEXT(ROW()-9,"00")) | L49: =IF(OR($B49="",$K49=""),"",$K49-TODAY()) | M49: =IF($B49="","",IF($K49="","∞ Vitalício",IF($L49<0,"■ Vencido",IF($L49<=Listas!$H$6,"▲ A vencer","● Ativo")))) | P49: =IF($B49="","",IF(N($N49)=0,0,MIN(1,N($O49)/$N49))) | Q49: =IF($B49="","",SUMIFS('Diário de Estudo'!$D$7:$D$506,'Diário de Estudo'!$C$7:$C$506,$B49)) | R49: =IF($B49="","",IF(AND(N($Q49)>0,N($H49)>0),$H49/$Q49,"")) | S49: =IF($B49="","",IF(OR(N($N49)=0,$I49=""),"",IF(N($O49)>=$N49,"Concluído",IF(OR(N($O49)<=0,TODAY()<=$I49),"Sem ritmo",TODAY()+ROUNDUP(($N49-$O49)/($O49/(TODAY()-$I49)),0))))) | T49: =IF($B49="","",IF(ISNUMBER($S49),IF(AND(ISNUMBER($K49),$S49>$K49),"■ Estoura o acesso",IF(AND(ISNUMBER($J49),$S49>$J49),"▲ Atrasado vs plano","● No prazo")),IF($S49="Concluído","◆ Concluído","—")))

Sheet Livros
A1: LIVROS
A2: Biblioteca de leitura · páginas lidas, formato, nota e previsão de término | T2: ← Voltar ao Início
B5: ITENS | D5: EM ANDAMENTO | F5: CONCLUÍDOS | H5: INVESTIDO | J5: PROGRESSO MÉDIO | L5: PÁGINAS LIDAS
B6: =COUNTA(B10:B49) -> 1 | D6: =COUNTIF(R10:R49,"Em andamento") -> 1 | F6: =COUNTIF(R10:R49,"Concluído") -> 0 | H6: =SUM(H10:H49) -> 49.9 | J6: =IFERROR(AVERAGE(M10:M49),0) -> 0.375 | L6: =SUM(L10:L49) -> 120
A8: Células cinza = automáticas (não edite) · Linha 10 = exemplo: substitua ou apague · Use a seta das células Status, Prioridade e Certificado
A9: ID | B9: Título | C9: Autor(a) | D9: Tema / Categoria | E9: Editora / Loja | F9: Formato | G9: Data da compra | H9: Valor pago (R$) | I9: Data de início | J9: Término previsto | K9: Páginas (total) | L9: Páginas lidas | M9: % Andamento | N9: Horas lidas | O9: Custo por hora (R$) | P9: Previsão de término | Q9: Risco de prazo | R9: Status | S9: Prioridade | T9: Nota (1–5) | U9: Link / Onde está | V9: Observações
A10: =IF($B10="","","LV-"&TEXT(ROW()-9,"00")) -> LV-01 | B10: Hábitos Atômicos (exemplo) | C10: James Clear | D10: Produtividade | E10: Livraria Exemplo | F10: Físico | G10: 46285 | H10: 49.9 | I10: 46290 | J10: 46341 | K10: 320 | L10: 120 | M10: =IF($B10="","",IF(N($K10)=0,0,MIN(1,N($L10)/$K10))) -> 0.375 | N10: =IF($B10="","",SUMIFS('Diário de Estudo'!$D$7:$D$506,'Diário de Estudo'!$C$7:$C$506,$B10)) -> 1 | O10: =IF($B10="","",IF(AND(N($N10)>0,N($H10)>0),$H10/$N10,"")) -> 49.9 | P10: =IF($B10="","",IF(OR(N($K10)=0,$I10=""),"",IF(N($L10)>=$K10,"Concluído",IF(OR(N($L10)<=0,TODAY()<=$I10),"Sem ritmo",TODAY()+ROUNDUP(($K10-$L10)/($L10/(TODAY()-$I10)),0))))) -> 46312 | Q10: =IF($B10="","",IF(ISNUMBER($P10),IF(AND(ISNUMBER($J10),$P10>$J10),"▲ Atrasado vs plano","● No prazo"),IF($P10="Concluído","◆ Concluído","—"))) -> ● No prazo | R10: Em andamento | S10: Média | U10: Estante — prateleira 2 | V10: Linha de exemplo — substitua pelos seus dados.
A11: =IF($B11="","","LV-"&TEXT(ROW()-9,"00")) | M11: =IF($B11="","",IF(N($K11)=0,0,MIN(1,N($L11)/$K11))) | N11: =IF($B11="","",SUMIFS('Diário de Estudo'!$D$7:$D$506,'Diário de Estudo'!$C$7:$C$506,$B11)) | O11: =IF($B11="","",IF(AND(N($N11)>0,N($H11)>0),$H11/$N11,"")) | P11: =IF($B11="","",IF(OR(N($K11)=0,$I11=""),"",IF(N($L11)>=$K11,"Concluído",IF(OR(N($L11)<=0,TODAY()<=$I11),"Sem ritmo",TODAY()+ROUNDUP(($K11-$L11)/($L11/(TODAY()-$I11)),0))))) | Q11: =IF($B11="","",IF(ISNUMBER($P11),IF(AND(ISNUMBER($J11),$P11>$J11),"▲ Atrasado vs plano","● No prazo"),IF($P11="Concluído","◆ Concluído","—")))
A12: =IF($B12="","","LV-"&TEXT(ROW()-9,"00")) | M12: =IF($B12="","",IF(N($K12)=0,0,MIN(1,N($L12)/$K12))) | N12: =IF($B12="","",SUMIFS('Diário de Estudo'!$D$7:$D$506,'Diário de Estudo'!$C$7:$C$506,$B12)) | O12: =IF($B12="","",IF(AND(N($N12)>0,N($H12)>0),$H12/$N12,"")) | P12: =IF($B12="","",IF(OR(N($K12)=0,$I12=""),"",IF(N($L12)>=$K12,"Concluído",IF(OR(N($L12)<=0,TODAY()<=$I12),"Sem ritmo",TODAY()+ROUNDUP(($K12-$L12)/($L12/(TODAY()-$I12)),0))))) | Q12: =IF($B12="","",IF(ISNUMBER($P12),IF(AND(ISNUMBER($J12),$P12>$J12),"▲ Atrasado vs plano","● No prazo"),IF($P12="Concluído","◆ Concluído","—")))
A13: =IF($B13="","","LV-"&TEXT(ROW()-9,"00")) | M13: =IF($B13="","",IF(N($K13)=0,0,MIN(1,N($L13)/$K13))) | N13: =IF($B13="","",SUMIFS('Diário de Estudo'!$D$7:$D$506,'Diário de Estudo'!$C$7:$C$506,$B13)) | O13: =IF($B13="","",IF(AND(N($N13)>0,N($H13)>0),$H13/$N13,"")) | P13: =IF($B13="","",IF(OR(N($K13)=0,$I13=""),"",IF(N($L13)>=$K13,"Concluído",IF(OR(N($L13)<=0,TODAY()<=$I13),"Sem ritmo",TODAY()+ROUNDUP(($K13-$L13)/($L13/(TODAY()-$I13)),0))))) | Q13: =IF($B13="","",IF(ISNUMBER($P13),IF(AND(ISNUMBER($J13),$P13>$J13),"▲ Atrasado vs plano","● No prazo"),IF($P13="Concluído","◆ Concluído","—")))
A14: =IF($B14="","","LV-"&TEXT(ROW()-9,"00")) | M14: =IF($B14="","",IF(N($K14)=0,0,MIN(1,N($L14)/$K14))) | N14: =IF($B14="","",SUMIFS('Diário de Estudo'!$D$7:$D$506,'Diário de Estudo'!$C$7:$C$506,$B14)) | O14: =IF($B14="","",IF(AND(N($N14)>0,N($H14)>0),$H14/$N14,"")) | P14: =IF($B14="","",IF(OR(N($K14)=0,$I14=""),"",IF(N($L14)>=$K14,"Concluído",IF(OR(N($L14)<=0,TODAY()<=$I14),"Sem ritmo",TODAY()+ROUNDUP(($K14-$L14)/($L14/(TODAY()-$I14)),0))))) | Q14: =IF($B14="","",IF(ISNUMBER($P14),IF(AND(ISNUMBER($J14),$P14>$J14),"▲ Atrasado vs plano","● No prazo"),IF($P14="Concluído","◆ Concluído","—")))
A15: =IF($B15="","","LV-"&TEXT(ROW()-9,"00")) | M15: =IF($B15="","",IF(N($K15)=0,0,MIN(1,N($L15)/$K15))) | N15: =IF($B15="","",SUMIFS('Diário de Estudo'!$D$7:$D$506,'Diário de Estudo'!$C$7:$C$506,$B15)) | O15: =IF($B15="","",IF(AND(N($N15)>0,N($H15)>0),$H15/$N15,"")) | P15: =IF($B15="","",IF(OR(N($K15)=0,$I15=""),"",IF(N($L15)>=$K15,"Concluído",IF(OR(N($L15)<=0,TODAY()<=$I15),"Sem ritmo",TODAY()+ROUNDUP(($K15-$L15)/($L15/(TODAY()-$I15)),0))))) | Q15: =IF($B15="","",IF(ISNUMBER($P15),IF(AND(ISNUMBER($J15),$P15>$J15),"▲ Atrasado vs plano","● No prazo"),IF($P15="Concluído","◆ Concluído","—")))
A16: =IF($B16="","","LV-"&TEXT(ROW()-9,"00")) | M16: =IF($B16="","",IF(N($K16)=0,0,MIN(1,N($L16)/$K16))) | N16: =IF($B16="","",SUMIFS('Diário de Estudo'!$D$7:$D$506,'Diário de Estudo'!$C$7:$C$506,$B16)) | O16: =IF($B16="","",IF(AND(N($N16)>0,N($H16)>0),$H16/$N16,"")) | P16: =IF($B16="","",IF(OR(N($K16)=0,$I16=""),"",IF(N($L16)>=$K16,"Concluído",IF(OR(N($L16)<=0,TODAY()<=$I16),"Sem ritmo",TODAY()+ROUNDUP(($K16-$L16)/($L16/(TODAY()-$I16)),0))))) | Q16: =IF($B16="","",IF(ISNUMBER($P16),IF(AND(ISNUMBER($J16),$P16>$J16),"▲ Atrasado vs plano","● No prazo"),IF($P16="Concluído","◆ Concluído","—")))
A17: =IF($B17="","","LV-"&TEXT(ROW()-9,"00")) | M17: =IF($B17="","",IF(N($K17)=0,0,MIN(1,N($L17)/$K17))) | N17: =IF($B17="","",SUMIFS('Diário de Estudo'!$D$7:$D$506,'Diário de Estudo'!$C$7:$C$506,$B17)) | O17: =IF($B17="","",IF(AND(N($N17)>0,N($H17)>0),$H17/$N17,"")) | P17: =IF($B17="","",IF(OR(N($K17)=0,$I17=""),"",IF(N($L17)>=$K17,"Concluído",IF(OR(N($L17)<=0,TODAY()<=$I17),"Sem ritmo",TODAY()+ROUNDUP(($K17-$L17)/($L17/(TODAY()-$I17)),0))))) | Q17: =IF($B17="","",IF(ISNUMBER($P17),IF(AND(ISNUMBER($J17),$P17>$J17),"▲ Atrasado vs plano","● No prazo"),IF($P17="Concluído","◆ Concluído","—")))
A18: =IF($B18="","","LV-"&TEXT(ROW()-9,"00")) | M18: =IF($B18="","",IF(N($K18)=0,0,MIN(1,N($L18)/$K18))) | N18: =IF($B18="","",SUMIFS('Diário de Estudo'!$D$7:$D$506,'Diário de Estudo'!$C$7:$C$506,$B18)) | O18: =IF($B18="","",IF(AND(N($N18)>0,N($H18)>0),$H18/$N18,"")) | P18: =IF($B18="","",IF(OR(N($K18)=0,$I18=""),"",IF(N($L18)>=$K18,"Concluído",IF(OR(N($L18)<=0,TODAY()<=$I18),"Sem ritmo",TODAY()+ROUNDUP(($K18-$L18)/($L18/(TODAY()-$I18)),0))))) | Q18: =IF($B18="","",IF(ISNUMBER($P18),IF(AND(ISNUMBER($J18),$P18>$J18),"▲ Atrasado vs plano","● No prazo"),IF($P18="Concluído","◆ Concluído","—")))
A19: =IF($B19="","","LV-"&TEXT(ROW()-9,"00")) | M19: =IF($B19="","",IF(N($K19)=0,0,MIN(1,N($L19)/$K19))) | N19: =IF($B19="","",SUMIFS('Diário de Estudo'!$D$7:$D$506,'Diário de Estudo'!$C$7:$C$506,$B19)) | O19: =IF($B19="","",IF(AND(N($N19)>0,N($H19)>0),$H19/$N19,"")) | P19: =IF($B19="","",IF(OR(N($K19)=0,$I19=""),"",IF(N($L19)>=$K19,"Concluído",IF(OR(N($L19)<=0,TODAY()<=$I19),"Sem ritmo",TODAY()+ROUNDUP(($K19-$L19)/($L19/(TODAY()-$I19)),0))))) | Q19: =IF($B19="","",IF(ISNUMBER($P19),IF(AND(ISNUMBER($J19),$P19>$J19),"▲ Atrasado vs plano","● No prazo"),IF($P19="Concluído","◆ Concluído","—")))
A20: =IF($B20="","","LV-"&TEXT(ROW()-9,"00")) | M20: =IF($B20="","",IF(N($K20)=0,0,MIN(1,N($L20)/$K20))) | N20: =IF($B20="","",SUMIFS('Diário de Estudo'!$D$7:$D$506,'Diário de Estudo'!$C$7:$C$506,$B20)) | O20: =IF($B20="","",IF(AND(N($N20)>0,N($H20)>0),$H20/$N20,"")) | P20: =IF($B20="","",IF(OR(N($K20)=0,$I20=""),"",IF(N($L20)>=$K20,"Concluído",IF(OR(N($L20)<=0,TODAY()<=$I20),"Sem ritmo",TODAY()+ROUNDUP(($K20-$L20)/($L20/(TODAY()-$I20)),0))))) | Q20: =IF($B20="","",IF(ISNUMBER($P20),IF(AND(ISNUMBER($J20),$P20>$J20),"▲ Atrasado vs plano","● No prazo"),IF($P20="Concluído","◆ Concluído","—")))
A21: =IF($B21="","","LV-"&TEXT(ROW()-9,"00")) | M21: =IF($B21="","",IF(N($K21)=0,0,MIN(1,N($L21)/$K21))) | N21: =IF($B21="","",SUMIFS('Diário de Estudo'!$D$7:$D$506,'Diário de Estudo'!$C$7:$C$506,$B21)) | O21: =IF($B21="","",IF(AND(N($N21)>0,N($H21)>0),$H21/$N21,"")) | P21: =IF($B21="","",IF(OR(N($K21)=0,$I21=""),"",IF(N($L21)>=$K21,"Concluído",IF(OR(N($L21)<=0,TODAY()<=$I21),"Sem ritmo",TODAY()+ROUNDUP(($K21-$L21)/($L21/(TODAY()-$I21)),0))))) | Q21: =IF($B21="","",IF(ISNUMBER($P21),IF(AND(ISNUMBER($J21),$P21>$J21),"▲ Atrasado vs plano","● No prazo"),IF($P21="Concluído","◆ Concluído","—")))
A22: =IF($B22="","","LV-"&TEXT(ROW()-9,"00")) | M22: =IF($B22="","",IF(N($K22)=0,0,MIN(1,N($L22)/$K22))) | N22: =IF($B22="","",SUMIFS('Diário de Estudo'!$D$7:$D$506,'Diário de Estudo'!$C$7:$C$506,$B22)) | O22: =IF($B22="","",IF(AND(N($N22)>0,N($H22)>0),$H22/$N22,"")) | P22: =IF($B22="","",IF(OR(N($K22)=0,$I22=""),"",IF(N($L22)>=$K22,"Concluído",IF(OR(N($L22)<=0,TODAY()<=$I22),"Sem ritmo",TODAY()+ROUNDUP(($K22-$L22)/($L22/(TODAY()-$I22)),0))))) | Q22: =IF($B22="","",IF(ISNUMBER($P22),IF(AND(ISNUMBER($J22),$P22>$J22),"▲ Atrasado vs plano","● No prazo"),IF($P22="Concluído","◆ Concluído","—")))
... A49: =IF($B49="","","LV-"&TEXT(ROW()-9,"00")) | M49: =IF($B49="","",IF(N($K49)=0,0,MIN(1,N($L49)/$K49))) | N49: =IF($B49="","",SUMIFS('Diário de Estudo'!$D$7:$D$506,'Diário de Estudo'!$C$7:$C$506,$B49)) | O49: =IF($B49="","",IF(AND(N($N49)>0,N($H49)>0),$H49/$N49,"")) | P49: =IF($B49="","",IF(OR(N($K49)=0,$I49=""),"",IF(N($L49)>=$K49,"Concluído",IF(OR(N($L49)<=0,TODAY()<=$I49),"Sem ritmo",TODAY()+ROUNDUP(($K49-$L49)/($L49/(TODAY()-$I49)),0))))) | Q49: =IF($B49="","",IF(ISNUMBER($P49),IF(AND(ISNUMBER($J49),$P49>$J49),"▲ Atrasado vs plano","● No prazo"),IF($P49="Concluído","◆ Concluído","—")))

Sheet Cursos IA
A1: CURSOS · FOCO EM IA
A2: Inteligência artificial, agentes, automação e ferramentas · do aprendizado à aplicação | W2: ← Voltar ao Início
B5: ITENS | D5: EM ANDAMENTO | F5: CONCLUÍDOS | H5: INVESTIDO | J5: PROGRESSO MÉDIO | L5: ACESSOS A VENCER
B6: =COUNTA(B10:B49) -> 1 | D6: =COUNTIF(S10:S49,"Em andamento") -> 1 | F6: =COUNTIF(S10:S49,"Concluído") -> 0 | H6: =SUM(F10:F49) -> 497 | J6: =IFERROR(AVERAGE(N10:N49),0) -> 0.3 | L6: =COUNTIF(K10:K49,"*A vencer") -> 0
A8: Células cinza = automáticas (não edite) · Linha 10 = exemplo: substitua ou apague · Use a seta das células Status, Prioridade e Certificado
A9: ID | B9: Curso | C9: Instituição / Plataforma | D9: Foco / Ferramenta | E9: Data da compra | F9: Valor pago (R$) | G9: Data de início | H9: Término previsto | I9: Vencimento do acesso | J9: Dias p/ vencer | K9: Situação do acesso | L9: Aulas (total) | M9: Aulas concluídas | N9: % Andamento | O9: Horas estudadas | P9: Custo por hora (R$) | Q9: Previsão de término | R9: Risco de prazo | S9: Status | T9: Prioridade | U9: Certificado | V9: Login | W9: Senha | X9: Link de acesso | Y9: Observações
A10: =IF($B10="","","IA-"&TEXT(ROW()-9,"00")) -> IA-01 | B10: Agentes de IA na Prática (exemplo) | C10: Plataforma Exemplo | D10: Agentes · automação | E10: 46277 | F10: 497 | G10: 46285 | H10: 46376 | I10: 46642 | J10: =IF(OR($B10="",$I10=""),"",$I10-TODAY()) -> 344 | K10: =IF($B10="","",IF($I10="","∞ Vitalício",IF($J10<0,"■ Vencido",IF($J10<=Listas!$H$6,"▲ A vencer","● Ativo")))) -> ● Ativo | L10: 60 | M10: 18 | N10: =IF($B10="","",IF(N($L10)=0,0,MIN(1,N($M10)/$L10))) -> 0.3 | O10: =IF($B10="","",SUMIFS('Diário de Estudo'!$D$7:$D$506,'Diário de Estudo'!$C$7:$C$506,$B10)) -> 1.5 | P10: =IF($B10="","",IF(AND(N($O10)>0,N($F10)>0),$F10/$O10,"")) -> 331.33333 | Q10: =IF($B10="","",IF(OR(N($L10)=0,$G10=""),"",IF(N($M10)>=$L10,"Concluído",IF(OR(N($M10)<=0,TODAY()<=$G10),"Sem ritmo",TODAY()+ROUNDUP(($L10-$M10)/($M10/(TODAY()-$G10)),0))))) -> 46329 | R10: =IF($B10="","",IF(ISNUMBER($Q10),IF(AND(ISNUMBER($I10),$Q10>$I10),"■ Estoura o acesso",IF(AND(ISNUMBER($H10),$Q10>$H10),"▲ Atrasado vs plano","● No prazo")),IF($Q10="Concluído","◆ Concluído","—"))) -> ● No prazo | S10: Em andamento | T10: Alta | U10: Não emitido | V10: seu.email@exemplo.com | W10: (guarde no gerenciador de senhas) | X10: https://plataforma.exemplo.com | Y10: Linha de exemplo — substitua pelos seus dados.
A11: =IF($B11="","","IA-"&TEXT(ROW()-9,"00")) | J11: =IF(OR($B11="",$I11=""),"",$I11-TODAY()) | K11: =IF($B11="","",IF($I11="","∞ Vitalício",IF($J11<0,"■ Vencido",IF($J11<=Listas!$H$6,"▲ A vencer","● Ativo")))) | N11: =IF($B11="","",IF(N($L11)=0,0,MIN(1,N($M11)/$L11))) | O11: =IF($B11="","",SUMIFS('Diário de Estudo'!$D$7:$D$506,'Diário de Estudo'!$C$7:$C$506,$B11)) | P11: =IF($B11="","",IF(AND(N($O11)>0,N($F11)>0),$F11/$O11,"")) | Q11: =IF($B11="","",IF(OR(N($L11)=0,$G11=""),"",IF(N($M11)>=$L11,"Concluído",IF(OR(N($M11)<=0,TODAY()<=$G11),"Sem ritmo",TODAY()+ROUNDUP(($L11-$M11)/($M11/(TODAY()-$G11)),0))))) | R11: =IF($B11="","",IF(ISNUMBER($Q11),IF(AND(ISNUMBER($I11),$Q11>$I11),"■ Estoura o acesso",IF(AND(ISNUMBER($H11),$Q11>$H11),"▲ Atrasado vs plano","● No prazo")),IF($Q11="Concluído","◆ Concluído","—")))
A12: =IF($B12="","","IA-"&TEXT(ROW()-9,"00")) | J12: =IF(OR($B12="",$I12=""),"",$I12-TODAY()) | K12: =IF($B12="","",IF($I12="","∞ Vitalício",IF($J12<0,"■ Vencido",IF($J12<=Listas!$H$6,"▲ A vencer","● Ativo")))) | N12: =IF($B12="","",IF(N($L12)=0,0,MIN(1,N($M12)/$L12))) | O12: =IF($B12="","",SUMIFS('Diário de Estudo'!$D$7:$D$506,'Diário de Estudo'!$C$7:$C$506,$B12)) | P12: =IF($B12="","",IF(AND(N($O12)>0,N($F12)>0),$F12/$O12,"")) | Q12: =IF($B12="","",IF(OR(N($L12)=0,$G12=""),"",IF(N($M12)>=$L12,"Concluído",IF(OR(N($M12)<=0,TODAY()<=$G12),"Sem ritmo",TODAY()+ROUNDUP(($L12-$M12)/($M12/(TODAY()-$G12)),0))))) | R12: =IF($B12="","",IF(ISNUMBER($Q12),IF(AND(ISNUMBER($I12),$Q12>$I12),"■ Estoura o acesso",IF(AND(ISNUMBER($H12),$Q12>$H12),"▲ Atrasado vs plano","● No prazo")),IF($Q12="Concluído","◆ Concluído","—")))
A13: =IF($B13="","","IA-"&TEXT(ROW()-9,"00")) | J13: =IF(OR($B13="",$I13=""),"",$I13-TODAY()) | K13: =IF($B13="","",IF($I13="","∞ Vitalício",IF($J13<0,"■ Vencido",IF($J13<=Listas!$H$6,"▲ A vencer","● Ativo")))) | N13: =IF($B13="","",IF(N($L13)=0,0,MIN(1,N($M13)/$L13))) | O13: =IF($B13="","",SUMIFS('Diário de Estudo'!$D$7:$D$506,'Diário de Estudo'!$C$7:$C$506,$B13)) | P13: =IF($B13="","",IF(AND(N($O13)>0,N($F13)>0),$F13/$O13,"")) | Q13: =IF($B13="","",IF(OR(N($L13)=0,$G13=""),"",IF(N($M13)>=$L13,"Concluído",IF(OR(N($M13)<=0,TODAY()<=$G13),"Sem ritmo",TODAY()+ROUNDUP(($L13-$M13)/($M13/(TODAY()-$G13)),0))))) | R13: =IF($B13="","",IF(ISNUMBER($Q13),IF(AND(ISNUMBER($I13),$Q13>$I13),"■ Estoura o acesso",IF(AND(ISNUMBER($H13),$Q13>$H13),"▲ Atrasado vs plano","● No prazo")),IF($Q13="Concluído","◆ Concluído","—")))
A14: =IF($B14="","","IA-"&TEXT(ROW()-9,"00")) | J14: =IF(OR($B14="",$I14=""),"",$I14-TODAY()) | K14: =IF($B14="","",IF($I14="","∞ Vitalício",IF($J14<0,"■ Vencido",IF($J14<=Listas!$H$6,"▲ A vencer","● Ativo")))) | N14: =IF($B14="","",IF(N($L14)=0,0,MIN(1,N($M14)/$L14))) | O14: =IF($B14="","",SUMIFS('Diário de Estudo'!$D$7:$D$506,'Diário de Estudo'!$C$7:$C$506,$B14)) | P14: =IF($B14="","",IF(AND(N($O14)>0,N($F14)>0),$F14/$O14,"")) | Q14: =IF($B14="","",IF(OR(N($L14)=0,$G14=""),"",IF(N($M14)>=$L14,"Concluído",IF(OR(N($M14)<=0,TODAY()<=$G14),"Sem ritmo",TODAY()+ROUNDUP(($L14-$M14)/($M14/(TODAY()-$G14)),0))))) | R14: =IF($B14="","",IF(ISNUMBER($Q14),IF(AND(ISNUMBER($I14),$Q14>$I14),"■ Estoura o acesso",IF(AND(ISNUMBER($H14),$Q14>$H14),"▲ Atrasado vs plano","● No prazo")),IF($Q14="Concluído","◆ Concluído","—")))
A15: =IF($B15="","","IA-"&TEXT(ROW()-9,"00")) | J15: =IF(OR($B15="",$I15=""),"",$I15-TODAY()) | K15: =IF($B15="","",IF($I15="","∞ Vitalício",IF($J15<0,"■ Vencido",IF($J15<=Listas!$H$6,"▲ A vencer","● Ativo")))) | N15: =IF($B15="","",IF(N($L15)=0,0,MIN(1,N($M15)/$L15))) | O15: =IF($B15="","",SUMIFS('Diário de Estudo'!$D$7:$D$506,'Diário de Estudo'!$C$7:$C$506,$B15)) | P15: =IF($B15="","",IF(AND(N($O15)>0,N($F15)>0),$F15/$O15,"")) | Q15: =IF($B15="","",IF(OR(N($L15)=0,$G15=""),"",IF(N($M15)>=$L15,"Concluído",IF(OR(N($M15)<=0,TODAY()<=$G15),"Sem ritmo",TODAY()+ROUNDUP(($L15-$M15)/($M15/(TODAY()-$G15)),0))))) | R15: =IF($B15="","",IF(ISNUMBER($Q15),IF(AND(ISNUMBER($I15),$Q15>$I15),"■ Estoura o acesso",IF(AND(ISNUMBER($H15),$Q15>$H15),"▲ Atrasado vs plano","● No prazo")),IF($Q15="Concluído","◆ Concluído","—")))
A16: =IF($B16="","","IA-"&TEXT(ROW()-9,"00")) | J16: =IF(OR($B16="",$I16=""),"",$I16-TODAY()) | K16: =IF($B16="","",IF($I16="","∞ Vitalício",IF($J16<0,"■ Vencido",IF($J16<=Listas!$H$6,"▲ A vencer","● Ativo")))) | N16: =IF($B16="","",IF(N($L16)=0,0,MIN(1,N($M16)/$L16))) | O16: =IF($B16="","",SUMIFS('Diário de Estudo'!$D$7:$D$506,'Diário de Estudo'!$C$7:$C$506,$B16)) | P16: =IF($B16="","",IF(AND(N($O16)>0,N($F16)>0),$F16/$O16,"")) | Q16: =IF($B16="","",IF(OR(N($L16)=0,$G16=""),"",IF(N($M16)>=$L16,"Concluído",IF(OR(N($M16)<=0,TODAY()<=$G16),"Sem ritmo",TODAY()+ROUNDUP(($L16-$M16)/($M16/(TODAY()-$G16)),0))))) | R16: =IF($B16="","",IF(ISNUMBER($Q16),IF(AND(ISNUMBER($I16),$Q16>$I16),"■ Estoura o acesso",IF(AND(ISNUMBER($H16),$Q16>$H16),"▲ Atrasado vs plano","● No prazo")),IF($Q16="Concluído","◆ Concluído","—")))
A17: =IF($B17="","","IA-"&TEXT(ROW()-9,"00")) | J17: =IF(OR($B17="",$I17=""),"",$I17-TODAY()) | K17: =IF($B17="","",IF($I17="","∞ Vitalício",IF($J17<0,"■ Vencido",IF($J17<=Listas!$H$6,"▲ A vencer","● Ativo")))) | N17: =IF($B17="","",IF(N($L17)=0,0,MIN(1,N($M17)/$L17))) | O17: =IF($B17="","",SUMIFS('Diário de Estudo'!$D$7:$D$506,'Diário de Estudo'!$C$7:$C$506,$B17)) | P17: =IF($B17="","",IF(AND(N($O17)>0,N($F17)>0),$F17/$O17,"")) | Q17: =IF($B17="","",IF(OR(N($L17)=0,$G17=""),"",IF(N($M17)>=$L17,"Concluído",IF(OR(N($M17)<=0,TODAY()<=$G17),"Sem ritmo",TODAY()+ROUNDUP(($L17-$M17)/($M17/(TODAY()-$G17)),0))))) | R17: =IF($B17="","",IF(ISNUMBER($Q17),IF(AND(ISNUMBER($I17),$Q17>$I17),"■ Estoura o acesso",IF(AND(ISNUMBER($H17),$Q17>$H17),"▲ Atrasado vs plano","● No prazo")),IF($Q17="Concluído","◆ Concluído","—")))
A18: =IF($B18="","","IA-"&TEXT(ROW()-9,"00")) | J18: =IF(OR($B18="",$I18=""),"",$I18-TODAY()) | K18: =IF($B18="","",IF($I18="","∞ Vitalício",IF($J18<0,"■ Vencido",IF($J18<=Listas!$H$6,"▲ A vencer","● Ativo")))) | N18: =IF($B18="","",IF(N($L18)=0,0,MIN(1,N($M18)/$L18))) | O18: =IF($B18="","",SUMIFS('Diário de Estudo'!$D$7:$D$506,'Diário de Estudo'!$C$7:$C$506,$B18)) | P18: =IF($B18="","",IF(AND(N($O18)>0,N($F18)>0),$F18/$O18,"")) | Q18: =IF($B18="","",IF(OR(N($L18)=0,$G18=""),"",IF(N($M18)>=$L18,"Concluído",IF(OR(N($M18)<=0,TODAY()<=$G18),"Sem ritmo",TODAY()+ROUNDUP(($L18-$M18)/($M18/(TODAY()-$G18)),0))))) | R18: =IF($B18="","",IF(ISNUMBER($Q18),IF(AND(ISNUMBER($I18),$Q18>$I18),"■ Estoura o acesso",IF(AND(ISNUMBER($H18),$Q18>$H18),"▲ Atrasado vs plano","● No prazo")),IF($Q18="Concluído","◆ Concluído","—")))
A19: =IF($B19="","","IA-"&TEXT(ROW()-9,"00")) | J19: =IF(OR($B19="",$I19=""),"",$I19-TODAY()) | K19: =IF($B19="","",IF($I19="","∞ Vitalício",IF($J19<0,"■ Vencido",IF($J19<=Listas!$H$6,"▲ A vencer","● Ativo")))) | N19: =IF($B19="","",IF(N($L19)=0,0,MIN(1,N($M19)/$L19))) | O19: =IF($B19="","",SUMIFS('Diário de Estudo'!$D$7:$D$506,'Diário de Estudo'!$C$7:$C$506,$B19)) | P19: =IF($B19="","",IF(AND(N($O19)>0,N($F19)>0),$F19/$O19,"")) | Q19: =IF($B19="","",IF(OR(N($L19)=0,$G19=""),"",IF(N($M19)>=$L19,"Concluído",IF(OR(N($M19)<=0,TODAY()<=$G19),"Sem ritmo",TODAY()+ROUNDUP(($L19-$M19)/($M19/(TODAY()-$G19)),0))))) | R19: =IF($B19="","",IF(ISNUMBER($Q19),IF(AND(ISNUMBER($I19),$Q19>$I19),"■ Estoura o acesso",IF(AND(ISNUMBER($H19),$Q19>$H19),"▲ Atrasado vs plano","● No prazo")),IF($Q19="Concluído","◆ Concluído","—")))
A20: =IF($B20="","","IA-"&TEXT(ROW()-9,"00")) | J20: =IF(OR($B20="",$I20=""),"",$I20-TODAY()) | K20: =IF($B20="","",IF($I20="","∞ Vitalício",IF($J20<0,"■ Vencido",IF($J20<=Listas!$H$6,"▲ A vencer","● Ativo")))) | N20: =IF($B20="","",IF(N($L20)=0,0,MIN(1,N($M20)/$L20))) | O20: =IF($B20="","",SUMIFS('Diário de Estudo'!$D$7:$D$506,'Diário de Estudo'!$C$7:$C$506,$B20)) | P20: =IF($B20="","",IF(AND(N($O20)>0,N($F20)>0),$F20/$O20,"")) | Q20: =IF($B20="","",IF(OR(N($L20)=0,$G20=""),"",IF(N($M20)>=$L20,"Concluído",IF(OR(N($M20)<=0,TODAY()<=$G20),"Sem ritmo",TODAY()+ROUNDUP(($L20-$M20)/($M20/(TODAY()-$G20)),0))))) | R20: =IF($B20="","",IF(ISNUMBER($Q20),IF(AND(ISNUMBER($I20),$Q20>$I20),"■ Estoura o acesso",IF(AND(ISNUMBER($H20),$Q20>$H20),"▲ Atrasado vs plano","● No prazo")),IF($Q20="Concluído","◆ Concluído","—")))
A21: =IF($B21="","","IA-"&TEXT(ROW()-9,"00")) | J21: =IF(OR($B21="",$I21=""),"",$I21-TODAY()) | K21: =IF($B21="","",IF($I21="","∞ Vitalício",IF($J21<0,"■ Vencido",IF($J21<=Listas!$H$6,"▲ A vencer","● Ativo")))) | N21: =IF($B21="","",IF(N($L21)=0,0,MIN(1,N($M21)/$L21))) | O21: =IF($B21="","",SUMIFS('Diário de Estudo'!$D$7:$D$506,'Diário de Estudo'!$C$7:$C$506,$B21)) | P21: =IF($B21="","",IF(AND(N($O21)>0,N($F21)>0),$F21/$O21,"")) | Q21: =IF($B21="","",IF(OR(N($L21)=0,$G21=""),"",IF(N($M21)>=$L21,"Concluído",IF(OR(N($M21)<=0,TODAY()<=$G21),"Sem ritmo",TODAY()+ROUNDUP(($L21-$M21)/($M21/(TODAY()-$G21)),0))))) | R21: =IF($B21="","",IF(ISNUMBER($Q21),IF(AND(ISNUMBER($I21),$Q21>$I21),"■ Estoura o acesso",IF(AND(ISNUMBER($H21),$Q21>$H21),"▲ Atrasado vs plano","● No prazo")),IF($Q21="Concluído","◆ Concluído","—")))
A22: =IF($B22="","","IA-"&TEXT(ROW()-9,"00")) | J22: =IF(OR($B22="",$I22=""),"",$I22-TODAY()) | K22: =IF($B22="","",IF($I22="","∞ Vitalício",IF($J22<0,"■ Vencido",IF($J22<=Listas!$H$6,"▲ A vencer","● Ativo")))) | N22: =IF($B22="","",IF(N($L22)=0,0,MIN(1,N($M22)/$L22))) | O22: =IF($B22="","",SUMIFS('Diário de Estudo'!$D$7:$D$506,'Diário de Estudo'!$C$7:$C$506,$B22)) | P22: =IF($B22="","",IF(AND(N($O22)>0,N($F22)>0),$F22/$O22,"")) | Q22: =IF($B22="","",IF(OR(N($L22)=0,$G22=""),"",IF(N($M22)>=$L22,"Concluído",IF(OR(N($M22)<=0,TODAY()<=$G22),"Sem ritmo",TODAY()+ROUNDUP(($L22-$M22)/($M22/(TODAY()-$G22)),0))))) | R22: =IF($B22="","",IF(ISNUMBER($Q22),IF(AND(ISNUMBER($I22),$Q22>$I22),"■ Estoura o acesso",IF(AND(ISNUMBER($H22),$Q22>$H22),"▲ Atrasado vs plano","● No prazo")),IF($Q22="Concluído","◆ Concluído","—")))
... A49: =IF($B49="","","IA-"&TEXT(ROW()-9,"00")) | J49: =IF(OR($B49="",$I49=""),"",$I49-TODAY()) | K49: =IF($B49="","",IF($I49="","∞ Vitalício",IF($J49<0,"■ Vencido",IF($J49<=Listas!$H$6,"▲ A vencer","● Ativo")))) | N49: =IF($B49="","",IF(N($L49)=0,0,MIN(1,N($M49)/$L49))) | O49: =IF($B49="","",SUMIFS('Diário de Estudo'!$D$7:$D$506,'Diário de Estudo'!$C$7:$C$506,$B49)) | P49: =IF($B49="","",IF(AND(N($O49)>0,N($F49)>0),$F49/$O49,"")) | Q49: =IF($B49="","",IF(OR(N($L49)=0,$G49=""),"",IF(N($M49)>=$L49,"Concluído",IF(OR(N($M49)<=0,TODAY()<=$G49),"Sem ritmo",TODAY()+ROUNDUP(($L49-$M49)/($M49/(TODAY()-$G49)),0))))) | R49: =IF($B49="","",IF(ISNUMBER($Q49),IF(AND(ISNUMBER($I49),$Q49>$I49),"■ Estoura o acesso",IF(AND(ISNUMBER($H49),$Q49>$H49),"▲ Atrasado vs plano","● No prazo")),IF($Q49="Concluído","◆ Concluído","—")))

Sheet Renda Extra
A1: CURSOS · FOCO EM RENDA EXTRA
A2: Afiliados, freelas, infoprodutos e negócios digitais · aprendizado e retorno financeiro | AC2: ← Voltar ao Início
B5: ITENS | D5: EM ANDAMENTO | F5: CONCLUÍDOS | H5: INVESTIDO | J5: PROGRESSO MÉDIO | L5: RESULTADO/MÊS ATUAL
B6: =COUNTA(B10:B49) -> 1 | D6: =COUNTIF(S10:S49,"Em andamento") -> 1 | F6: =COUNTIF(S10:S49,"Concluído") -> 0 | H6: =SUM(F10:F49) -> 297 | J6: =IFERROR(AVERAGE(N10:N49),0) -> 0.22222222 | L6: =SUM(W10:W49) -> 120
A8: Células cinza = automáticas (não edite) · Linha 10 = exemplo: substitua ou apague · Use a seta das células Status, Prioridade e Certificado
A9: ID | B9: Curso | C9: Instituição / Plataforma | D9: Modelo de renda | E9: Data da compra | F9: Valor pago (R$) | G9: Data de início | H9: Término previsto | I9: Vencimento do acesso | J9: Dias p/ vencer | K9: Situação do acesso | L9: Aulas (total) | M9: Aulas concluídas | N9: % Andamento | O9: Horas estudadas | P9: Custo por hora (R$) | Q9: Previsão de término | R9: Risco de prazo | S9: Status | T9: Prioridade | U9: Certificado | V9: Meta de ganho/mês (R$) | W9: Resultado atual/mês (R$) | X9: Receita acumulada (R$) | Y9: ROI | Z9: Payback (meses) | AA9: Retorno | AB9: Login | AC9: Senha | AD9: Link de acesso | AE9: Observações
A10: =IF($B10="","","RE-"&TEXT(ROW()-9,"00")) -> RE-01 | B10: Marketing de Afiliados do Zero (exemplo) | C10: Plataforma Exemplo | D10: Afiliados | E10: 46266 | F10: 297 | G10: 46268 | H10: 46356 | I10: 46631 | J10: =IF(OR($B10="",$I10=""),"",$I10-TODAY()) -> 333 | K10: =IF($B10="","",IF($I10="","∞ Vitalício",IF($J10<0,"■ Vencido",IF($J10<=Listas!$H$6,"▲ A vencer","● Ativo")))) -> ● Ativo | L10: 45 | M10: 10 | N10: =IF($B10="","",IF(N($L10)=0,0,MIN(1,N($M10)/$L10))) -> 0.22222222 | O10: =IF($B10="","",SUMIFS('Diário de Estudo'!$D$7:$D$506,'Diário de Estudo'!$C$7:$C$506,$B10)) -> 0 | P10: =IF($B10="","",IF(AND(N($O10)>0,N($F10)>0),$F10/$O10,"")) | Q10: =IF($B10="","",IF(OR(N($L10)=0,$G10=""),"",IF(N($M10)>=$L10,"Concluído",IF(OR(N($M10)<=0,TODAY()<=$G10),"Sem ritmo",TODAY()+ROUNDUP(($L10-$M10)/($M10/(TODAY()-$G10)),0))))) -> 46403 | R10: =IF($B10="","",IF(ISNUMBER($Q10),IF(AND(ISNUMBER($I10),$Q10>$I10),"■ Estoura o acesso",IF(AND(ISNUMBER($H10),$Q10>$H10),"▲ Atrasado vs plano","● No prazo")),IF($Q10="Concluído","◆ Concluído","—"))) -> ▲ Atrasado vs plano | S10: Em andamento | T10: Média | U10: Não emitido | V10: 1500 | W10: 120 | X10: 180 | Y10: =IF($B10="","",IF(N($F10)=0,"",(N($X10)-$F10)/$F10)) -> -0.39393939 | Z10: =IF($B10="","",IF(N($F10)=0,"",IF(N($X10)>=$F10,0,IF(N($W10)>0,($F10-N($X10))/$W10,"—")))) -> 0.975 | AA10: =IF($B10="","",IF(N($F10)=0,"—",IF(N($X10)>=$F10,"● Pago",IF(N($X10)>0,"▲ Em retorno","■ Sem retorno")))) -> ▲ Em retorno | AB10: seu.email@exemplo.com | AC10: (guarde no gerenciador de senhas) | AD10: https://plataforma.exemplo.com | AE10: Linha de exemplo — substitua pelos seus dados.
A11: =IF($B11="","","RE-"&TEXT(ROW()-9,"00")) | J11: =IF(OR($B11="",$I11=""),"",$I11-TODAY()) | K11: =IF($B11="","",IF($I11="","∞ Vitalício",IF($J11<0,"■ Vencido",IF($J11<=Listas!$H$6,"▲ A vencer","● Ativo")))) | N11: =IF($B11="","",IF(N($L11)=0,0,MIN(1,N($M11)/$L11))) | O11: =IF($B11="","",SUMIFS('Diário de Estudo'!$D$7:$D$506,'Diário de Estudo'!$C$7:$C$506,$B11)) | P11: =IF($B11="","",IF(AND(N($O11)>0,N($F11)>0),$F11/$O11,"")) | Q11: =IF($B11="","",IF(OR(N($L11)=0,$G11=""),"",IF(N($M11)>=$L11,"Concluído",IF(OR(N($M11)<=0,TODAY()<=$G11),"Sem ritmo",TODAY()+ROUNDUP(($L11-$M11)/($M11/(TODAY()-$G11)),0))))) | R11: =IF($B11="","",IF(ISNUMBER($Q11),IF(AND(ISNUMBER($I11),$Q11>$I11),"■ Estoura o acesso",IF(AND(ISNUMBER($H11),$Q11>$H11),"▲ Atrasado vs plano","● No prazo")),IF($Q11="Concluído","◆ Concluído","—"))) | Y11: =IF($B11="","",IF(N($F11)=0,"",(N($X11)-$F11)/$F11)) | Z11: =IF($B11="","",IF(N($F11)=0,"",IF(N($X11)>=$F11,0,IF(N($W11)>0,($F11-N($X11))/$W11,"—")))) | AA11: =IF($B11="","",IF(N($F11)=0,"—",IF(N($X11)>=$F11,"● Pago",IF(N($X11)>0,"▲ Em retorno","■ Sem retorno"))))
A12: =IF($B12="","","RE-"&TEXT(ROW()-9,"00")) | J12: =IF(OR($B12="",$I12=""),"",$I12-TODAY()) | K12: =IF($B12="","",IF($I12="","∞ Vitalício",IF($J12<0,"■ Vencido",IF($J12<=Listas!$H$6,"▲ A vencer","● Ativo")))) | N12: =IF($B12="","",IF(N($L12)=0,0,MIN(1,N($M12)/$L12))) | O12: =IF($B12="","",SUMIFS('Diário de Estudo'!$D$7:$D$506,'Diário de Estudo'!$C$7:$C$506,$B12)) | P12: =IF($B12="","",IF(AND(N($O12)>0,N($F12)>0),$F12/$O12,"")) | Q12: =IF($B12="","",IF(OR(N($L12)=0,$G12=""),"",IF(N($M12)>=$L12,"Concluído",IF(OR(N($M12)<=0,TODAY()<=$G12),"Sem ritmo",TODAY()+ROUNDUP(($L12-$M12)/($M12/(TODAY()-$G12)),0))))) | R12: =IF($B12="","",IF(ISNUMBER($Q12),IF(AND(ISNUMBER($I12),$Q12>$I12),"■ Estoura o acesso",IF(AND(ISNUMBER($H12),$Q12>$H12),"▲ Atrasado vs plano","● No prazo")),IF($Q12="Concluído","◆ Concluído","—"))) | Y12: =IF($B12="","",IF(N($F12)=0,"",(N($X12)-$F12)/$F12)) | Z12: =IF($B12="","",IF(N($F12)=0,"",IF(N($X12)>=$F12,0,IF(N($W12)>0,($F12-N($X12))/$W12,"—")))) | AA12: =IF($B12="","",IF(N($F12)=0,"—",IF(N($X12)>=$F12,"● Pago",IF(N($X12)>0,"▲ Em retorno","■ Sem retorno"))))
A13: =IF($B13="","","RE-"&TEXT(ROW()-9,"00")) | J13: =IF(OR($B13="",$I13=""),"",$I13-TODAY()) | K13: =IF($B13="","",IF($I13="","∞ Vitalício",IF($J13<0,"■ Vencido",IF($J13<=Listas!$H$6,"▲ A vencer","● Ativo")))) | N13: =IF($B13="","",IF(N($L13)=0,0,MIN(1,N($M13)/$L13))) | O13: =IF($B13="","",SUMIFS('Diário de Estudo'!$D$7:$D$506,'Diário de Estudo'!$C$7:$C$506,$B13)) | P13: =IF($B13="","",IF(AND(N($O13)>0,N($F13)>0),$F13/$O13,"")) | Q13: =IF($B13="","",IF(OR(N($L13)=0,$G13=""),"",IF(N($M13)>=$L13,"Concluído",IF(OR(N($M13)<=0,TODAY()<=$G13),"Sem ritmo",TODAY()+ROUNDUP(($L13-$M13)/($M13/(TODAY()-$G13)),0))))) | R13: =IF($B13="","",IF(ISNUMBER($Q13),IF(AND(ISNUMBER($I13),$Q13>$I13),"■ Estoura o acesso",IF(AND(ISNUMBER($H13),$Q13>$H13),"▲ Atrasado vs plano","● No prazo")),IF($Q13="Concluído","◆ Concluído","—"))) | Y13: =IF($B13="","",IF(N($F13)=0,"",(N($X13)-$F13)/$F13)) | Z13: =IF($B13="","",IF(N($F13)=0,"",IF(N($X13)>=$F13,0,IF(N($W13)>0,($F13-N($X13))/$W13,"—")))) | AA13: =IF($B13="","",IF(N($F13)=0,"—",IF(N($X13)>=$F13,"● Pago",IF(N($X13)>0,"▲ Em retorno","■ Sem retorno"))))
A14: =IF($B14="","","RE-"&TEXT(ROW()-9,"00")) | J14: =IF(OR($B14="",$I14=""),"",$I14-TODAY()) | K14: =IF($B14="","",IF($I14="","∞ Vitalício",IF($J14<0,"■ Vencido",IF($J14<=Listas!$H$6,"▲ A vencer","● Ativo")))) | N14: =IF($B14="","",IF(N($L14)=0,0,MIN(1,N($M14)/$L14))) | O14: =IF($B14="","",SUMIFS('Diário de Estudo'!$D$7:$D$506,'Diário de Estudo'!$C$7:$C$506,$B14)) | P14: =IF($B14="","",IF(AND(N($O14)>0,N($F14)>0),$F14/$O14,"")) | Q14: =IF($B14="","",IF(OR(N($L14)=0,$G14=""),"",IF(N($M14)>=$L14,"Concluído",IF(OR(N($M14)<=0,TODAY()<=$G14),"Sem ritmo",TODAY()+ROUNDUP(($L14-$M14)/($M14/(TODAY()-$G14)),0))))) | R14: =IF($B14="","",IF(ISNUMBER($Q14),IF(AND(ISNUMBER($I14),$Q14>$I14),"■ Estoura o acesso",IF(AND(ISNUMBER($H14),$Q14>$H14),"▲ Atrasado vs plano","● No prazo")),IF($Q14="Concluído","◆ Concluído","—"))) | Y14: =IF($B14="","",IF(N($F14)=0,"",(N($X14)-$F14)/$F14)) | Z14: =IF($B14="","",IF(N($F14)=0,"",IF(N($X14)>=$F14,0,IF(N($W14)>0,($F14-N($X14))/$W14,"—")))) | AA14: =IF($B14="","",IF(N($F14)=0,"—",IF(N($X14)>=$F14,"● Pago",IF(N($X14)>0,"▲ Em retorno","■ Sem retorno"))))
A15: =IF($B15="","","RE-"&TEXT(ROW()-9,"00")) | J15: =IF(OR($B15="",$I15=""),"",$I15-TODAY()) | K15: =IF($B15="","",IF($I15="","∞ Vitalício",IF($J15<0,"■ Vencido",IF($J15<=Listas!$H$6,"▲ A vencer","● Ativo")))) | N15: =IF($B15="","",IF(N($L15)=0,0,MIN(1,N($M15)/$L15))) | O15: =IF($B15="","",SUMIFS('Diário de Estudo'!$D$7:$D$506,'Diário de Estudo'!$C$7:$C$506,$B15)) | P15: =IF($B15="","",IF(AND(N($O15)>0,N($F15)>0),$F15/$O15,"")) | Q15: =IF($B15="","",IF(OR(N($L15)=0,$G15=""),"",IF(N($M15)>=$L15,"Concluído",IF(OR(N($M15)<=0,TODAY()<=$G15),"Sem ritmo",TODAY()+ROUNDUP(($L15-$M15)/($M15/(TODAY()-$G15)),0))))) | R15: =IF($B15="","",IF(ISNUMBER($Q15),IF(AND(ISNUMBER($I15),$Q15>$I15),"■ Estoura o acesso",IF(AND(ISNUMBER($H15),$Q15>$H15),"▲ Atrasado vs plano","● No prazo")),IF($Q15="Concluído","◆ Concluído","—"))) | Y15: =IF($B15="","",IF(N($F15)=0,"",(N($X15)-$F15)/$F15)) | Z15: =IF($B15="","",IF(N($F15)=0,"",IF(N($X15)>=$F15,0,IF(N($W15)>0,($F15-N($X15))/$W15,"—")))) | AA15: =IF($B15="","",IF(N($F15)=0,"—",IF(N($X15)>=$F15,"● Pago",IF(N($X15)>0,"▲ Em retorno","■ Sem retorno"))))
A16: =IF($B16="","","RE-"&TEXT(ROW()-9,"00")) | J16: =IF(OR($B16="",$I16=""),"",$I16-TODAY()) | K16: =IF($B16="","",IF($I16="","∞ Vitalício",IF($J16<0,"■ Vencido",IF($J16<=Listas!$H$6,"▲ A vencer","● Ativo")))) | N16: =IF($B16="","",IF(N($L16)=0,0,MIN(1,N($M16)/$L16))) | O16: =IF($B16="","",SUMIFS('Diário de Estudo'!$D$7:$D$506,'Diário de Estudo'!$C$7:$C$506,$B16)) | P16: =IF($B16="","",IF(AND(N($O16)>0,N($F16)>0),$F16/$O16,"")) | Q16: =IF($B16="","",IF(OR(N($L16)=0,$G16=""),"",IF(N($M16)>=$L16,"Concluído",IF(OR(N($M16)<=0,TODAY()<=$G16),"Sem ritmo",TODAY()+ROUNDUP(($L16-$M16)/($M16/(TODAY()-$G16)),0))))) | R16: =IF($B16="","",IF(ISNUMBER($Q16),IF(AND(ISNUMBER($I16),$Q16>$I16),"■ Estoura o acesso",IF(AND(ISNUMBER($H16),$Q16>$H16),"▲ Atrasado vs plano","● No prazo")),IF($Q16="Concluído","◆ Concluído","—"))) | Y16: =IF($B16="","",IF(N($F16)=0,"",(N($X16)-$F16)/$F16)) | Z16: =IF($B16="","",IF(N($F16)=0,"",IF(N($X16)>=$F16,0,IF(N($W16)>0,($F16-N($X16))/$W16,"—")))) | AA16: =IF($B16="","",IF(N($F16)=0,"—",IF(N($X16)>=$F16,"● Pago",IF(N($X16)>0,"▲ Em retorno","■ Sem retorno"))))
A17: =IF($B17="","","RE-"&TEXT(ROW()-9,"00")) | J17: =IF(OR($B17="",$I17=""),"",$I17-TODAY()) | K17: =IF($B17="","",IF($I17="","∞ Vitalício",IF($J17<0,"■ Vencido",IF($J17<=Listas!$H$6,"▲ A vencer","● Ativo")))) | N17: =IF($B17="","",IF(N($L17)=0,0,MIN(1,N($M17)/$L17))) | O17: =IF($B17="","",SUMIFS('Diário de Estudo'!$D$7:$D$506,'Diário de Estudo'!$C$7:$C$506,$B17)) | P17: =IF($B17="","",IF(AND(N($O17)>0,N($F17)>0),$F17/$O17,"")) | Q17: =IF($B17="","",IF(OR(N($L17)=0,$G17=""),"",IF(N($M17)>=$L17,"Concluído",IF(OR(N($M17)<=0,TODAY()<=$G17),"Sem ritmo",TODAY()+ROUNDUP(($L17-$M17)/($M17/(TODAY()-$G17)),0))))) | R17: =IF($B17="","",IF(ISNUMBER($Q17),IF(AND(ISNUMBER($I17),$Q17>$I17),"■ Estoura o acesso",IF(AND(ISNUMBER($H17),$Q17>$H17),"▲ Atrasado vs plano","● No prazo")),IF($Q17="Concluído","◆ Concluído","—"))) | Y17: =IF($B17="","",IF(N($F17)=0,"",(N($X17)-$F17)/$F17)) | Z17: =IF($B17="","",IF(N($F17)=0,"",IF(N($X17)>=$F17,0,IF(N($W17)>0,($F17-N($X17))/$W17,"—")))) | AA17: =IF($B17="","",IF(N($F17)=0,"—",IF(N($X17)>=$F17,"● Pago",IF(N($X17)>0,"▲ Em retorno","■ Sem retorno"))))
A18: =IF($B18="","","RE-"&TEXT(ROW()-9,"00")) | J18: =IF(OR($B18="",$I18=""),"",$I18-TODAY()) | K18: =IF($B18="","",IF($I18="","∞ Vitalício",IF($J18<0,"■ Vencido",IF($J18<=Listas!$H$6,"▲ A vencer","● Ativo")))) | N18: =IF($B18="","",IF(N($L18)=0,0,MIN(1,N($M18)/$L18))) | O18: =IF($B18="","",SUMIFS('Diário de Estudo'!$D$7:$D$506,'Diário de Estudo'!$C$7:$C$506,$B18)) | P18: =IF($B18="","",IF(AND(N($O18)>0,N($F18)>0),$F18/$O18,"")) | Q18: =IF($B18="","",IF(OR(N($L18)=0,$G18=""),"",IF(N($M18)>=$L18,"Concluído",IF(OR(N($M18)<=0,TODAY()<=$G18),"Sem ritmo",TODAY()+ROUNDUP(($L18-$M18)/($M18/(TODAY()-$G18)),0))))) | R18: =IF($B18="","",IF(ISNUMBER($Q18),IF(AND(ISNUMBER($I18),$Q18>$I18),"■ Estoura o acesso",IF(AND(ISNUMBER($H18),$Q18>$H18),"▲ Atrasado vs plano","● No prazo")),IF($Q18="Concluído","◆ Concluído","—"))) | Y18: =IF($B18="","",IF(N($F18)=0,"",(N($X18)-$F18)/$F18)) | Z18: =IF($B18="","",IF(N($F18)=0,"",IF(N($X18)>=$F18,0,IF(N($W18)>0,($F18-N($X18))/$W18,"—")))) | AA18: =IF($B18="","",IF(N($F18)=0,"—",IF(N($X18)>=$F18,"● Pago",IF(N($X18)>0,"▲ Em retorno","■ Sem retorno"))))
A19: =IF($B19="","","RE-"&TEXT(ROW()-9,"00")) | J19: =IF(OR($B19="",$I19=""),"",$I19-TODAY()) | K19: =IF($B19="","",IF($I19="","∞ Vitalício",IF($J19<0,"■ Vencido",IF($J19<=Listas!$H$6,"▲ A vencer","● Ativo")))) | N19: =IF($B19="","",IF(N($L19)=0,0,MIN(1,N($M19)/$L19))) | O19: =IF($B19="","",SUMIFS('Diário de Estudo'!$D$7:$D$506,'Diário de Estudo'!$C$7:$C$506,$B19)) | P19: =IF($B19="","",IF(AND(N($O19)>0,N($F19)>0),$F19/$O19,"")) | Q19: =IF($B19="","",IF(OR(N($L19)=0,$G19=""),"",IF(N($M19)>=$L19,"Concluído",IF(OR(N($M19)<=0,TODAY()<=$G19),"Sem ritmo",TODAY()+ROUNDUP(($L19-$M19)/($M19/(TODAY()-$G19)),0))))) | R19: =IF($B19="","",IF(ISNUMBER($Q19),IF(AND(ISNUMBER($I19),$Q19>$I19),"■ Estoura o acesso",IF(AND(ISNUMBER($H19),$Q19>$H19),"▲ Atrasado vs plano","● No prazo")),IF($Q19="Concluído","◆ Concluído","—"))) | Y19: =IF($B19="","",IF(N($F19)=0,"",(N($X19)-$F19)/$F19)) | Z19: =IF($B19="","",IF(N($F19)=0,"",IF(N($X19)>=$F19,0,IF(N($W19)>0,($F19-N($X19))/$W19,"—")))) | AA19: =IF($B19="","",IF(N($F19)=0,"—",IF(N($X19)>=$F19,"● Pago",IF(N($X19)>0,"▲ Em retorno","■ Sem retorno"))))
A20: =IF($B20="","","RE-"&TEXT(ROW()-9,"00")) | J20: =IF(OR($B20="",$I20=""),"",$I20-TODAY()) | K20: =IF($B20="","",IF($I20="","∞ Vitalício",IF($J20<0,"■ Vencido",IF($J20<=Listas!$H$6,"▲ A vencer","● Ativo")))) | N20: =IF($B20="","",IF(N($L20)=0,0,MIN(1,N($M20)/$L20))) | O20: =IF($B20="","",SUMIFS('Diário de Estudo'!$D$7:$D$506,'Diário de Estudo'!$C$7:$C$506,$B20)) | P20: =IF($B20="","",IF(AND(N($O20)>0,N($F20)>0),$F20/$O20,"")) | Q20: =IF($B20="","",IF(OR(N($L20)=0,$G20=""),"",IF(N($M20)>=$L20,"Concluído",IF(OR(N($M20)<=0,TODAY()<=$G20),"Sem ritmo",TODAY()+ROUNDUP(($L20-$M20)/($M20/(TODAY()-$G20)),0))))) | R20: =IF($B20="","",IF(ISNUMBER($Q20),IF(AND(ISNUMBER($I20),$Q20>$I20),"■ Estoura o acesso",IF(AND(ISNUMBER($H20),$Q20>$H20),"▲ Atrasado vs plano","● No prazo")),IF($Q20="Concluído","◆ Concluído","—"))) | Y20: =IF($B20="","",IF(N($F20)=0,"",(N($X20)-$F20)/$F20)) | Z20: =IF($B20="","",IF(N($F20)=0,"",IF(N($X20)>=$F20,0,IF(N($W20)>0,($F20-N($X20))/$W20,"—")))) | AA20: =IF($B20="","",IF(N($F20)=0,"—",IF(N($X20)>=$F20,"● Pago",IF(N($X20)>0,"▲ Em retorno","■ Sem retorno"))))
A21: =IF($B21="","","RE-"&TEXT(ROW()-9,"00")) | J21: =IF(OR($B21="",$I21=""),"",$I21-TODAY()) | K21: =IF($B21="","",IF($I21="","∞ Vitalício",IF($J21<0,"■ Vencido",IF($J21<=Listas!$H$6,"▲ A vencer","● Ativo")))) | N21: =IF($B21="","",IF(N($L21)=0,0,MIN(1,N($M21)/$L21))) | O21: =IF($B21="","",SUMIFS('Diário de Estudo'!$D$7:$D$506,'Diário de Estudo'!$C$7:$C$506,$B21)) | P21: =IF($B21="","",IF(AND(N($O21)>0,N($F21)>0),$F21/$O21,"")) | Q21: =IF($B21="","",IF(OR(N($L21)=0,$G21=""),"",IF(N($M21)>=$L21,"Concluído",IF(OR(N($M21)<=0,TODAY()<=$G21),"Sem ritmo",TODAY()+ROUNDUP(($L21-$M21)/($M21/(TODAY()-$G21)),0))))) | R21: =IF($B21="","",IF(ISNUMBER($Q21),IF(AND(ISNUMBER($I21),$Q21>$I21),"■ Estoura o acesso",IF(AND(ISNUMBER($H21),$Q21>$H21),"▲ Atrasado vs plano","● No prazo")),IF($Q21="Concluído","◆ Concluído","—"))) | Y21: =IF($B21="","",IF(N($F21)=0,"",(N($X21)-$F21)/$F21)) | Z21: =IF($B21="","",IF(N($F21)=0,"",IF(N($X21)>=$F21,0,IF(N($W21)>0,($F21-N($X21))/$W21,"—")))) | AA21: =IF($B21="","",IF(N($F21)=0,"—",IF(N($X21)>=$F21,"● Pago",IF(N($X21)>0,"▲ Em retorno","■ Sem retorno"))))
A22: =IF($B22="","","RE-"&TEXT(ROW()-9,"00")) | J22: =IF(OR($B22="",$I22=""),"",$I22-TODAY()) | K22: =IF($B22="","",IF($I22="","∞ Vitalício",IF($J22<0,"■ Vencido",IF($J22<=Listas!$H$6,"▲ A vencer","● Ativo")))) | N22: =IF($B22="","",IF(N($L22)=0,0,MIN(1,N($M22)/$L22))) | O22: =IF($B22="","",SUMIFS('Diário de Estudo'!$D$7:$D$506,'Diário de Estudo'!$C$7:$C$506,$B22)) | P22: =IF($B22="","",IF(AND(N($O22)>0,N($F22)>0),$F22/$O22,"")) | Q22: =IF($B22="","",IF(OR(N($L22)=0,$G22=""),"",IF(N($M22)>=$L22,"Concluído",IF(OR(N($M22)<=0,TODAY()<=$G22),"Sem ritmo",TODAY()+ROUNDUP(($L22-$M22)/($M22/(TODAY()-$G22)),0))))) | R22: =IF($B22="","",IF(ISNUMBER($Q22),IF(AND(ISNUMBER($I22),$Q22>$I22),"■ Estoura o acesso",IF(AND(ISNUMBER($H22),$Q22>$H22),"▲ Atrasado vs plano","● No prazo")),IF($Q22="Concluído","◆ Concluído","—"))) | Y22: =IF($B22="","",IF(N($F22)=0,"",(N($X22)-$F22)/$F22)) | Z22: =IF($B22="","",IF(N($F22)=0,"",IF(N($X22)>=$F22,0,IF(N($W22)>0,($F22-N($X22))/$W22,"—")))) | AA22: =IF($B22="","",IF(N($F22)=0,"—",IF(N($X22)>=$F22,"● Pago",IF(N($X22)>0,"▲ Em retorno","■ Sem retorno"))))
... A49: =IF($B49="","","RE-"&TEXT(ROW()-9,"00")) | J49: =IF(OR($B49="",$I49=""),"",$I49-TODAY()) | K49: =IF($B49="","",IF($I49="","∞ Vitalício",IF($J49<0,"■ Vencido",IF($J49<=Listas!$H$6,"▲ A vencer","● Ativo")))) | N49: =IF($B49="","",IF(N($L49)=0,0,MIN(1,N($M49)/$L49))) | O49: =IF($B49="","",SUMIFS('Diário de Estudo'!$D$7:$D$506,'Diário de Estudo'!$C$7:$C$506,$B49)) | P49: =IF($B49="","",IF(AND(N($O49)>0,N($F49)>0),$F49/$O49,"")) | Q49: =IF($B49="","",IF(OR(N($L49)=0,$G49=""),"",IF(N($M49)>=$L49,"Concluído",IF(OR(N($M49)<=0,TODAY()<=$G49),"Sem ritmo",TODAY()+ROUNDUP(($L49-$M49)/($M49/(TODAY()-$G49)),0))))) | R49: =IF($B49="","",IF(ISNUMBER($Q49),IF(AND(ISNUMBER($I49),$Q49>$I49),"■ Estoura o acesso",IF(AND(ISNUMBER($H49),$Q49>$H49),"▲ Atrasado vs plano","● No prazo")),IF($Q49="Concluído","◆ Concluído","—"))) | Y49: =IF($B49="","",IF(N($F49)=0,"",(N($X49)-$F49)/$F49)) | Z49: =IF($B49="","",IF(N($F49)=0,"",IF(N($X49)>=$F49,0,IF(N($W49)>0,($F49-N($X49))/$W49,"—")))) | AA49: =IF($B49="","",IF(N($F49)=0,"—",IF(N($X49)>=$F49,"● Pago",IF(N($X49)>0,"▲ Em retorno","■ Sem retorno"))))

Sheet Listas
A1: LISTAS E CONFIGURAÇÕES
A2: Edite as listas das setas e o prazo de alerta. Não renomeie os 4 Status. | F2: ← Voltar ao Início
A5: Status | B5: Prioridade | C5: Modalidade | D5: Formato (livros) | E5: Categoria (diário) | F5: Certificado | H5: Alerta de vencimento (dias)
A6: Não iniciado | B6: Alta | C6: EAD | D6: Físico | E6: Pós-graduação | F6: Não emitido | H6: 30
A7: Em andamento | B7: Média | C7: Presencial | D7: E-book | E7: Concurso | F7: Em emissão | H7: Acessos que vencem em até este nº de dias aparecem como “▲ A vencer”. Prazo padrão sugerido: 30 dias (editável).
A8: Concluído | B8: Baixa | C8: Híbrido | D8: Audiobook | E8: Livros | F8: Emitido
A9: Pausado | D9: PDF | E9: Cursos IA | F9: Não se aplica
E10: Renda Extra
A13: As categorias da coluna E alimentam o Diário de Estudo e as Metas. Se renomear, renomeie também as abas correspondentes só se quiser manter a coerência visual.

Sheet Apoio
A1: APOIO · CÁLCULOS AUTOMÁTICOS
A2: Alimenta os painéis do Dashboard e a lista de cursos do Diário. Não edite. | N2: ← Voltar ao Início
A4: Categoria | B4: Item | C4: Vencimento | D4: Dias | E4: Chave venc. | F4: Previsão término | G4: Folga (dias) | H4: Chave risco | J4: Posição | K4: Chave venc. | L4: Linha venc. | M4: Chave risco | N4: Linha risco | P4: Todos os cursos
A5: =IF('Pós-graduação'!$B10="","","Pós-graduação") -> Pós-graduação | B5: =IF('Pós-graduação'!$B10="","",'Pós-graduação'!$B10) -> MBA em Inteligência Artificial (exemplo) | C5: =IF(OR('Pós-graduação'!$B10="",'Pós-graduação'!$I10=""),"",'Pós-graduação'!$I10) -> 46997 | D5: =IF(C5="","",C5-TODAY()) -> 699 | E5: =IF(C5="","",D5+ROW()/100000) -> 699.00005 | F5: =IF('Pós-graduação'!$B10="","",'Pós-graduação'!$Q10) -> 46586 | G5: =IF(AND(ISNUMBER(C5),ISNUMBER(F5)),C5-F5,"") -> 411 | H5: =IF(ISNUMBER(G5),IF(G5<0,G5+ROW()/100000,""),"") | J5: 1 | K5: =IFERROR(SMALL($E$5:$E$164,J5),"") -> 270.00045 | L5: =IF(K5="","",MATCH(K5,$E$5:$E$164,0)) -> 41 | M5: =IFERROR(SMALL($H$5:$H$164,J5),"") | N5: =IF(M5="","",MATCH(M5,$H$5:$H$164,0)) | P5: =IF('Pós-graduação'!$B10="","",'Pós-graduação'!$B10) -> MBA em Inteligência Artificial (exemplo)
A6: =IF('Pós-graduação'!$B11="","","Pós-graduação") | B6: =IF('Pós-graduação'!$B11="","",'Pós-graduação'!$B11) | C6: =IF(OR('Pós-graduação'!$B11="",'Pós-graduação'!$I11=""),"",'Pós-graduação'!$I11) | D6: =IF(C6="","",C6-TODAY()) | E6: =IF(C6="","",D6+ROW()/100000) | F6: =IF('Pós-graduação'!$B11="","",'Pós-graduação'!$Q11) | G6: =IF(AND(ISNUMBER(C6),ISNUMBER(F6)),C6-F6,"") | H6: =IF(ISNUMBER(G6),IF(G6<0,G6+ROW()/100000,""),"") | J6: 2 | K6: =IFERROR(SMALL($E$5:$E$164,J6),"") -> 333.00125 | L6: =IF(K6="","",MATCH(K6,$E$5:$E$164,0)) -> 121 | M6: =IFERROR(SMALL($H$5:$H$164,J6),"") | N6: =IF(M6="","",MATCH(M6,$H$5:$H$164,0)) | P6: =IF('Pós-graduação'!$B11="","",'Pós-graduação'!$B11)
A7: =IF('Pós-graduação'!$B12="","","Pós-graduação") | B7: =IF('Pós-graduação'!$B12="","",'Pós-graduação'!$B12) | C7: =IF(OR('Pós-graduação'!$B12="",'Pós-graduação'!$I12=""),"",'Pós-graduação'!$I12) | D7: =IF(C7="","",C7-TODAY()) | E7: =IF(C7="","",D7+ROW()/100000) | F7: =IF('Pós-graduação'!$B12="","",'Pós-graduação'!$Q12) | G7: =IF(AND(ISNUMBER(C7),ISNUMBER(F7)),C7-F7,"") | H7: =IF(ISNUMBER(G7),IF(G7<0,G7+ROW()/100000,""),"") | J7: 3 | K7: =IFERROR(SMALL($E$5:$E$164,J7),"") -> 344.00085 | L7: =IF(K7="","",MATCH(K7,$E$5:$E$164,0)) -> 81 | M7: =IFERROR(SMALL($H$5:$H$164,J7),"") | N7: =IF(M7="","",MATCH(M7,$H$5:$H$164,0)) | P7: =IF('Pós-graduação'!$B12="","",'Pós-graduação'!$B12)
A8: =IF('Pós-graduação'!$B13="","","Pós-graduação") | B8: =IF('Pós-graduação'!$B13="","",'Pós-graduação'!$B13) | C8: =IF(OR('Pós-graduação'!$B13="",'Pós-graduação'!$I13=""),"",'Pós-graduação'!$I13) | D8: =IF(C8="","",C8-TODAY()) | E8: =IF(C8="","",D8+ROW()/100000) | F8: =IF('Pós-graduação'!$B13="","",'Pós-graduação'!$Q13) | G8: =IF(AND(ISNUMBER(C8),ISNUMBER(F8)),C8-F8,"") | H8: =IF(ISNUMBER(G8),IF(G8<0,G8+ROW()/100000,""),"") | J8: 4 | K8: =IFERROR(SMALL($E$5:$E$164,J8),"") -> 699.00005 | L8: =IF(K8="","",MATCH(K8,$E$5:$E$164,0)) -> 1 | M8: =IFERROR(SMALL($H$5:$H$164,J8),"") | N8: =IF(M8="","",MATCH(M8,$H$5:$H$164,0)) | P8: =IF('Pós-graduação'!$B13="","",'Pós-graduação'!$B13)
A9: =IF('Pós-graduação'!$B14="","","Pós-graduação") | B9: =IF('Pós-graduação'!$B14="","",'Pós-graduação'!$B14) | C9: =IF(OR('Pós-graduação'!$B14="",'Pós-graduação'!$I14=""),"",'Pós-graduação'!$I14) | D9: =IF(C9="","",C9-TODAY()) | E9: =IF(C9="","",D9+ROW()/100000) | F9: =IF('Pós-graduação'!$B14="","",'Pós-graduação'!$Q14) | G9: =IF(AND(ISNUMBER(C9),ISNUMBER(F9)),C9-F9,"") | H9: =IF(ISNUMBER(G9),IF(G9<0,G9+ROW()/100000,""),"") | J9: 5 | K9: =IFERROR(SMALL($E$5:$E$164,J9),"") | L9: =IF(K9="","",MATCH(K9,$E$5:$E$164,0)) | M9: =IFERROR(SMALL($H$5:$H$164,J9),"") | N9: =IF(M9="","",MATCH(M9,$H$5:$H$164,0)) | P9: =IF('Pós-graduação'!$B14="","",'Pós-graduação'!$B14)
A10: =IF('Pós-graduação'!$B15="","","Pós-graduação") | B10: =IF('Pós-graduação'!$B15="","",'Pós-graduação'!$B15) | C10: =IF(OR('Pós-graduação'!$B15="",'Pós-graduação'!$I15=""),"",'Pós-graduação'!$I15) | D10: =IF(C10="","",C10-TODAY()) | E10: =IF(C10="","",D10+ROW()/100000) | F10: =IF('Pós-graduação'!$B15="","",'Pós-graduação'!$Q15) | G10: =IF(AND(ISNUMBER(C10),ISNUMBER(F10)),C10-F10,"") | H10: =IF(ISNUMBER(G10),IF(G10<0,G10+ROW()/100000,""),"") | J10: 6 | K10: =IFERROR(SMALL($E$5:$E$164,J10),"") | L10: =IF(K10="","",MATCH(K10,$E$5:$E$164,0)) | M10: =IFERROR(SMALL($H$5:$H$164,J10),"") | N10: =IF(M10="","",MATCH(M10,$H$5:$H$164,0)) | P10: =IF('Pós-graduação'!$B15="","",'Pós-graduação'!$B15)
A11: =IF('Pós-graduação'!$B16="","","Pós-graduação") | B11: =IF('Pós-graduação'!$B16="","",'Pós-graduação'!$B16) | C11: =IF(OR('Pós-graduação'!$B16="",'Pós-graduação'!$I16=""),"",'Pós-graduação'!$I16) | D11: =IF(C11="","",C11-TODAY()) | E11: =IF(C11="","",D11+ROW()/100000) | F11: =IF('Pós-graduação'!$B16="","",'Pós-graduação'!$Q16) | G11: =IF(AND(ISNUMBER(C11),ISNUMBER(F11)),C11-F11,"") | H11: =IF(ISNUMBER(G11),IF(G11<0,G11+ROW()/100000,""),"") | J11: 7 | K11: =IFERROR(SMALL($E$5:$E$164,J11),"") | L11: =IF(K11="","",MATCH(K11,$E$5:$E$164,0)) | M11: =IFERROR(SMALL($H$5:$H$164,J11),"") | N11: =IF(M11="","",MATCH(M11,$H$5:$H$164,0)) | P11: =IF('Pós-graduação'!$B16="","",'Pós-graduação'!$B16)
A12: =IF('Pós-graduação'!$B17="","","Pós-graduação") | B12: =IF('Pós-graduação'!$B17="","",'Pós-graduação'!$B17) | C12: =IF(OR('Pós-graduação'!$B17="",'Pós-graduação'!$I17=""),"",'Pós-graduação'!$I17) | D12: =IF(C12="","",C12-TODAY()) | E12: =IF(C12="","",D12+ROW()/100000) | F12: =IF('Pós-graduação'!$B17="","",'Pós-graduação'!$Q17) | G12: =IF(AND(ISNUMBER(C12),ISNUMBER(F12)),C12-F12,"") | H12: =IF(ISNUMBER(G12),IF(G12<0,G12+ROW()/100000,""),"") | J12: 8 | K12: =IFERROR(SMALL($E$5:$E$164,J12),"") | L12: =IF(K12="","",MATCH(K12,$E$5:$E$164,0)) | M12: =IFERROR(SMALL($H$5:$H$164,J12),"") | N12: =IF(M12="","",MATCH(M12,$H$5:$H$164,0)) | P12: =IF('Pós-graduação'!$B17="","",'Pós-graduação'!$B17)
A13: =IF('Pós-graduação'!$B18="","","Pós-graduação") | B13: =IF('Pós-graduação'!$B18="","",'Pós-graduação'!$B18) | C13: =IF(OR('Pós-graduação'!$B18="",'Pós-graduação'!$I18=""),"",'Pós-graduação'!$I18) | D13: =IF(C13="","",C13-TODAY()) | E13: =IF(C13="","",D13+ROW()/100000) | F13: =IF('Pós-graduação'!$B18="","",'Pós-graduação'!$Q18) | G13: =IF(AND(ISNUMBER(C13),ISNUMBER(F13)),C13-F13,"") | H13: =IF(ISNUMBER(G13),IF(G13<0,G13+ROW()/100000,""),"") | P13: =IF('Pós-graduação'!$B18="","",'Pós-graduação'!$B18)
A14: =IF('Pós-graduação'!$B19="","","Pós-graduação") | B14: =IF('Pós-graduação'!$B19="","",'Pós-graduação'!$B19) | C14: =IF(OR('Pós-graduação'!$B19="",'Pós-graduação'!$I19=""),"",'Pós-graduação'!$I19) | D14: =IF(C14="","",C14-TODAY()) | E14: =IF(C14="","",D14+ROW()/100000) | F14: =IF('Pós-graduação'!$B19="","",'Pós-graduação'!$Q19) | G14: =IF(AND(ISNUMBER(C14),ISNUMBER(F14)),C14-F14,"") | H14: =IF(ISNUMBER(G14),IF(G14<0,G14+ROW()/100000,""),"") | P14: =IF('Pós-graduação'!$B19="","",'Pós-graduação'!$B19)
A15: =IF('Pós-graduação'!$B20="","","Pós-graduação") | B15: =IF('Pós-graduação'!$B20="","",'Pós-graduação'!$B20) | C15: =IF(OR('Pós-graduação'!$B20="",'Pós-graduação'!$I20=""),"",'Pós-graduação'!$I20) | D15: =IF(C15="","",C15-TODAY()) | E15: =IF(C15="","",D15+ROW()/100000) | F15: =IF('Pós-graduação'!$B20="","",'Pós-graduação'!$Q20) | G15: =IF(AND(ISNUMBER(C15),ISNUMBER(F15)),C15-F15,"") | H15: =IF(ISNUMBER(G15),IF(G15<0,G15+ROW()/100000,""),"") | P15: =IF('Pós-graduação'!$B20="","",'Pós-graduação'!$B20)
A16: =IF('Pós-graduação'!$B21="","","Pós-graduação") | B16: =IF('Pós-graduação'!$B21="","",'Pós-graduação'!$B21) | C16: =IF(OR('Pós-graduação'!$B21="",'Pós-graduação'!$I21=""),"",'Pós-graduação'!$I21) | D16: =IF(C16="","",C16-TODAY()) | E16: =IF(C16="","",D16+ROW()/100000) | F16: =IF('Pós-graduação'!$B21="","",'Pós-graduação'!$Q21) | G16: =IF(AND(ISNUMBER(C16),ISNUMBER(F16)),C16-F16,"") | H16: =IF(ISNUMBER(G16),IF(G16<0,G16+ROW()/100000,""),"") | P16: =IF('Pós-graduação'!$B21="","",'Pós-graduação'!$B21)
A17: =IF('Pós-graduação'!$B22="","","Pós-graduação") | B17: =IF('Pós-graduação'!$B22="","",'Pós-graduação'!$B22) | C17: =IF(OR('Pós-graduação'!$B22="",'Pós-graduação'!$I22=""),"",'Pós-graduação'!$I22) | D17: =IF(C17="","",C17-TODAY()) | E17: =IF(C17="","",D17+ROW()/100000) | F17: =IF('Pós-graduação'!$B22="","",'Pós-graduação'!$Q22) | G17: =IF(AND(ISNUMBER(C17),ISNUMBER(F17)),C17-F17,"") | H17: =IF(ISNUMBER(G17),IF(G17<0,G17+ROW()/100000,""),"") | P17: =IF('Pós-graduação'!$B22="","",'Pós-graduação'!$B22)
A18: =IF('Pós-graduação'!$B23="","","Pós-graduação") | B18: =IF('Pós-graduação'!$B23="","",'Pós-graduação'!$B23) | C18: =IF(OR('Pós-graduação'!$B23="",'Pós-graduação'!$I23=""),"",'Pós-graduação'!$I23) | D18: =IF(C18="","",C18-TODAY()) | E18: =IF(C18="","",D18+ROW()/100000) | F18: =IF('Pós-graduação'!$B23="","",'Pós-graduação'!$Q23) | G18: =IF(AND(ISNUMBER(C18),ISNUMBER(F18)),C18-F18,"") | H18: =IF(ISNUMBER(G18),IF(G18<0,G18+ROW()/100000,""),"") | P18: =IF('Pós-graduação'!$B23="","",'Pós-graduação'!$B23)
A19: =IF('Pós-graduação'!$B24="","","Pós-graduação") | B19: =IF('Pós-graduação'!$B24="","",'Pós-graduação'!$B24) | C19: =IF(OR('Pós-graduação'!$B24="",'Pós-graduação'!$I24=""),"",'Pós-graduação'!$I24) | D19: =IF(C19="","",C19-TODAY()) | E19: =IF(C19="","",D19+ROW()/100000) | F19: =IF('Pós-graduação'!$B24="","",'Pós-graduação'!$Q24) | G19: =IF(AND(ISNUMBER(C19),ISNUMBER(F19)),C19-F19,"") | H19: =IF(ISNUMBER(G19),IF(G19<0,G19+ROW()/100000,""),"") | P19: =IF('Pós-graduação'!$B24="","",'Pós-graduação'!$B24)
A20: =IF('Pós-graduação'!$B25="","","Pós-graduação") | B20: =IF('Pós-graduação'!$B25="","",'Pós-graduação'!$B25) | C20: =IF(OR('Pós-graduação'!$B25="",'Pós-graduação'!$I25=""),"",'Pós-graduação'!$I25) | D20: =IF(C20="","",C20-TODAY()) | E20: =IF(C20="","",D20+ROW()/100000) | F20: =IF('Pós-graduação'!$B25="","",'Pós-graduação'!$Q25) | G20: =IF(AND(ISNUMBER(C20),ISNUMBER(F20)),C20-F20,"") | H20: =IF(ISNUMBER(G20),IF(G20<0,G20+ROW()/100000,""),"") | P20: =IF('Pós-graduação'!$B25="","",'Pós-graduação'!$B25)
A21: =IF('Pós-graduação'!$B26="","","Pós-graduação") | B21: =IF('Pós-graduação'!$B26="","",'Pós-graduação'!$B26) | C21: =IF(OR('Pós-graduação'!$B26="",'Pós-graduação'!$I26=""),"",'Pós-graduação'!$I26) | D21: =IF(C21="","",C21-TODAY()) | E21: =IF(C21="","",D21+ROW()/100000) | F21: =IF('Pós-graduação'!$B26="","",'Pós-graduação'!$Q26) | G21: =IF(AND(ISNUMBER(C21),ISNUMBER(F21)),C21-F21,"") | H21: =IF(ISNUMBER(G21),IF(G21<0,G21+ROW()/100000,""),"") | P21: =IF('Pós-graduação'!$B26="","",'Pós-graduação'!$B26)
A22: =IF('Pós-graduação'!$B27="","","Pós-graduação") | B22: =IF('Pós-graduação'!$B27="","",'Pós-graduação'!$B27) | C22: =IF(OR('Pós-graduação'!$B27="",'Pós-graduação'!$I27=""),"",'Pós-graduação'!$I27) | D22: =IF(C22="","",C22-TODAY()) | E22: =IF(C22="","",D22+ROW()/100000) | F22: =IF('Pós-graduação'!$B27="","",'Pós-graduação'!$Q27) | G22: =IF(AND(ISNUMBER(C22),ISNUMBER(F22)),C22-F22,"") | H22: =IF(ISNUMBER(G22),IF(G22<0,G22+ROW()/100000,""),"") | P22: =IF('Pós-graduação'!$B27="","",'Pós-graduação'!$B27)
A23: =IF('Pós-graduação'!$B28="","","Pós-graduação") | B23: =IF('Pós-graduação'!$B28="","",'Pós-graduação'!$B28) | C23: =IF(OR('Pós-graduação'!$B28="",'Pós-graduação'!$I28=""),"",'Pós-graduação'!$I28) | D23: =IF(C23="","",C23-TODAY()) | E23: =IF(C23="","",D23+ROW()/100000) | F23: =IF('Pós-graduação'!$B28="","",'Pós-graduação'!$Q28) | G23: =IF(AND(ISNUMBER(C23),ISNUMBER(F23)),C23-F23,"") | H23: =IF(ISNUMBER(G23),IF(G23<0,G23+ROW()/100000,""),"") | P23: =IF('Pós-graduação'!$B28="","",'Pós-graduação'!$B28)
A24: =IF('Pós-graduação'!$B29="","","Pós-graduação") | B24: =IF('Pós-graduação'!$B29="","",'Pós-graduação'!$B29) | C24: =IF(OR('Pós-graduação'!$B29="",'Pós-graduação'!$I29=""),"",'Pós-graduação'!$I29) | D24: =IF(C24="","",C24-TODAY()) | E24: =IF(C24="","",D24+ROW()/100000) | F24: =IF('Pós-graduação'!$B29="","",'Pós-graduação'!$Q29) | G24: =IF(AND(ISNUMBER(C24),ISNUMBER(F24)),C24-F24,"") | H24: =IF(ISNUMBER(G24),IF(G24<0,G24+ROW()/100000,""),"") | P24: =IF('Pós-graduação'!$B29="","",'Pós-graduação'!$B29)
... A44: =IF('Pós-graduação'!$B49="","","Pós-graduação") | B44: =IF('Pós-graduação'!$B49="","",'Pós-graduação'!$B49) | C44: =IF(OR('Pós-graduação'!$B49="",'Pós-graduação'!$I49=""),"",'Pós-graduação'!$I49) | D44: =IF(C44="","",C44-TODAY()) | E44: =IF(C44="","",D44+ROW()/100000) | F44: =IF('Pós-graduação'!$B49="","",'Pós-graduação'!$Q49) | G44: =IF(AND(ISNUMBER(C44),ISNUMBER(F44)),C44-F44,"") | H44: =IF(ISNUMBER(G44),IF(G44<0,G44+ROW()/100000,""),"") | P44: =IF('Pós-graduação'!$B49="","",'Pós-graduação'!$B49)
A45: =IF(Concurso!$B10="","","Concurso") -> Concurso | B45: =IF(Concurso!$B10="","",Concurso!$B10) -> Curso Preparatório Completo (exemplo) | C45: =IF(OR(Concurso!$B10="",Concurso!$K10=""),"",Concurso!$K10) -> 46568 | D45: =IF(C45="","",C45-TODAY()) -> 270 | E45: =IF(C45="","",D45+ROW()/100000) -> 270.00045 | F45: =IF(Concurso!$B10="","",Concurso!$S10) -> 46352 | G45: =IF(AND(ISNUMBER(C45),ISNUMBER(F45)),C45-F45,"") -> 216 | H45: =IF(ISNUMBER(G45),IF(G45<0,G45+ROW()/100000,""),"") | P45: =IF(Concurso!$B10="","",Concurso!$B10) -> Curso Preparatório Completo (exemplo)
A46: =IF(Concurso!$B11="","","Concurso") | B46: =IF(Concurso!$B11="","",Concurso!$B11) | C46: =IF(OR(Concurso!$B11="",Concurso!$K11=""),"",Concurso!$K11) | D46: =IF(C46="","",C46-TODAY()) | E46: =IF(C46="","",D46+ROW()/100000) | F46: =IF(Concurso!$B11="","",Concurso!$S11) | G46: =IF(AND(ISNUMBER(C46),ISNUMBER(F46)),C46-F46,"") | H46: =IF(ISNUMBER(G46),IF(G46<0,G46+ROW()/100000,""),"") | P46: =IF(Concurso!$B11="","",Concurso!$B11)
A47: =IF(Concurso!$B12="","","Concurso") | B47: =IF(Concurso!$B12="","",Concurso!$B12) | C47: =IF(OR(Concurso!$B12="",Concurso!$K12=""),"",Concurso!$K12) | D47: =IF(C47="","",C47-TODAY()) | E47: =IF(C47="","",D47+ROW()/100000) | F47: =IF(Concurso!$B12="","",Concurso!$S12) | G47: =IF(AND(ISNUMBER(C47),ISNUMBER(F47)),C47-F47,"") | H47: =IF(ISNUMBER(G47),IF(G47<0,G47+ROW()/100000,""),"") | P47: =IF(Concurso!$B12="","",Concurso!$B12)
A48: =IF(Concurso!$B13="","","Concurso") | B48: =IF(Concurso!$B13="","",Concurso!$B13) | C48: =IF(OR(Concurso!$B13="",Concurso!$K13=""),"",Concurso!$K13) | D48: =IF(C48="","",C48-TODAY()) | E48: =IF(C48="","",D48+ROW()/100000) | F48: =IF(Concurso!$B13="","",Concurso!$S13) | G48: =IF(AND(ISNUMBER(C48),ISNUMBER(F48)),C48-F48,"") | H48: =IF(ISNUMBER(G48),IF(G48<0,G48+ROW()/100000,""),"") | P48: =IF(Concurso!$B13="","",Concurso!$B13)
A49: =IF(Concurso!$B14="","","Concurso") | B49: =IF(Concurso!$B14="","",Concurso!$B14) | C49: =IF(OR(Concurso!$B14="",Concurso!$K14=""),"",Concurso!$K14) | D49: =IF(C49="","",C49-TODAY()) | E49: =IF(C49="","",D49+ROW()/100000) | F49: =IF(Concurso!$B14="","",Concurso!$S14) | G49: =IF(AND(ISNUMBER(C49),ISNUMBER(F49)),C49-F49,"") | H49: =IF(ISNUMBER(G49),IF(G49<0,G49+ROW()/100000,""),"") | P49: =IF(Concurso!$B14="","",Concurso!$B14)
A50: =IF(Concurso!$B15="","","Concurso") | B50: =IF(Concurso!$B15="","",Concurso!$B15) | C50: =IF(OR(Concurso!$B15="",Concurso!$K15=""),"",Concurso!$K15) | D50: =IF(C50="","",C50-TODAY()) | E50: =IF(C50="","",D50+ROW()/100000) | F50: =IF(Concurso!$B15="","",Concurso!$S15) | G50: =IF(AND(ISNUMBER(C50),ISNUMBER(F50)),C50-F50,"") | H50: =IF(ISNUMBER(G50),IF(G50<0,G50+ROW()/100000,""),"") | P50: =IF(Concurso!$B15="","",Concurso!$B15)
A51: =IF(Concurso!$B16="","","Concurso") | B51: =IF(Concurso!$B16="","",Concurso!$B16) | C51: =IF(OR(Concurso!$B16="",Concurso!$K16=""),"",Concurso!$K16) | D51: =IF(C51="","",C51-TODAY()) | E51: =IF(C51="","",D51+ROW()/100000) | F51: =IF(Concurso!$B16="","",Concurso!$S16) | G51: =IF(AND(ISNUMBER(C51),ISNUMBER(F51)),C51-F51,"") | H51: =IF(ISNUMBER(G51),IF(G51<0,G51+ROW()/100000,""),"") | P51: =IF(Concurso!$B16="","",Concurso!$B16)
A52: =IF(Concurso!$B17="","","Concurso") | B52: =IF(Concurso!$B17="","",Concurso!$B17) | C52: =IF(OR(Concurso!$B17="",Concurso!$K17=""),"",Concurso!$K17) | D52: =IF(C52="","",C52-TODAY()) | E52: =IF(C52="","",D52+ROW()/100000) | F52: =IF(Concurso!$B17="","",Concurso!$S17) | G52: =IF(AND(ISNUMBER(C52),ISNUMBER(F52)),C52-F52,"") | H52: =IF(ISNUMBER(G52),IF(G52<0,G52+ROW()/100000,""),"") | P52: =IF(Concurso!$B17="","",Concurso!$B17)
A53: =IF(Concurso!$B18="","","Concurso") | B53: =IF(Concurso!$B18="","",Concurso!$B18) | C53: =IF(OR(Concurso!$B18="",Concurso!$K18=""),"",Concurso!$K18) | D53: =IF(C53="","",C53-TODAY()) | E53: =IF(C53="","",D53+ROW()/100000) | F53: =IF(Concurso!$B18="","",Concurso!$S18) | G53: =IF(AND(ISNUMBER(C53),ISNUMBER(F53)),C53-F53,"") | H53: =IF(ISNUMBER(G53),IF(G53<0,G53+ROW()/100000,""),"") | P53: =IF(Concurso!$B18="","",Concurso!$B18)
A54: =IF(Concurso!$B19="","","Concurso") | B54: =IF(Concurso!$B19="","",Concurso!$B19) | C54: =IF(OR(Concurso!$B19="",Concurso!$K19=""),"",Concurso!$K19) | D54: =IF(C54="","",C54-TODAY()) | E54: =IF(C54="","",D54+ROW()/100000) | F54: =IF(Concurso!$B19="","",Concurso!$S19) | G54: =IF(AND(ISNUMBER(C54),ISNUMBER(F54)),C54-F54,"") | H54: =IF(ISNUMBER(G54),IF(G54<0,G54+ROW()/100000,""),"") | P54: =IF(Concurso!$B19="","",Concurso!$B19)
A55: =IF(Concurso!$B20="","","Concurso") | B55: =IF(Concurso!$B20="","",Concurso!$B20) | C55: =IF(OR(Concurso!$B20="",Concurso!$K20=""),"",Concurso!$K20) | D55: =IF(C55="","",C55-TODAY()) | E55: =IF(C55="","",D55+ROW()/100000) | F55: =IF(Concurso!$B20="","",Concurso!$S20) | G55: =IF(AND(ISNUMBER(C55),ISNUMBER(F55)),C55-F55,"") | H55: =IF(ISNUMBER(G55),IF(G55<0,G55+ROW()/100000,""),"") | P55: =IF(Concurso!$B20="","",Concurso!$B20)
A56: =IF(Concurso!$B21="","","Concurso") | B56: =IF(Concurso!$B21="","",Concurso!$B21) | C56: =IF(OR(Concurso!$B21="",Concurso!$K21=""),"",Concurso!$K21) | D56: =IF(C56="","",C56-TODAY()) | E56: =IF(C56="","",D56+ROW()/100000) | F56: =IF(Concurso!$B21="","",Concurso!$S21) | G56: =IF(AND(ISNUMBER(C56),ISNUMBER(F56)),C56-F56,"") | H56: =IF(ISNUMBER(G56),IF(G56<0,G56+ROW()/100000,""),"") | P56: =IF(Concurso!$B21="","",Concurso!$B21)
... A84: =IF(Concurso!$B49="","","Concurso") | B84: =IF(Concurso!$B49="","",Concurso!$B49) | C84: =IF(OR(Concurso!$B49="",Concurso!$K49=""),"",Concurso!$K49) | D84: =IF(C84="","",C84-TODAY()) | E84: =IF(C84="","",D84+ROW()/100000) | F84: =IF(Concurso!$B49="","",Concurso!$S49) | G84: =IF(AND(ISNUMBER(C84),ISNUMBER(F84)),C84-F84,"") | H84: =IF(ISNUMBER(G84),IF(G84<0,G84+ROW()/100000,""),"") | P84: =IF(Concurso!$B49="","",Concurso!$B49)
A85: =IF('Cursos IA'!$B10="","","Cursos IA") -> Cursos IA | B85: =IF('Cursos IA'!$B10="","",'Cursos IA'!$B10) -> Agentes de IA na Prática (exemplo) | C85: =IF(OR('Cursos IA'!$B10="",'Cursos IA'!$I10=""),"",'Cursos IA'!$I10) -> 46642 | D85: =IF(C85="","",C85-TODAY()) -> 344 | E85: =IF(C85="","",D85+ROW()/100000) -> 344.00085 | F85: =IF('Cursos IA'!$B10="","",'Cursos IA'!$Q10) -> 46329 | G85: =IF(AND(ISNUMBER(C85),ISNUMBER(F85)),C85-F85,"") -> 313 | H85: =IF(ISNUMBER(G85),IF(G85<0,G85+ROW()/100000,""),"") | P85: =IF(Livros!$B10="","",Livros!$B10) -> Hábitos Atômicos (exemplo)
A86: =IF('Cursos IA'!$B11="","","Cursos IA") | B86: =IF('Cursos IA'!$B11="","",'Cursos IA'!$B11) | C86: =IF(OR('Cursos IA'!$B11="",'Cursos IA'!$I11=""),"",'Cursos IA'!$I11) | D86: =IF(C86="","",C86-TODAY()) | E86: =IF(C86="","",D86+ROW()/100000) | F86: =IF('Cursos IA'!$B11="","",'Cursos IA'!$Q11) | G86: =IF(AND(ISNUMBER(C86),ISNUMBER(F86)),C86-F86,"") | H86: =IF(ISNUMBER(G86),IF(G86<0,G86+ROW()/100000,""),"") | P86: =IF(Livros!$B11="","",Livros!$B11)
A87: =IF('Cursos IA'!$B12="","","Cursos IA") | B87: =IF('Cursos IA'!$B12="","",'Cursos IA'!$B12) | C87: =IF(OR('Cursos IA'!$B12="",'Cursos IA'!$I12=""),"",'Cursos IA'!$I12) | D87: =IF(C87="","",C87-TODAY()) | E87: =IF(C87="","",D87+ROW()/100000) | F87: =IF('Cursos IA'!$B12="","",'Cursos IA'!$Q12) | G87: =IF(AND(ISNUMBER(C87),ISNUMBER(F87)),C87-F87,"") | H87: =IF(ISNUMBER(G87),IF(G87<0,G87+ROW()/100000,""),"") | P87: =IF(Livros!$B12="","",Livros!$B12)
A88: =IF('Cursos IA'!$B13="","","Cursos IA") | B88: =IF('Cursos IA'!$B13="","",'Cursos IA'!$B13) | C88: =IF(OR('Cursos IA'!$B13="",'Cursos IA'!$I13=""),"",'Cursos IA'!$I13) | D88: =IF(C88="","",C88-TODAY()) | E88: =IF(C88="","",D88+ROW()/100000) | F88: =IF('Cursos IA'!$B13="","",'Cursos IA'!$Q13) | G88: =IF(AND(ISNUMBER(C88),ISNUMBER(F88)),C88-F88,"") | H88: =IF(ISNUMBER(G88),IF(G88<0,G88+ROW()/100000,""),"") | P88: =IF(Livros!$B13="","",Livros!$B13)
A89: =IF('Cursos IA'!$B14="","","Cursos IA") | B89: =IF('Cursos IA'!$B14="","",'Cursos IA'!$B14) | C89: =IF(OR('Cursos IA'!$B14="",'Cursos IA'!$I14=""),"",'Cursos IA'!$I14) | D89: =IF(C89="","",C89-TODAY()) | E89: =IF(C89="","",D89+ROW()/100000) | F89: =IF('Cursos IA'!$B14="","",'Cursos IA'!$Q14) | G89: =IF(AND(ISNUMBER(C89),ISNUMBER(F89)),C89-F89,"") | H89: =IF(ISNUMBER(G89),IF(G89<0,G89+ROW()/100000,""),"") | P89: =IF(Livros!$B14="","",Livros!$B14)
A90: =IF('Cursos IA'!$B15="","","Cursos IA") | B90: =IF('Cursos IA'!$B15="","",'Cursos IA'!$B15) | C90: =IF(OR('Cursos IA'!$B15="",'Cursos IA'!$I15=""),"",'Cursos IA'!$I15) | D90: =IF(C90="","",C90-TODAY()) | E90: =IF(C90="","",D90+ROW()/100000) | F90: =IF('Cursos IA'!$B15="","",'Cursos IA'!$Q15) | G90: =IF(AND(ISNUMBER(C90),ISNUMBER(F90)),C90-F90,"") | H90: =IF(ISNUMBER(G90),IF(G90<0,G90+ROW()/100000,""),"") | P90: =IF(Livros!$B15="","",Livros!$B15)
A91: =IF('Cursos IA'!$B16="","","Cursos IA") | B91: =IF('Cursos IA'!$B16="","",'Cursos IA'!$B16) | C91: =IF(OR('Cursos IA'!$B16="",'Cursos IA'!$I16=""),"",'Cursos IA'!$I16) | D91: =IF(C91="","",C91-TODAY()) | E91: =IF(C91="","",D91+ROW()/100000) | F91: =IF('Cursos IA'!$B16="","",'Cursos IA'!$Q16) | G91: =IF(AND(ISNUMBER(C91),ISNUMBER(F91)),C91-F91,"") | H91: =IF(ISNUMBER(G91),IF(G91<0,G91+ROW()/100000,""),"") | P91: =IF(Livros!$B16="","",Livros!$B16)
A92: =IF('Cursos IA'!$B17="","","Cursos IA") | B92: =IF('Cursos IA'!$B17="","",'Cursos IA'!$B17) | C92: =IF(OR('Cursos IA'!$B17="",'Cursos IA'!$I17=""),"",'Cursos IA'!$I17) | D92: =IF(C92="","",C92-TODAY()) | E92: =IF(C92="","",D92+ROW()/100000) | F92: =IF('Cursos IA'!$B17="","",'Cursos IA'!$Q17) | G92: =IF(AND(ISNUMBER(C92),ISNUMBER(F92)),C92-F92,"") | H92: =IF(ISNUMBER(G92),IF(G92<0,G92+ROW()/100000,""),"") | P92: =IF(Livros!$B17="","",Livros!$B17)
A93: =IF('Cursos IA'!$B18="","","Cursos IA") | B93: =IF('Cursos IA'!$B18="","",'Cursos IA'!$B18) | C93: =IF(OR('Cursos IA'!$B18="",'Cursos IA'!$I18=""),"",'Cursos IA'!$I18) | D93: =IF(C93="","",C93-TODAY()) | E93: =IF(C93="","",D93+ROW()/100000) | F93: =IF('Cursos IA'!$B18="","",'Cursos IA'!$Q18) | G93: =IF(AND(ISNUMBER(C93),ISNUMBER(F93)),C93-F93,"") | H93: =IF(ISNUMBER(G93),IF(G93<0,G93+ROW()/100000,""),"") | P93: =IF(Livros!$B18="","",Livros!$B18)
A94: =IF('Cursos IA'!$B19="","","Cursos IA") | B94: =IF('Cursos IA'!$B19="","",'Cursos IA'!$B19) | C94: =IF(OR('Cursos IA'!$B19="",'Cursos IA'!$I19=""),"",'Cursos IA'!$I19) | D94: =IF(C94="","",C94-TODAY()) | E94: =IF(C94="","",D94+ROW()/100000) | F94: =IF('Cursos IA'!$B19="","",'Cursos IA'!$Q19) | G94: =IF(AND(ISNUMBER(C94),ISNUMBER(F94)),C94-F94,"") | H94: =IF(ISNUMBER(G94),IF(G94<0,G94+ROW()/100000,""),"") | P94: =IF(Livros!$B19="","",Livros!$B19)
A95: =IF('Cursos IA'!$B20="","","Cursos IA") | B95: =IF('Cursos IA'!$B20="","",'Cursos IA'!$B20) | C95: =IF(OR('Cursos IA'!$B20="",'Cursos IA'!$I20=""),"",'Cursos IA'!$I20) | D95: =IF(C95="","",C95-TODAY()) | E95: =IF(C95="","",D95+ROW()/100000) | F95: =IF('Cursos IA'!$B20="","",'Cursos IA'!$Q20) | G95: =IF(AND(ISNUMBER(C95),ISNUMBER(F95)),C95-F95,"") | H95: =IF(ISNUMBER(G95),IF(G95<0,G95+ROW()/100000,""),"") | P95: =IF(Livros!$B20="","",Livros!$B20)
A96: =IF('Cursos IA'!$B21="","","Cursos IA") | B96: =IF('Cursos IA'!$B21="","",'Cursos IA'!$B21) | C96: =IF(OR('Cursos IA'!$B21="",'Cursos IA'!$I21=""),"",'Cursos IA'!$I21) | D96: =IF(C96="","",C96-TODAY()) | E96: =IF(C96="","",D96+ROW()/100000) | F96: =IF('Cursos IA'!$B21="","",'Cursos IA'!$Q21) | G96: =IF(AND(ISNUMBER(C96),ISNUMBER(F96)),C96-F96,"") | H96: =IF(ISNUMBER(G96),IF(G96<0,G96+ROW()/100000,""),"") | P96: =IF(Livros!$B21="","",Livros!$B21)
... A124: =IF('Cursos IA'!$B49="","","Cursos IA") | B124: =IF('Cursos IA'!$B49="","",'Cursos IA'!$B49) | C124: =IF(OR('Cursos IA'!$B49="",'Cursos IA'!$I49=""),"",'Cursos IA'!$I49) | D124: =IF(C124="","",C124-TODAY()) | E124: =IF(C124="","",D124+ROW()/100000) | F124: =IF('Cursos IA'!$B49="","",'Cursos IA'!$Q49) | G124: =IF(AND(ISNUMBER(C124),ISNUMBER(F124)),C124-F124,"") | H124: =IF(ISNUMBER(G124),IF(G124<0,G124+ROW()/100000,""),"") | P124: =IF(Livros!$B49="","",Livros!$B49)
A125: =IF('Renda Extra'!$B10="","","Renda Extra") -> Renda Extra | B125: =IF('Renda Extra'!$B10="","",'Renda Extra'!$B10) -> Marketing de Afiliados do Zero (exemplo) | C125: =IF(OR('Renda Extra'!$B10="",'Renda Extra'!$I10=""),"",'Renda Extra'!$I10) -> 46631 | D125: =IF(C125="","",C125-TODAY()) -> 333 | E125: =IF(C125="","",D125+ROW()/100000) -> 333.00125 | F125: =IF('Renda Extra'!$B10="","",'Renda Extra'!$Q10) -> 46403 | G125: =IF(AND(ISNUMBER(C125),ISNUMBER(F125)),C125-F125,"") -> 228 | H125: =IF(ISNUMBER(G125),IF(G125<0,G125+ROW()/100000,""),"") | P125: =IF('Cursos IA'!$B10="","",'Cursos IA'!$B10) -> Agentes de IA na Prática (exemplo)
A126: =IF('Renda Extra'!$B11="","","Renda Extra") | B126: =IF('Renda Extra'!$B11="","",'Renda Extra'!$B11) | C126: =IF(OR('Renda Extra'!$B11="",'Renda Extra'!$I11=""),"",'Renda Extra'!$I11) | D126: =IF(C126="","",C126-TODAY()) | E126: =IF(C126="","",D126+ROW()/100000) | F126: =IF('Renda Extra'!$B11="","",'Renda Extra'!$Q11) | G126: =IF(AND(ISNUMBER(C126),ISNUMBER(F126)),C126-F126,"") | H126: =IF(ISNUMBER(G126),IF(G126<0,G126+ROW()/100000,""),"") | P126: =IF('Cursos IA'!$B11="","",'Cursos IA'!$B11)
A127: =IF('Renda Extra'!$B12="","","Renda Extra") | B127: =IF('Renda Extra'!$B12="","",'Renda Extra'!$B12) | C127: =IF(OR('Renda Extra'!$B12="",'Renda Extra'!$I12=""),"",'Renda Extra'!$I12) | D127: =IF(C127="","",C127-TODAY()) | E127: =IF(C127="","",D127+ROW()/100000) | F127: =IF('Renda Extra'!$B12="","",'Renda Extra'!$Q12) | G127: =IF(AND(ISNUMBER(C127),ISNUMBER(F127)),C127-F127,"") | H127: =IF(ISNUMBER(G127),IF(G127<0,G127+ROW()/100000,""),"") | P127: =IF('Cursos IA'!$B12="","",'Cursos IA'!$B12)
A128: =IF('Renda Extra'!$B13="","","Renda Extra") | B128: =IF('Renda Extra'!$B13="","",'Renda Extra'!$B13) | C128: =IF(OR('Renda Extra'!$B13="",'Renda Extra'!$I13=""),"",'Renda Extra'!$I13) | D128: =IF(C128="","",C128-TODAY()) | E128: =IF(C128="","",D128+ROW()/100000) | F128: =IF('Renda Extra'!$B13="","",'Renda Extra'!$Q13) | G128: =IF(AND(ISNUMBER(C128),ISNUMBER(F128)),C128-F128,"") | H128: =IF(ISNUMBER(G128),IF(G128<0,G128+ROW()/100000,""),"") | P128: =IF('Cursos IA'!$B13="","",'Cursos IA'!$B13)
A129: =IF('Renda Extra'!$B14="","","Renda Extra") | B129: =IF('Renda Extra'!$B14="","",'Renda Extra'!$B14) | C129: =IF(OR('Renda Extra'!$B14="",'Renda Extra'!$I14=""),"",'Renda Extra'!$I14) | D129: =IF(C129="","",C129-TODAY()) | E129: =IF(C129="","",D129+ROW()/100000) | F129: =IF('Renda Extra'!$B14="","",'Renda Extra'!$Q14) | G129: =IF(AND(ISNUMBER(C129),ISNUMBER(F129)),C129-F129,"") | H129: =IF(ISNUMBER(G129),IF(G129<0,G129+ROW()/100000,""),"") | P129: =IF('Cursos IA'!$B14="","",'Cursos IA'!$B14)
A130: =IF('Renda Extra'!$B15="","","Renda Extra") | B130: =IF('Renda Extra'!$B15="","",'Renda Extra'!$B15) | C130: =IF(OR('Renda Extra'!$B15="",'Renda Extra'!$I15=""),"",'Renda Extra'!$I15) | D130: =IF(C130="","",C130-TODAY()) | E130: =IF(C130="","",D130+ROW()/100000) | F130: =IF('Renda Extra'!$B15="","",'Renda Extra'!$Q15) | G130: =IF(AND(ISNUMBER(C130),ISNUMBER(F130)),C130-F130,"") | H130: =IF(ISNUMBER(G130),IF(G130<0,G130+ROW()/100000,""),"") | P130: =IF('Cursos IA'!$B15="","",'Cursos IA'!$B15)
A131: =IF('Renda Extra'!$B16="","","Renda Extra") | B131: =IF('Renda Extra'!$B16="","",'Renda Extra'!$B16) | C131: =IF(OR('Renda Extra'!$B16="",'Renda Extra'!$I16=""),"",'Renda Extra'!$I16) | D131: =IF(C131="","",C131-TODAY()) | E131: =IF(C131="","",D131+ROW()/100000) | F131: =IF('Renda Extra'!$B16="","",'Renda Extra'!$Q16) | G131: =IF(AND(ISNUMBER(C131),ISNUMBER(F131)),C131-F131,"") | H131: =IF(ISNUMBER(G131),IF(G131<0,G131+ROW()/100000,""),"") | P131: =IF('Cursos IA'!$B16="","",'Cursos IA'!$B16)
A132: =IF('Renda Extra'!$B17="","","Renda Extra") | B132: =IF('Renda Extra'!$B17="","",'Renda Extra'!$B17) | C132: =IF(OR('Renda Extra'!$B17="",'Renda Extra'!$I17=""),"",'Renda Extra'!$I17) | D132: =IF(C132="","",C132-TODAY()) | E132: =IF(C132="","",D132+ROW()/100000) | F132: =IF('Renda Extra'!$B17="","",'Renda Extra'!$Q17) | G132: =IF(AND(ISNUMBER(C132),ISNUMBER(F132)),C132-F132,"") | H132: =IF(ISNUMBER(G132),IF(G132<0,G132+ROW()/100000,""),"") | P132: =IF('Cursos IA'!$B17="","",'Cursos IA'!$B17)
A133: =IF('Renda Extra'!$B18="","","Renda Extra") | B133: =IF('Renda Extra'!$B18="","",'Renda Extra'!$B18) | C133: =IF(OR('Renda Extra'!$B18="",'Renda Extra'!$I18=""),"",'Renda Extra'!$I18) | D133: =IF(C133="","",C133-TODAY()) | E133: =IF(C133="","",D133+ROW()/100000) | F133: =IF('Renda Extra'!$B18="","",'Renda Extra'!$Q18) | G133: =IF(AND(ISNUMBER(C133),ISNUMBER(F133)),C133-F133,"") | H133: =IF(ISNUMBER(G133),IF(G133<0,G133+ROW()/100000,""),"") | P133: =IF('Cursos IA'!$B18="","",'Cursos IA'!$B18)
A134: =IF('Renda Extra'!$B19="","","Renda Extra") | B134: =IF('Renda Extra'!$B19="","",'Renda Extra'!$B19) | C134: =IF(OR('Renda Extra'!$B19="",'Renda Extra'!$I19=""),"",'Renda Extra'!$I19) | D134: =IF(C134="","",C134-TODAY()) | E134: =IF(C134="","",D134+ROW()/100000) | F134: =IF('Renda Extra'!$B19="","",'Renda Extra'!$Q19) | G134: =IF(AND(ISNUMBER(C134),ISNUMBER(F134)),C134-F134,"") | H134: =IF(ISNUMBER(G134),IF(G134<0,G134+ROW()/100000,""),"") | P134: =IF('Cursos IA'!$B19="","",'Cursos IA'!$B19)
A135: =IF('Renda Extra'!$B20="","","Renda Extra") | B135: =IF('Renda Extra'!$B20="","",'Renda Extra'!$B20) | C135: =IF(OR('Renda Extra'!$B20="",'Renda Extra'!$I20=""),"",'Renda Extra'!$I20) | D135: =IF(C135="","",C135-TODAY()) | E135: =IF(C135="","",D135+ROW()/100000) | F135: =IF('Renda Extra'!$B20="","",'Renda Extra'!$Q20) | G135: =IF(AND(ISNUMBER(C135),ISNUMBER(F135)),C135-F135,"") | H135: =IF(ISNUMBER(G135),IF(G135<0,G135+ROW()/100000,""),"") | P135: =IF('Cursos IA'!$B20="","",'Cursos IA'!$B20)
A136: =IF('Renda Extra'!$B21="","","Renda Extra") | B136: =IF('Renda Extra'!$B21="","",'Renda Extra'!$B21) | C136: =IF(OR('Renda Extra'!$B21="",'Renda Extra'!$I21=""),"",'Renda Extra'!$I21) | D136: =IF(C136="","",C136-TODAY()) | E136: =IF(C136="","",D136+ROW()/100000) | F136: =IF('Renda Extra'!$B21="","",'Renda Extra'!$Q21) | G136: =IF(AND(ISNUMBER(C136),ISNUMBER(F136)),C136-F136,"") | H136: =IF(ISNUMBER(G136),IF(G136<0,G136+ROW()/100000,""),"") | P136: =IF('Cursos IA'!$B21="","",'Cursos IA'!$B21)
... A164: =IF('Renda Extra'!$B49="","","Renda Extra") | B164: =IF('Renda Extra'!$B49="","",'Renda Extra'!$B49) | C164: =IF(OR('Renda Extra'!$B49="",'Renda Extra'!$I49=""),"",'Renda Extra'!$I49) | D164: =IF(C164="","",C164-TODAY()) | E164: =IF(C164="","",D164+ROW()/100000) | F164: =IF('Renda Extra'!$B49="","",'Renda Extra'!$Q49) | G164: =IF(AND(ISNUMBER(C164),ISNUMBER(F164)),C164-F164,"") | H164: =IF(ISNUMBER(G164),IF(G164<0,G164+ROW()/100000,""),"") | P164: =IF('Cursos IA'!$B49="","",'Cursos IA'!$B49)
P165: =IF('Renda Extra'!$B10="","",'Renda Extra'!$B10) -> Marketing de Afiliados do Zero (exemplo)
P166: =IF('Renda Extra'!$B11="","",'Renda Extra'!$B11)
P167: =IF('Renda Extra'!$B12="","",'Renda Extra'!$B12)
P168: =IF('Renda Extra'!$B13="","",'Renda Extra'!$B13)
P169: =IF('Renda Extra'!$B14="","",'Renda Extra'!$B14)
P170: =IF('Renda Extra'!$B15="","",'Renda Extra'!$B15)
P171: =IF('Renda Extra'!$B16="","",'Renda Extra'!$B16)
P172: =IF('Renda Extra'!$B17="","",'Renda Extra'!$B17)
P173: =IF('Renda Extra'!$B18="","",'Renda Extra'!$B18)
P174: =IF('Renda Extra'!$B19="","",'Renda Extra'!$B19)
P175: =IF('Renda Extra'!$B20="","",'Renda Extra'!$B20)
P176: =IF('Renda Extra'!$B21="","",'Renda Extra'!$B21)
... P204: =IF('Renda Extra'!$B49="","",'Renda Extra'!$B49)
