Workbook

Sheet Início
A1: ROADMAP DE CURSOS & APRENDIZADO
A2: Pós-graduação · Concursos · Livros · Cursos de IA · Renda Extra — Sage Dreams · Calm & Natural
B5: NAVEGAÇÃO · CLIQUE PARA ABRIR
B6: Dashboard | E6: Roadmap | H6: Metas de Estudo | K6: Diário de Estudo
B7: Visão executiva, vencimentos urgentes e gráficos | E7: Linha do tempo de 12 meses (Gantt) | H7: Metas de horas, ritmo e mapa de calor | K7: Registro de cada sessão de estudo
B9: Pós-graduação | E9: Concurso | H9: Livros | K9: Cursos IA
B10: MBAs, especializações e extensões | E10: Preparatórios, banca e data da prova | H10: Biblioteca, páginas lidas e notas | K10: Inteligência artificial e automação
B12: Renda Extra | E12: Listas
B13: Cursos de renda e resultado mensal | E13: Listas das setas e prazo de alerta
B16: COMO USAR EM 6 PASSOS
B17: 1 | C17: Abra a aba da categoria e substitua a linha 10 (exemplo) pelo seu primeiro curso. Cada aba comporta 40 itens.
B18: 2 | C18: Preencha instituição, datas (compra, início, término previsto e vencimento do acesso), valor, login e senha.
B19: 3 | C19: Informe o total de aulas, disciplinas ou páginas e atualize o quanto já concluiu — o % de andamento é automático.
B20: 4 | C20: Escolha Status, Prioridade e Certificado pela seta da célula. Vencimento em branco = acesso vitalício.
B21: 5 | C21: Registre cada sessão no Diário de Estudo (linha 7 em diante) e defina suas metas mensais em Metas de Estudo.
B22: 6 | C22: Acompanhe tudo no Dashboard e no Roadmap — não precisa atualizar nada manualmente por lá.
B24: LEGENDA
B25: Célula branca | D25: Campo para preencher.
B26: Célula cinza-areia | D26: Fórmula automática — não edite nem apague.
B27: Em andamento | D27: Status em andamento · barra do Roadmap em verde-sálvia.
B28: Concluído | D28: Status concluído · barra do Roadmap em verde-escuro.
B29: ▲ A vencer | D29: Acesso com vencimento dentro do prazo de alerta (padrão 30 dias, editável em Listas).
B30: ■ Vencido | D30: Acesso expirado — priorize ou renove.
B32: IMPORTANTE
B33: • Não edite as células cinza-areia nem a aba Apoio: elas alimentam o Dashboard, o Roadmap e as Metas.
B34: • Segurança: planilha não é cofre. Prefira um gerenciador de senhas, use a coluna Senha só como lembrete e não compartilhe este arquivo.
B35: • As linhas de exemplo (cursos e diário) entram nos totais até serem substituídas ou apagadas. As metas de horas iniciais (20/20/8/15/10) são sugestões — ajuste em Metas de Estudo.
B36: • Mais de 40 itens? Copie uma linha inteira e use “Inserir células copiadas” ENTRE as linhas do meio da tabela, para fórmulas e gráficos acompanharem.

Sheet Dashboard
A1: DASHBOARD · ROADMAP DE APRENDIZADO
A2: Visão executiva de todas as categorias — tudo atualiza sozinho | K2: ← Voltar ao Início
B5: TOTAL DE ITENS | D5: EM ANDAMENTO | F5: CONCLUÍDOS | H5: INVESTIMENTO TOTAL | J5: PROGRESSO MÉDIO | L5: CERTIFICADOS EMITIDOS
B6: =C16 -> 5 | D6: =E16 -> 5 | F6: =F16 -> 0 | H6: =H16 -> 14933.9 | J6: =I16 -> 0.24944444 | L6: =M16 -> 0
B8: Atualizado em: | C8: =TODAY() -> 46298
B9: RESUMO POR CATEGORIA
B10: Categoria | C10: Itens | D10: Não iniciado | E10: Em andamento | F10: Concluído | G10: Pausado | H10: Investimento (R$) | I10: % médio | J10: Progresso | K10: A vencer | L10: Vencidos | M10: Certificados
B11: Pós-graduação | C11: =COUNTA('Pós-graduação'!B10:B49) -> 1 | D11: =COUNTIF('Pós-graduação'!O10:O49,D$10) -> 0 | E11: =COUNTIF('Pós-graduação'!O10:O49,E$10) -> 1 | F11: =COUNTIF('Pós-graduação'!O10:O49,F$10) -> 0 | G11: =COUNTIF('Pós-graduação'!O10:O49,G$10) -> 0 | H11: =SUM('Pós-graduação'!F10:F49) -> 12600 | I11: =IFERROR(AVERAGE('Pós-graduação'!N10:N49),0) -> 0.1 | J11: =REPT("█",MIN(10,ROUND(I11*10,0)))&REPT("░",10-MIN(10,ROUND(I11*10,0))) -> █░░░░░░░░░ | K11: =COUNTIF('Pós-graduação'!K10:K49,"*A vencer") -> 0 | L11: =COUNTIF('Pós-graduação'!K10:K49,"*Vencido") -> 0 | M11: =COUNTIF('Pós-graduação'!Q10:Q49,"Emitido") -> 0
B12: Concurso | C12: =COUNTA(Concurso!B10:B49) -> 1 | D12: =COUNTIF(Concurso!Q10:Q49,D$10) -> 0 | E12: =COUNTIF(Concurso!Q10:Q49,E$10) -> 1 | F12: =COUNTIF(Concurso!Q10:Q49,F$10) -> 0 | G12: =COUNTIF(Concurso!Q10:Q49,G$10) -> 0 | H12: =SUM(Concurso!H10:H49) -> 1490 | I12: =IFERROR(AVERAGE(Concurso!P10:P49),0) -> 0.25 | J12: =REPT("█",MIN(10,ROUND(I12*10,0)))&REPT("░",10-MIN(10,ROUND(I12*10,0))) -> ███░░░░░░░ | K12: =COUNTIF(Concurso!M10:M49,"*A vencer") -> 0 | L12: =COUNTIF(Concurso!M10:M49,"*Vencido") -> 0 | M12: =COUNTIF(Concurso!S10:S49,"Emitido") -> 0
B13: Livros | C13: =COUNTA(Livros!B10:B49) -> 1 | D13: =COUNTIF(Livros!N10:N49,D$10) -> 0 | E13: =COUNTIF(Livros!N10:N49,E$10) -> 1 | F13: =COUNTIF(Livros!N10:N49,F$10) -> 0 | G13: =COUNTIF(Livros!N10:N49,G$10) -> 0 | H13: =SUM(Livros!H10:H49) -> 49.9 | I13: =IFERROR(AVERAGE(Livros!M10:M49),0) -> 0.375 | J13: =REPT("█",MIN(10,ROUND(I13*10,0)))&REPT("░",10-MIN(10,ROUND(I13*10,0))) -> ████░░░░░░ | K13: — | L13: — | M13: —
B14: Cursos IA | C14: =COUNTA('Cursos IA'!B10:B49) -> 1 | D14: =COUNTIF('Cursos IA'!O10:O49,D$10) -> 0 | E14: =COUNTIF('Cursos IA'!O10:O49,E$10) -> 1 | F14: =COUNTIF('Cursos IA'!O10:O49,F$10) -> 0 | G14: =COUNTIF('Cursos IA'!O10:O49,G$10) -> 0 | H14: =SUM('Cursos IA'!F10:F49) -> 497 | I14: =IFERROR(AVERAGE('Cursos IA'!N10:N49),0) -> 0.3 | J14: =REPT("█",MIN(10,ROUND(I14*10,0)))&REPT("░",10-MIN(10,ROUND(I14*10,0))) -> ███░░░░░░░ | K14: =COUNTIF('Cursos IA'!K10:K49,"*A vencer") -> 0 | L14: =COUNTIF('Cursos IA'!K10:K49,"*Vencido") -> 0 | M14: =COUNTIF('Cursos IA'!Q10:Q49,"Emitido") -> 0
B15: Renda Extra | C15: =COUNTA('Renda Extra'!B10:B49) -> 1 | D15: =COUNTIF('Renda Extra'!O10:O49,D$10) -> 0 | E15: =COUNTIF('Renda Extra'!O10:O49,E$10) -> 1 | F15: =COUNTIF('Renda Extra'!O10:O49,F$10) -> 0 | G15: =COUNTIF('Renda Extra'!O10:O49,G$10) -> 0 | H15: =SUM('Renda Extra'!F10:F49) -> 297 | I15: =IFERROR(AVERAGE('Renda Extra'!N10:N49),0) -> 0.22222222 | J15: =REPT("█",MIN(10,ROUND(I15*10,0)))&REPT("░",10-MIN(10,ROUND(I15*10,0))) -> ██░░░░░░░░ | K15: =COUNTIF('Renda Extra'!K10:K49,"*A vencer") -> 0 | L15: =COUNTIF('Renda Extra'!K10:K49,"*Vencido") -> 0 | M15: =COUNTIF('Renda Extra'!Q10:Q49,"Emitido") -> 0
B16: TOTAL | C16: =SUM(C11:C15) -> 5 | D16: =SUM(D11:D15) -> 0 | E16: =SUM(E11:E15) -> 5 | F16: =SUM(F11:F15) -> 0 | G16: =SUM(G11:G15) -> 0 | H16: =SUM(H11:H15) -> 14933.9 | I16: =IFERROR(SUMPRODUCT(C11:C15,I11:I15)/C16,0) -> 0.24944444 | J16: =REPT("█",MIN(10,ROUND(I16*10,0)))&REPT("░",10-MIN(10,ROUND(I16*10,0))) -> ██░░░░░░░░ | K16: =SUM(K11:K15) -> 0 | L16: =SUM(L11:L15) -> 0 | M16: =SUM(M11:M15) -> 0
B18: VENCIMENTOS DE ACESSO · MAIS URGENTES PRIMEIRO | H18: METAS DE ESTUDO DO MÊS | M18: ='Metas de Estudo'!E5 -> 46296
B19: Categoria | C19: Item | F19: Vence em | G19: Dias | H19: Categoria | J19: Meta (h) | K19: Realizado | L19: % meta | M19: Progresso
B20: =IF(Apoio!$H$5="","",INDEX(Apoio!$A$5:$A$164,Apoio!$H$5)) -> Concurso | C20: =IF(Apoio!$H$5="","",INDEX(Apoio!$B$5:$B$164,Apoio!$H$5)) -> Curso Preparatório Completo (exemplo) | F20: =IF(Apoio!$H$5="","",INDEX(Apoio!$C$5:$C$164,Apoio!$H$5)) -> 46568 | G20: =IF(Apoio!$H$5="","",INDEX(Apoio!$D$5:$D$164,Apoio!$H$5)) -> 270 | H20: ='Metas de Estudo'!B13 -> Pós-graduação | J20: ='Metas de Estudo'!C13 -> 20 | K20: ='Metas de Estudo'!D13 -> 2 | L20: ='Metas de Estudo'!E13 -> 0.1 | M20: ='Metas de Estudo'!F13 -> █░░░░░░░░░
B21: =IF(Apoio!$H$6="","",INDEX(Apoio!$A$5:$A$164,Apoio!$H$6)) -> Renda Extra | C21: =IF(Apoio!$H$6="","",INDEX(Apoio!$B$5:$B$164,Apoio!$H$6)) -> Marketing de Afiliados do Zero (exemplo) | F21: =IF(Apoio!$H$6="","",INDEX(Apoio!$C$5:$C$164,Apoio!$H$6)) -> 46631 | G21: =IF(Apoio!$H$6="","",INDEX(Apoio!$D$5:$D$164,Apoio!$H$6)) -> 333 | H21: ='Metas de Estudo'!B14 -> Concurso | J21: ='Metas de Estudo'!C14 -> 20 | K21: ='Metas de Estudo'!D14 -> 0 | L21: ='Metas de Estudo'!E14 -> 0 | M21: ='Metas de Estudo'!F14 -> ░░░░░░░░░░
B22: =IF(Apoio!$H$7="","",INDEX(Apoio!$A$5:$A$164,Apoio!$H$7)) -> Cursos IA | C22: =IF(Apoio!$H$7="","",INDEX(Apoio!$B$5:$B$164,Apoio!$H$7)) -> Agentes de IA na Prática (exemplo) | F22: =IF(Apoio!$H$7="","",INDEX(Apoio!$C$5:$C$164,Apoio!$H$7)) -> 46642 | G22: =IF(Apoio!$H$7="","",INDEX(Apoio!$D$5:$D$164,Apoio!$H$7)) -> 344 | H22: ='Metas de Estudo'!B15 -> Livros | J22: ='Metas de Estudo'!C15 -> 8 | K22: ='Metas de Estudo'!D15 -> 1 | L22: ='Metas de Estudo'!E15 -> 0.125 | M22: ='Metas de Estudo'!F15 -> █░░░░░░░░░
B23: =IF(Apoio!$H$8="","",INDEX(Apoio!$A$5:$A$164,Apoio!$H$8)) -> Pós-graduação | C23: =IF(Apoio!$H$8="","",INDEX(Apoio!$B$5:$B$164,Apoio!$H$8)) -> MBA em Inteligência Artificial (exemplo) | F23: =IF(Apoio!$H$8="","",INDEX(Apoio!$C$5:$C$164,Apoio!$H$8)) -> 46997 | G23: =IF(Apoio!$H$8="","",INDEX(Apoio!$D$5:$D$164,Apoio!$H$8)) -> 699 | H23: ='Metas de Estudo'!B16 -> Cursos IA | J23: ='Metas de Estudo'!C16 -> 15 | K23: ='Metas de Estudo'!D16 -> 1.5 | L23: ='Metas de Estudo'!E16 -> 0.1 | M23: ='Metas de Estudo'!F16 -> █░░░░░░░░░
B24: =IF(Apoio!$H$9="","",INDEX(Apoio!$A$5:$A$164,Apoio!$H$9)) | C24: =IF(Apoio!$H$9="","",INDEX(Apoio!$B$5:$B$164,Apoio!$H$9)) | F24: =IF(Apoio!$H$9="","",INDEX(Apoio!$C$5:$C$164,Apoio!$H$9)) | G24: =IF(Apoio!$H$9="","",INDEX(Apoio!$D$5:$D$164,Apoio!$H$9)) | H24: ='Metas de Estudo'!B17 -> Renda Extra | J24: ='Metas de Estudo'!C17 -> 10 | K24: ='Metas de Estudo'!D17 -> 0 | L24: ='Metas de Estudo'!E17 -> 0 | M24: ='Metas de Estudo'!F17 -> ░░░░░░░░░░
B25: =IF(Apoio!$H$10="","",INDEX(Apoio!$A$5:$A$164,Apoio!$H$10)) | C25: =IF(Apoio!$H$10="","",INDEX(Apoio!$B$5:$B$164,Apoio!$H$10)) | F25: =IF(Apoio!$H$10="","",INDEX(Apoio!$C$5:$C$164,Apoio!$H$10)) | G25: =IF(Apoio!$H$10="","",INDEX(Apoio!$D$5:$D$164,Apoio!$H$10)) | H25: Dias estudados | J25: ='Metas de Estudo'!G8 -> 3
B26: =IF(Apoio!$H$11="","",INDEX(Apoio!$A$5:$A$164,Apoio!$H$11)) | C26: =IF(Apoio!$H$11="","",INDEX(Apoio!$B$5:$B$164,Apoio!$H$11)) | F26: =IF(Apoio!$H$11="","",INDEX(Apoio!$C$5:$C$164,Apoio!$H$11)) | G26: =IF(Apoio!$H$11="","",INDEX(Apoio!$D$5:$D$164,Apoio!$H$11)) | H26: Média por dia | J26: =IFERROR('Metas de Estudo'!D18/'Metas de Estudo'!G8,0) -> 1.5
B27: =IF(Apoio!$H$12="","",INDEX(Apoio!$A$5:$A$164,Apoio!$H$12)) | C27: =IF(Apoio!$H$12="","",INDEX(Apoio!$B$5:$B$164,Apoio!$H$12)) | F27: =IF(Apoio!$H$12="","",INDEX(Apoio!$C$5:$C$164,Apoio!$H$12)) | G27: =IF(Apoio!$H$12="","",INDEX(Apoio!$D$5:$D$164,Apoio!$H$12)) | H27: Total do mês | J27: ='Metas de Estudo'!D18 -> 4.5
B64: “A vencer” usa o prazo definido em Listas (H6). Livros não têm vencimento de acesso. Painel de vencimentos mostra os 8 acessos mais urgentes, incluindo os já vencidos.

Sheet Roadmap
A1: ROADMAP · LINHA DO TEMPO
A2: Barras = início → término previsto (cor pelo status) · ▼ = mês do vencimento do acesso | Q2: ← Voltar ao Início
A5: Mês inicial: | B5: 46296 | C5: ← altere para deslocar a janela de 12 meses · mostra os 12 primeiros itens de cada aba
A7: Categoria | B7: Item | C7: Status | D7: Início | E7: Término | F7: Vence acesso | G7: % Andam. | H7: =$B$5 -> 46296 | I7: =EDATE(H7,1) -> 46327 | J7: =EDATE(I7,1) -> 46357 | K7: =EDATE(J7,1) -> 46388 | L7: =EDATE(K7,1) -> 46419 | M7: =EDATE(L7,1) -> 46447 | N7: =EDATE(M7,1) -> 46478 | O7: =EDATE(N7,1) -> 46508 | P7: =EDATE(O7,1) -> 46539 | ... S7: =EDATE(R7,1) -> 46631
A8: PÓS-GRADUAÇÃO
A9: =IF($B9="","","Pós-graduação") -> Pós-graduação | B9: =IF('Pós-graduação'!B10="","",'Pós-graduação'!B10) -> MBA em Inteligência Artificial (exemplo) | C9: =IF($B9="","",IF('Pós-graduação'!O10="","",'Pós-graduação'!O10)) -> Em andamento | D9: =IF($B9="","",IF('Pós-graduação'!G10="","",'Pós-graduação'!G10)) -> 46266 | E9: =IF($B9="","",IF('Pós-graduação'!H10<>"",'Pós-graduação'!H10,IF('Pós-graduação'!I10<>"",'Pós-graduação'!I10,""))) -> 46813 | F9: =IF($B9="","",IF('Pós-graduação'!I10="","",'Pós-graduação'!I10)) -> 46997 | G9: =IF($B9="","",'Pós-graduação'!N10) -> 0.1 | H9: =IF(OR($B9="",$F9=""),"",IF(AND($F9>=H$7,$F9<EDATE(H$7,1)),"▼","")) | I9: =IF(OR($B9="",$F9=""),"",IF(AND($F9>=I$7,$F9<EDATE(I$7,1)),"▼","")) | J9: =IF(OR($B9="",$F9=""),"",IF(AND($F9>=J$7,$F9<EDATE(J$7,1)),"▼","")) | K9: =IF(OR($B9="",$F9=""),"",IF(AND($F9>=K$7,$F9<EDATE(K$7,1)),"▼","")) | L9: =IF(OR($B9="",$F9=""),"",IF(AND($F9>=L$7,$F9<EDATE(L$7,1)),"▼","")) | M9: =IF(OR($B9="",$F9=""),"",IF(AND($F9>=M$7,$F9<EDATE(M$7,1)),"▼","")) | N9: =IF(OR($B9="",$F9=""),"",IF(AND($F9>=N$7,$F9<EDATE(N$7,1)),"▼","")) | O9: =IF(OR($B9="",$F9=""),"",IF(AND($F9>=O$7,$F9<EDATE(O$7,1)),"▼","")) | ... S9: =IF(OR($B9="",$F9=""),"",IF(AND($F9>=S$7,$F9<EDATE(S$7,1)),"▼",""))
A10: =IF($B10="","","Pós-graduação") | B10: =IF('Pós-graduação'!B11="","",'Pós-graduação'!B11) | C10: =IF($B10="","",IF('Pós-graduação'!O11="","",'Pós-graduação'!O11)) | D10: =IF($B10="","",IF('Pós-graduação'!G11="","",'Pós-graduação'!G11)) | E10: =IF($B10="","",IF('Pós-graduação'!H11<>"",'Pós-graduação'!H11,IF('Pós-graduação'!I11<>"",'Pós-graduação'!I11,""))) | F10: =IF($B10="","",IF('Pós-graduação'!I11="","",'Pós-graduação'!I11)) | G10: =IF($B10="","",'Pós-graduação'!N11) | H10: =IF(OR($B10="",$F10=""),"",IF(AND($F10>=H$7,$F10<EDATE(H$7,1)),"▼","")) | I10: =IF(OR($B10="",$F10=""),"",IF(AND($F10>=I$7,$F10<EDATE(I$7,1)),"▼","")) | J10: =IF(OR($B10="",$F10=""),"",IF(AND($F10>=J$7,$F10<EDATE(J$7,1)),"▼","")) | K10: =IF(OR($B10="",$F10=""),"",IF(AND($F10>=K$7,$F10<EDATE(K$7,1)),"▼","")) | L10: =IF(OR($B10="",$F10=""),"",IF(AND($F10>=L$7,$F10<EDATE(L$7,1)),"▼","")) | M10: =IF(OR($B10="",$F10=""),"",IF(AND($F10>=M$7,$F10<EDATE(M$7,1)),"▼","")) | N10: =IF(OR($B10="",$F10=""),"",IF(AND($F10>=N$7,$F10<EDATE(N$7,1)),"▼","")) | O10: =IF(OR($B10="",$F10=""),"",IF(AND($F10>=O$7,$F10<EDATE(O$7,1)),"▼","")) | ... S10: =IF(OR($B10="",$F10=""),"",IF(AND($F10>=S$7,$F10<EDATE(S$7,1)),"▼",""))
A11: =IF($B11="","","Pós-graduação") | B11: =IF('Pós-graduação'!B12="","",'Pós-graduação'!B12) | C11: =IF($B11="","",IF('Pós-graduação'!O12="","",'Pós-graduação'!O12)) | D11: =IF($B11="","",IF('Pós-graduação'!G12="","",'Pós-graduação'!G12)) | E11: =IF($B11="","",IF('Pós-graduação'!H12<>"",'Pós-graduação'!H12,IF('Pós-graduação'!I12<>"",'Pós-graduação'!I12,""))) | F11: =IF($B11="","",IF('Pós-graduação'!I12="","",'Pós-graduação'!I12)) | G11: =IF($B11="","",'Pós-graduação'!N12) | H11: =IF(OR($B11="",$F11=""),"",IF(AND($F11>=H$7,$F11<EDATE(H$7,1)),"▼","")) | I11: =IF(OR($B11="",$F11=""),"",IF(AND($F11>=I$7,$F11<EDATE(I$7,1)),"▼","")) | J11: =IF(OR($B11="",$F11=""),"",IF(AND($F11>=J$7,$F11<EDATE(J$7,1)),"▼","")) | K11: =IF(OR($B11="",$F11=""),"",IF(AND($F11>=K$7,$F11<EDATE(K$7,1)),"▼","")) | L11: =IF(OR($B11="",$F11=""),"",IF(AND($F11>=L$7,$F11<EDATE(L$7,1)),"▼","")) | M11: =IF(OR($B11="",$F11=""),"",IF(AND($F11>=M$7,$F11<EDATE(M$7,1)),"▼","")) | N11: =IF(OR($B11="",$F11=""),"",IF(AND($F11>=N$7,$F11<EDATE(N$7,1)),"▼","")) | O11: =IF(OR($B11="",$F11=""),"",IF(AND($F11>=O$7,$F11<EDATE(O$7,1)),"▼","")) | ... S11: =IF(OR($B11="",$F11=""),"",IF(AND($F11>=S$7,$F11<EDATE(S$7,1)),"▼",""))
A12: =IF($B12="","","Pós-graduação") | B12: =IF('Pós-graduação'!B13="","",'Pós-graduação'!B13) | C12: =IF($B12="","",IF('Pós-graduação'!O13="","",'Pós-graduação'!O13)) | D12: =IF($B12="","",IF('Pós-graduação'!G13="","",'Pós-graduação'!G13)) | E12: =IF($B12="","",IF('Pós-graduação'!H13<>"",'Pós-graduação'!H13,IF('Pós-graduação'!I13<>"",'Pós-graduação'!I13,""))) | F12: =IF($B12="","",IF('Pós-graduação'!I13="","",'Pós-graduação'!I13)) | G12: =IF($B12="","",'Pós-graduação'!N13) | H12: =IF(OR($B12="",$F12=""),"",IF(AND($F12>=H$7,$F12<EDATE(H$7,1)),"▼","")) | I12: =IF(OR($B12="",$F12=""),"",IF(AND($F12>=I$7,$F12<EDATE(I$7,1)),"▼","")) | J12: =IF(OR($B12="",$F12=""),"",IF(AND($F12>=J$7,$F12<EDATE(J$7,1)),"▼","")) | K12: =IF(OR($B12="",$F12=""),"",IF(AND($F12>=K$7,$F12<EDATE(K$7,1)),"▼","")) | L12: =IF(OR($B12="",$F12=""),"",IF(AND($F12>=L$7,$F12<EDATE(L$7,1)),"▼","")) | M12: =IF(OR($B12="",$F12=""),"",IF(AND($F12>=M$7,$F12<EDATE(M$7,1)),"▼","")) | N12: =IF(OR($B12="",$F12=""),"",IF(AND($F12>=N$7,$F12<EDATE(N$7,1)),"▼","")) | O12: =IF(OR($B12="",$F12=""),"",IF(AND($F12>=O$7,$F12<EDATE(O$7,1)),"▼","")) | ... S12: =IF(OR($B12="",$F12=""),"",IF(AND($F12>=S$7,$F12<EDATE(S$7,1)),"▼",""))
A13: =IF($B13="","","Pós-graduação") | B13: =IF('Pós-graduação'!B14="","",'Pós-graduação'!B14) | C13: =IF($B13="","",IF('Pós-graduação'!O14="","",'Pós-graduação'!O14)) | D13: =IF($B13="","",IF('Pós-graduação'!G14="","",'Pós-graduação'!G14)) | E13: =IF($B13="","",IF('Pós-graduação'!H14<>"",'Pós-graduação'!H14,IF('Pós-graduação'!I14<>"",'Pós-graduação'!I14,""))) | F13: =IF($B13="","",IF('Pós-graduação'!I14="","",'Pós-graduação'!I14)) | G13: =IF($B13="","",'Pós-graduação'!N14) | H13: =IF(OR($B13="",$F13=""),"",IF(AND($F13>=H$7,$F13<EDATE(H$7,1)),"▼","")) | I13: =IF(OR($B13="",$F13=""),"",IF(AND($F13>=I$7,$F13<EDATE(I$7,1)),"▼","")) | J13: =IF(OR($B13="",$F13=""),"",IF(AND($F13>=J$7,$F13<EDATE(J$7,1)),"▼","")) | K13: =IF(OR($B13="",$F13=""),"",IF(AND($F13>=K$7,$F13<EDATE(K$7,1)),"▼","")) | L13: =IF(OR($B13="",$F13=""),"",IF(AND($F13>=L$7,$F13<EDATE(L$7,1)),"▼","")) | M13: =IF(OR($B13="",$F13=""),"",IF(AND($F13>=M$7,$F13<EDATE(M$7,1)),"▼","")) | N13: =IF(OR($B13="",$F13=""),"",IF(AND($F13>=N$7,$F13<EDATE(N$7,1)),"▼","")) | O13: =IF(OR($B13="",$F13=""),"",IF(AND($F13>=O$7,$F13<EDATE(O$7,1)),"▼","")) | ... S13: =IF(OR($B13="",$F13=""),"",IF(AND($F13>=S$7,$F13<EDATE(S$7,1)),"▼",""))
A14: =IF($B14="","","Pós-graduação") | B14: =IF('Pós-graduação'!B15="","",'Pós-graduação'!B15) | C14: =IF($B14="","",IF('Pós-graduação'!O15="","",'Pós-graduação'!O15)) | D14: =IF($B14="","",IF('Pós-graduação'!G15="","",'Pós-graduação'!G15)) | E14: =IF($B14="","",IF('Pós-graduação'!H15<>"",'Pós-graduação'!H15,IF('Pós-graduação'!I15<>"",'Pós-graduação'!I15,""))) | F14: =IF($B14="","",IF('Pós-graduação'!I15="","",'Pós-graduação'!I15)) | G14: =IF($B14="","",'Pós-graduação'!N15) | H14: =IF(OR($B14="",$F14=""),"",IF(AND($F14>=H$7,$F14<EDATE(H$7,1)),"▼","")) | I14: =IF(OR($B14="",$F14=""),"",IF(AND($F14>=I$7,$F14<EDATE(I$7,1)),"▼","")) | J14: =IF(OR($B14="",$F14=""),"",IF(AND($F14>=J$7,$F14<EDATE(J$7,1)),"▼","")) | K14: =IF(OR($B14="",$F14=""),"",IF(AND($F14>=K$7,$F14<EDATE(K$7,1)),"▼","")) | L14: =IF(OR($B14="",$F14=""),"",IF(AND($F14>=L$7,$F14<EDATE(L$7,1)),"▼","")) | M14: =IF(OR($B14="",$F14=""),"",IF(AND($F14>=M$7,$F14<EDATE(M$7,1)),"▼","")) | N14: =IF(OR($B14="",$F14=""),"",IF(AND($F14>=N$7,$F14<EDATE(N$7,1)),"▼","")) | O14: =IF(OR($B14="",$F14=""),"",IF(AND($F14>=O$7,$F14<EDATE(O$7,1)),"▼","")) | ... S14: =IF(OR($B14="",$F14=""),"",IF(AND($F14>=S$7,$F14<EDATE(S$7,1)),"▼",""))
A15: =IF($B15="","","Pós-graduação") | B15: =IF('Pós-graduação'!B16="","",'Pós-graduação'!B16) | C15: =IF($B15="","",IF('Pós-graduação'!O16="","",'Pós-graduação'!O16)) | D15: =IF($B15="","",IF('Pós-graduação'!G16="","",'Pós-graduação'!G16)) | E15: =IF($B15="","",IF('Pós-graduação'!H16<>"",'Pós-graduação'!H16,IF('Pós-graduação'!I16<>"",'Pós-graduação'!I16,""))) | F15: =IF($B15="","",IF('Pós-graduação'!I16="","",'Pós-graduação'!I16)) | G15: =IF($B15="","",'Pós-graduação'!N16) | H15: =IF(OR($B15="",$F15=""),"",IF(AND($F15>=H$7,$F15<EDATE(H$7,1)),"▼","")) | I15: =IF(OR($B15="",$F15=""),"",IF(AND($F15>=I$7,$F15<EDATE(I$7,1)),"▼","")) | J15: =IF(OR($B15="",$F15=""),"",IF(AND($F15>=J$7,$F15<EDATE(J$7,1)),"▼","")) | K15: =IF(OR($B15="",$F15=""),"",IF(AND($F15>=K$7,$F15<EDATE(K$7,1)),"▼","")) | L15: =IF(OR($B15="",$F15=""),"",IF(AND($F15>=L$7,$F15<EDATE(L$7,1)),"▼","")) | M15: =IF(OR($B15="",$F15=""),"",IF(AND($F15>=M$7,$F15<EDATE(M$7,1)),"▼","")) | N15: =IF(OR($B15="",$F15=""),"",IF(AND($F15>=N$7,$F15<EDATE(N$7,1)),"▼","")) | O15: =IF(OR($B15="",$F15=""),"",IF(AND($F15>=O$7,$F15<EDATE(O$7,1)),"▼","")) | ... S15: =IF(OR($B15="",$F15=""),"",IF(AND($F15>=S$7,$F15<EDATE(S$7,1)),"▼",""))
A16: =IF($B16="","","Pós-graduação") | B16: =IF('Pós-graduação'!B17="","",'Pós-graduação'!B17) | C16: =IF($B16="","",IF('Pós-graduação'!O17="","",'Pós-graduação'!O17)) | D16: =IF($B16="","",IF('Pós-graduação'!G17="","",'Pós-graduação'!G17)) | E16: =IF($B16="","",IF('Pós-graduação'!H17<>"",'Pós-graduação'!H17,IF('Pós-graduação'!I17<>"",'Pós-graduação'!I17,""))) | F16: =IF($B16="","",IF('Pós-graduação'!I17="","",'Pós-graduação'!I17)) | G16: =IF($B16="","",'Pós-graduação'!N17) | H16: =IF(OR($B16="",$F16=""),"",IF(AND($F16>=H$7,$F16<EDATE(H$7,1)),"▼","")) | I16: =IF(OR($B16="",$F16=""),"",IF(AND($F16>=I$7,$F16<EDATE(I$7,1)),"▼","")) | J16: =IF(OR($B16="",$F16=""),"",IF(AND($F16>=J$7,$F16<EDATE(J$7,1)),"▼","")) | K16: =IF(OR($B16="",$F16=""),"",IF(AND($F16>=K$7,$F16<EDATE(K$7,1)),"▼","")) | L16: =IF(OR($B16="",$F16=""),"",IF(AND($F16>=L$7,$F16<EDATE(L$7,1)),"▼","")) | M16: =IF(OR($B16="",$F16=""),"",IF(AND($F16>=M$7,$F16<EDATE(M$7,1)),"▼","")) | N16: =IF(OR($B16="",$F16=""),"",IF(AND($F16>=N$7,$F16<EDATE(N$7,1)),"▼","")) | O16: =IF(OR($B16="",$F16=""),"",IF(AND($F16>=O$7,$F16<EDATE(O$7,1)),"▼","")) | ... S16: =IF(OR($B16="",$F16=""),"",IF(AND($F16>=S$7,$F16<EDATE(S$7,1)),"▼",""))
A17: =IF($B17="","","Pós-graduação") | B17: =IF('Pós-graduação'!B18="","",'Pós-graduação'!B18) | C17: =IF($B17="","",IF('Pós-graduação'!O18="","",'Pós-graduação'!O18)) | D17: =IF($B17="","",IF('Pós-graduação'!G18="","",'Pós-graduação'!G18)) | E17: =IF($B17="","",IF('Pós-graduação'!H18<>"",'Pós-graduação'!H18,IF('Pós-graduação'!I18<>"",'Pós-graduação'!I18,""))) | F17: =IF($B17="","",IF('Pós-graduação'!I18="","",'Pós-graduação'!I18)) | G17: =IF($B17="","",'Pós-graduação'!N18) | H17: =IF(OR($B17="",$F17=""),"",IF(AND($F17>=H$7,$F17<EDATE(H$7,1)),"▼","")) | I17: =IF(OR($B17="",$F17=""),"",IF(AND($F17>=I$7,$F17<EDATE(I$7,1)),"▼","")) | J17: =IF(OR($B17="",$F17=""),"",IF(AND($F17>=J$7,$F17<EDATE(J$7,1)),"▼","")) | K17: =IF(OR($B17="",$F17=""),"",IF(AND($F17>=K$7,$F17<EDATE(K$7,1)),"▼","")) | L17: =IF(OR($B17="",$F17=""),"",IF(AND($F17>=L$7,$F17<EDATE(L$7,1)),"▼","")) | M17: =IF(OR($B17="",$F17=""),"",IF(AND($F17>=M$7,$F17<EDATE(M$7,1)),"▼","")) | N17: =IF(OR($B17="",$F17=""),"",IF(AND($F17>=N$7,$F17<EDATE(N$7,1)),"▼","")) | O17: =IF(OR($B17="",$F17=""),"",IF(AND($F17>=O$7,$F17<EDATE(O$7,1)),"▼","")) | ... S17: =IF(OR($B17="",$F17=""),"",IF(AND($F17>=S$7,$F17<EDATE(S$7,1)),"▼",""))
A18: =IF($B18="","","Pós-graduação") | B18: =IF('Pós-graduação'!B19="","",'Pós-graduação'!B19) | C18: =IF($B18="","",IF('Pós-graduação'!O19="","",'Pós-graduação'!O19)) | D18: =IF($B18="","",IF('Pós-graduação'!G19="","",'Pós-graduação'!G19)) | E18: =IF($B18="","",IF('Pós-graduação'!H19<>"",'Pós-graduação'!H19,IF('Pós-graduação'!I19<>"",'Pós-graduação'!I19,""))) | F18: =IF($B18="","",IF('Pós-graduação'!I19="","",'Pós-graduação'!I19)) | G18: =IF($B18="","",'Pós-graduação'!N19) | H18: =IF(OR($B18="",$F18=""),"",IF(AND($F18>=H$7,$F18<EDATE(H$7,1)),"▼","")) | I18: =IF(OR($B18="",$F18=""),"",IF(AND($F18>=I$7,$F18<EDATE(I$7,1)),"▼","")) | J18: =IF(OR($B18="",$F18=""),"",IF(AND($F18>=J$7,$F18<EDATE(J$7,1)),"▼","")) | K18: =IF(OR($B18="",$F18=""),"",IF(AND($F18>=K$7,$F18<EDATE(K$7,1)),"▼","")) | L18: =IF(OR($B18="",$F18=""),"",IF(AND($F18>=L$7,$F18<EDATE(L$7,1)),"▼","")) | M18: =IF(OR($B18="",$F18=""),"",IF(AND($F18>=M$7,$F18<EDATE(M$7,1)),"▼","")) | N18: =IF(OR($B18="",$F18=""),"",IF(AND($F18>=N$7,$F18<EDATE(N$7,1)),"▼","")) | O18: =IF(OR($B18="",$F18=""),"",IF(AND($F18>=O$7,$F18<EDATE(O$7,1)),"▼","")) | ... S18: =IF(OR($B18="",$F18=""),"",IF(AND($F18>=S$7,$F18<EDATE(S$7,1)),"▼",""))
A19: =IF($B19="","","Pós-graduação") | B19: =IF('Pós-graduação'!B20="","",'Pós-graduação'!B20) | C19: =IF($B19="","",IF('Pós-graduação'!O20="","",'Pós-graduação'!O20)) | D19: =IF($B19="","",IF('Pós-graduação'!G20="","",'Pós-graduação'!G20)) | E19: =IF($B19="","",IF('Pós-graduação'!H20<>"",'Pós-graduação'!H20,IF('Pós-graduação'!I20<>"",'Pós-graduação'!I20,""))) | F19: =IF($B19="","",IF('Pós-graduação'!I20="","",'Pós-graduação'!I20)) | G19: =IF($B19="","",'Pós-graduação'!N20) | H19: =IF(OR($B19="",$F19=""),"",IF(AND($F19>=H$7,$F19<EDATE(H$7,1)),"▼","")) | I19: =IF(OR($B19="",$F19=""),"",IF(AND($F19>=I$7,$F19<EDATE(I$7,1)),"▼","")) | J19: =IF(OR($B19="",$F19=""),"",IF(AND($F19>=J$7,$F19<EDATE(J$7,1)),"▼","")) | K19: =IF(OR($B19="",$F19=""),"",IF(AND($F19>=K$7,$F19<EDATE(K$7,1)),"▼","")) | L19: =IF(OR($B19="",$F19=""),"",IF(AND($F19>=L$7,$F19<EDATE(L$7,1)),"▼","")) | M19: =IF(OR($B19="",$F19=""),"",IF(AND($F19>=M$7,$F19<EDATE(M$7,1)),"▼","")) | N19: =IF(OR($B19="",$F19=""),"",IF(AND($F19>=N$7,$F19<EDATE(N$7,1)),"▼","")) | O19: =IF(OR($B19="",$F19=""),"",IF(AND($F19>=O$7,$F19<EDATE(O$7,1)),"▼","")) | ... S19: =IF(OR($B19="",$F19=""),"",IF(AND($F19>=S$7,$F19<EDATE(S$7,1)),"▼",""))
A20: =IF($B20="","","Pós-graduação") | B20: =IF('Pós-graduação'!B21="","",'Pós-graduação'!B21) | C20: =IF($B20="","",IF('Pós-graduação'!O21="","",'Pós-graduação'!O21)) | D20: =IF($B20="","",IF('Pós-graduação'!G21="","",'Pós-graduação'!G21)) | E20: =IF($B20="","",IF('Pós-graduação'!H21<>"",'Pós-graduação'!H21,IF('Pós-graduação'!I21<>"",'Pós-graduação'!I21,""))) | F20: =IF($B20="","",IF('Pós-graduação'!I21="","",'Pós-graduação'!I21)) | G20: =IF($B20="","",'Pós-graduação'!N21) | H20: =IF(OR($B20="",$F20=""),"",IF(AND($F20>=H$7,$F20<EDATE(H$7,1)),"▼","")) | I20: =IF(OR($B20="",$F20=""),"",IF(AND($F20>=I$7,$F20<EDATE(I$7,1)),"▼","")) | J20: =IF(OR($B20="",$F20=""),"",IF(AND($F20>=J$7,$F20<EDATE(J$7,1)),"▼","")) | K20: =IF(OR($B20="",$F20=""),"",IF(AND($F20>=K$7,$F20<EDATE(K$7,1)),"▼","")) | L20: =IF(OR($B20="",$F20=""),"",IF(AND($F20>=L$7,$F20<EDATE(L$7,1)),"▼","")) | M20: =IF(OR($B20="",$F20=""),"",IF(AND($F20>=M$7,$F20<EDATE(M$7,1)),"▼","")) | N20: =IF(OR($B20="",$F20=""),"",IF(AND($F20>=N$7,$F20<EDATE(N$7,1)),"▼","")) | O20: =IF(OR($B20="",$F20=""),"",IF(AND($F20>=O$7,$F20<EDATE(O$7,1)),"▼","")) | ... S20: =IF(OR($B20="",$F20=""),"",IF(AND($F20>=S$7,$F20<EDATE(S$7,1)),"▼",""))
A21: CONCURSO
A22: =IF($B22="","","Concurso") -> Concurso | B22: =IF(Concurso!B10="","",Concurso!B10) -> Curso Preparatório Completo (exemplo) | C22: =IF($B22="","",IF(Concurso!Q10="","",Concurso!Q10)) -> Em andamento | D22: =IF($B22="","",IF(Concurso!I10="","",Concurso!I10)) -> 46280 | E22: =IF($B22="","",IF(Concurso!J10<>"",Concurso!J10,IF(Concurso!K10<>"",Concurso!K10,""))) -> 46446 | F22: =IF($B22="","",IF(Concurso!K10="","",Concurso!K10)) -> 46568 | G22: =IF($B22="","",Concurso!P10) -> 0.25 | H22: =IF(OR($B22="",$F22=""),"",IF(AND($F22>=H$7,$F22<EDATE(H$7,1)),"▼","")) | I22: =IF(OR($B22="",$F22=""),"",IF(AND($F22>=I$7,$F22<EDATE(I$7,1)),"▼","")) | J22: =IF(OR($B22="",$F22=""),"",IF(AND($F22>=J$7,$F22<EDATE(J$7,1)),"▼","")) | K22: =IF(OR($B22="",$F22=""),"",IF(AND($F22>=K$7,$F22<EDATE(K$7,1)),"▼","")) | L22: =IF(OR($B22="",$F22=""),"",IF(AND($F22>=L$7,$F22<EDATE(L$7,1)),"▼","")) | M22: =IF(OR($B22="",$F22=""),"",IF(AND($F22>=M$7,$F22<EDATE(M$7,1)),"▼","")) | N22: =IF(OR($B22="",$F22=""),"",IF(AND($F22>=N$7,$F22<EDATE(N$7,1)),"▼","")) | O22: =IF(OR($B22="",$F22=""),"",IF(AND($F22>=O$7,$F22<EDATE(O$7,1)),"▼","")) | ... S22: =IF(OR($B22="",$F22=""),"",IF(AND($F22>=S$7,$F22<EDATE(S$7,1)),"▼",""))
A23: =IF($B23="","","Concurso") | B23: =IF(Concurso!B11="","",Concurso!B11) | C23: =IF($B23="","",IF(Concurso!Q11="","",Concurso!Q11)) | D23: =IF($B23="","",IF(Concurso!I11="","",Concurso!I11)) | E23: =IF($B23="","",IF(Concurso!J11<>"",Concurso!J11,IF(Concurso!K11<>"",Concurso!K11,""))) | F23: =IF($B23="","",IF(Concurso!K11="","",Concurso!K11)) | G23: =IF($B23="","",Concurso!P11) | H23: =IF(OR($B23="",$F23=""),"",IF(AND($F23>=H$7,$F23<EDATE(H$7,1)),"▼","")) | I23: =IF(OR($B23="",$F23=""),"",IF(AND($F23>=I$7,$F23<EDATE(I$7,1)),"▼","")) | J23: =IF(OR($B23="",$F23=""),"",IF(AND($F23>=J$7,$F23<EDATE(J$7,1)),"▼","")) | K23: =IF(OR($B23="",$F23=""),"",IF(AND($F23>=K$7,$F23<EDATE(K$7,1)),"▼","")) | L23: =IF(OR($B23="",$F23=""),"",IF(AND($F23>=L$7,$F23<EDATE(L$7,1)),"▼","")) | M23: =IF(OR($B23="",$F23=""),"",IF(AND($F23>=M$7,$F23<EDATE(M$7,1)),"▼","")) | N23: =IF(OR($B23="",$F23=""),"",IF(AND($F23>=N$7,$F23<EDATE(N$7,1)),"▼","")) | O23: =IF(OR($B23="",$F23=""),"",IF(AND($F23>=O$7,$F23<EDATE(O$7,1)),"▼","")) | ... S23: =IF(OR($B23="",$F23=""),"",IF(AND($F23>=S$7,$F23<EDATE(S$7,1)),"▼",""))
A24: =IF($B24="","","Concurso") | B24: =IF(Concurso!B12="","",Concurso!B12) | C24: =IF($B24="","",IF(Concurso!Q12="","",Concurso!Q12)) | D24: =IF($B24="","",IF(Concurso!I12="","",Concurso!I12)) | E24: =IF($B24="","",IF(Concurso!J12<>"",Concurso!J12,IF(Concurso!K12<>"",Concurso!K12,""))) | F24: =IF($B24="","",IF(Concurso!K12="","",Concurso!K12)) | G24: =IF($B24="","",Concurso!P12) | H24: =IF(OR($B24="",$F24=""),"",IF(AND($F24>=H$7,$F24<EDATE(H$7,1)),"▼","")) | I24: =IF(OR($B24="",$F24=""),"",IF(AND($F24>=I$7,$F24<EDATE(I$7,1)),"▼","")) | J24: =IF(OR($B24="",$F24=""),"",IF(AND($F24>=J$7,$F24<EDATE(J$7,1)),"▼","")) | K24: =IF(OR($B24="",$F24=""),"",IF(AND($F24>=K$7,$F24<EDATE(K$7,1)),"▼","")) | L24: =IF(OR($B24="",$F24=""),"",IF(AND($F24>=L$7,$F24<EDATE(L$7,1)),"▼","")) | M24: =IF(OR($B24="",$F24=""),"",IF(AND($F24>=M$7,$F24<EDATE(M$7,1)),"▼","")) | N24: =IF(OR($B24="",$F24=""),"",IF(AND($F24>=N$7,$F24<EDATE(N$7,1)),"▼","")) | O24: =IF(OR($B24="",$F24=""),"",IF(AND($F24>=O$7,$F24<EDATE(O$7,1)),"▼","")) | ... S24: =IF(OR($B24="",$F24=""),"",IF(AND($F24>=S$7,$F24<EDATE(S$7,1)),"▼",""))
A25: =IF($B25="","","Concurso") | B25: =IF(Concurso!B13="","",Concurso!B13) | C25: =IF($B25="","",IF(Concurso!Q13="","",Concurso!Q13)) | D25: =IF($B25="","",IF(Concurso!I13="","",Concurso!I13)) | E25: =IF($B25="","",IF(Concurso!J13<>"",Concurso!J13,IF(Concurso!K13<>"",Concurso!K13,""))) | F25: =IF($B25="","",IF(Concurso!K13="","",Concurso!K13)) | G25: =IF($B25="","",Concurso!P13) | H25: =IF(OR($B25="",$F25=""),"",IF(AND($F25>=H$7,$F25<EDATE(H$7,1)),"▼","")) | I25: =IF(OR($B25="",$F25=""),"",IF(AND($F25>=I$7,$F25<EDATE(I$7,1)),"▼","")) | J25: =IF(OR($B25="",$F25=""),"",IF(AND($F25>=J$7,$F25<EDATE(J$7,1)),"▼","")) | K25: =IF(OR($B25="",$F25=""),"",IF(AND($F25>=K$7,$F25<EDATE(K$7,1)),"▼","")) | L25: =IF(OR($B25="",$F25=""),"",IF(AND($F25>=L$7,$F25<EDATE(L$7,1)),"▼","")) | M25: =IF(OR($B25="",$F25=""),"",IF(AND($F25>=M$7,$F25<EDATE(M$7,1)),"▼","")) | N25: =IF(OR($B25="",$F25=""),"",IF(AND($F25>=N$7,$F25<EDATE(N$7,1)),"▼","")) | O25: =IF(OR($B25="",$F25=""),"",IF(AND($F25>=O$7,$F25<EDATE(O$7,1)),"▼","")) | ... S25: =IF(OR($B25="",$F25=""),"",IF(AND($F25>=S$7,$F25<EDATE(S$7,1)),"▼",""))
A26: =IF($B26="","","Concurso") | B26: =IF(Concurso!B14="","",Concurso!B14) | C26: =IF($B26="","",IF(Concurso!Q14="","",Concurso!Q14)) | D26: =IF($B26="","",IF(Concurso!I14="","",Concurso!I14)) | E26: =IF($B26="","",IF(Concurso!J14<>"",Concurso!J14,IF(Concurso!K14<>"",Concurso!K14,""))) | F26: =IF($B26="","",IF(Concurso!K14="","",Concurso!K14)) | G26: =IF($B26="","",Concurso!P14) | H26: =IF(OR($B26="",$F26=""),"",IF(AND($F26>=H$7,$F26<EDATE(H$7,1)),"▼","")) | I26: =IF(OR($B26="",$F26=""),"",IF(AND($F26>=I$7,$F26<EDATE(I$7,1)),"▼","")) | J26: =IF(OR($B26="",$F26=""),"",IF(AND($F26>=J$7,$F26<EDATE(J$7,1)),"▼","")) | K26: =IF(OR($B26="",$F26=""),"",IF(AND($F26>=K$7,$F26<EDATE(K$7,1)),"▼","")) | L26: =IF(OR($B26="",$F26=""),"",IF(AND($F26>=L$7,$F26<EDATE(L$7,1)),"▼","")) | M26: =IF(OR($B26="",$F26=""),"",IF(AND($F26>=M$7,$F26<EDATE(M$7,1)),"▼","")) | N26: =IF(OR($B26="",$F26=""),"",IF(AND($F26>=N$7,$F26<EDATE(N$7,1)),"▼","")) | O26: =IF(OR($B26="",$F26=""),"",IF(AND($F26>=O$7,$F26<EDATE(O$7,1)),"▼","")) | ... S26: =IF(OR($B26="",$F26=""),"",IF(AND($F26>=S$7,$F26<EDATE(S$7,1)),"▼",""))
A27: =IF($B27="","","Concurso") | B27: =IF(Concurso!B15="","",Concurso!B15) | C27: =IF($B27="","",IF(Concurso!Q15="","",Concurso!Q15)) | D27: =IF($B27="","",IF(Concurso!I15="","",Concurso!I15)) | E27: =IF($B27="","",IF(Concurso!J15<>"",Concurso!J15,IF(Concurso!K15<>"",Concurso!K15,""))) | F27: =IF($B27="","",IF(Concurso!K15="","",Concurso!K15)) | G27: =IF($B27="","",Concurso!P15) | H27: =IF(OR($B27="",$F27=""),"",IF(AND($F27>=H$7,$F27<EDATE(H$7,1)),"▼","")) | I27: =IF(OR($B27="",$F27=""),"",IF(AND($F27>=I$7,$F27<EDATE(I$7,1)),"▼","")) | J27: =IF(OR($B27="",$F27=""),"",IF(AND($F27>=J$7,$F27<EDATE(J$7,1)),"▼","")) | K27: =IF(OR($B27="",$F27=""),"",IF(AND($F27>=K$7,$F27<EDATE(K$7,1)),"▼","")) | L27: =IF(OR($B27="",$F27=""),"",IF(AND($F27>=L$7,$F27<EDATE(L$7,1)),"▼","")) | M27: =IF(OR($B27="",$F27=""),"",IF(AND($F27>=M$7,$F27<EDATE(M$7,1)),"▼","")) | N27: =IF(OR($B27="",$F27=""),"",IF(AND($F27>=N$7,$F27<EDATE(N$7,1)),"▼","")) | O27: =IF(OR($B27="",$F27=""),"",IF(AND($F27>=O$7,$F27<EDATE(O$7,1)),"▼","")) | ... S27: =IF(OR($B27="",$F27=""),"",IF(AND($F27>=S$7,$F27<EDATE(S$7,1)),"▼",""))
A28: =IF($B28="","","Concurso") | B28: =IF(Concurso!B16="","",Concurso!B16) | C28: =IF($B28="","",IF(Concurso!Q16="","",Concurso!Q16)) | D28: =IF($B28="","",IF(Concurso!I16="","",Concurso!I16)) | E28: =IF($B28="","",IF(Concurso!J16<>"",Concurso!J16,IF(Concurso!K16<>"",Concurso!K16,""))) | F28: =IF($B28="","",IF(Concurso!K16="","",Concurso!K16)) | G28: =IF($B28="","",Concurso!P16) | H28: =IF(OR($B28="",$F28=""),"",IF(AND($F28>=H$7,$F28<EDATE(H$7,1)),"▼","")) | I28: =IF(OR($B28="",$F28=""),"",IF(AND($F28>=I$7,$F28<EDATE(I$7,1)),"▼","")) | J28: =IF(OR($B28="",$F28=""),"",IF(AND($F28>=J$7,$F28<EDATE(J$7,1)),"▼","")) | K28: =IF(OR($B28="",$F28=""),"",IF(AND($F28>=K$7,$F28<EDATE(K$7,1)),"▼","")) | L28: =IF(OR($B28="",$F28=""),"",IF(AND($F28>=L$7,$F28<EDATE(L$7,1)),"▼","")) | M28: =IF(OR($B28="",$F28=""),"",IF(AND($F28>=M$7,$F28<EDATE(M$7,1)),"▼","")) | N28: =IF(OR($B28="",$F28=""),"",IF(AND($F28>=N$7,$F28<EDATE(N$7,1)),"▼","")) | O28: =IF(OR($B28="",$F28=""),"",IF(AND($F28>=O$7,$F28<EDATE(O$7,1)),"▼","")) | ... S28: =IF(OR($B28="",$F28=""),"",IF(AND($F28>=S$7,$F28<EDATE(S$7,1)),"▼",""))
A29: =IF($B29="","","Concurso") | B29: =IF(Concurso!B17="","",Concurso!B17) | C29: =IF($B29="","",IF(Concurso!Q17="","",Concurso!Q17)) | D29: =IF($B29="","",IF(Concurso!I17="","",Concurso!I17)) | E29: =IF($B29="","",IF(Concurso!J17<>"",Concurso!J17,IF(Concurso!K17<>"",Concurso!K17,""))) | F29: =IF($B29="","",IF(Concurso!K17="","",Concurso!K17)) | G29: =IF($B29="","",Concurso!P17) | H29: =IF(OR($B29="",$F29=""),"",IF(AND($F29>=H$7,$F29<EDATE(H$7,1)),"▼","")) | I29: =IF(OR($B29="",$F29=""),"",IF(AND($F29>=I$7,$F29<EDATE(I$7,1)),"▼","")) | J29: =IF(OR($B29="",$F29=""),"",IF(AND($F29>=J$7,$F29<EDATE(J$7,1)),"▼","")) | K29: =IF(OR($B29="",$F29=""),"",IF(AND($F29>=K$7,$F29<EDATE(K$7,1)),"▼","")) | L29: =IF(OR($B29="",$F29=""),"",IF(AND($F29>=L$7,$F29<EDATE(L$7,1)),"▼","")) | M29: =IF(OR($B29="",$F29=""),"",IF(AND($F29>=M$7,$F29<EDATE(M$7,1)),"▼","")) | N29: =IF(OR($B29="",$F29=""),"",IF(AND($F29>=N$7,$F29<EDATE(N$7,1)),"▼","")) | O29: =IF(OR($B29="",$F29=""),"",IF(AND($F29>=O$7,$F29<EDATE(O$7,1)),"▼","")) | ... S29: =IF(OR($B29="",$F29=""),"",IF(AND($F29>=S$7,$F29<EDATE(S$7,1)),"▼",""))
A30: =IF($B30="","","Concurso") | B30: =IF(Concurso!B18="","",Concurso!B18) | C30: =IF($B30="","",IF(Concurso!Q18="","",Concurso!Q18)) | D30: =IF($B30="","",IF(Concurso!I18="","",Concurso!I18)) | E30: =IF($B30="","",IF(Concurso!J18<>"",Concurso!J18,IF(Concurso!K18<>"",Concurso!K18,""))) | F30: =IF($B30="","",IF(Concurso!K18="","",Concurso!K18)) | G30: =IF($B30="","",Concurso!P18) | H30: =IF(OR($B30="",$F30=""),"",IF(AND($F30>=H$7,$F30<EDATE(H$7,1)),"▼","")) | I30: =IF(OR($B30="",$F30=""),"",IF(AND($F30>=I$7,$F30<EDATE(I$7,1)),"▼","")) | J30: =IF(OR($B30="",$F30=""),"",IF(AND($F30>=J$7,$F30<EDATE(J$7,1)),"▼","")) | K30: =IF(OR($B30="",$F30=""),"",IF(AND($F30>=K$7,$F30<EDATE(K$7,1)),"▼","")) | L30: =IF(OR($B30="",$F30=""),"",IF(AND($F30>=L$7,$F30<EDATE(L$7,1)),"▼","")) | M30: =IF(OR($B30="",$F30=""),"",IF(AND($F30>=M$7,$F30<EDATE(M$7,1)),"▼","")) | N30: =IF(OR($B30="",$F30=""),"",IF(AND($F30>=N$7,$F30<EDATE(N$7,1)),"▼","")) | O30: =IF(OR($B30="",$F30=""),"",IF(AND($F30>=O$7,$F30<EDATE(O$7,1)),"▼","")) | ... S30: =IF(OR($B30="",$F30=""),"",IF(AND($F30>=S$7,$F30<EDATE(S$7,1)),"▼",""))
A31: =IF($B31="","","Concurso") | B31: =IF(Concurso!B19="","",Concurso!B19) | C31: =IF($B31="","",IF(Concurso!Q19="","",Concurso!Q19)) | D31: =IF($B31="","",IF(Concurso!I19="","",Concurso!I19)) | E31: =IF($B31="","",IF(Concurso!J19<>"",Concurso!J19,IF(Concurso!K19<>"",Concurso!K19,""))) | F31: =IF($B31="","",IF(Concurso!K19="","",Concurso!K19)) | G31: =IF($B31="","",Concurso!P19) | H31: =IF(OR($B31="",$F31=""),"",IF(AND($F31>=H$7,$F31<EDATE(H$7,1)),"▼","")) | I31: =IF(OR($B31="",$F31=""),"",IF(AND($F31>=I$7,$F31<EDATE(I$7,1)),"▼","")) | J31: =IF(OR($B31="",$F31=""),"",IF(AND($F31>=J$7,$F31<EDATE(J$7,1)),"▼","")) | K31: =IF(OR($B31="",$F31=""),"",IF(AND($F31>=K$7,$F31<EDATE(K$7,1)),"▼","")) | L31: =IF(OR($B31="",$F31=""),"",IF(AND($F31>=L$7,$F31<EDATE(L$7,1)),"▼","")) | M31: =IF(OR($B31="",$F31=""),"",IF(AND($F31>=M$7,$F31<EDATE(M$7,1)),"▼","")) | N31: =IF(OR($B31="",$F31=""),"",IF(AND($F31>=N$7,$F31<EDATE(N$7,1)),"▼","")) | O31: =IF(OR($B31="",$F31=""),"",IF(AND($F31>=O$7,$F31<EDATE(O$7,1)),"▼","")) | ... S31: =IF(OR($B31="",$F31=""),"",IF(AND($F31>=S$7,$F31<EDATE(S$7,1)),"▼",""))
A32: =IF($B32="","","Concurso") | B32: =IF(Concurso!B20="","",Concurso!B20) | C32: =IF($B32="","",IF(Concurso!Q20="","",Concurso!Q20)) | D32: =IF($B32="","",IF(Concurso!I20="","",Concurso!I20)) | E32: =IF($B32="","",IF(Concurso!J20<>"",Concurso!J20,IF(Concurso!K20<>"",Concurso!K20,""))) | F32: =IF($B32="","",IF(Concurso!K20="","",Concurso!K20)) | G32: =IF($B32="","",Concurso!P20) | H32: =IF(OR($B32="",$F32=""),"",IF(AND($F32>=H$7,$F32<EDATE(H$7,1)),"▼","")) | I32: =IF(OR($B32="",$F32=""),"",IF(AND($F32>=I$7,$F32<EDATE(I$7,1)),"▼","")) | J32: =IF(OR($B32="",$F32=""),"",IF(AND($F32>=J$7,$F32<EDATE(J$7,1)),"▼","")) | K32: =IF(OR($B32="",$F32=""),"",IF(AND($F32>=K$7,$F32<EDATE(K$7,1)),"▼","")) | L32: =IF(OR($B32="",$F32=""),"",IF(AND($F32>=L$7,$F32<EDATE(L$7,1)),"▼","")) | M32: =IF(OR($B32="",$F32=""),"",IF(AND($F32>=M$7,$F32<EDATE(M$7,1)),"▼","")) | N32: =IF(OR($B32="",$F32=""),"",IF(AND($F32>=N$7,$F32<EDATE(N$7,1)),"▼","")) | O32: =IF(OR($B32="",$F32=""),"",IF(AND($F32>=O$7,$F32<EDATE(O$7,1)),"▼","")) | ... S32: =IF(OR($B32="",$F32=""),"",IF(AND($F32>=S$7,$F32<EDATE(S$7,1)),"▼",""))
A33: =IF($B33="","","Concurso") | B33: =IF(Concurso!B21="","",Concurso!B21) | C33: =IF($B33="","",IF(Concurso!Q21="","",Concurso!Q21)) | D33: =IF($B33="","",IF(Concurso!I21="","",Concurso!I21)) | E33: =IF($B33="","",IF(Concurso!J21<>"",Concurso!J21,IF(Concurso!K21<>"",Concurso!K21,""))) | F33: =IF($B33="","",IF(Concurso!K21="","",Concurso!K21)) | G33: =IF($B33="","",Concurso!P21) | H33: =IF(OR($B33="",$F33=""),"",IF(AND($F33>=H$7,$F33<EDATE(H$7,1)),"▼","")) | I33: =IF(OR($B33="",$F33=""),"",IF(AND($F33>=I$7,$F33<EDATE(I$7,1)),"▼","")) | J33: =IF(OR($B33="",$F33=""),"",IF(AND($F33>=J$7,$F33<EDATE(J$7,1)),"▼","")) | K33: =IF(OR($B33="",$F33=""),"",IF(AND($F33>=K$7,$F33<EDATE(K$7,1)),"▼","")) | L33: =IF(OR($B33="",$F33=""),"",IF(AND($F33>=L$7,$F33<EDATE(L$7,1)),"▼","")) | M33: =IF(OR($B33="",$F33=""),"",IF(AND($F33>=M$7,$F33<EDATE(M$7,1)),"▼","")) | N33: =IF(OR($B33="",$F33=""),"",IF(AND($F33>=N$7,$F33<EDATE(N$7,1)),"▼","")) | O33: =IF(OR($B33="",$F33=""),"",IF(AND($F33>=O$7,$F33<EDATE(O$7,1)),"▼","")) | ... S33: =IF(OR($B33="",$F33=""),"",IF(AND($F33>=S$7,$F33<EDATE(S$7,1)),"▼",""))
A34: LIVROS
A35: =IF($B35="","","Livros") -> Livros | B35: =IF(Livros!B10="","",Livros!B10) -> Hábitos Atômicos (exemplo) | C35: =IF($B35="","",IF(Livros!N10="","",Livros!N10)) -> Em andamento | D35: =IF($B35="","",IF(Livros!I10="","",Livros!I10)) -> 46290 | E35: =IF($B35="","",IF(Livros!J10="","",Livros!J10)) -> 46341 | F35: ="" | G35: =IF($B35="","",Livros!M10) -> 0.375 | H35: =IF(OR($B35="",$F35=""),"",IF(AND($F35>=H$7,$F35<EDATE(H$7,1)),"▼","")) | I35: =IF(OR($B35="",$F35=""),"",IF(AND($F35>=I$7,$F35<EDATE(I$7,1)),"▼","")) | J35: =IF(OR($B35="",$F35=""),"",IF(AND($F35>=J$7,$F35<EDATE(J$7,1)),"▼","")) | K35: =IF(OR($B35="",$F35=""),"",IF(AND($F35>=K$7,$F35<EDATE(K$7,1)),"▼","")) | L35: =IF(OR($B35="",$F35=""),"",IF(AND($F35>=L$7,$F35<EDATE(L$7,1)),"▼","")) | M35: =IF(OR($B35="",$F35=""),"",IF(AND($F35>=M$7,$F35<EDATE(M$7,1)),"▼","")) | N35: =IF(OR($B35="",$F35=""),"",IF(AND($F35>=N$7,$F35<EDATE(N$7,1)),"▼","")) | O35: =IF(OR($B35="",$F35=""),"",IF(AND($F35>=O$7,$F35<EDATE(O$7,1)),"▼","")) | ... S35: =IF(OR($B35="",$F35=""),"",IF(AND($F35>=S$7,$F35<EDATE(S$7,1)),"▼",""))
A36: =IF($B36="","","Livros") | B36: =IF(Livros!B11="","",Livros!B11) | C36: =IF($B36="","",IF(Livros!N11="","",Livros!N11)) | D36: =IF($B36="","",IF(Livros!I11="","",Livros!I11)) | E36: =IF($B36="","",IF(Livros!J11="","",Livros!J11)) | F36: ="" | G36: =IF($B36="","",Livros!M11) | H36: =IF(OR($B36="",$F36=""),"",IF(AND($F36>=H$7,$F36<EDATE(H$7,1)),"▼","")) | I36: =IF(OR($B36="",$F36=""),"",IF(AND($F36>=I$7,$F36<EDATE(I$7,1)),"▼","")) | J36: =IF(OR($B36="",$F36=""),"",IF(AND($F36>=J$7,$F36<EDATE(J$7,1)),"▼","")) | K36: =IF(OR($B36="",$F36=""),"",IF(AND($F36>=K$7,$F36<EDATE(K$7,1)),"▼","")) | L36: =IF(OR($B36="",$F36=""),"",IF(AND($F36>=L$7,$F36<EDATE(L$7,1)),"▼","")) | M36: =IF(OR($B36="",$F36=""),"",IF(AND($F36>=M$7,$F36<EDATE(M$7,1)),"▼","")) | N36: =IF(OR($B36="",$F36=""),"",IF(AND($F36>=N$7,$F36<EDATE(N$7,1)),"▼","")) | O36: =IF(OR($B36="",$F36=""),"",IF(AND($F36>=O$7,$F36<EDATE(O$7,1)),"▼","")) | ... S36: =IF(OR($B36="",$F36=""),"",IF(AND($F36>=S$7,$F36<EDATE(S$7,1)),"▼",""))
A37: =IF($B37="","","Livros") | B37: =IF(Livros!B12="","",Livros!B12) | C37: =IF($B37="","",IF(Livros!N12="","",Livros!N12)) | D37: =IF($B37="","",IF(Livros!I12="","",Livros!I12)) | E37: =IF($B37="","",IF(Livros!J12="","",Livros!J12)) | F37: ="" | G37: =IF($B37="","",Livros!M12) | H37: =IF(OR($B37="",$F37=""),"",IF(AND($F37>=H$7,$F37<EDATE(H$7,1)),"▼","")) | I37: =IF(OR($B37="",$F37=""),"",IF(AND($F37>=I$7,$F37<EDATE(I$7,1)),"▼","")) | J37: =IF(OR($B37="",$F37=""),"",IF(AND($F37>=J$7,$F37<EDATE(J$7,1)),"▼","")) | K37: =IF(OR($B37="",$F37=""),"",IF(AND($F37>=K$7,$F37<EDATE(K$7,1)),"▼","")) | L37: =IF(OR($B37="",$F37=""),"",IF(AND($F37>=L$7,$F37<EDATE(L$7,1)),"▼","")) | M37: =IF(OR($B37="",$F37=""),"",IF(AND($F37>=M$7,$F37<EDATE(M$7,1)),"▼","")) | N37: =IF(OR($B37="",$F37=""),"",IF(AND($F37>=N$7,$F37<EDATE(N$7,1)),"▼","")) | O37: =IF(OR($B37="",$F37=""),"",IF(AND($F37>=O$7,$F37<EDATE(O$7,1)),"▼","")) | ... S37: =IF(OR($B37="",$F37=""),"",IF(AND($F37>=S$7,$F37<EDATE(S$7,1)),"▼",""))
A38: =IF($B38="","","Livros") | B38: =IF(Livros!B13="","",Livros!B13) | C38: =IF($B38="","",IF(Livros!N13="","",Livros!N13)) | D38: =IF($B38="","",IF(Livros!I13="","",Livros!I13)) | E38: =IF($B38="","",IF(Livros!J13="","",Livros!J13)) | F38: ="" | G38: =IF($B38="","",Livros!M13) | H38: =IF(OR($B38="",$F38=""),"",IF(AND($F38>=H$7,$F38<EDATE(H$7,1)),"▼","")) | I38: =IF(OR($B38="",$F38=""),"",IF(AND($F38>=I$7,$F38<EDATE(I$7,1)),"▼","")) | J38: =IF(OR($B38="",$F38=""),"",IF(AND($F38>=J$7,$F38<EDATE(J$7,1)),"▼","")) | K38: =IF(OR($B38="",$F38=""),"",IF(AND($F38>=K$7,$F38<EDATE(K$7,1)),"▼","")) | L38: =IF(OR($B38="",$F38=""),"",IF(AND($F38>=L$7,$F38<EDATE(L$7,1)),"▼","")) | M38: =IF(OR($B38="",$F38=""),"",IF(AND($F38>=M$7,$F38<EDATE(M$7,1)),"▼","")) | N38: =IF(OR($B38="",$F38=""),"",IF(AND($F38>=N$7,$F38<EDATE(N$7,1)),"▼","")) | O38: =IF(OR($B38="",$F38=""),"",IF(AND($F38>=O$7,$F38<EDATE(O$7,1)),"▼","")) | ... S38: =IF(OR($B38="",$F38=""),"",IF(AND($F38>=S$7,$F38<EDATE(S$7,1)),"▼",""))
A39: =IF($B39="","","Livros") | B39: =IF(Livros!B14="","",Livros!B14) | C39: =IF($B39="","",IF(Livros!N14="","",Livros!N14)) | D39: =IF($B39="","",IF(Livros!I14="","",Livros!I14)) | E39: =IF($B39="","",IF(Livros!J14="","",Livros!J14)) | F39: ="" | G39: =IF($B39="","",Livros!M14) | H39: =IF(OR($B39="",$F39=""),"",IF(AND($F39>=H$7,$F39<EDATE(H$7,1)),"▼","")) | I39: =IF(OR($B39="",$F39=""),"",IF(AND($F39>=I$7,$F39<EDATE(I$7,1)),"▼","")) | J39: =IF(OR($B39="",$F39=""),"",IF(AND($F39>=J$7,$F39<EDATE(J$7,1)),"▼","")) | K39: =IF(OR($B39="",$F39=""),"",IF(AND($F39>=K$7,$F39<EDATE(K$7,1)),"▼","")) | L39: =IF(OR($B39="",$F39=""),"",IF(AND($F39>=L$7,$F39<EDATE(L$7,1)),"▼","")) | M39: =IF(OR($B39="",$F39=""),"",IF(AND($F39>=M$7,$F39<EDATE(M$7,1)),"▼","")) | N39: =IF(OR($B39="",$F39=""),"",IF(AND($F39>=N$7,$F39<EDATE(N$7,1)),"▼","")) | O39: =IF(OR($B39="",$F39=""),"",IF(AND($F39>=O$7,$F39<EDATE(O$7,1)),"▼","")) | ... S39: =IF(OR($B39="",$F39=""),"",IF(AND($F39>=S$7,$F39<EDATE(S$7,1)),"▼",""))
A40: =IF($B40="","","Livros") | B40: =IF(Livros!B15="","",Livros!B15) | C40: =IF($B40="","",IF(Livros!N15="","",Livros!N15)) | D40: =IF($B40="","",IF(Livros!I15="","",Livros!I15)) | E40: =IF($B40="","",IF(Livros!J15="","",Livros!J15)) | F40: ="" | G40: =IF($B40="","",Livros!M15) | H40: =IF(OR($B40="",$F40=""),"",IF(AND($F40>=H$7,$F40<EDATE(H$7,1)),"▼","")) | I40: =IF(OR($B40="",$F40=""),"",IF(AND($F40>=I$7,$F40<EDATE(I$7,1)),"▼","")) | J40: =IF(OR($B40="",$F40=""),"",IF(AND($F40>=J$7,$F40<EDATE(J$7,1)),"▼","")) | K40: =IF(OR($B40="",$F40=""),"",IF(AND($F40>=K$7,$F40<EDATE(K$7,1)),"▼","")) | L40: =IF(OR($B40="",$F40=""),"",IF(AND($F40>=L$7,$F40<EDATE(L$7,1)),"▼","")) | M40: =IF(OR($B40="",$F40=""),"",IF(AND($F40>=M$7,$F40<EDATE(M$7,1)),"▼","")) | N40: =IF(OR($B40="",$F40=""),"",IF(AND($F40>=N$7,$F40<EDATE(N$7,1)),"▼","")) | O40: =IF(OR($B40="",$F40=""),"",IF(AND($F40>=O$7,$F40<EDATE(O$7,1)),"▼","")) | ... S40: =IF(OR($B40="",$F40=""),"",IF(AND($F40>=S$7,$F40<EDATE(S$7,1)),"▼",""))
A41: =IF($B41="","","Livros") | B41: =IF(Livros!B16="","",Livros!B16) | C41: =IF($B41="","",IF(Livros!N16="","",Livros!N16)) | D41: =IF($B41="","",IF(Livros!I16="","",Livros!I16)) | E41: =IF($B41="","",IF(Livros!J16="","",Livros!J16)) | F41: ="" | G41: =IF($B41="","",Livros!M16) | H41: =IF(OR($B41="",$F41=""),"",IF(AND($F41>=H$7,$F41<EDATE(H$7,1)),"▼","")) | I41: =IF(OR($B41="",$F41=""),"",IF(AND($F41>=I$7,$F41<EDATE(I$7,1)),"▼","")) | J41: =IF(OR($B41="",$F41=""),"",IF(AND($F41>=J$7,$F41<EDATE(J$7,1)),"▼","")) | K41: =IF(OR($B41="",$F41=""),"",IF(AND($F41>=K$7,$F41<EDATE(K$7,1)),"▼","")) | L41: =IF(OR($B41="",$F41=""),"",IF(AND($F41>=L$7,$F41<EDATE(L$7,1)),"▼","")) | M41: =IF(OR($B41="",$F41=""),"",IF(AND($F41>=M$7,$F41<EDATE(M$7,1)),"▼","")) | N41: =IF(OR($B41="",$F41=""),"",IF(AND($F41>=N$7,$F41<EDATE(N$7,1)),"▼","")) | O41: =IF(OR($B41="",$F41=""),"",IF(AND($F41>=O$7,$F41<EDATE(O$7,1)),"▼","")) | ... S41: =IF(OR($B41="",$F41=""),"",IF(AND($F41>=S$7,$F41<EDATE(S$7,1)),"▼",""))
A42: =IF($B42="","","Livros") | B42: =IF(Livros!B17="","",Livros!B17) | C42: =IF($B42="","",IF(Livros!N17="","",Livros!N17)) | D42: =IF($B42="","",IF(Livros!I17="","",Livros!I17)) | E42: =IF($B42="","",IF(Livros!J17="","",Livros!J17)) | F42: ="" | G42: =IF($B42="","",Livros!M17) | H42: =IF(OR($B42="",$F42=""),"",IF(AND($F42>=H$7,$F42<EDATE(H$7,1)),"▼","")) | I42: =IF(OR($B42="",$F42=""),"",IF(AND($F42>=I$7,$F42<EDATE(I$7,1)),"▼","")) | J42: =IF(OR($B42="",$F42=""),"",IF(AND($F42>=J$7,$F42<EDATE(J$7,1)),"▼","")) | K42: =IF(OR($B42="",$F42=""),"",IF(AND($F42>=K$7,$F42<EDATE(K$7,1)),"▼","")) | L42: =IF(OR($B42="",$F42=""),"",IF(AND($F42>=L$7,$F42<EDATE(L$7,1)),"▼","")) | M42: =IF(OR($B42="",$F42=""),"",IF(AND($F42>=M$7,$F42<EDATE(M$7,1)),"▼","")) | N42: =IF(OR($B42="",$F42=""),"",IF(AND($F42>=N$7,$F42<EDATE(N$7,1)),"▼","")) | O42: =IF(OR($B42="",$F42=""),"",IF(AND($F42>=O$7,$F42<EDATE(O$7,1)),"▼","")) | ... S42: =IF(OR($B42="",$F42=""),"",IF(AND($F42>=S$7,$F42<EDATE(S$7,1)),"▼",""))
A43: =IF($B43="","","Livros") | B43: =IF(Livros!B18="","",Livros!B18) | C43: =IF($B43="","",IF(Livros!N18="","",Livros!N18)) | D43: =IF($B43="","",IF(Livros!I18="","",Livros!I18)) | E43: =IF($B43="","",IF(Livros!J18="","",Livros!J18)) | F43: ="" | G43: =IF($B43="","",Livros!M18) | H43: =IF(OR($B43="",$F43=""),"",IF(AND($F43>=H$7,$F43<EDATE(H$7,1)),"▼","")) | I43: =IF(OR($B43="",$F43=""),"",IF(AND($F43>=I$7,$F43<EDATE(I$7,1)),"▼","")) | J43: =IF(OR($B43="",$F43=""),"",IF(AND($F43>=J$7,$F43<EDATE(J$7,1)),"▼","")) | K43: =IF(OR($B43="",$F43=""),"",IF(AND($F43>=K$7,$F43<EDATE(K$7,1)),"▼","")) | L43: =IF(OR($B43="",$F43=""),"",IF(AND($F43>=L$7,$F43<EDATE(L$7,1)),"▼","")) | M43: =IF(OR($B43="",$F43=""),"",IF(AND($F43>=M$7,$F43<EDATE(M$7,1)),"▼","")) | N43: =IF(OR($B43="",$F43=""),"",IF(AND($F43>=N$7,$F43<EDATE(N$7,1)),"▼","")) | O43: =IF(OR($B43="",$F43=""),"",IF(AND($F43>=O$7,$F43<EDATE(O$7,1)),"▼","")) | ... S43: =IF(OR($B43="",$F43=""),"",IF(AND($F43>=S$7,$F43<EDATE(S$7,1)),"▼",""))
A44: =IF($B44="","","Livros") | B44: =IF(Livros!B19="","",Livros!B19) | C44: =IF($B44="","",IF(Livros!N19="","",Livros!N19)) | D44: =IF($B44="","",IF(Livros!I19="","",Livros!I19)) | E44: =IF($B44="","",IF(Livros!J19="","",Livros!J19)) | F44: ="" | G44: =IF($B44="","",Livros!M19) | H44: =IF(OR($B44="",$F44=""),"",IF(AND($F44>=H$7,$F44<EDATE(H$7,1)),"▼","")) | I44: =IF(OR($B44="",$F44=""),"",IF(AND($F44>=I$7,$F44<EDATE(I$7,1)),"▼","")) | J44: =IF(OR($B44="",$F44=""),"",IF(AND($F44>=J$7,$F44<EDATE(J$7,1)),"▼","")) | K44: =IF(OR($B44="",$F44=""),"",IF(AND($F44>=K$7,$F44<EDATE(K$7,1)),"▼","")) | L44: =IF(OR($B44="",$F44=""),"",IF(AND($F44>=L$7,$F44<EDATE(L$7,1)),"▼","")) | M44: =IF(OR($B44="",$F44=""),"",IF(AND($F44>=M$7,$F44<EDATE(M$7,1)),"▼","")) | N44: =IF(OR($B44="",$F44=""),"",IF(AND($F44>=N$7,$F44<EDATE(N$7,1)),"▼","")) | O44: =IF(OR($B44="",$F44=""),"",IF(AND($F44>=O$7,$F44<EDATE(O$7,1)),"▼","")) | ... S44: =IF(OR($B44="",$F44=""),"",IF(AND($F44>=S$7,$F44<EDATE(S$7,1)),"▼",""))
A45: =IF($B45="","","Livros") | B45: =IF(Livros!B20="","",Livros!B20) | C45: =IF($B45="","",IF(Livros!N20="","",Livros!N20)) | D45: =IF($B45="","",IF(Livros!I20="","",Livros!I20)) | E45: =IF($B45="","",IF(Livros!J20="","",Livros!J20)) | F45: ="" | G45: =IF($B45="","",Livros!M20) | H45: =IF(OR($B45="",$F45=""),"",IF(AND($F45>=H$7,$F45<EDATE(H$7,1)),"▼","")) | I45: =IF(OR($B45="",$F45=""),"",IF(AND($F45>=I$7,$F45<EDATE(I$7,1)),"▼","")) | J45: =IF(OR($B45="",$F45=""),"",IF(AND($F45>=J$7,$F45<EDATE(J$7,1)),"▼","")) | K45: =IF(OR($B45="",$F45=""),"",IF(AND($F45>=K$7,$F45<EDATE(K$7,1)),"▼","")) | L45: =IF(OR($B45="",$F45=""),"",IF(AND($F45>=L$7,$F45<EDATE(L$7,1)),"▼","")) | M45: =IF(OR($B45="",$F45=""),"",IF(AND($F45>=M$7,$F45<EDATE(M$7,1)),"▼","")) | N45: =IF(OR($B45="",$F45=""),"",IF(AND($F45>=N$7,$F45<EDATE(N$7,1)),"▼","")) | O45: =IF(OR($B45="",$F45=""),"",IF(AND($F45>=O$7,$F45<EDATE(O$7,1)),"▼","")) | ... S45: =IF(OR($B45="",$F45=""),"",IF(AND($F45>=S$7,$F45<EDATE(S$7,1)),"▼",""))
A46: =IF($B46="","","Livros") | B46: =IF(Livros!B21="","",Livros!B21) | C46: =IF($B46="","",IF(Livros!N21="","",Livros!N21)) | D46: =IF($B46="","",IF(Livros!I21="","",Livros!I21)) | E46: =IF($B46="","",IF(Livros!J21="","",Livros!J21)) | F46: ="" | G46: =IF($B46="","",Livros!M21) | H46: =IF(OR($B46="",$F46=""),"",IF(AND($F46>=H$7,$F46<EDATE(H$7,1)),"▼","")) | I46: =IF(OR($B46="",$F46=""),"",IF(AND($F46>=I$7,$F46<EDATE(I$7,1)),"▼","")) | J46: =IF(OR($B46="",$F46=""),"",IF(AND($F46>=J$7,$F46<EDATE(J$7,1)),"▼","")) | K46: =IF(OR($B46="",$F46=""),"",IF(AND($F46>=K$7,$F46<EDATE(K$7,1)),"▼","")) | L46: =IF(OR($B46="",$F46=""),"",IF(AND($F46>=L$7,$F46<EDATE(L$7,1)),"▼","")) | M46: =IF(OR($B46="",$F46=""),"",IF(AND($F46>=M$7,$F46<EDATE(M$7,1)),"▼","")) | N46: =IF(OR($B46="",$F46=""),"",IF(AND($F46>=N$7,$F46<EDATE(N$7,1)),"▼","")) | O46: =IF(OR($B46="",$F46=""),"",IF(AND($F46>=O$7,$F46<EDATE(O$7,1)),"▼","")) | ... S46: =IF(OR($B46="",$F46=""),"",IF(AND($F46>=S$7,$F46<EDATE(S$7,1)),"▼",""))
A47: CURSOS IA
A48: =IF($B48="","","Cursos IA") -> Cursos IA | B48: =IF('Cursos IA'!B10="","",'Cursos IA'!B10) -> Agentes de IA na Prática (exemplo) | C48: =IF($B48="","",IF('Cursos IA'!O10="","",'Cursos IA'!O10)) -> Em andamento | D48: =IF($B48="","",IF('Cursos IA'!G10="","",'Cursos IA'!G10)) -> 46285 | E48: =IF($B48="","",IF('Cursos IA'!H10<>"",'Cursos IA'!H10,IF('Cursos IA'!I10<>"",'Cursos IA'!I10,""))) -> 46376 | F48: =IF($B48="","",IF('Cursos IA'!I10="","",'Cursos IA'!I10)) -> 46642 | G48: =IF($B48="","",'Cursos IA'!N10) -> 0.3 | H48: =IF(OR($B48="",$F48=""),"",IF(AND($F48>=H$7,$F48<EDATE(H$7,1)),"▼","")) | I48: =IF(OR($B48="",$F48=""),"",IF(AND($F48>=I$7,$F48<EDATE(I$7,1)),"▼","")) | J48: =IF(OR($B48="",$F48=""),"",IF(AND($F48>=J$7,$F48<EDATE(J$7,1)),"▼","")) | K48: =IF(OR($B48="",$F48=""),"",IF(AND($F48>=K$7,$F48<EDATE(K$7,1)),"▼","")) | L48: =IF(OR($B48="",$F48=""),"",IF(AND($F48>=L$7,$F48<EDATE(L$7,1)),"▼","")) | M48: =IF(OR($B48="",$F48=""),"",IF(AND($F48>=M$7,$F48<EDATE(M$7,1)),"▼","")) | N48: =IF(OR($B48="",$F48=""),"",IF(AND($F48>=N$7,$F48<EDATE(N$7,1)),"▼","")) | O48: =IF(OR($B48="",$F48=""),"",IF(AND($F48>=O$7,$F48<EDATE(O$7,1)),"▼","")) | ... S48: =IF(OR($B48="",$F48=""),"",IF(AND($F48>=S$7,$F48<EDATE(S$7,1)),"▼","")) -> ▼
A49: =IF($B49="","","Cursos IA") | B49: =IF('Cursos IA'!B11="","",'Cursos IA'!B11) | C49: =IF($B49="","",IF('Cursos IA'!O11="","",'Cursos IA'!O11)) | D49: =IF($B49="","",IF('Cursos IA'!G11="","",'Cursos IA'!G11)) | E49: =IF($B49="","",IF('Cursos IA'!H11<>"",'Cursos IA'!H11,IF('Cursos IA'!I11<>"",'Cursos IA'!I11,""))) | F49: =IF($B49="","",IF('Cursos IA'!I11="","",'Cursos IA'!I11)) | G49: =IF($B49="","",'Cursos IA'!N11) | H49: =IF(OR($B49="",$F49=""),"",IF(AND($F49>=H$7,$F49<EDATE(H$7,1)),"▼","")) | I49: =IF(OR($B49="",$F49=""),"",IF(AND($F49>=I$7,$F49<EDATE(I$7,1)),"▼","")) | J49: =IF(OR($B49="",$F49=""),"",IF(AND($F49>=J$7,$F49<EDATE(J$7,1)),"▼","")) | K49: =IF(OR($B49="",$F49=""),"",IF(AND($F49>=K$7,$F49<EDATE(K$7,1)),"▼","")) | L49: =IF(OR($B49="",$F49=""),"",IF(AND($F49>=L$7,$F49<EDATE(L$7,1)),"▼","")) | M49: =IF(OR($B49="",$F49=""),"",IF(AND($F49>=M$7,$F49<EDATE(M$7,1)),"▼","")) | N49: =IF(OR($B49="",$F49=""),"",IF(AND($F49>=N$7,$F49<EDATE(N$7,1)),"▼","")) | O49: =IF(OR($B49="",$F49=""),"",IF(AND($F49>=O$7,$F49<EDATE(O$7,1)),"▼","")) | ... S49: =IF(OR($B49="",$F49=""),"",IF(AND($F49>=S$7,$F49<EDATE(S$7,1)),"▼",""))
A50: =IF($B50="","","Cursos IA") | B50: =IF('Cursos IA'!B12="","",'Cursos IA'!B12) | C50: =IF($B50="","",IF('Cursos IA'!O12="","",'Cursos IA'!O12)) | D50: =IF($B50="","",IF('Cursos IA'!G12="","",'Cursos IA'!G12)) | E50: =IF($B50="","",IF('Cursos IA'!H12<>"",'Cursos IA'!H12,IF('Cursos IA'!I12<>"",'Cursos IA'!I12,""))) | F50: =IF($B50="","",IF('Cursos IA'!I12="","",'Cursos IA'!I12)) | G50: =IF($B50="","",'Cursos IA'!N12) | H50: =IF(OR($B50="",$F50=""),"",IF(AND($F50>=H$7,$F50<EDATE(H$7,1)),"▼","")) | I50: =IF(OR($B50="",$F50=""),"",IF(AND($F50>=I$7,$F50<EDATE(I$7,1)),"▼","")) | J50: =IF(OR($B50="",$F50=""),"",IF(AND($F50>=J$7,$F50<EDATE(J$7,1)),"▼","")) | K50: =IF(OR($B50="",$F50=""),"",IF(AND($F50>=K$7,$F50<EDATE(K$7,1)),"▼","")) | L50: =IF(OR($B50="",$F50=""),"",IF(AND($F50>=L$7,$F50<EDATE(L$7,1)),"▼","")) | M50: =IF(OR($B50="",$F50=""),"",IF(AND($F50>=M$7,$F50<EDATE(M$7,1)),"▼","")) | N50: =IF(OR($B50="",$F50=""),"",IF(AND($F50>=N$7,$F50<EDATE(N$7,1)),"▼","")) | O50: =IF(OR($B50="",$F50=""),"",IF(AND($F50>=O$7,$F50<EDATE(O$7,1)),"▼","")) | ... S50: =IF(OR($B50="",$F50=""),"",IF(AND($F50>=S$7,$F50<EDATE(S$7,1)),"▼",""))
A51: =IF($B51="","","Cursos IA") | B51: =IF('Cursos IA'!B13="","",'Cursos IA'!B13) | C51: =IF($B51="","",IF('Cursos IA'!O13="","",'Cursos IA'!O13)) | D51: =IF($B51="","",IF('Cursos IA'!G13="","",'Cursos IA'!G13)) | E51: =IF($B51="","",IF('Cursos IA'!H13<>"",'Cursos IA'!H13,IF('Cursos IA'!I13<>"",'Cursos IA'!I13,""))) | F51: =IF($B51="","",IF('Cursos IA'!I13="","",'Cursos IA'!I13)) | G51: =IF($B51="","",'Cursos IA'!N13) | H51: =IF(OR($B51="",$F51=""),"",IF(AND($F51>=H$7,$F51<EDATE(H$7,1)),"▼","")) | I51: =IF(OR($B51="",$F51=""),"",IF(AND($F51>=I$7,$F51<EDATE(I$7,1)),"▼","")) | J51: =IF(OR($B51="",$F51=""),"",IF(AND($F51>=J$7,$F51<EDATE(J$7,1)),"▼","")) | K51: =IF(OR($B51="",$F51=""),"",IF(AND($F51>=K$7,$F51<EDATE(K$7,1)),"▼","")) | L51: =IF(OR($B51="",$F51=""),"",IF(AND($F51>=L$7,$F51<EDATE(L$7,1)),"▼","")) | M51: =IF(OR($B51="",$F51=""),"",IF(AND($F51>=M$7,$F51<EDATE(M$7,1)),"▼","")) | N51: =IF(OR($B51="",$F51=""),"",IF(AND($F51>=N$7,$F51<EDATE(N$7,1)),"▼","")) | O51: =IF(OR($B51="",$F51=""),"",IF(AND($F51>=O$7,$F51<EDATE(O$7,1)),"▼","")) | ... S51: =IF(OR($B51="",$F51=""),"",IF(AND($F51>=S$7,$F51<EDATE(S$7,1)),"▼",""))
A52: =IF($B52="","","Cursos IA") | B52: =IF('Cursos IA'!B14="","",'Cursos IA'!B14) | C52: =IF($B52="","",IF('Cursos IA'!O14="","",'Cursos IA'!O14)) | D52: =IF($B52="","",IF('Cursos IA'!G14="","",'Cursos IA'!G14)) | E52: =IF($B52="","",IF('Cursos IA'!H14<>"",'Cursos IA'!H14,IF('Cursos IA'!I14<>"",'Cursos IA'!I14,""))) | F52: =IF($B52="","",IF('Cursos IA'!I14="","",'Cursos IA'!I14)) | G52: =IF($B52="","",'Cursos IA'!N14) | H52: =IF(OR($B52="",$F52=""),"",IF(AND($F52>=H$7,$F52<EDATE(H$7,1)),"▼","")) | I52: =IF(OR($B52="",$F52=""),"",IF(AND($F52>=I$7,$F52<EDATE(I$7,1)),"▼","")) | J52: =IF(OR($B52="",$F52=""),"",IF(AND($F52>=J$7,$F52<EDATE(J$7,1)),"▼","")) | K52: =IF(OR($B52="",$F52=""),"",IF(AND($F52>=K$7,$F52<EDATE(K$7,1)),"▼","")) | L52: =IF(OR($B52="",$F52=""),"",IF(AND($F52>=L$7,$F52<EDATE(L$7,1)),"▼","")) | M52: =IF(OR($B52="",$F52=""),"",IF(AND($F52>=M$7,$F52<EDATE(M$7,1)),"▼","")) | N52: =IF(OR($B52="",$F52=""),"",IF(AND($F52>=N$7,$F52<EDATE(N$7,1)),"▼","")) | O52: =IF(OR($B52="",$F52=""),"",IF(AND($F52>=O$7,$F52<EDATE(O$7,1)),"▼","")) | ... S52: =IF(OR($B52="",$F52=""),"",IF(AND($F52>=S$7,$F52<EDATE(S$7,1)),"▼",""))
A53: =IF($B53="","","Cursos IA") | B53: =IF('Cursos IA'!B15="","",'Cursos IA'!B15) | C53: =IF($B53="","",IF('Cursos IA'!O15="","",'Cursos IA'!O15)) | D53: =IF($B53="","",IF('Cursos IA'!G15="","",'Cursos IA'!G15)) | E53: =IF($B53="","",IF('Cursos IA'!H15<>"",'Cursos IA'!H15,IF('Cursos IA'!I15<>"",'Cursos IA'!I15,""))) | F53: =IF($B53="","",IF('Cursos IA'!I15="","",'Cursos IA'!I15)) | G53: =IF($B53="","",'Cursos IA'!N15) | H53: =IF(OR($B53="",$F53=""),"",IF(AND($F53>=H$7,$F53<EDATE(H$7,1)),"▼","")) | I53: =IF(OR($B53="",$F53=""),"",IF(AND($F53>=I$7,$F53<EDATE(I$7,1)),"▼","")) | J53: =IF(OR($B53="",$F53=""),"",IF(AND($F53>=J$7,$F53<EDATE(J$7,1)),"▼","")) | K53: =IF(OR($B53="",$F53=""),"",IF(AND($F53>=K$7,$F53<EDATE(K$7,1)),"▼","")) | L53: =IF(OR($B53="",$F53=""),"",IF(AND($F53>=L$7,$F53<EDATE(L$7,1)),"▼","")) | M53: =IF(OR($B53="",$F53=""),"",IF(AND($F53>=M$7,$F53<EDATE(M$7,1)),"▼","")) | N53: =IF(OR($B53="",$F53=""),"",IF(AND($F53>=N$7,$F53<EDATE(N$7,1)),"▼","")) | O53: =IF(OR($B53="",$F53=""),"",IF(AND($F53>=O$7,$F53<EDATE(O$7,1)),"▼","")) | ... S53: =IF(OR($B53="",$F53=""),"",IF(AND($F53>=S$7,$F53<EDATE(S$7,1)),"▼",""))
A54: =IF($B54="","","Cursos IA") | B54: =IF('Cursos IA'!B16="","",'Cursos IA'!B16) | C54: =IF($B54="","",IF('Cursos IA'!O16="","",'Cursos IA'!O16)) | D54: =IF($B54="","",IF('Cursos IA'!G16="","",'Cursos IA'!G16)) | E54: =IF($B54="","",IF('Cursos IA'!H16<>"",'Cursos IA'!H16,IF('Cursos IA'!I16<>"",'Cursos IA'!I16,""))) | F54: =IF($B54="","",IF('Cursos IA'!I16="","",'Cursos IA'!I16)) | G54: =IF($B54="","",'Cursos IA'!N16) | H54: =IF(OR($B54="",$F54=""),"",IF(AND($F54>=H$7,$F54<EDATE(H$7,1)),"▼","")) | I54: =IF(OR($B54="",$F54=""),"",IF(AND($F54>=I$7,$F54<EDATE(I$7,1)),"▼","")) | J54: =IF(OR($B54="",$F54=""),"",IF(AND($F54>=J$7,$F54<EDATE(J$7,1)),"▼","")) | K54: =IF(OR($B54="",$F54=""),"",IF(AND($F54>=K$7,$F54<EDATE(K$7,1)),"▼","")) | L54: =IF(OR($B54="",$F54=""),"",IF(AND($F54>=L$7,$F54<EDATE(L$7,1)),"▼","")) | M54: =IF(OR($B54="",$F54=""),"",IF(AND($F54>=M$7,$F54<EDATE(M$7,1)),"▼","")) | N54: =IF(OR($B54="",$F54=""),"",IF(AND($F54>=N$7,$F54<EDATE(N$7,1)),"▼","")) | O54: =IF(OR($B54="",$F54=""),"",IF(AND($F54>=O$7,$F54<EDATE(O$7,1)),"▼","")) | ... S54: =IF(OR($B54="",$F54=""),"",IF(AND($F54>=S$7,$F54<EDATE(S$7,1)),"▼",""))
A55: =IF($B55="","","Cursos IA") | B55: =IF('Cursos IA'!B17="","",'Cursos IA'!B17) | C55: =IF($B55="","",IF('Cursos IA'!O17="","",'Cursos IA'!O17)) | D55: =IF($B55="","",IF('Cursos IA'!G17="","",'Cursos IA'!G17)) | E55: =IF($B55="","",IF('Cursos IA'!H17<>"",'Cursos IA'!H17,IF('Cursos IA'!I17<>"",'Cursos IA'!I17,""))) | F55: =IF($B55="","",IF('Cursos IA'!I17="","",'Cursos IA'!I17)) | G55: =IF($B55="","",'Cursos IA'!N17) | H55: =IF(OR($B55="",$F55=""),"",IF(AND($F55>=H$7,$F55<EDATE(H$7,1)),"▼","")) | I55: =IF(OR($B55="",$F55=""),"",IF(AND($F55>=I$7,$F55<EDATE(I$7,1)),"▼","")) | J55: =IF(OR($B55="",$F55=""),"",IF(AND($F55>=J$7,$F55<EDATE(J$7,1)),"▼","")) | K55: =IF(OR($B55="",$F55=""),"",IF(AND($F55>=K$7,$F55<EDATE(K$7,1)),"▼","")) | L55: =IF(OR($B55="",$F55=""),"",IF(AND($F55>=L$7,$F55<EDATE(L$7,1)),"▼","")) | M55: =IF(OR($B55="",$F55=""),"",IF(AND($F55>=M$7,$F55<EDATE(M$7,1)),"▼","")) | N55: =IF(OR($B55="",$F55=""),"",IF(AND($F55>=N$7,$F55<EDATE(N$7,1)),"▼","")) | O55: =IF(OR($B55="",$F55=""),"",IF(AND($F55>=O$7,$F55<EDATE(O$7,1)),"▼","")) | ... S55: =IF(OR($B55="",$F55=""),"",IF(AND($F55>=S$7,$F55<EDATE(S$7,1)),"▼",""))
A56: =IF($B56="","","Cursos IA") | B56: =IF('Cursos IA'!B18="","",'Cursos IA'!B18) | C56: =IF($B56="","",IF('Cursos IA'!O18="","",'Cursos IA'!O18)) | D56: =IF($B56="","",IF('Cursos IA'!G18="","",'Cursos IA'!G18)) | E56: =IF($B56="","",IF('Cursos IA'!H18<>"",'Cursos IA'!H18,IF('Cursos IA'!I18<>"",'Cursos IA'!I18,""))) | F56: =IF($B56="","",IF('Cursos IA'!I18="","",'Cursos IA'!I18)) | G56: =IF($B56="","",'Cursos IA'!N18) | H56: =IF(OR($B56="",$F56=""),"",IF(AND($F56>=H$7,$F56<EDATE(H$7,1)),"▼","")) | I56: =IF(OR($B56="",$F56=""),"",IF(AND($F56>=I$7,$F56<EDATE(I$7,1)),"▼","")) | J56: =IF(OR($B56="",$F56=""),"",IF(AND($F56>=J$7,$F56<EDATE(J$7,1)),"▼","")) | K56: =IF(OR($B56="",$F56=""),"",IF(AND($F56>=K$7,$F56<EDATE(K$7,1)),"▼","")) | L56: =IF(OR($B56="",$F56=""),"",IF(AND($F56>=L$7,$F56<EDATE(L$7,1)),"▼","")) | M56: =IF(OR($B56="",$F56=""),"",IF(AND($F56>=M$7,$F56<EDATE(M$7,1)),"▼","")) | N56: =IF(OR($B56="",$F56=""),"",IF(AND($F56>=N$7,$F56<EDATE(N$7,1)),"▼","")) | O56: =IF(OR($B56="",$F56=""),"",IF(AND($F56>=O$7,$F56<EDATE(O$7,1)),"▼","")) | ... S56: =IF(OR($B56="",$F56=""),"",IF(AND($F56>=S$7,$F56<EDATE(S$7,1)),"▼",""))
A57: =IF($B57="","","Cursos IA") | B57: =IF('Cursos IA'!B19="","",'Cursos IA'!B19) | C57: =IF($B57="","",IF('Cursos IA'!O19="","",'Cursos IA'!O19)) | D57: =IF($B57="","",IF('Cursos IA'!G19="","",'Cursos IA'!G19)) | E57: =IF($B57="","",IF('Cursos IA'!H19<>"",'Cursos IA'!H19,IF('Cursos IA'!I19<>"",'Cursos IA'!I19,""))) | F57: =IF($B57="","",IF('Cursos IA'!I19="","",'Cursos IA'!I19)) | G57: =IF($B57="","",'Cursos IA'!N19) | H57: =IF(OR($B57="",$F57=""),"",IF(AND($F57>=H$7,$F57<EDATE(H$7,1)),"▼","")) | I57: =IF(OR($B57="",$F57=""),"",IF(AND($F57>=I$7,$F57<EDATE(I$7,1)),"▼","")) | J57: =IF(OR($B57="",$F57=""),"",IF(AND($F57>=J$7,$F57<EDATE(J$7,1)),"▼","")) | K57: =IF(OR($B57="",$F57=""),"",IF(AND($F57>=K$7,$F57<EDATE(K$7,1)),"▼","")) | L57: =IF(OR($B57="",$F57=""),"",IF(AND($F57>=L$7,$F57<EDATE(L$7,1)),"▼","")) | M57: =IF(OR($B57="",$F57=""),"",IF(AND($F57>=M$7,$F57<EDATE(M$7,1)),"▼","")) | N57: =IF(OR($B57="",$F57=""),"",IF(AND($F57>=N$7,$F57<EDATE(N$7,1)),"▼","")) | O57: =IF(OR($B57="",$F57=""),"",IF(AND($F57>=O$7,$F57<EDATE(O$7,1)),"▼","")) | ... S57: =IF(OR($B57="",$F57=""),"",IF(AND($F57>=S$7,$F57<EDATE(S$7,1)),"▼",""))
A58: =IF($B58="","","Cursos IA") | B58: =IF('Cursos IA'!B20="","",'Cursos IA'!B20) | C58: =IF($B58="","",IF('Cursos IA'!O20="","",'Cursos IA'!O20)) | D58: =IF($B58="","",IF('Cursos IA'!G20="","",'Cursos IA'!G20)) | E58: =IF($B58="","",IF('Cursos IA'!H20<>"",'Cursos IA'!H20,IF('Cursos IA'!I20<>"",'Cursos IA'!I20,""))) | F58: =IF($B58="","",IF('Cursos IA'!I20="","",'Cursos IA'!I20)) | G58: =IF($B58="","",'Cursos IA'!N20) | H58: =IF(OR($B58="",$F58=""),"",IF(AND($F58>=H$7,$F58<EDATE(H$7,1)),"▼","")) | I58: =IF(OR($B58="",$F58=""),"",IF(AND($F58>=I$7,$F58<EDATE(I$7,1)),"▼","")) | J58: =IF(OR($B58="",$F58=""),"",IF(AND($F58>=J$7,$F58<EDATE(J$7,1)),"▼","")) | K58: =IF(OR($B58="",$F58=""),"",IF(AND($F58>=K$7,$F58<EDATE(K$7,1)),"▼","")) | L58: =IF(OR($B58="",$F58=""),"",IF(AND($F58>=L$7,$F58<EDATE(L$7,1)),"▼","")) | M58: =IF(OR($B58="",$F58=""),"",IF(AND($F58>=M$7,$F58<EDATE(M$7,1)),"▼","")) | N58: =IF(OR($B58="",$F58=""),"",IF(AND($F58>=N$7,$F58<EDATE(N$7,1)),"▼","")) | O58: =IF(OR($B58="",$F58=""),"",IF(AND($F58>=O$7,$F58<EDATE(O$7,1)),"▼","")) | ... S58: =IF(OR($B58="",$F58=""),"",IF(AND($F58>=S$7,$F58<EDATE(S$7,1)),"▼",""))
A59: =IF($B59="","","Cursos IA") | B59: =IF('Cursos IA'!B21="","",'Cursos IA'!B21) | C59: =IF($B59="","",IF('Cursos IA'!O21="","",'Cursos IA'!O21)) | D59: =IF($B59="","",IF('Cursos IA'!G21="","",'Cursos IA'!G21)) | E59: =IF($B59="","",IF('Cursos IA'!H21<>"",'Cursos IA'!H21,IF('Cursos IA'!I21<>"",'Cursos IA'!I21,""))) | F59: =IF($B59="","",IF('Cursos IA'!I21="","",'Cursos IA'!I21)) | G59: =IF($B59="","",'Cursos IA'!N21) | H59: =IF(OR($B59="",$F59=""),"",IF(AND($F59>=H$7,$F59<EDATE(H$7,1)),"▼","")) | I59: =IF(OR($B59="",$F59=""),"",IF(AND($F59>=I$7,$F59<EDATE(I$7,1)),"▼","")) | J59: =IF(OR($B59="",$F59=""),"",IF(AND($F59>=J$7,$F59<EDATE(J$7,1)),"▼","")) | K59: =IF(OR($B59="",$F59=""),"",IF(AND($F59>=K$7,$F59<EDATE(K$7,1)),"▼","")) | L59: =IF(OR($B59="",$F59=""),"",IF(AND($F59>=L$7,$F59<EDATE(L$7,1)),"▼","")) | M59: =IF(OR($B59="",$F59=""),"",IF(AND($F59>=M$7,$F59<EDATE(M$7,1)),"▼","")) | N59: =IF(OR($B59="",$F59=""),"",IF(AND($F59>=N$7,$F59<EDATE(N$7,1)),"▼","")) | O59: =IF(OR($B59="",$F59=""),"",IF(AND($F59>=O$7,$F59<EDATE(O$7,1)),"▼","")) | ... S59: =IF(OR($B59="",$F59=""),"",IF(AND($F59>=S$7,$F59<EDATE(S$7,1)),"▼",""))
A60: RENDA EXTRA
A61: =IF($B61="","","Renda Extra") -> Renda Extra | B61: =IF('Renda Extra'!B10="","",'Renda Extra'!B10) -> Marketing de Afiliados do Zero (exemplo) | C61: =IF($B61="","",IF('Renda Extra'!O10="","",'Renda Extra'!O10)) -> Em andamento | D61: =IF($B61="","",IF('Renda Extra'!G10="","",'Renda Extra'!G10)) -> 46268 | E61: =IF($B61="","",IF('Renda Extra'!H10<>"",'Renda Extra'!H10,IF('Renda Extra'!I10<>"",'Renda Extra'!I10,""))) -> 46356 | F61: =IF($B61="","",IF('Renda Extra'!I10="","",'Renda Extra'!I10)) -> 46631 | G61: =IF($B61="","",'Renda Extra'!N10) -> 0.22222222 | H61: =IF(OR($B61="",$F61=""),"",IF(AND($F61>=H$7,$F61<EDATE(H$7,1)),"▼","")) | I61: =IF(OR($B61="",$F61=""),"",IF(AND($F61>=I$7,$F61<EDATE(I$7,1)),"▼","")) | J61: =IF(OR($B61="",$F61=""),"",IF(AND($F61>=J$7,$F61<EDATE(J$7,1)),"▼","")) | K61: =IF(OR($B61="",$F61=""),"",IF(AND($F61>=K$7,$F61<EDATE(K$7,1)),"▼","")) | L61: =IF(OR($B61="",$F61=""),"",IF(AND($F61>=L$7,$F61<EDATE(L$7,1)),"▼","")) | M61: =IF(OR($B61="",$F61=""),"",IF(AND($F61>=M$7,$F61<EDATE(M$7,1)),"▼","")) | N61: =IF(OR($B61="",$F61=""),"",IF(AND($F61>=N$7,$F61<EDATE(N$7,1)),"▼","")) | O61: =IF(OR($B61="",$F61=""),"",IF(AND($F61>=O$7,$F61<EDATE(O$7,1)),"▼","")) | ... S61: =IF(OR($B61="",$F61=""),"",IF(AND($F61>=S$7,$F61<EDATE(S$7,1)),"▼","")) -> ▼
A62: =IF($B62="","","Renda Extra") | B62: =IF('Renda Extra'!B11="","",'Renda Extra'!B11) | C62: =IF($B62="","",IF('Renda Extra'!O11="","",'Renda Extra'!O11)) | D62: =IF($B62="","",IF('Renda Extra'!G11="","",'Renda Extra'!G11)) | E62: =IF($B62="","",IF('Renda Extra'!H11<>"",'Renda Extra'!H11,IF('Renda Extra'!I11<>"",'Renda Extra'!I11,""))) | F62: =IF($B62="","",IF('Renda Extra'!I11="","",'Renda Extra'!I11)) | G62: =IF($B62="","",'Renda Extra'!N11) | H62: =IF(OR($B62="",$F62=""),"",IF(AND($F62>=H$7,$F62<EDATE(H$7,1)),"▼","")) | I62: =IF(OR($B62="",$F62=""),"",IF(AND($F62>=I$7,$F62<EDATE(I$7,1)),"▼","")) | J62: =IF(OR($B62="",$F62=""),"",IF(AND($F62>=J$7,$F62<EDATE(J$7,1)),"▼","")) | K62: =IF(OR($B62="",$F62=""),"",IF(AND($F62>=K$7,$F62<EDATE(K$7,1)),"▼","")) | L62: =IF(OR($B62="",$F62=""),"",IF(AND($F62>=L$7,$F62<EDATE(L$7,1)),"▼","")) | M62: =IF(OR($B62="",$F62=""),"",IF(AND($F62>=M$7,$F62<EDATE(M$7,1)),"▼","")) | N62: =IF(OR($B62="",$F62=""),"",IF(AND($F62>=N$7,$F62<EDATE(N$7,1)),"▼","")) | O62: =IF(OR($B62="",$F62=""),"",IF(AND($F62>=O$7,$F62<EDATE(O$7,1)),"▼","")) | ... S62: =IF(OR($B62="",$F62=""),"",IF(AND($F62>=S$7,$F62<EDATE(S$7,1)),"▼",""))
A63: =IF($B63="","","Renda Extra") | B63: =IF('Renda Extra'!B12="","",'Renda Extra'!B12) | C63: =IF($B63="","",IF('Renda Extra'!O12="","",'Renda Extra'!O12)) | D63: =IF($B63="","",IF('Renda Extra'!G12="","",'Renda Extra'!G12)) | E63: =IF($B63="","",IF('Renda Extra'!H12<>"",'Renda Extra'!H12,IF('Renda Extra'!I12<>"",'Renda Extra'!I12,""))) | F63: =IF($B63="","",IF('Renda Extra'!I12="","",'Renda Extra'!I12)) | G63: =IF($B63="","",'Renda Extra'!N12) | H63: =IF(OR($B63="",$F63=""),"",IF(AND($F63>=H$7,$F63<EDATE(H$7,1)),"▼","")) | I63: =IF(OR($B63="",$F63=""),"",IF(AND($F63>=I$7,$F63<EDATE(I$7,1)),"▼","")) | J63: =IF(OR($B63="",$F63=""),"",IF(AND($F63>=J$7,$F63<EDATE(J$7,1)),"▼","")) | K63: =IF(OR($B63="",$F63=""),"",IF(AND($F63>=K$7,$F63<EDATE(K$7,1)),"▼","")) | L63: =IF(OR($B63="",$F63=""),"",IF(AND($F63>=L$7,$F63<EDATE(L$7,1)),"▼","")) | M63: =IF(OR($B63="",$F63=""),"",IF(AND($F63>=M$7,$F63<EDATE(M$7,1)),"▼","")) | N63: =IF(OR($B63="",$F63=""),"",IF(AND($F63>=N$7,$F63<EDATE(N$7,1)),"▼","")) | O63: =IF(OR($B63="",$F63=""),"",IF(AND($F63>=O$7,$F63<EDATE(O$7,1)),"▼","")) | ... S63: =IF(OR($B63="",$F63=""),"",IF(AND($F63>=S$7,$F63<EDATE(S$7,1)),"▼",""))
A64: =IF($B64="","","Renda Extra") | B64: =IF('Renda Extra'!B13="","",'Renda Extra'!B13) | C64: =IF($B64="","",IF('Renda Extra'!O13="","",'Renda Extra'!O13)) | D64: =IF($B64="","",IF('Renda Extra'!G13="","",'Renda Extra'!G13)) | E64: =IF($B64="","",IF('Renda Extra'!H13<>"",'Renda Extra'!H13,IF('Renda Extra'!I13<>"",'Renda Extra'!I13,""))) | F64: =IF($B64="","",IF('Renda Extra'!I13="","",'Renda Extra'!I13)) | G64: =IF($B64="","",'Renda Extra'!N13) | H64: =IF(OR($B64="",$F64=""),"",IF(AND($F64>=H$7,$F64<EDATE(H$7,1)),"▼","")) | I64: =IF(OR($B64="",$F64=""),"",IF(AND($F64>=I$7,$F64<EDATE(I$7,1)),"▼","")) | J64: =IF(OR($B64="",$F64=""),"",IF(AND($F64>=J$7,$F64<EDATE(J$7,1)),"▼","")) | K64: =IF(OR($B64="",$F64=""),"",IF(AND($F64>=K$7,$F64<EDATE(K$7,1)),"▼","")) | L64: =IF(OR($B64="",$F64=""),"",IF(AND($F64>=L$7,$F64<EDATE(L$7,1)),"▼","")) | M64: =IF(OR($B64="",$F64=""),"",IF(AND($F64>=M$7,$F64<EDATE(M$7,1)),"▼","")) | N64: =IF(OR($B64="",$F64=""),"",IF(AND($F64>=N$7,$F64<EDATE(N$7,1)),"▼","")) | O64: =IF(OR($B64="",$F64=""),"",IF(AND($F64>=O$7,$F64<EDATE(O$7,1)),"▼","")) | ... S64: =IF(OR($B64="",$F64=""),"",IF(AND($F64>=S$7,$F64<EDATE(S$7,1)),"▼",""))
A65: =IF($B65="","","Renda Extra") | B65: =IF('Renda Extra'!B14="","",'Renda Extra'!B14) | C65: =IF($B65="","",IF('Renda Extra'!O14="","",'Renda Extra'!O14)) | D65: =IF($B65="","",IF('Renda Extra'!G14="","",'Renda Extra'!G14)) | E65: =IF($B65="","",IF('Renda Extra'!H14<>"",'Renda Extra'!H14,IF('Renda Extra'!I14<>"",'Renda Extra'!I14,""))) | F65: =IF($B65="","",IF('Renda Extra'!I14="","",'Renda Extra'!I14)) | G65: =IF($B65="","",'Renda Extra'!N14) | H65: =IF(OR($B65="",$F65=""),"",IF(AND($F65>=H$7,$F65<EDATE(H$7,1)),"▼","")) | I65: =IF(OR($B65="",$F65=""),"",IF(AND($F65>=I$7,$F65<EDATE(I$7,1)),"▼","")) | J65: =IF(OR($B65="",$F65=""),"",IF(AND($F65>=J$7,$F65<EDATE(J$7,1)),"▼","")) | K65: =IF(OR($B65="",$F65=""),"",IF(AND($F65>=K$7,$F65<EDATE(K$7,1)),"▼","")) | L65: =IF(OR($B65="",$F65=""),"",IF(AND($F65>=L$7,$F65<EDATE(L$7,1)),"▼","")) | M65: =IF(OR($B65="",$F65=""),"",IF(AND($F65>=M$7,$F65<EDATE(M$7,1)),"▼","")) | N65: =IF(OR($B65="",$F65=""),"",IF(AND($F65>=N$7,$F65<EDATE(N$7,1)),"▼","")) | O65: =IF(OR($B65="",$F65=""),"",IF(AND($F65>=O$7,$F65<EDATE(O$7,1)),"▼","")) | ... S65: =IF(OR($B65="",$F65=""),"",IF(AND($F65>=S$7,$F65<EDATE(S$7,1)),"▼",""))
A66: =IF($B66="","","Renda Extra") | B66: =IF('Renda Extra'!B15="","",'Renda Extra'!B15) | C66: =IF($B66="","",IF('Renda Extra'!O15="","",'Renda Extra'!O15)) | D66: =IF($B66="","",IF('Renda Extra'!G15="","",'Renda Extra'!G15)) | E66: =IF($B66="","",IF('Renda Extra'!H15<>"",'Renda Extra'!H15,IF('Renda Extra'!I15<>"",'Renda Extra'!I15,""))) | F66: =IF($B66="","",IF('Renda Extra'!I15="","",'Renda Extra'!I15)) | G66: =IF($B66="","",'Renda Extra'!N15) | H66: =IF(OR($B66="",$F66=""),"",IF(AND($F66>=H$7,$F66<EDATE(H$7,1)),"▼","")) | I66: =IF(OR($B66="",$F66=""),"",IF(AND($F66>=I$7,$F66<EDATE(I$7,1)),"▼","")) | J66: =IF(OR($B66="",$F66=""),"",IF(AND($F66>=J$7,$F66<EDATE(J$7,1)),"▼","")) | K66: =IF(OR($B66="",$F66=""),"",IF(AND($F66>=K$7,$F66<EDATE(K$7,1)),"▼","")) | L66: =IF(OR($B66="",$F66=""),"",IF(AND($F66>=L$7,$F66<EDATE(L$7,1)),"▼","")) | M66: =IF(OR($B66="",$F66=""),"",IF(AND($F66>=M$7,$F66<EDATE(M$7,1)),"▼","")) | N66: =IF(OR($B66="",$F66=""),"",IF(AND($F66>=N$7,$F66<EDATE(N$7,1)),"▼","")) | O66: =IF(OR($B66="",$F66=""),"",IF(AND($F66>=O$7,$F66<EDATE(O$7,1)),"▼","")) | ... S66: =IF(OR($B66="",$F66=""),"",IF(AND($F66>=S$7,$F66<EDATE(S$7,1)),"▼",""))
A67: =IF($B67="","","Renda Extra") | B67: =IF('Renda Extra'!B16="","",'Renda Extra'!B16) | C67: =IF($B67="","",IF('Renda Extra'!O16="","",'Renda Extra'!O16)) | D67: =IF($B67="","",IF('Renda Extra'!G16="","",'Renda Extra'!G16)) | E67: =IF($B67="","",IF('Renda Extra'!H16<>"",'Renda Extra'!H16,IF('Renda Extra'!I16<>"",'Renda Extra'!I16,""))) | F67: =IF($B67="","",IF('Renda Extra'!I16="","",'Renda Extra'!I16)) | G67: =IF($B67="","",'Renda Extra'!N16) | H67: =IF(OR($B67="",$F67=""),"",IF(AND($F67>=H$7,$F67<EDATE(H$7,1)),"▼","")) | I67: =IF(OR($B67="",$F67=""),"",IF(AND($F67>=I$7,$F67<EDATE(I$7,1)),"▼","")) | J67: =IF(OR($B67="",$F67=""),"",IF(AND($F67>=J$7,$F67<EDATE(J$7,1)),"▼","")) | K67: =IF(OR($B67="",$F67=""),"",IF(AND($F67>=K$7,$F67<EDATE(K$7,1)),"▼","")) | L67: =IF(OR($B67="",$F67=""),"",IF(AND($F67>=L$7,$F67<EDATE(L$7,1)),"▼","")) | M67: =IF(OR($B67="",$F67=""),"",IF(AND($F67>=M$7,$F67<EDATE(M$7,1)),"▼","")) | N67: =IF(OR($B67="",$F67=""),"",IF(AND($F67>=N$7,$F67<EDATE(N$7,1)),"▼","")) | O67: =IF(OR($B67="",$F67=""),"",IF(AND($F67>=O$7,$F67<EDATE(O$7,1)),"▼","")) | ... S67: =IF(OR($B67="",$F67=""),"",IF(AND($F67>=S$7,$F67<EDATE(S$7,1)),"▼",""))
A68: =IF($B68="","","Renda Extra") | B68: =IF('Renda Extra'!B17="","",'Renda Extra'!B17) | C68: =IF($B68="","",IF('Renda Extra'!O17="","",'Renda Extra'!O17)) | D68: =IF($B68="","",IF('Renda Extra'!G17="","",'Renda Extra'!G17)) | E68: =IF($B68="","",IF('Renda Extra'!H17<>"",'Renda Extra'!H17,IF('Renda Extra'!I17<>"",'Renda Extra'!I17,""))) | F68: =IF($B68="","",IF('Renda Extra'!I17="","",'Renda Extra'!I17)) | G68: =IF($B68="","",'Renda Extra'!N17) | H68: =IF(OR($B68="",$F68=""),"",IF(AND($F68>=H$7,$F68<EDATE(H$7,1)),"▼","")) | I68: =IF(OR($B68="",$F68=""),"",IF(AND($F68>=I$7,$F68<EDATE(I$7,1)),"▼","")) | J68: =IF(OR($B68="",$F68=""),"",IF(AND($F68>=J$7,$F68<EDATE(J$7,1)),"▼","")) | K68: =IF(OR($B68="",$F68=""),"",IF(AND($F68>=K$7,$F68<EDATE(K$7,1)),"▼","")) | L68: =IF(OR($B68="",$F68=""),"",IF(AND($F68>=L$7,$F68<EDATE(L$7,1)),"▼","")) | M68: =IF(OR($B68="",$F68=""),"",IF(AND($F68>=M$7,$F68<EDATE(M$7,1)),"▼","")) | N68: =IF(OR($B68="",$F68=""),"",IF(AND($F68>=N$7,$F68<EDATE(N$7,1)),"▼","")) | O68: =IF(OR($B68="",$F68=""),"",IF(AND($F68>=O$7,$F68<EDATE(O$7,1)),"▼","")) | ... S68: =IF(OR($B68="",$F68=""),"",IF(AND($F68>=S$7,$F68<EDATE(S$7,1)),"▼",""))
A69: =IF($B69="","","Renda Extra") | B69: =IF('Renda Extra'!B18="","",'Renda Extra'!B18) | C69: =IF($B69="","",IF('Renda Extra'!O18="","",'Renda Extra'!O18)) | D69: =IF($B69="","",IF('Renda Extra'!G18="","",'Renda Extra'!G18)) | E69: =IF($B69="","",IF('Renda Extra'!H18<>"",'Renda Extra'!H18,IF('Renda Extra'!I18<>"",'Renda Extra'!I18,""))) | F69: =IF($B69="","",IF('Renda Extra'!I18="","",'Renda Extra'!I18)) | G69: =IF($B69="","",'Renda Extra'!N18) | H69: =IF(OR($B69="",$F69=""),"",IF(AND($F69>=H$7,$F69<EDATE(H$7,1)),"▼","")) | I69: =IF(OR($B69="",$F69=""),"",IF(AND($F69>=I$7,$F69<EDATE(I$7,1)),"▼","")) | J69: =IF(OR($B69="",$F69=""),"",IF(AND($F69>=J$7,$F69<EDATE(J$7,1)),"▼","")) | K69: =IF(OR($B69="",$F69=""),"",IF(AND($F69>=K$7,$F69<EDATE(K$7,1)),"▼","")) | L69: =IF(OR($B69="",$F69=""),"",IF(AND($F69>=L$7,$F69<EDATE(L$7,1)),"▼","")) | M69: =IF(OR($B69="",$F69=""),"",IF(AND($F69>=M$7,$F69<EDATE(M$7,1)),"▼","")) | N69: =IF(OR($B69="",$F69=""),"",IF(AND($F69>=N$7,$F69<EDATE(N$7,1)),"▼","")) | O69: =IF(OR($B69="",$F69=""),"",IF(AND($F69>=O$7,$F69<EDATE(O$7,1)),"▼","")) | ... S69: =IF(OR($B69="",$F69=""),"",IF(AND($F69>=S$7,$F69<EDATE(S$7,1)),"▼",""))
A70: =IF($B70="","","Renda Extra") | B70: =IF('Renda Extra'!B19="","",'Renda Extra'!B19) | C70: =IF($B70="","",IF('Renda Extra'!O19="","",'Renda Extra'!O19)) | D70: =IF($B70="","",IF('Renda Extra'!G19="","",'Renda Extra'!G19)) | E70: =IF($B70="","",IF('Renda Extra'!H19<>"",'Renda Extra'!H19,IF('Renda Extra'!I19<>"",'Renda Extra'!I19,""))) | F70: =IF($B70="","",IF('Renda Extra'!I19="","",'Renda Extra'!I19)) | G70: =IF($B70="","",'Renda Extra'!N19) | H70: =IF(OR($B70="",$F70=""),"",IF(AND($F70>=H$7,$F70<EDATE(H$7,1)),"▼","")) | I70: =IF(OR($B70="",$F70=""),"",IF(AND($F70>=I$7,$F70<EDATE(I$7,1)),"▼","")) | J70: =IF(OR($B70="",$F70=""),"",IF(AND($F70>=J$7,$F70<EDATE(J$7,1)),"▼","")) | K70: =IF(OR($B70="",$F70=""),"",IF(AND($F70>=K$7,$F70<EDATE(K$7,1)),"▼","")) | L70: =IF(OR($B70="",$F70=""),"",IF(AND($F70>=L$7,$F70<EDATE(L$7,1)),"▼","")) | M70: =IF(OR($B70="",$F70=""),"",IF(AND($F70>=M$7,$F70<EDATE(M$7,1)),"▼","")) | N70: =IF(OR($B70="",$F70=""),"",IF(AND($F70>=N$7,$F70<EDATE(N$7,1)),"▼","")) | O70: =IF(OR($B70="",$F70=""),"",IF(AND($F70>=O$7,$F70<EDATE(O$7,1)),"▼","")) | ... S70: =IF(OR($B70="",$F70=""),"",IF(AND($F70>=S$7,$F70<EDATE(S$7,1)),"▼",""))
A71: =IF($B71="","","Renda Extra") | B71: =IF('Renda Extra'!B20="","",'Renda Extra'!B20) | C71: =IF($B71="","",IF('Renda Extra'!O20="","",'Renda Extra'!O20)) | D71: =IF($B71="","",IF('Renda Extra'!G20="","",'Renda Extra'!G20)) | E71: =IF($B71="","",IF('Renda Extra'!H20<>"",'Renda Extra'!H20,IF('Renda Extra'!I20<>"",'Renda Extra'!I20,""))) | F71: =IF($B71="","",IF('Renda Extra'!I20="","",'Renda Extra'!I20)) | G71: =IF($B71="","",'Renda Extra'!N20) | H71: =IF(OR($B71="",$F71=""),"",IF(AND($F71>=H$7,$F71<EDATE(H$7,1)),"▼","")) | I71: =IF(OR($B71="",$F71=""),"",IF(AND($F71>=I$7,$F71<EDATE(I$7,1)),"▼","")) | J71: =IF(OR($B71="",$F71=""),"",IF(AND($F71>=J$7,$F71<EDATE(J$7,1)),"▼","")) | K71: =IF(OR($B71="",$F71=""),"",IF(AND($F71>=K$7,$F71<EDATE(K$7,1)),"▼","")) | L71: =IF(OR($B71="",$F71=""),"",IF(AND($F71>=L$7,$F71<EDATE(L$7,1)),"▼","")) | M71: =IF(OR($B71="",$F71=""),"",IF(AND($F71>=M$7,$F71<EDATE(M$7,1)),"▼","")) | N71: =IF(OR($B71="",$F71=""),"",IF(AND($F71>=N$7,$F71<EDATE(N$7,1)),"▼","")) | O71: =IF(OR($B71="",$F71=""),"",IF(AND($F71>=O$7,$F71<EDATE(O$7,1)),"▼","")) | ... S71: =IF(OR($B71="",$F71=""),"",IF(AND($F71>=S$7,$F71<EDATE(S$7,1)),"▼",""))
A72: =IF($B72="","","Renda Extra") | B72: =IF('Renda Extra'!B21="","",'Renda Extra'!B21) | C72: =IF($B72="","",IF('Renda Extra'!O21="","",'Renda Extra'!O21)) | D72: =IF($B72="","",IF('Renda Extra'!G21="","",'Renda Extra'!G21)) | E72: =IF($B72="","",IF('Renda Extra'!H21<>"",'Renda Extra'!H21,IF('Renda Extra'!I21<>"",'Renda Extra'!I21,""))) | F72: =IF($B72="","",IF('Renda Extra'!I21="","",'Renda Extra'!I21)) | G72: =IF($B72="","",'Renda Extra'!N21) | H72: =IF(OR($B72="",$F72=""),"",IF(AND($F72>=H$7,$F72<EDATE(H$7,1)),"▼","")) | I72: =IF(OR($B72="",$F72=""),"",IF(AND($F72>=I$7,$F72<EDATE(I$7,1)),"▼","")) | J72: =IF(OR($B72="",$F72=""),"",IF(AND($F72>=J$7,$F72<EDATE(J$7,1)),"▼","")) | K72: =IF(OR($B72="",$F72=""),"",IF(AND($F72>=K$7,$F72<EDATE(K$7,1)),"▼","")) | L72: =IF(OR($B72="",$F72=""),"",IF(AND($F72>=L$7,$F72<EDATE(L$7,1)),"▼","")) | M72: =IF(OR($B72="",$F72=""),"",IF(AND($F72>=M$7,$F72<EDATE(M$7,1)),"▼","")) | N72: =IF(OR($B72="",$F72=""),"",IF(AND($F72>=N$7,$F72<EDATE(N$7,1)),"▼","")) | O72: =IF(OR($B72="",$F72=""),"",IF(AND($F72>=O$7,$F72<EDATE(O$7,1)),"▼","")) | ... S72: =IF(OR($B72="",$F72=""),"",IF(AND($F72>=S$7,$F72<EDATE(S$7,1)),"▼",""))

Sheet Metas de Estudo
A1: METAS DE ESTUDO
A2: Defina metas mensais de horas, acompanhe o ritmo e veja seu mapa de calor | N2: ← Voltar ao Início
B5: Mês de referência: | C5: 46296 | D5: 1º dia (auto): | E5: =DATE(YEAR($C$5),MONTH($C$5),1) -> 46296 | F5: % do mês decorrido: | G5: =MAX(0,MIN(1,(TODAY()-$E$5+1)/(EOMONTH($E$5,0)-$E$5+1))) -> 0.096774194 | H5: ← digite qualquer data do mês
B7: HORAS NO MÊS | D7: META DO MÊS | F7: % DA META | G7: DIAS ESTUDADOS
B8: =D18 -> 4.5 | D8: =C18 -> 73 | F8: =E18 -> 0.061643836 | G8: =COUNTIF(J14:P14,">0")+COUNTIF(J16:P16,">0")+COUNTIF(J18:P18,">0")+COUNTIF(J20:P20,">0")+COUNTIF(J22:P22,">0")+COUNTIF(J24:P24,">0") -> 3
B11: METAS POR CATEGORIA | J11: MAPA DE CALOR DO MÊS
B12: Categoria | C12: Meta (h) | D12: Realizado (h) | E12: % da meta | F12: Progresso | G12: Faltam (h) | H12: Ritmo | J12: Seg | K12: Ter | L12: Qua | M12: Qui | N12: Sex | O12: Sáb | P12: Dom
B13: =Listas!$E$6 -> Pós-graduação | C13: 20 | D13: =SUMIFS('Diário de Estudo'!$D$7:$D$506,'Diário de Estudo'!$B$7:$B$506,$B13,'Diário de Estudo'!$A$7:$A$506,">="&$E$5,'Diário de Estudo'!$A$7:$A$506,"<"&EDATE($E$5,1)) -> 2 | E13: =IF(C13=0,0,D13/C13) -> 0.1 | F13: =REPT("█",MIN(10,ROUND(E13*10,0)))&REPT("░",10-MIN(10,ROUND(E13*10,0))) -> █░░░░░░░░░ | G13: =MAX(0,C13-D13) -> 18 | H13: =IF(C13=0,"—",IF(D13>=C13,"Meta batida",IF(D13>=C13*$G$5,"No ritmo","Abaixo do ritmo"))) -> No ritmo | J13: =IF(MONTH($E$5-WEEKDAY($E$5,2)+1+0)=MONTH($E$5),$E$5-WEEKDAY($E$5,2)+1+0,"") | K13: =IF(MONTH($E$5-WEEKDAY($E$5,2)+1+1)=MONTH($E$5),$E$5-WEEKDAY($E$5,2)+1+1,"") | L13: =IF(MONTH($E$5-WEEKDAY($E$5,2)+1+2)=MONTH($E$5),$E$5-WEEKDAY($E$5,2)+1+2,"") | M13: =IF(MONTH($E$5-WEEKDAY($E$5,2)+1+3)=MONTH($E$5),$E$5-WEEKDAY($E$5,2)+1+3,"") -> 46296 | N13: =IF(MONTH($E$5-WEEKDAY($E$5,2)+1+4)=MONTH($E$5),$E$5-WEEKDAY($E$5,2)+1+4,"") -> 46297 | O13: =IF(MONTH($E$5-WEEKDAY($E$5,2)+1+5)=MONTH($E$5),$E$5-WEEKDAY($E$5,2)+1+5,"") -> 46298 | P13: =IF(MONTH($E$5-WEEKDAY($E$5,2)+1+6)=MONTH($E$5),$E$5-WEEKDAY($E$5,2)+1+6,"") -> 46299
B14: =Listas!$E$7 -> Concurso | C14: 20 | D14: =SUMIFS('Diário de Estudo'!$D$7:$D$506,'Diário de Estudo'!$B$7:$B$506,$B14,'Diário de Estudo'!$A$7:$A$506,">="&$E$5,'Diário de Estudo'!$A$7:$A$506,"<"&EDATE($E$5,1)) -> 0 | E14: =IF(C14=0,0,D14/C14) -> 0 | F14: =REPT("█",MIN(10,ROUND(E14*10,0)))&REPT("░",10-MIN(10,ROUND(E14*10,0))) -> ░░░░░░░░░░ | G14: =MAX(0,C14-D14) -> 20 | H14: =IF(C14=0,"—",IF(D14>=C14,"Meta batida",IF(D14>=C14*$G$5,"No ritmo","Abaixo do ritmo"))) -> Abaixo do ritmo | J14: =IF(J13="","",SUMIFS('Diário de Estudo'!$D$7:$D$506,'Diário de Estudo'!$A$7:$A$506,J13)) | K14: =IF(K13="","",SUMIFS('Diário de Estudo'!$D$7:$D$506,'Diário de Estudo'!$A$7:$A$506,K13)) | L14: =IF(L13="","",SUMIFS('Diário de Estudo'!$D$7:$D$506,'Diário de Estudo'!$A$7:$A$506,L13)) | M14: =IF(M13="","",SUMIFS('Diário de Estudo'!$D$7:$D$506,'Diário de Estudo'!$A$7:$A$506,M13)) -> 2 | N14: =IF(N13="","",SUMIFS('Diário de Estudo'!$D$7:$D$506,'Diário de Estudo'!$A$7:$A$506,N13)) -> 1.5 | O14: =IF(O13="","",SUMIFS('Diário de Estudo'!$D$7:$D$506,'Diário de Estudo'!$A$7:$A$506,O13)) -> 1 | P14: =IF(P13="","",SUMIFS('Diário de Estudo'!$D$7:$D$506,'Diário de Estudo'!$A$7:$A$506,P13)) -> 0
B15: =Listas!$E$8 -> Livros | C15: 8 | D15: =SUMIFS('Diário de Estudo'!$D$7:$D$506,'Diário de Estudo'!$B$7:$B$506,$B15,'Diário de Estudo'!$A$7:$A$506,">="&$E$5,'Diário de Estudo'!$A$7:$A$506,"<"&EDATE($E$5,1)) -> 1 | E15: =IF(C15=0,0,D15/C15) -> 0.125 | F15: =REPT("█",MIN(10,ROUND(E15*10,0)))&REPT("░",10-MIN(10,ROUND(E15*10,0))) -> █░░░░░░░░░ | G15: =MAX(0,C15-D15) -> 7 | H15: =IF(C15=0,"—",IF(D15>=C15,"Meta batida",IF(D15>=C15*$G$5,"No ritmo","Abaixo do ritmo"))) -> No ritmo | J15: =IF(MONTH($E$5-WEEKDAY($E$5,2)+1+7)=MONTH($E$5),$E$5-WEEKDAY($E$5,2)+1+7,"") -> 46300 | K15: =IF(MONTH($E$5-WEEKDAY($E$5,2)+1+8)=MONTH($E$5),$E$5-WEEKDAY($E$5,2)+1+8,"") -> 46301 | L15: =IF(MONTH($E$5-WEEKDAY($E$5,2)+1+9)=MONTH($E$5),$E$5-WEEKDAY($E$5,2)+1+9,"") -> 46302 | M15: =IF(MONTH($E$5-WEEKDAY($E$5,2)+1+10)=MONTH($E$5),$E$5-WEEKDAY($E$5,2)+1+10,"") -> 46303 | N15: =IF(MONTH($E$5-WEEKDAY($E$5,2)+1+11)=MONTH($E$5),$E$5-WEEKDAY($E$5,2)+1+11,"") -> 46304 | O15: =IF(MONTH($E$5-WEEKDAY($E$5,2)+1+12)=MONTH($E$5),$E$5-WEEKDAY($E$5,2)+1+12,"") -> 46305 | P15: =IF(MONTH($E$5-WEEKDAY($E$5,2)+1+13)=MONTH($E$5),$E$5-WEEKDAY($E$5,2)+1+13,"") -> 46306
B16: =Listas!$E$9 -> Cursos IA | C16: 15 | D16: =SUMIFS('Diário de Estudo'!$D$7:$D$506,'Diário de Estudo'!$B$7:$B$506,$B16,'Diário de Estudo'!$A$7:$A$506,">="&$E$5,'Diário de Estudo'!$A$7:$A$506,"<"&EDATE($E$5,1)) -> 1.5 | E16: =IF(C16=0,0,D16/C16) -> 0.1 | F16: =REPT("█",MIN(10,ROUND(E16*10,0)))&REPT("░",10-MIN(10,ROUND(E16*10,0))) -> █░░░░░░░░░ | G16: =MAX(0,C16-D16) -> 13.5 | H16: =IF(C16=0,"—",IF(D16>=C16,"Meta batida",IF(D16>=C16*$G$5,"No ritmo","Abaixo do ritmo"))) -> No ritmo | J16: =IF(J15="","",SUMIFS('Diário de Estudo'!$D$7:$D$506,'Diário de Estudo'!$A$7:$A$506,J15)) -> 0 | K16: =IF(K15="","",SUMIFS('Diário de Estudo'!$D$7:$D$506,'Diário de Estudo'!$A$7:$A$506,K15)) -> 0 | L16: =IF(L15="","",SUMIFS('Diário de Estudo'!$D$7:$D$506,'Diário de Estudo'!$A$7:$A$506,L15)) -> 0 | M16: =IF(M15="","",SUMIFS('Diário de Estudo'!$D$7:$D$506,'Diário de Estudo'!$A$7:$A$506,M15)) -> 0 | N16: =IF(N15="","",SUMIFS('Diário de Estudo'!$D$7:$D$506,'Diário de Estudo'!$A$7:$A$506,N15)) -> 0 | O16: =IF(O15="","",SUMIFS('Diário de Estudo'!$D$7:$D$506,'Diário de Estudo'!$A$7:$A$506,O15)) -> 0 | P16: =IF(P15="","",SUMIFS('Diário de Estudo'!$D$7:$D$506,'Diário de Estudo'!$A$7:$A$506,P15)) -> 0
B17: =Listas!$E$10 -> Renda Extra | C17: 10 | D17: =SUMIFS('Diário de Estudo'!$D$7:$D$506,'Diário de Estudo'!$B$7:$B$506,$B17,'Diário de Estudo'!$A$7:$A$506,">="&$E$5,'Diário de Estudo'!$A$7:$A$506,"<"&EDATE($E$5,1)) -> 0 | E17: =IF(C17=0,0,D17/C17) -> 0 | F17: =REPT("█",MIN(10,ROUND(E17*10,0)))&REPT("░",10-MIN(10,ROUND(E17*10,0))) -> ░░░░░░░░░░ | G17: =MAX(0,C17-D17) -> 10 | H17: =IF(C17=0,"—",IF(D17>=C17,"Meta batida",IF(D17>=C17*$G$5,"No ritmo","Abaixo do ritmo"))) -> Abaixo do ritmo | J17: =IF(MONTH($E$5-WEEKDAY($E$5,2)+1+14)=MONTH($E$5),$E$5-WEEKDAY($E$5,2)+1+14,"") -> 46307 | K17: =IF(MONTH($E$5-WEEKDAY($E$5,2)+1+15)=MONTH($E$5),$E$5-WEEKDAY($E$5,2)+1+15,"") -> 46308 | L17: =IF(MONTH($E$5-WEEKDAY($E$5,2)+1+16)=MONTH($E$5),$E$5-WEEKDAY($E$5,2)+1+16,"") -> 46309 | M17: =IF(MONTH($E$5-WEEKDAY($E$5,2)+1+17)=MONTH($E$5),$E$5-WEEKDAY($E$5,2)+1+17,"") -> 46310 | N17: =IF(MONTH($E$5-WEEKDAY($E$5,2)+1+18)=MONTH($E$5),$E$5-WEEKDAY($E$5,2)+1+18,"") -> 46311 | O17: =IF(MONTH($E$5-WEEKDAY($E$5,2)+1+19)=MONTH($E$5),$E$5-WEEKDAY($E$5,2)+1+19,"") -> 46312 | P17: =IF(MONTH($E$5-WEEKDAY($E$5,2)+1+20)=MONTH($E$5),$E$5-WEEKDAY($E$5,2)+1+20,"") -> 46313
B18: TOTAL | C18: =SUM(C13:C17) -> 73 | D18: =SUM(D13:D17) -> 4.5 | E18: =IF(C18=0,0,D18/C18) -> 0.061643836 | F18: =REPT("█",MIN(10,ROUND(E18*10,0)))&REPT("░",10-MIN(10,ROUND(E18*10,0))) -> █░░░░░░░░░ | G18: =MAX(0,C18-D18) -> 68.5 | H18: =IF(C18=0,"—",IF(D18>=C18,"Meta batida",IF(D18>=C18*$G$5,"No ritmo","Abaixo do ritmo"))) -> Abaixo do ritmo | J18: =IF(J17="","",SUMIFS('Diário de Estudo'!$D$7:$D$506,'Diário de Estudo'!$A$7:$A$506,J17)) -> 0 | K18: =IF(K17="","",SUMIFS('Diário de Estudo'!$D$7:$D$506,'Diário de Estudo'!$A$7:$A$506,K17)) -> 0 | L18: =IF(L17="","",SUMIFS('Diário de Estudo'!$D$7:$D$506,'Diário de Estudo'!$A$7:$A$506,L17)) -> 0 | M18: =IF(M17="","",SUMIFS('Diário de Estudo'!$D$7:$D$506,'Diário de Estudo'!$A$7:$A$506,M17)) -> 0 | N18: =IF(N17="","",SUMIFS('Diário de Estudo'!$D$7:$D$506,'Diário de Estudo'!$A$7:$A$506,N17)) -> 0 | O18: =IF(O17="","",SUMIFS('Diário de Estudo'!$D$7:$D$506,'Diário de Estudo'!$A$7:$A$506,O17)) -> 0 | P18: =IF(P17="","",SUMIFS('Diário de Estudo'!$D$7:$D$506,'Diário de Estudo'!$A$7:$A$506,P17)) -> 0
J19: =IF(MONTH($E$5-WEEKDAY($E$5,2)+1+21)=MONTH($E$5),$E$5-WEEKDAY($E$5,2)+1+21,"") -> 46314 | K19: =IF(MONTH($E$5-WEEKDAY($E$5,2)+1+22)=MONTH($E$5),$E$5-WEEKDAY($E$5,2)+1+22,"") -> 46315 | L19: =IF(MONTH($E$5-WEEKDAY($E$5,2)+1+23)=MONTH($E$5),$E$5-WEEKDAY($E$5,2)+1+23,"") -> 46316 | M19: =IF(MONTH($E$5-WEEKDAY($E$5,2)+1+24)=MONTH($E$5),$E$5-WEEKDAY($E$5,2)+1+24,"") -> 46317 | N19: =IF(MONTH($E$5-WEEKDAY($E$5,2)+1+25)=MONTH($E$5),$E$5-WEEKDAY($E$5,2)+1+25,"") -> 46318 | O19: =IF(MONTH($E$5-WEEKDAY($E$5,2)+1+26)=MONTH($E$5),$E$5-WEEKDAY($E$5,2)+1+26,"") -> 46319 | P19: =IF(MONTH($E$5-WEEKDAY($E$5,2)+1+27)=MONTH($E$5),$E$5-WEEKDAY($E$5,2)+1+27,"") -> 46320
J20: =IF(J19="","",SUMIFS('Diário de Estudo'!$D$7:$D$506,'Diário de Estudo'!$A$7:$A$506,J19)) -> 0 | K20: =IF(K19="","",SUMIFS('Diário de Estudo'!$D$7:$D$506,'Diário de Estudo'!$A$7:$A$506,K19)) -> 0 | L20: =IF(L19="","",SUMIFS('Diário de Estudo'!$D$7:$D$506,'Diário de Estudo'!$A$7:$A$506,L19)) -> 0 | M20: =IF(M19="","",SUMIFS('Diário de Estudo'!$D$7:$D$506,'Diário de Estudo'!$A$7:$A$506,M19)) -> 0 | N20: =IF(N19="","",SUMIFS('Diário de Estudo'!$D$7:$D$506,'Diário de Estudo'!$A$7:$A$506,N19)) -> 0 | O20: =IF(O19="","",SUMIFS('Diário de Estudo'!$D$7:$D$506,'Diário de Estudo'!$A$7:$A$506,O19)) -> 0 | P20: =IF(P19="","",SUMIFS('Diário de Estudo'!$D$7:$D$506,'Diário de Estudo'!$A$7:$A$506,P19)) -> 0
J21: =IF(MONTH($E$5-WEEKDAY($E$5,2)+1+28)=MONTH($E$5),$E$5-WEEKDAY($E$5,2)+1+28,"") -> 46321 | K21: =IF(MONTH($E$5-WEEKDAY($E$5,2)+1+29)=MONTH($E$5),$E$5-WEEKDAY($E$5,2)+1+29,"") -> 46322 | L21: =IF(MONTH($E$5-WEEKDAY($E$5,2)+1+30)=MONTH($E$5),$E$5-WEEKDAY($E$5,2)+1+30,"") -> 46323 | M21: =IF(MONTH($E$5-WEEKDAY($E$5,2)+1+31)=MONTH($E$5),$E$5-WEEKDAY($E$5,2)+1+31,"") -> 46324 | N21: =IF(MONTH($E$5-WEEKDAY($E$5,2)+1+32)=MONTH($E$5),$E$5-WEEKDAY($E$5,2)+1+32,"") -> 46325 | O21: =IF(MONTH($E$5-WEEKDAY($E$5,2)+1+33)=MONTH($E$5),$E$5-WEEKDAY($E$5,2)+1+33,"") -> 46326 | P21: =IF(MONTH($E$5-WEEKDAY($E$5,2)+1+34)=MONTH($E$5),$E$5-WEEKDAY($E$5,2)+1+34,"")
J22: =IF(J21="","",SUMIFS('Diário de Estudo'!$D$7:$D$506,'Diário de Estudo'!$A$7:$A$506,J21)) -> 0 | K22: =IF(K21="","",SUMIFS('Diário de Estudo'!$D$7:$D$506,'Diário de Estudo'!$A$7:$A$506,K21)) -> 0 | L22: =IF(L21="","",SUMIFS('Diário de Estudo'!$D$7:$D$506,'Diário de Estudo'!$A$7:$A$506,L21)) -> 0 | M22: =IF(M21="","",SUMIFS('Diário de Estudo'!$D$7:$D$506,'Diário de Estudo'!$A$7:$A$506,M21)) -> 0 | N22: =IF(N21="","",SUMIFS('Diário de Estudo'!$D$7:$D$506,'Diário de Estudo'!$A$7:$A$506,N21)) -> 0 | O22: =IF(O21="","",SUMIFS('Diário de Estudo'!$D$7:$D$506,'Diário de Estudo'!$A$7:$A$506,O21)) -> 0 | P22: =IF(P21="","",SUMIFS('Diário de Estudo'!$D$7:$D$506,'Diário de Estudo'!$A$7:$A$506,P21))
J23: =IF(MONTH($E$5-WEEKDAY($E$5,2)+1+35)=MONTH($E$5),$E$5-WEEKDAY($E$5,2)+1+35,"") | K23: =IF(MONTH($E$5-WEEKDAY($E$5,2)+1+36)=MONTH($E$5),$E$5-WEEKDAY($E$5,2)+1+36,"") | L23: =IF(MONTH($E$5-WEEKDAY($E$5,2)+1+37)=MONTH($E$5),$E$5-WEEKDAY($E$5,2)+1+37,"") | M23: =IF(MONTH($E$5-WEEKDAY($E$5,2)+1+38)=MONTH($E$5),$E$5-WEEKDAY($E$5,2)+1+38,"") | N23: =IF(MONTH($E$5-WEEKDAY($E$5,2)+1+39)=MONTH($E$5),$E$5-WEEKDAY($E$5,2)+1+39,"") | O23: =IF(MONTH($E$5-WEEKDAY($E$5,2)+1+40)=MONTH($E$5),$E$5-WEEKDAY($E$5,2)+1+40,"") | P23: =IF(MONTH($E$5-WEEKDAY($E$5,2)+1+41)=MONTH($E$5),$E$5-WEEKDAY($E$5,2)+1+41,"")
J24: =IF(J23="","",SUMIFS('Diário de Estudo'!$D$7:$D$506,'Diário de Estudo'!$A$7:$A$506,J23)) | K24: =IF(K23="","",SUMIFS('Diário de Estudo'!$D$7:$D$506,'Diário de Estudo'!$A$7:$A$506,K23)) | L24: =IF(L23="","",SUMIFS('Diário de Estudo'!$D$7:$D$506,'Diário de Estudo'!$A$7:$A$506,L23)) | M24: =IF(M23="","",SUMIFS('Diário de Estudo'!$D$7:$D$506,'Diário de Estudo'!$A$7:$A$506,M23)) | N24: =IF(N23="","",SUMIFS('Diário de Estudo'!$D$7:$D$506,'Diário de Estudo'!$A$7:$A$506,N23)) | O24: =IF(O23="","",SUMIFS('Diário de Estudo'!$D$7:$D$506,'Diário de Estudo'!$A$7:$A$506,O23)) | P24: =IF(P23="","",SUMIFS('Diário de Estudo'!$D$7:$D$506,'Diário de Estudo'!$A$7:$A$506,P23))
J25: Quanto mais escura a célula, mais horas estudadas no dia · dia de hoje em verde-escuro

Sheet Diário de Estudo
A1: DIÁRIO DE ESTUDO
A2: Registre cada sessão de estudo — alimenta as Metas, o mapa de calor e o Dashboard | D2: ← Voltar ao Início
A5: Linhas 7–9 = exemplo (substitua ou apague) · Escolha a categoria na seta | D5: =SUM(D7:D506) -> 4.5 | E5: ← total de horas registradas
A6: Data | B6: Categoria | C6: Curso / Livro | D6: Horas | E6: Tema estudado | F6: Foco (1–5)
A7: 46296 | B7: Pós-graduação | C7: MBA em Inteligência Artificial (exemplo) | D7: 2 | E7: Introdução a machine learning | F7: 4
A8: 46297 | B8: Cursos IA | C8: Agentes de IA na Prática (exemplo) | D8: 1.5 | E8: Fluxos de automação | F8: 5
A9: 46298 | B9: Livros | C9: Hábitos Atômicos (exemplo) | D9: 1 | E9: Capítulos 5 a 7 | F9: 4

Sheet Pós-graduação
A1: PÓS-GRADUAÇÃO
A2: MBAs, especializações, mestrado e extensões · disciplinas, acesso, certificado e investimento | S2: ← Voltar ao Início
B5: ITENS | D5: EM ANDAMENTO | F5: CONCLUÍDOS | H5: INVESTIDO | J5: PROGRESSO MÉDIO | L5: ACESSOS A VENCER
B6: =COUNTA(B10:B49) -> 1 | D6: =COUNTIF(O10:O49,"Em andamento") -> 1 | F6: =COUNTIF(O10:O49,"Concluído") -> 0 | H6: =SUM(F10:F49) -> 12600 | J6: =IFERROR(AVERAGE(N10:N49),0) -> 0.1 | L6: =COUNTIF(K10:K49,"*A vencer") -> 0
A8: Células cinza = automáticas (não edite) · Linha 10 = exemplo: substitua ou apague · Use a seta das células Status, Prioridade e Certificado
A9: ID | B9: Curso / Pós-graduação | C9: Instituição | D9: Modalidade | E9: Data da compra | F9: Valor pago (R$) | G9: Data de início | H9: Término previsto | I9: Vencimento do acesso | J9: Dias p/ vencer | K9: Situação do acesso | L9: Disciplinas (total) | M9: Disciplinas concluídas | N9: % Andamento | O9: Status | P9: Prioridade | Q9: Certificado | R9: Login | S9: Senha | T9: Link de acesso | U9: Observações
A10: =IF($B10="","","PG-"&TEXT(ROW()-9,"00")) -> PG-01 | B10: MBA em Inteligência Artificial (exemplo) | C10: Universidade Exemplo | D10: EAD | E10: 46244 | F10: 12600 | G10: 46266 | H10: 46813 | I10: 46997 | J10: =IF(OR($B10="",$I10=""),"",$I10-TODAY()) -> 699 | K10: =IF($B10="","",IF($I10="","∞ Vitalício",IF($J10<0,"■ Vencido",IF($J10<=Listas!$H$6,"▲ A vencer","● Ativo")))) -> ● Ativo | L10: 20 | M10: 2 | N10: =IF($B10="","",IF(N($L10)=0,0,MIN(1,N($M10)/$L10))) -> 0.1 | O10: Em andamento | P10: Alta | Q10: Não emitido | R10: seu.email@exemplo.com | S10: (guarde no gerenciador de senhas) | T10: https://portal.exemplo.com | U10: Linha de exemplo — substitua pelos seus dados.
A11: =IF($B11="","","PG-"&TEXT(ROW()-9,"00")) | J11: =IF(OR($B11="",$I11=""),"",$I11-TODAY()) | K11: =IF($B11="","",IF($I11="","∞ Vitalício",IF($J11<0,"■ Vencido",IF($J11<=Listas!$H$6,"▲ A vencer","● Ativo")))) | N11: =IF($B11="","",IF(N($L11)=0,0,MIN(1,N($M11)/$L11)))
A12: =IF($B12="","","PG-"&TEXT(ROW()-9,"00")) | J12: =IF(OR($B12="",$I12=""),"",$I12-TODAY()) | K12: =IF($B12="","",IF($I12="","∞ Vitalício",IF($J12<0,"■ Vencido",IF($J12<=Listas!$H$6,"▲ A vencer","● Ativo")))) | N12: =IF($B12="","",IF(N($L12)=0,0,MIN(1,N($M12)/$L12)))
A13: =IF($B13="","","PG-"&TEXT(ROW()-9,"00")) | J13: =IF(OR($B13="",$I13=""),"",$I13-TODAY()) | K13: =IF($B13="","",IF($I13="","∞ Vitalício",IF($J13<0,"■ Vencido",IF($J13<=Listas!$H$6,"▲ A vencer","● Ativo")))) | N13: =IF($B13="","",IF(N($L13)=0,0,MIN(1,N($M13)/$L13)))
A14: =IF($B14="","","PG-"&TEXT(ROW()-9,"00")) | J14: =IF(OR($B14="",$I14=""),"",$I14-TODAY()) | K14: =IF($B14="","",IF($I14="","∞ Vitalício",IF($J14<0,"■ Vencido",IF($J14<=Listas!$H$6,"▲ A vencer","● Ativo")))) | N14: =IF($B14="","",IF(N($L14)=0,0,MIN(1,N($M14)/$L14)))
A15: =IF($B15="","","PG-"&TEXT(ROW()-9,"00")) | J15: =IF(OR($B15="",$I15=""),"",$I15-TODAY()) | K15: =IF($B15="","",IF($I15="","∞ Vitalício",IF($J15<0,"■ Vencido",IF($J15<=Listas!$H$6,"▲ A vencer","● Ativo")))) | N15: =IF($B15="","",IF(N($L15)=0,0,MIN(1,N($M15)/$L15)))
A16: =IF($B16="","","PG-"&TEXT(ROW()-9,"00")) | J16: =IF(OR($B16="",$I16=""),"",$I16-TODAY()) | K16: =IF($B16="","",IF($I16="","∞ Vitalício",IF($J16<0,"■ Vencido",IF($J16<=Listas!$H$6,"▲ A vencer","● Ativo")))) | N16: =IF($B16="","",IF(N($L16)=0,0,MIN(1,N($M16)/$L16)))
A17: =IF($B17="","","PG-"&TEXT(ROW()-9,"00")) | J17: =IF(OR($B17="",$I17=""),"",$I17-TODAY()) | K17: =IF($B17="","",IF($I17="","∞ Vitalício",IF($J17<0,"■ Vencido",IF($J17<=Listas!$H$6,"▲ A vencer","● Ativo")))) | N17: =IF($B17="","",IF(N($L17)=0,0,MIN(1,N($M17)/$L17)))
A18: =IF($B18="","","PG-"&TEXT(ROW()-9,"00")) | J18: =IF(OR($B18="",$I18=""),"",$I18-TODAY()) | K18: =IF($B18="","",IF($I18="","∞ Vitalício",IF($J18<0,"■ Vencido",IF($J18<=Listas!$H$6,"▲ A vencer","● Ativo")))) | N18: =IF($B18="","",IF(N($L18)=0,0,MIN(1,N($M18)/$L18)))
A19: =IF($B19="","","PG-"&TEXT(ROW()-9,"00")) | J19: =IF(OR($B19="",$I19=""),"",$I19-TODAY()) | K19: =IF($B19="","",IF($I19="","∞ Vitalício",IF($J19<0,"■ Vencido",IF($J19<=Listas!$H$6,"▲ A vencer","● Ativo")))) | N19: =IF($B19="","",IF(N($L19)=0,0,MIN(1,N($M19)/$L19)))
A20: =IF($B20="","","PG-"&TEXT(ROW()-9,"00")) | J20: =IF(OR($B20="",$I20=""),"",$I20-TODAY()) | K20: =IF($B20="","",IF($I20="","∞ Vitalício",IF($J20<0,"■ Vencido",IF($J20<=Listas!$H$6,"▲ A vencer","● Ativo")))) | N20: =IF($B20="","",IF(N($L20)=0,0,MIN(1,N($M20)/$L20)))
A21: =IF($B21="","","PG-"&TEXT(ROW()-9,"00")) | J21: =IF(OR($B21="",$I21=""),"",$I21-TODAY()) | K21: =IF($B21="","",IF($I21="","∞ Vitalício",IF($J21<0,"■ Vencido",IF($J21<=Listas!$H$6,"▲ A vencer","● Ativo")))) | N21: =IF($B21="","",IF(N($L21)=0,0,MIN(1,N($M21)/$L21)))
A22: =IF($B22="","","PG-"&TEXT(ROW()-9,"00")) | J22: =IF(OR($B22="",$I22=""),"",$I22-TODAY()) | K22: =IF($B22="","",IF($I22="","∞ Vitalício",IF($J22<0,"■ Vencido",IF($J22<=Listas!$H$6,"▲ A vencer","● Ativo")))) | N22: =IF($B22="","",IF(N($L22)=0,0,MIN(1,N($M22)/$L22)))
... A49: =IF($B49="","","PG-"&TEXT(ROW()-9,"00")) | J49: =IF(OR($B49="",$I49=""),"",$I49-TODAY()) | K49: =IF($B49="","",IF($I49="","∞ Vitalício",IF($J49<0,"■ Vencido",IF($J49<=Listas!$H$6,"▲ A vencer","● Ativo")))) | N49: =IF($B49="","",IF(N($L49)=0,0,MIN(1,N($M49)/$L49)))

Sheet Concurso
A1: CONCURSOS PÚBLICOS
A2: Cursos preparatórios, bancos de questões e materiais · vincule cada curso ao concurso-alvo | U2: ← Voltar ao Início
B5: ITENS | D5: EM ANDAMENTO | F5: CONCLUÍDOS | H5: INVESTIDO | J5: PROGRESSO MÉDIO | L5: ACESSOS A VENCER
B6: =COUNTA(B10:B49) -> 1 | D6: =COUNTIF(Q10:Q49,"Em andamento") -> 1 | F6: =COUNTIF(Q10:Q49,"Concluído") -> 0 | H6: =SUM(H10:H49) -> 1490 | J6: =IFERROR(AVERAGE(P10:P49),0) -> 0.25 | L6: =COUNTIF(M10:M49,"*A vencer") -> 0
A8: Células cinza = automáticas (não edite) · Linha 10 = exemplo: substitua ou apague · Use a seta das células Status, Prioridade e Certificado
A9: ID | B9: Curso / Material | C9: Plataforma / Instituição | D9: Concurso / Cargo alvo | E9: Banca | F9: Data da prova | G9: Data da compra | H9: Valor pago (R$) | I9: Data de início | J9: Término previsto | K9: Vencimento do acesso | L9: Dias p/ vencer | M9: Situação do acesso | N9: Aulas / Tópicos (total) | O9: Aulas / Tópicos concluídos | P9: % Andamento | Q9: Status | R9: Prioridade | S9: Certificado | T9: Login | U9: Senha | V9: Link de acesso | W9: Observações
A10: =IF($B10="","","CO-"&TEXT(ROW()-9,"00")) -> CO-01 | B10: Curso Preparatório Completo (exemplo) | C10: Plataforma Exemplo | D10: Analista — Órgão Exemplo | E10: CEBRASPE | F10: 46460 | G10: 46270 | H10: 1490 | I10: 46280 | J10: 46446 | K10: 46568 | L10: =IF(OR($B10="",$K10=""),"",$K10-TODAY()) -> 270 | M10: =IF($B10="","",IF($K10="","∞ Vitalício",IF($L10<0,"■ Vencido",IF($L10<=Listas!$H$6,"▲ A vencer","● Ativo")))) -> ● Ativo | N10: 180 | O10: 45 | P10: =IF($B10="","",IF(N($N10)=0,0,MIN(1,N($O10)/$N10))) -> 0.25 | Q10: Em andamento | R10: Alta | S10: Não se aplica | T10: seu.email@exemplo.com | U10: (guarde no gerenciador de senhas) | V10: https://plataforma.exemplo.com | W10: Linha de exemplo — substitua pelos seus dados.
A11: =IF($B11="","","CO-"&TEXT(ROW()-9,"00")) | L11: =IF(OR($B11="",$K11=""),"",$K11-TODAY()) | M11: =IF($B11="","",IF($K11="","∞ Vitalício",IF($L11<0,"■ Vencido",IF($L11<=Listas!$H$6,"▲ A vencer","● Ativo")))) | P11: =IF($B11="","",IF(N($N11)=0,0,MIN(1,N($O11)/$N11)))
A12: =IF($B12="","","CO-"&TEXT(ROW()-9,"00")) | L12: =IF(OR($B12="",$K12=""),"",$K12-TODAY()) | M12: =IF($B12="","",IF($K12="","∞ Vitalício",IF($L12<0,"■ Vencido",IF($L12<=Listas!$H$6,"▲ A vencer","● Ativo")))) | P12: =IF($B12="","",IF(N($N12)=0,0,MIN(1,N($O12)/$N12)))
A13: =IF($B13="","","CO-"&TEXT(ROW()-9,"00")) | L13: =IF(OR($B13="",$K13=""),"",$K13-TODAY()) | M13: =IF($B13="","",IF($K13="","∞ Vitalício",IF($L13<0,"■ Vencido",IF($L13<=Listas!$H$6,"▲ A vencer","● Ativo")))) | P13: =IF($B13="","",IF(N($N13)=0,0,MIN(1,N($O13)/$N13)))
A14: =IF($B14="","","CO-"&TEXT(ROW()-9,"00")) | L14: =IF(OR($B14="",$K14=""),"",$K14-TODAY()) | M14: =IF($B14="","",IF($K14="","∞ Vitalício",IF($L14<0,"■ Vencido",IF($L14<=Listas!$H$6,"▲ A vencer","● Ativo")))) | P14: =IF($B14="","",IF(N($N14)=0,0,MIN(1,N($O14)/$N14)))
A15: =IF($B15="","","CO-"&TEXT(ROW()-9,"00")) | L15: =IF(OR($B15="",$K15=""),"",$K15-TODAY()) | M15: =IF($B15="","",IF($K15="","∞ Vitalício",IF($L15<0,"■ Vencido",IF($L15<=Listas!$H$6,"▲ A vencer","● Ativo")))) | P15: =IF($B15="","",IF(N($N15)=0,0,MIN(1,N($O15)/$N15)))
A16: =IF($B16="","","CO-"&TEXT(ROW()-9,"00")) | L16: =IF(OR($B16="",$K16=""),"",$K16-TODAY()) | M16: =IF($B16="","",IF($K16="","∞ Vitalício",IF($L16<0,"■ Vencido",IF($L16<=Listas!$H$6,"▲ A vencer","● Ativo")))) | P16: =IF($B16="","",IF(N($N16)=0,0,MIN(1,N($O16)/$N16)))
A17: =IF($B17="","","CO-"&TEXT(ROW()-9,"00")) | L17: =IF(OR($B17="",$K17=""),"",$K17-TODAY()) | M17: =IF($B17="","",IF($K17="","∞ Vitalício",IF($L17<0,"■ Vencido",IF($L17<=Listas!$H$6,"▲ A vencer","● Ativo")))) | P17: =IF($B17="","",IF(N($N17)=0,0,MIN(1,N($O17)/$N17)))
A18: =IF($B18="","","CO-"&TEXT(ROW()-9,"00")) | L18: =IF(OR($B18="",$K18=""),"",$K18-TODAY()) | M18: =IF($B18="","",IF($K18="","∞ Vitalício",IF($L18<0,"■ Vencido",IF($L18<=Listas!$H$6,"▲ A vencer","● Ativo")))) | P18: =IF($B18="","",IF(N($N18)=0,0,MIN(1,N($O18)/$N18)))
A19: =IF($B19="","","CO-"&TEXT(ROW()-9,"00")) | L19: =IF(OR($B19="",$K19=""),"",$K19-TODAY()) | M19: =IF($B19="","",IF($K19="","∞ Vitalício",IF($L19<0,"■ Vencido",IF($L19<=Listas!$H$6,"▲ A vencer","● Ativo")))) | P19: =IF($B19="","",IF(N($N19)=0,0,MIN(1,N($O19)/$N19)))
A20: =IF($B20="","","CO-"&TEXT(ROW()-9,"00")) | L20: =IF(OR($B20="",$K20=""),"",$K20-TODAY()) | M20: =IF($B20="","",IF($K20="","∞ Vitalício",IF($L20<0,"■ Vencido",IF($L20<=Listas!$H$6,"▲ A vencer","● Ativo")))) | P20: =IF($B20="","",IF(N($N20)=0,0,MIN(1,N($O20)/$N20)))
A21: =IF($B21="","","CO-"&TEXT(ROW()-9,"00")) | L21: =IF(OR($B21="",$K21=""),"",$K21-TODAY()) | M21: =IF($B21="","",IF($K21="","∞ Vitalício",IF($L21<0,"■ Vencido",IF($L21<=Listas!$H$6,"▲ A vencer","● Ativo")))) | P21: =IF($B21="","",IF(N($N21)=0,0,MIN(1,N($O21)/$N21)))
A22: =IF($B22="","","CO-"&TEXT(ROW()-9,"00")) | L22: =IF(OR($B22="",$K22=""),"",$K22-TODAY()) | M22: =IF($B22="","",IF($K22="","∞ Vitalício",IF($L22<0,"■ Vencido",IF($L22<=Listas!$H$6,"▲ A vencer","● Ativo")))) | P22: =IF($B22="","",IF(N($N22)=0,0,MIN(1,N($O22)/$N22)))
... A49: =IF($B49="","","CO-"&TEXT(ROW()-9,"00")) | L49: =IF(OR($B49="",$K49=""),"",$K49-TODAY()) | M49: =IF($B49="","",IF($K49="","∞ Vitalício",IF($L49<0,"■ Vencido",IF($L49<=Listas!$H$6,"▲ A vencer","● Ativo")))) | P49: =IF($B49="","",IF(N($N49)=0,0,MIN(1,N($O49)/$N49)))

Sheet Livros
A1: LIVROS
A2: Biblioteca de leitura · páginas lidas, formato, nota e previsão de término | P2: ← Voltar ao Início
B5: ITENS | D5: EM ANDAMENTO | F5: CONCLUÍDOS | H5: INVESTIDO | J5: PROGRESSO MÉDIO | L5: PÁGINAS LIDAS
B6: =COUNTA(B10:B49) -> 1 | D6: =COUNTIF(N10:N49,"Em andamento") -> 1 | F6: =COUNTIF(N10:N49,"Concluído") -> 0 | H6: =SUM(H10:H49) -> 49.9 | J6: =IFERROR(AVERAGE(M10:M49),0) -> 0.375 | L6: =SUM(L10:L49) -> 120
A8: Células cinza = automáticas (não edite) · Linha 10 = exemplo: substitua ou apague · Use a seta das células Status, Prioridade e Certificado
A9: ID | B9: Título | C9: Autor(a) | D9: Tema / Categoria | E9: Editora / Loja | F9: Formato | G9: Data da compra | H9: Valor pago (R$) | I9: Data de início | J9: Término previsto | K9: Páginas (total) | L9: Páginas lidas | M9: % Andamento | N9: Status | O9: Prioridade | P9: Nota (1–5) | Q9: Link / Onde está | R9: Observações
A10: =IF($B10="","","LV-"&TEXT(ROW()-9,"00")) -> LV-01 | B10: Hábitos Atômicos (exemplo) | C10: James Clear | D10: Produtividade | E10: Livraria Exemplo | F10: Físico | G10: 46285 | H10: 49.9 | I10: 46290 | J10: 46341 | K10: 320 | L10: 120 | M10: =IF($B10="","",IF(N($K10)=0,0,MIN(1,N($L10)/$K10))) -> 0.375 | N10: Em andamento | O10: Média | Q10: Estante — prateleira 2 | R10: Linha de exemplo — substitua pelos seus dados.
A11: =IF($B11="","","LV-"&TEXT(ROW()-9,"00")) | M11: =IF($B11="","",IF(N($K11)=0,0,MIN(1,N($L11)/$K11)))
A12: =IF($B12="","","LV-"&TEXT(ROW()-9,"00")) | M12: =IF($B12="","",IF(N($K12)=0,0,MIN(1,N($L12)/$K12)))
A13: =IF($B13="","","LV-"&TEXT(ROW()-9,"00")) | M13: =IF($B13="","",IF(N($K13)=0,0,MIN(1,N($L13)/$K13)))
A14: =IF($B14="","","LV-"&TEXT(ROW()-9,"00")) | M14: =IF($B14="","",IF(N($K14)=0,0,MIN(1,N($L14)/$K14)))
A15: =IF($B15="","","LV-"&TEXT(ROW()-9,"00")) | M15: =IF($B15="","",IF(N($K15)=0,0,MIN(1,N($L15)/$K15)))
A16: =IF($B16="","","LV-"&TEXT(ROW()-9,"00")) | M16: =IF($B16="","",IF(N($K16)=0,0,MIN(1,N($L16)/$K16)))
A17: =IF($B17="","","LV-"&TEXT(ROW()-9,"00")) | M17: =IF($B17="","",IF(N($K17)=0,0,MIN(1,N($L17)/$K17)))
A18: =IF($B18="","","LV-"&TEXT(ROW()-9,"00")) | M18: =IF($B18="","",IF(N($K18)=0,0,MIN(1,N($L18)/$K18)))
A19: =IF($B19="","","LV-"&TEXT(ROW()-9,"00")) | M19: =IF($B19="","",IF(N($K19)=0,0,MIN(1,N($L19)/$K19)))
A20: =IF($B20="","","LV-"&TEXT(ROW()-9,"00")) | M20: =IF($B20="","",IF(N($K20)=0,0,MIN(1,N($L20)/$K20)))
A21: =IF($B21="","","LV-"&TEXT(ROW()-9,"00")) | M21: =IF($B21="","",IF(N($K21)=0,0,MIN(1,N($L21)/$K21)))
A22: =IF($B22="","","LV-"&TEXT(ROW()-9,"00")) | M22: =IF($B22="","",IF(N($K22)=0,0,MIN(1,N($L22)/$K22)))
... A49: =IF($B49="","","LV-"&TEXT(ROW()-9,"00")) | M49: =IF($B49="","",IF(N($K49)=0,0,MIN(1,N($L49)/$K49)))

Sheet Cursos IA
A1: CURSOS · FOCO EM IA
A2: Inteligência artificial, agentes, automação e ferramentas · do aprendizado à aplicação | S2: ← Voltar ao Início
B5: ITENS | D5: EM ANDAMENTO | F5: CONCLUÍDOS | H5: INVESTIDO | J5: PROGRESSO MÉDIO | L5: ACESSOS A VENCER
B6: =COUNTA(B10:B49) -> 1 | D6: =COUNTIF(O10:O49,"Em andamento") -> 1 | F6: =COUNTIF(O10:O49,"Concluído") -> 0 | H6: =SUM(F10:F49) -> 497 | J6: =IFERROR(AVERAGE(N10:N49),0) -> 0.3 | L6: =COUNTIF(K10:K49,"*A vencer") -> 0
A8: Células cinza = automáticas (não edite) · Linha 10 = exemplo: substitua ou apague · Use a seta das células Status, Prioridade e Certificado
A9: ID | B9: Curso | C9: Instituição / Plataforma | D9: Foco / Ferramenta | E9: Data da compra | F9: Valor pago (R$) | G9: Data de início | H9: Término previsto | I9: Vencimento do acesso | J9: Dias p/ vencer | K9: Situação do acesso | L9: Aulas (total) | M9: Aulas concluídas | N9: % Andamento | O9: Status | P9: Prioridade | Q9: Certificado | R9: Login | S9: Senha | T9: Link de acesso | U9: Observações
A10: =IF($B10="","","IA-"&TEXT(ROW()-9,"00")) -> IA-01 | B10: Agentes de IA na Prática (exemplo) | C10: Plataforma Exemplo | D10: Agentes · automação | E10: 46277 | F10: 497 | G10: 46285 | H10: 46376 | I10: 46642 | J10: =IF(OR($B10="",$I10=""),"",$I10-TODAY()) -> 344 | K10: =IF($B10="","",IF($I10="","∞ Vitalício",IF($J10<0,"■ Vencido",IF($J10<=Listas!$H$6,"▲ A vencer","● Ativo")))) -> ● Ativo | L10: 60 | M10: 18 | N10: =IF($B10="","",IF(N($L10)=0,0,MIN(1,N($M10)/$L10))) -> 0.3 | O10: Em andamento | P10: Alta | Q10: Não emitido | R10: seu.email@exemplo.com | S10: (guarde no gerenciador de senhas) | T10: https://plataforma.exemplo.com | U10: Linha de exemplo — substitua pelos seus dados.
A11: =IF($B11="","","IA-"&TEXT(ROW()-9,"00")) | J11: =IF(OR($B11="",$I11=""),"",$I11-TODAY()) | K11: =IF($B11="","",IF($I11="","∞ Vitalício",IF($J11<0,"■ Vencido",IF($J11<=Listas!$H$6,"▲ A vencer","● Ativo")))) | N11: =IF($B11="","",IF(N($L11)=0,0,MIN(1,N($M11)/$L11)))
A12: =IF($B12="","","IA-"&TEXT(ROW()-9,"00")) | J12: =IF(OR($B12="",$I12=""),"",$I12-TODAY()) | K12: =IF($B12="","",IF($I12="","∞ Vitalício",IF($J12<0,"■ Vencido",IF($J12<=Listas!$H$6,"▲ A vencer","● Ativo")))) | N12: =IF($B12="","",IF(N($L12)=0,0,MIN(1,N($M12)/$L12)))
A13: =IF($B13="","","IA-"&TEXT(ROW()-9,"00")) | J13: =IF(OR($B13="",$I13=""),"",$I13-TODAY()) | K13: =IF($B13="","",IF($I13="","∞ Vitalício",IF($J13<0,"■ Vencido",IF($J13<=Listas!$H$6,"▲ A vencer","● Ativo")))) | N13: =IF($B13="","",IF(N($L13)=0,0,MIN(1,N($M13)/$L13)))
A14: =IF($B14="","","IA-"&TEXT(ROW()-9,"00")) | J14: =IF(OR($B14="",$I14=""),"",$I14-TODAY()) | K14: =IF($B14="","",IF($I14="","∞ Vitalício",IF($J14<0,"■ Vencido",IF($J14<=Listas!$H$6,"▲ A vencer","● Ativo")))) | N14: =IF($B14="","",IF(N($L14)=0,0,MIN(1,N($M14)/$L14)))
A15: =IF($B15="","","IA-"&TEXT(ROW()-9,"00")) | J15: =IF(OR($B15="",$I15=""),"",$I15-TODAY()) | K15: =IF($B15="","",IF($I15="","∞ Vitalício",IF($J15<0,"■ Vencido",IF($J15<=Listas!$H$6,"▲ A vencer","● Ativo")))) | N15: =IF($B15="","",IF(N($L15)=0,0,MIN(1,N($M15)/$L15)))
A16: =IF($B16="","","IA-"&TEXT(ROW()-9,"00")) | J16: =IF(OR($B16="",$I16=""),"",$I16-TODAY()) | K16: =IF($B16="","",IF($I16="","∞ Vitalício",IF($J16<0,"■ Vencido",IF($J16<=Listas!$H$6,"▲ A vencer","● Ativo")))) | N16: =IF($B16="","",IF(N($L16)=0,0,MIN(1,N($M16)/$L16)))
A17: =IF($B17="","","IA-"&TEXT(ROW()-9,"00")) | J17: =IF(OR($B17="",$I17=""),"",$I17-TODAY()) | K17: =IF($B17="","",IF($I17="","∞ Vitalício",IF($J17<0,"■ Vencido",IF($J17<=Listas!$H$6,"▲ A vencer","● Ativo")))) | N17: =IF($B17="","",IF(N($L17)=0,0,MIN(1,N($M17)/$L17)))
A18: =IF($B18="","","IA-"&TEXT(ROW()-9,"00")) | J18: =IF(OR($B18="",$I18=""),"",$I18-TODAY()) | K18: =IF($B18="","",IF($I18="","∞ Vitalício",IF($J18<0,"■ Vencido",IF($J18<=Listas!$H$6,"▲ A vencer","● Ativo")))) | N18: =IF($B18="","",IF(N($L18)=0,0,MIN(1,N($M18)/$L18)))
A19: =IF($B19="","","IA-"&TEXT(ROW()-9,"00")) | J19: =IF(OR($B19="",$I19=""),"",$I19-TODAY()) | K19: =IF($B19="","",IF($I19="","∞ Vitalício",IF($J19<0,"■ Vencido",IF($J19<=Listas!$H$6,"▲ A vencer","● Ativo")))) | N19: =IF($B19="","",IF(N($L19)=0,0,MIN(1,N($M19)/$L19)))
A20: =IF($B20="","","IA-"&TEXT(ROW()-9,"00")) | J20: =IF(OR($B20="",$I20=""),"",$I20-TODAY()) | K20: =IF($B20="","",IF($I20="","∞ Vitalício",IF($J20<0,"■ Vencido",IF($J20<=Listas!$H$6,"▲ A vencer","● Ativo")))) | N20: =IF($B20="","",IF(N($L20)=0,0,MIN(1,N($M20)/$L20)))
A21: =IF($B21="","","IA-"&TEXT(ROW()-9,"00")) | J21: =IF(OR($B21="",$I21=""),"",$I21-TODAY()) | K21: =IF($B21="","",IF($I21="","∞ Vitalício",IF($J21<0,"■ Vencido",IF($J21<=Listas!$H$6,"▲ A vencer","● Ativo")))) | N21: =IF($B21="","",IF(N($L21)=0,0,MIN(1,N($M21)/$L21)))
A22: =IF($B22="","","IA-"&TEXT(ROW()-9,"00")) | J22: =IF(OR($B22="",$I22=""),"",$I22-TODAY()) | K22: =IF($B22="","",IF($I22="","∞ Vitalício",IF($J22<0,"■ Vencido",IF($J22<=Listas!$H$6,"▲ A vencer","● Ativo")))) | N22: =IF($B22="","",IF(N($L22)=0,0,MIN(1,N($M22)/$L22)))
... A49: =IF($B49="","","IA-"&TEXT(ROW()-9,"00")) | J49: =IF(OR($B49="",$I49=""),"",$I49-TODAY()) | K49: =IF($B49="","",IF($I49="","∞ Vitalício",IF($J49<0,"■ Vencido",IF($J49<=Listas!$H$6,"▲ A vencer","● Ativo")))) | N49: =IF($B49="","",IF(N($L49)=0,0,MIN(1,N($M49)/$L49)))

Sheet Renda Extra
A1: CURSOS · FOCO EM RENDA EXTRA
A2: Afiliados, freelas, infoprodutos e negócios digitais · aprendizado e retorno financeiro | U2: ← Voltar ao Início
B5: ITENS | D5: EM ANDAMENTO | F5: CONCLUÍDOS | H5: INVESTIDO | J5: PROGRESSO MÉDIO | L5: RESULTADO/MÊS ATUAL
B6: =COUNTA(B10:B49) -> 1 | D6: =COUNTIF(O10:O49,"Em andamento") -> 1 | F6: =COUNTIF(O10:O49,"Concluído") -> 0 | H6: =SUM(F10:F49) -> 297 | J6: =IFERROR(AVERAGE(N10:N49),0) -> 0.22222222 | L6: =SUM(S10:S49) -> 0
A8: Células cinza = automáticas (não edite) · Linha 10 = exemplo: substitua ou apague · Use a seta das células Status, Prioridade e Certificado
A9: ID | B9: Curso | C9: Instituição / Plataforma | D9: Modelo de renda | E9: Data da compra | F9: Valor pago (R$) | G9: Data de início | H9: Término previsto | I9: Vencimento do acesso | J9: Dias p/ vencer | K9: Situação do acesso | L9: Aulas (total) | M9: Aulas concluídas | N9: % Andamento | O9: Status | P9: Prioridade | Q9: Certificado | R9: Meta de ganho/mês (R$) | S9: Resultado atual/mês (R$) | T9: Login | U9: Senha | V9: Link de acesso | W9: Observações
A10: =IF($B10="","","RE-"&TEXT(ROW()-9,"00")) -> RE-01 | B10: Marketing de Afiliados do Zero (exemplo) | C10: Plataforma Exemplo | D10: Afiliados | E10: 46266 | F10: 297 | G10: 46268 | H10: 46356 | I10: 46631 | J10: =IF(OR($B10="",$I10=""),"",$I10-TODAY()) -> 333 | K10: =IF($B10="","",IF($I10="","∞ Vitalício",IF($J10<0,"■ Vencido",IF($J10<=Listas!$H$6,"▲ A vencer","● Ativo")))) -> ● Ativo | L10: 45 | M10: 10 | N10: =IF($B10="","",IF(N($L10)=0,0,MIN(1,N($M10)/$L10))) -> 0.22222222 | O10: Em andamento | P10: Média | Q10: Não emitido | R10: 1500 | S10: 0 | T10: seu.email@exemplo.com | U10: (guarde no gerenciador de senhas) | V10: https://plataforma.exemplo.com | W10: Linha de exemplo — substitua pelos seus dados.
A11: =IF($B11="","","RE-"&TEXT(ROW()-9,"00")) | J11: =IF(OR($B11="",$I11=""),"",$I11-TODAY()) | K11: =IF($B11="","",IF($I11="","∞ Vitalício",IF($J11<0,"■ Vencido",IF($J11<=Listas!$H$6,"▲ A vencer","● Ativo")))) | N11: =IF($B11="","",IF(N($L11)=0,0,MIN(1,N($M11)/$L11)))
A12: =IF($B12="","","RE-"&TEXT(ROW()-9,"00")) | J12: =IF(OR($B12="",$I12=""),"",$I12-TODAY()) | K12: =IF($B12="","",IF($I12="","∞ Vitalício",IF($J12<0,"■ Vencido",IF($J12<=Listas!$H$6,"▲ A vencer","● Ativo")))) | N12: =IF($B12="","",IF(N($L12)=0,0,MIN(1,N($M12)/$L12)))
A13: =IF($B13="","","RE-"&TEXT(ROW()-9,"00")) | J13: =IF(OR($B13="",$I13=""),"",$I13-TODAY()) | K13: =IF($B13="","",IF($I13="","∞ Vitalício",IF($J13<0,"■ Vencido",IF($J13<=Listas!$H$6,"▲ A vencer","● Ativo")))) | N13: =IF($B13="","",IF(N($L13)=0,0,MIN(1,N($M13)/$L13)))
A14: =IF($B14="","","RE-"&TEXT(ROW()-9,"00")) | J14: =IF(OR($B14="",$I14=""),"",$I14-TODAY()) | K14: =IF($B14="","",IF($I14="","∞ Vitalício",IF($J14<0,"■ Vencido",IF($J14<=Listas!$H$6,"▲ A vencer","● Ativo")))) | N14: =IF($B14="","",IF(N($L14)=0,0,MIN(1,N($M14)/$L14)))
A15: =IF($B15="","","RE-"&TEXT(ROW()-9,"00")) | J15: =IF(OR($B15="",$I15=""),"",$I15-TODAY()) | K15: =IF($B15="","",IF($I15="","∞ Vitalício",IF($J15<0,"■ Vencido",IF($J15<=Listas!$H$6,"▲ A vencer","● Ativo")))) | N15: =IF($B15="","",IF(N($L15)=0,0,MIN(1,N($M15)/$L15)))
A16: =IF($B16="","","RE-"&TEXT(ROW()-9,"00")) | J16: =IF(OR($B16="",$I16=""),"",$I16-TODAY()) | K16: =IF($B16="","",IF($I16="","∞ Vitalício",IF($J16<0,"■ Vencido",IF($J16<=Listas!$H$6,"▲ A vencer","● Ativo")))) | N16: =IF($B16="","",IF(N($L16)=0,0,MIN(1,N($M16)/$L16)))
A17: =IF($B17="","","RE-"&TEXT(ROW()-9,"00")) | J17: =IF(OR($B17="",$I17=""),"",$I17-TODAY()) | K17: =IF($B17="","",IF($I17="","∞ Vitalício",IF($J17<0,"■ Vencido",IF($J17<=Listas!$H$6,"▲ A vencer","● Ativo")))) | N17: =IF($B17="","",IF(N($L17)=0,0,MIN(1,N($M17)/$L17)))
A18: =IF($B18="","","RE-"&TEXT(ROW()-9,"00")) | J18: =IF(OR($B18="",$I18=""),"",$I18-TODAY()) | K18: =IF($B18="","",IF($I18="","∞ Vitalício",IF($J18<0,"■ Vencido",IF($J18<=Listas!$H$6,"▲ A vencer","● Ativo")))) | N18: =IF($B18="","",IF(N($L18)=0,0,MIN(1,N($M18)/$L18)))
A19: =IF($B19="","","RE-"&TEXT(ROW()-9,"00")) | J19: =IF(OR($B19="",$I19=""),"",$I19-TODAY()) | K19: =IF($B19="","",IF($I19="","∞ Vitalício",IF($J19<0,"■ Vencido",IF($J19<=Listas!$H$6,"▲ A vencer","● Ativo")))) | N19: =IF($B19="","",IF(N($L19)=0,0,MIN(1,N($M19)/$L19)))
A20: =IF($B20="","","RE-"&TEXT(ROW()-9,"00")) | J20: =IF(OR($B20="",$I20=""),"",$I20-TODAY()) | K20: =IF($B20="","",IF($I20="","∞ Vitalício",IF($J20<0,"■ Vencido",IF($J20<=Listas!$H$6,"▲ A vencer","● Ativo")))) | N20: =IF($B20="","",IF(N($L20)=0,0,MIN(1,N($M20)/$L20)))
A21: =IF($B21="","","RE-"&TEXT(ROW()-9,"00")) | J21: =IF(OR($B21="",$I21=""),"",$I21-TODAY()) | K21: =IF($B21="","",IF($I21="","∞ Vitalício",IF($J21<0,"■ Vencido",IF($J21<=Listas!$H$6,"▲ A vencer","● Ativo")))) | N21: =IF($B21="","",IF(N($L21)=0,0,MIN(1,N($M21)/$L21)))
A22: =IF($B22="","","RE-"&TEXT(ROW()-9,"00")) | J22: =IF(OR($B22="",$I22=""),"",$I22-TODAY()) | K22: =IF($B22="","",IF($I22="","∞ Vitalício",IF($J22<0,"■ Vencido",IF($J22<=Listas!$H$6,"▲ A vencer","● Ativo")))) | N22: =IF($B22="","",IF(N($L22)=0,0,MIN(1,N($M22)/$L22)))
... A49: =IF($B49="","","RE-"&TEXT(ROW()-9,"00")) | J49: =IF(OR($B49="",$I49=""),"",$I49-TODAY()) | K49: =IF($B49="","",IF($I49="","∞ Vitalício",IF($J49<0,"■ Vencido",IF($J49<=Listas!$H$6,"▲ A vencer","● Ativo")))) | N49: =IF($B49="","",IF(N($L49)=0,0,MIN(1,N($M49)/$L49)))

Sheet Listas
A1: LISTAS E CONFIGURAÇÕES
A2: Edite as listas das setas e o prazo de alerta. Não renomeie os 4 Status. | F2: ← Voltar ao Início
A5: Status | B5: Prioridade | C5: Modalidade | D5: Formato (livros) | E5: Categoria (diário) | F5: Certificado | H5: Alerta de vencimento (dias)
A6: Não iniciado | B6: Alta | C6: EAD | D6: Físico | E6: Pós-graduação | F6: Não emitido | H6: 30
A7: Em andamento | B7: Média | C7: Presencial | D7: E-book | E7: Concurso | F7: Em emissão | H7: Acessos que vencem em até este nº de dias aparecem como “▲ A vencer”. Prazo padrão sugerido: 30 dias (editável).
A8: Concluído | B8: Baixa | C8: Híbrido | D8: Audiobook | E8: Livros | F8: Emitido
A9: Pausado | D9: PDF | E9: Cursos IA | F9: Não se aplica
E10: Renda Extra
A13: As categorias da coluna E alimentam o Diário de Estudo e as Metas. Se renomear, renomeie também as abas correspondentes só se quiser manter a coerência visual.

Sheet Apoio
A1: APOIO · CÁLCULOS AUTOMÁTICOS
A2: Alimenta o painel de vencimentos do Dashboard. Não edite. | F2: ← Voltar ao Início
A4: Categoria | B4: Item | C4: Vencimento | D4: Dias | E4: Chave de ordem | F4: Posição | G4: Chave | H4: Linha
A5: =IF('Pós-graduação'!$B10="","","Pós-graduação") -> Pós-graduação | B5: =IF('Pós-graduação'!$B10="","",'Pós-graduação'!$B10) -> MBA em Inteligência Artificial (exemplo) | C5: =IF(OR('Pós-graduação'!$B10="",'Pós-graduação'!$I10=""),"",'Pós-graduação'!$I10) -> 46997 | D5: =IF(C5="","",C5-TODAY()) -> 699 | E5: =IF(C5="","",D5+ROW()/100000) -> 699.00005 | F5: 1 | G5: =IFERROR(SMALL($E$5:$E$164,F5),"") -> 270.00045 | H5: =IF(G5="","",MATCH(G5,$E$5:$E$164,0)) -> 41
A6: =IF('Pós-graduação'!$B11="","","Pós-graduação") | B6: =IF('Pós-graduação'!$B11="","",'Pós-graduação'!$B11) | C6: =IF(OR('Pós-graduação'!$B11="",'Pós-graduação'!$I11=""),"",'Pós-graduação'!$I11) | D6: =IF(C6="","",C6-TODAY()) | E6: =IF(C6="","",D6+ROW()/100000) | F6: 2 | G6: =IFERROR(SMALL($E$5:$E$164,F6),"") -> 333.00125 | H6: =IF(G6="","",MATCH(G6,$E$5:$E$164,0)) -> 121
A7: =IF('Pós-graduação'!$B12="","","Pós-graduação") | B7: =IF('Pós-graduação'!$B12="","",'Pós-graduação'!$B12) | C7: =IF(OR('Pós-graduação'!$B12="",'Pós-graduação'!$I12=""),"",'Pós-graduação'!$I12) | D7: =IF(C7="","",C7-TODAY()) | E7: =IF(C7="","",D7+ROW()/100000) | F7: 3 | G7: =IFERROR(SMALL($E$5:$E$164,F7),"") -> 344.00085 | H7: =IF(G7="","",MATCH(G7,$E$5:$E$164,0)) -> 81
A8: =IF('Pós-graduação'!$B13="","","Pós-graduação") | B8: =IF('Pós-graduação'!$B13="","",'Pós-graduação'!$B13) | C8: =IF(OR('Pós-graduação'!$B13="",'Pós-graduação'!$I13=""),"",'Pós-graduação'!$I13) | D8: =IF(C8="","",C8-TODAY()) | E8: =IF(C8="","",D8+ROW()/100000) | F8: 4 | G8: =IFERROR(SMALL($E$5:$E$164,F8),"") -> 699.00005 | H8: =IF(G8="","",MATCH(G8,$E$5:$E$164,0)) -> 1
A9: =IF('Pós-graduação'!$B14="","","Pós-graduação") | B9: =IF('Pós-graduação'!$B14="","",'Pós-graduação'!$B14) | C9: =IF(OR('Pós-graduação'!$B14="",'Pós-graduação'!$I14=""),"",'Pós-graduação'!$I14) | D9: =IF(C9="","",C9-TODAY()) | E9: =IF(C9="","",D9+ROW()/100000) | F9: 5 | G9: =IFERROR(SMALL($E$5:$E$164,F9),"") | H9: =IF(G9="","",MATCH(G9,$E$5:$E$164,0))
A10: =IF('Pós-graduação'!$B15="","","Pós-graduação") | B10: =IF('Pós-graduação'!$B15="","",'Pós-graduação'!$B15) | C10: =IF(OR('Pós-graduação'!$B15="",'Pós-graduação'!$I15=""),"",'Pós-graduação'!$I15) | D10: =IF(C10="","",C10-TODAY()) | E10: =IF(C10="","",D10+ROW()/100000) | F10: 6 | G10: =IFERROR(SMALL($E$5:$E$164,F10),"") | H10: =IF(G10="","",MATCH(G10,$E$5:$E$164,0))
A11: =IF('Pós-graduação'!$B16="","","Pós-graduação") | B11: =IF('Pós-graduação'!$B16="","",'Pós-graduação'!$B16) | C11: =IF(OR('Pós-graduação'!$B16="",'Pós-graduação'!$I16=""),"",'Pós-graduação'!$I16) | D11: =IF(C11="","",C11-TODAY()) | E11: =IF(C11="","",D11+ROW()/100000) | F11: 7 | G11: =IFERROR(SMALL($E$5:$E$164,F11),"") | H11: =IF(G11="","",MATCH(G11,$E$5:$E$164,0))
A12: =IF('Pós-graduação'!$B17="","","Pós-graduação") | B12: =IF('Pós-graduação'!$B17="","",'Pós-graduação'!$B17) | C12: =IF(OR('Pós-graduação'!$B17="",'Pós-graduação'!$I17=""),"",'Pós-graduação'!$I17) | D12: =IF(C12="","",C12-TODAY()) | E12: =IF(C12="","",D12+ROW()/100000) | F12: 8 | G12: =IFERROR(SMALL($E$5:$E$164,F12),"") | H12: =IF(G12="","",MATCH(G12,$E$5:$E$164,0))
A13: =IF('Pós-graduação'!$B18="","","Pós-graduação") | B13: =IF('Pós-graduação'!$B18="","",'Pós-graduação'!$B18) | C13: =IF(OR('Pós-graduação'!$B18="",'Pós-graduação'!$I18=""),"",'Pós-graduação'!$I18) | D13: =IF(C13="","",C13-TODAY()) | E13: =IF(C13="","",D13+ROW()/100000)
A14: =IF('Pós-graduação'!$B19="","","Pós-graduação") | B14: =IF('Pós-graduação'!$B19="","",'Pós-graduação'!$B19) | C14: =IF(OR('Pós-graduação'!$B19="",'Pós-graduação'!$I19=""),"",'Pós-graduação'!$I19) | D14: =IF(C14="","",C14-TODAY()) | E14: =IF(C14="","",D14+ROW()/100000)
A15: =IF('Pós-graduação'!$B20="","","Pós-graduação") | B15: =IF('Pós-graduação'!$B20="","",'Pós-graduação'!$B20) | C15: =IF(OR('Pós-graduação'!$B20="",'Pós-graduação'!$I20=""),"",'Pós-graduação'!$I20) | D15: =IF(C15="","",C15-TODAY()) | E15: =IF(C15="","",D15+ROW()/100000)
A16: =IF('Pós-graduação'!$B21="","","Pós-graduação") | B16: =IF('Pós-graduação'!$B21="","",'Pós-graduação'!$B21) | C16: =IF(OR('Pós-graduação'!$B21="",'Pós-graduação'!$I21=""),"",'Pós-graduação'!$I21) | D16: =IF(C16="","",C16-TODAY()) | E16: =IF(C16="","",D16+ROW()/100000)
A17: =IF('Pós-graduação'!$B22="","","Pós-graduação") | B17: =IF('Pós-graduação'!$B22="","",'Pós-graduação'!$B22) | C17: =IF(OR('Pós-graduação'!$B22="",'Pós-graduação'!$I22=""),"",'Pós-graduação'!$I22) | D17: =IF(C17="","",C17-TODAY()) | E17: =IF(C17="","",D17+ROW()/100000)
A18: =IF('Pós-graduação'!$B23="","","Pós-graduação") | B18: =IF('Pós-graduação'!$B23="","",'Pós-graduação'!$B23) | C18: =IF(OR('Pós-graduação'!$B23="",'Pós-graduação'!$I23=""),"",'Pós-graduação'!$I23) | D18: =IF(C18="","",C18-TODAY()) | E18: =IF(C18="","",D18+ROW()/100000)
A19: =IF('Pós-graduação'!$B24="","","Pós-graduação") | B19: =IF('Pós-graduação'!$B24="","",'Pós-graduação'!$B24) | C19: =IF(OR('Pós-graduação'!$B24="",'Pós-graduação'!$I24=""),"",'Pós-graduação'!$I24) | D19: =IF(C19="","",C19-TODAY()) | E19: =IF(C19="","",D19+ROW()/100000)
A20: =IF('Pós-graduação'!$B25="","","Pós-graduação") | B20: =IF('Pós-graduação'!$B25="","",'Pós-graduação'!$B25) | C20: =IF(OR('Pós-graduação'!$B25="",'Pós-graduação'!$I25=""),"",'Pós-graduação'!$I25) | D20: =IF(C20="","",C20-TODAY()) | E20: =IF(C20="","",D20+ROW()/100000)
A21: =IF('Pós-graduação'!$B26="","","Pós-graduação") | B21: =IF('Pós-graduação'!$B26="","",'Pós-graduação'!$B26) | C21: =IF(OR('Pós-graduação'!$B26="",'Pós-graduação'!$I26=""),"",'Pós-graduação'!$I26) | D21: =IF(C21="","",C21-TODAY()) | E21: =IF(C21="","",D21+ROW()/100000)
A22: =IF('Pós-graduação'!$B27="","","Pós-graduação") | B22: =IF('Pós-graduação'!$B27="","",'Pós-graduação'!$B27) | C22: =IF(OR('Pós-graduação'!$B27="",'Pós-graduação'!$I27=""),"",'Pós-graduação'!$I27) | D22: =IF(C22="","",C22-TODAY()) | E22: =IF(C22="","",D22+ROW()/100000)
A23: =IF('Pós-graduação'!$B28="","","Pós-graduação") | B23: =IF('Pós-graduação'!$B28="","",'Pós-graduação'!$B28) | C23: =IF(OR('Pós-graduação'!$B28="",'Pós-graduação'!$I28=""),"",'Pós-graduação'!$I28) | D23: =IF(C23="","",C23-TODAY()) | E23: =IF(C23="","",D23+ROW()/100000)
A24: =IF('Pós-graduação'!$B29="","","Pós-graduação") | B24: =IF('Pós-graduação'!$B29="","",'Pós-graduação'!$B29) | C24: =IF(OR('Pós-graduação'!$B29="",'Pós-graduação'!$I29=""),"",'Pós-graduação'!$I29) | D24: =IF(C24="","",C24-TODAY()) | E24: =IF(C24="","",D24+ROW()/100000)
... A44: =IF('Pós-graduação'!$B49="","","Pós-graduação") | B44: =IF('Pós-graduação'!$B49="","",'Pós-graduação'!$B49) | C44: =IF(OR('Pós-graduação'!$B49="",'Pós-graduação'!$I49=""),"",'Pós-graduação'!$I49) | D44: =IF(C44="","",C44-TODAY()) | E44: =IF(C44="","",D44+ROW()/100000)
A45: =IF(Concurso!$B10="","","Concurso") -> Concurso | B45: =IF(Concurso!$B10="","",Concurso!$B10) -> Curso Preparatório Completo (exemplo) | C45: =IF(OR(Concurso!$B10="",Concurso!$K10=""),"",Concurso!$K10) -> 46568 | D45: =IF(C45="","",C45-TODAY()) -> 270 | E45: =IF(C45="","",D45+ROW()/100000) -> 270.00045
A46: =IF(Concurso!$B11="","","Concurso") | B46: =IF(Concurso!$B11="","",Concurso!$B11) | C46: =IF(OR(Concurso!$B11="",Concurso!$K11=""),"",Concurso!$K11) | D46: =IF(C46="","",C46-TODAY()) | E46: =IF(C46="","",D46+ROW()/100000)
A47: =IF(Concurso!$B12="","","Concurso") | B47: =IF(Concurso!$B12="","",Concurso!$B12) | C47: =IF(OR(Concurso!$B12="",Concurso!$K12=""),"",Concurso!$K12) | D47: =IF(C47="","",C47-TODAY()) | E47: =IF(C47="","",D47+ROW()/100000)
A48: =IF(Concurso!$B13="","","Concurso") | B48: =IF(Concurso!$B13="","",Concurso!$B13) | C48: =IF(OR(Concurso!$B13="",Concurso!$K13=""),"",Concurso!$K13) | D48: =IF(C48="","",C48-TODAY()) | E48: =IF(C48="","",D48+ROW()/100000)
A49: =IF(Concurso!$B14="","","Concurso") | B49: =IF(Concurso!$B14="","",Concurso!$B14) | C49: =IF(OR(Concurso!$B14="",Concurso!$K14=""),"",Concurso!$K14) | D49: =IF(C49="","",C49-TODAY()) | E49: =IF(C49="","",D49+ROW()/100000)
A50: =IF(Concurso!$B15="","","Concurso") | B50: =IF(Concurso!$B15="","",Concurso!$B15) | C50: =IF(OR(Concurso!$B15="",Concurso!$K15=""),"",Concurso!$K15) | D50: =IF(C50="","",C50-TODAY()) | E50: =IF(C50="","",D50+ROW()/100000)
A51: =IF(Concurso!$B16="","","Concurso") | B51: =IF(Concurso!$B16="","",Concurso!$B16) | C51: =IF(OR(Concurso!$B16="",Concurso!$K16=""),"",Concurso!$K16) | D51: =IF(C51="","",C51-TODAY()) | E51: =IF(C51="","",D51+ROW()/100000)
A52: =IF(Concurso!$B17="","","Concurso") | B52: =IF(Concurso!$B17="","",Concurso!$B17) | C52: =IF(OR(Concurso!$B17="",Concurso!$K17=""),"",Concurso!$K17) | D52: =IF(C52="","",C52-TODAY()) | E52: =IF(C52="","",D52+ROW()/100000)
A53: =IF(Concurso!$B18="","","Concurso") | B53: =IF(Concurso!$B18="","",Concurso!$B18) | C53: =IF(OR(Concurso!$B18="",Concurso!$K18=""),"",Concurso!$K18) | D53: =IF(C53="","",C53-TODAY()) | E53: =IF(C53="","",D53+ROW()/100000)
A54: =IF(Concurso!$B19="","","Concurso") | B54: =IF(Concurso!$B19="","",Concurso!$B19) | C54: =IF(OR(Concurso!$B19="",Concurso!$K19=""),"",Concurso!$K19) | D54: =IF(C54="","",C54-TODAY()) | E54: =IF(C54="","",D54+ROW()/100000)
A55: =IF(Concurso!$B20="","","Concurso") | B55: =IF(Concurso!$B20="","",Concurso!$B20) | C55: =IF(OR(Concurso!$B20="",Concurso!$K20=""),"",Concurso!$K20) | D55: =IF(C55="","",C55-TODAY()) | E55: =IF(C55="","",D55+ROW()/100000)
A56: =IF(Concurso!$B21="","","Concurso") | B56: =IF(Concurso!$B21="","",Concurso!$B21) | C56: =IF(OR(Concurso!$B21="",Concurso!$K21=""),"",Concurso!$K21) | D56: =IF(C56="","",C56-TODAY()) | E56: =IF(C56="","",D56+ROW()/100000)
... A84: =IF(Concurso!$B49="","","Concurso") | B84: =IF(Concurso!$B49="","",Concurso!$B49) | C84: =IF(OR(Concurso!$B49="",Concurso!$K49=""),"",Concurso!$K49) | D84: =IF(C84="","",C84-TODAY()) | E84: =IF(C84="","",D84+ROW()/100000)
A85: =IF('Cursos IA'!$B10="","","Cursos IA") -> Cursos IA | B85: =IF('Cursos IA'!$B10="","",'Cursos IA'!$B10) -> Agentes de IA na Prática (exemplo) | C85: =IF(OR('Cursos IA'!$B10="",'Cursos IA'!$I10=""),"",'Cursos IA'!$I10) -> 46642 | D85: =IF(C85="","",C85-TODAY()) -> 344 | E85: =IF(C85="","",D85+ROW()/100000) -> 344.00085
A86: =IF('Cursos IA'!$B11="","","Cursos IA") | B86: =IF('Cursos IA'!$B11="","",'Cursos IA'!$B11) | C86: =IF(OR('Cursos IA'!$B11="",'Cursos IA'!$I11=""),"",'Cursos IA'!$I11) | D86: =IF(C86="","",C86-TODAY()) | E86: =IF(C86="","",D86+ROW()/100000)
A87: =IF('Cursos IA'!$B12="","","Cursos IA") | B87: =IF('Cursos IA'!$B12="","",'Cursos IA'!$B12) | C87: =IF(OR('Cursos IA'!$B12="",'Cursos IA'!$I12=""),"",'Cursos IA'!$I12) | D87: =IF(C87="","",C87-TODAY()) | E87: =IF(C87="","",D87+ROW()/100000)
A88: =IF('Cursos IA'!$B13="","","Cursos IA") | B88: =IF('Cursos IA'!$B13="","",'Cursos IA'!$B13) | C88: =IF(OR('Cursos IA'!$B13="",'Cursos IA'!$I13=""),"",'Cursos IA'!$I13) | D88: =IF(C88="","",C88-TODAY()) | E88: =IF(C88="","",D88+ROW()/100000)
A89: =IF('Cursos IA'!$B14="","","Cursos IA") | B89: =IF('Cursos IA'!$B14="","",'Cursos IA'!$B14) | C89: =IF(OR('Cursos IA'!$B14="",'Cursos IA'!$I14=""),"",'Cursos IA'!$I14) | D89: =IF(C89="","",C89-TODAY()) | E89: =IF(C89="","",D89+ROW()/100000)
A90: =IF('Cursos IA'!$B15="","","Cursos IA") | B90: =IF('Cursos IA'!$B15="","",'Cursos IA'!$B15) | C90: =IF(OR('Cursos IA'!$B15="",'Cursos IA'!$I15=""),"",'Cursos IA'!$I15) | D90: =IF(C90="","",C90-TODAY()) | E90: =IF(C90="","",D90+ROW()/100000)
A91: =IF('Cursos IA'!$B16="","","Cursos IA") | B91: =IF('Cursos IA'!$B16="","",'Cursos IA'!$B16) | C91: =IF(OR('Cursos IA'!$B16="",'Cursos IA'!$I16=""),"",'Cursos IA'!$I16) | D91: =IF(C91="","",C91-TODAY()) | E91: =IF(C91="","",D91+ROW()/100000)
A92: =IF('Cursos IA'!$B17="","","Cursos IA") | B92: =IF('Cursos IA'!$B17="","",'Cursos IA'!$B17) | C92: =IF(OR('Cursos IA'!$B17="",'Cursos IA'!$I17=""),"",'Cursos IA'!$I17) | D92: =IF(C92="","",C92-TODAY()) | E92: =IF(C92="","",D92+ROW()/100000)
A93: =IF('Cursos IA'!$B18="","","Cursos IA") | B93: =IF('Cursos IA'!$B18="","",'Cursos IA'!$B18) | C93: =IF(OR('Cursos IA'!$B18="",'Cursos IA'!$I18=""),"",'Cursos IA'!$I18) | D93: =IF(C93="","",C93-TODAY()) | E93: =IF(C93="","",D93+ROW()/100000)
A94: =IF('Cursos IA'!$B19="","","Cursos IA") | B94: =IF('Cursos IA'!$B19="","",'Cursos IA'!$B19) | C94: =IF(OR('Cursos IA'!$B19="",'Cursos IA'!$I19=""),"",'Cursos IA'!$I19) | D94: =IF(C94="","",C94-TODAY()) | E94: =IF(C94="","",D94+ROW()/100000)
A95: =IF('Cursos IA'!$B20="","","Cursos IA") | B95: =IF('Cursos IA'!$B20="","",'Cursos IA'!$B20) | C95: =IF(OR('Cursos IA'!$B20="",'Cursos IA'!$I20=""),"",'Cursos IA'!$I20) | D95: =IF(C95="","",C95-TODAY()) | E95: =IF(C95="","",D95+ROW()/100000)
A96: =IF('Cursos IA'!$B21="","","Cursos IA") | B96: =IF('Cursos IA'!$B21="","",'Cursos IA'!$B21) | C96: =IF(OR('Cursos IA'!$B21="",'Cursos IA'!$I21=""),"",'Cursos IA'!$I21) | D96: =IF(C96="","",C96-TODAY()) | E96: =IF(C96="","",D96+ROW()/100000)
... A124: =IF('Cursos IA'!$B49="","","Cursos IA") | B124: =IF('Cursos IA'!$B49="","",'Cursos IA'!$B49) | C124: =IF(OR('Cursos IA'!$B49="",'Cursos IA'!$I49=""),"",'Cursos IA'!$I49) | D124: =IF(C124="","",C124-TODAY()) | E124: =IF(C124="","",D124+ROW()/100000)
A125: =IF('Renda Extra'!$B10="","","Renda Extra") -> Renda Extra | B125: =IF('Renda Extra'!$B10="","",'Renda Extra'!$B10) -> Marketing de Afiliados do Zero (exemplo) | C125: =IF(OR('Renda Extra'!$B10="",'Renda Extra'!$I10=""),"",'Renda Extra'!$I10) -> 46631 | D125: =IF(C125="","",C125-TODAY()) -> 333 | E125: =IF(C125="","",D125+ROW()/100000) -> 333.00125
A126: =IF('Renda Extra'!$B11="","","Renda Extra") | B126: =IF('Renda Extra'!$B11="","",'Renda Extra'!$B11) | C126: =IF(OR('Renda Extra'!$B11="",'Renda Extra'!$I11=""),"",'Renda Extra'!$I11) | D126: =IF(C126="","",C126-TODAY()) | E126: =IF(C126="","",D126+ROW()/100000)
A127: =IF('Renda Extra'!$B12="","","Renda Extra") | B127: =IF('Renda Extra'!$B12="","",'Renda Extra'!$B12) | C127: =IF(OR('Renda Extra'!$B12="",'Renda Extra'!$I12=""),"",'Renda Extra'!$I12) | D127: =IF(C127="","",C127-TODAY()) | E127: =IF(C127="","",D127+ROW()/100000)
A128: =IF('Renda Extra'!$B13="","","Renda Extra") | B128: =IF('Renda Extra'!$B13="","",'Renda Extra'!$B13) | C128: =IF(OR('Renda Extra'!$B13="",'Renda Extra'!$I13=""),"",'Renda Extra'!$I13) | D128: =IF(C128="","",C128-TODAY()) | E128: =IF(C128="","",D128+ROW()/100000)
A129: =IF('Renda Extra'!$B14="","","Renda Extra") | B129: =IF('Renda Extra'!$B14="","",'Renda Extra'!$B14) | C129: =IF(OR('Renda Extra'!$B14="",'Renda Extra'!$I14=""),"",'Renda Extra'!$I14) | D129: =IF(C129="","",C129-TODAY()) | E129: =IF(C129="","",D129+ROW()/100000)
A130: =IF('Renda Extra'!$B15="","","Renda Extra") | B130: =IF('Renda Extra'!$B15="","",'Renda Extra'!$B15) | C130: =IF(OR('Renda Extra'!$B15="",'Renda Extra'!$I15=""),"",'Renda Extra'!$I15) | D130: =IF(C130="","",C130-TODAY()) | E130: =IF(C130="","",D130+ROW()/100000)
A131: =IF('Renda Extra'!$B16="","","Renda Extra") | B131: =IF('Renda Extra'!$B16="","",'Renda Extra'!$B16) | C131: =IF(OR('Renda Extra'!$B16="",'Renda Extra'!$I16=""),"",'Renda Extra'!$I16) | D131: =IF(C131="","",C131-TODAY()) | E131: =IF(C131="","",D131+ROW()/100000)
A132: =IF('Renda Extra'!$B17="","","Renda Extra") | B132: =IF('Renda Extra'!$B17="","",'Renda Extra'!$B17) | C132: =IF(OR('Renda Extra'!$B17="",'Renda Extra'!$I17=""),"",'Renda Extra'!$I17) | D132: =IF(C132="","",C132-TODAY()) | E132: =IF(C132="","",D132+ROW()/100000)
A133: =IF('Renda Extra'!$B18="","","Renda Extra") | B133: =IF('Renda Extra'!$B18="","",'Renda Extra'!$B18) | C133: =IF(OR('Renda Extra'!$B18="",'Renda Extra'!$I18=""),"",'Renda Extra'!$I18) | D133: =IF(C133="","",C133-TODAY()) | E133: =IF(C133="","",D133+ROW()/100000)
A134: =IF('Renda Extra'!$B19="","","Renda Extra") | B134: =IF('Renda Extra'!$B19="","",'Renda Extra'!$B19) | C134: =IF(OR('Renda Extra'!$B19="",'Renda Extra'!$I19=""),"",'Renda Extra'!$I19) | D134: =IF(C134="","",C134-TODAY()) | E134: =IF(C134="","",D134+ROW()/100000)
A135: =IF('Renda Extra'!$B20="","","Renda Extra") | B135: =IF('Renda Extra'!$B20="","",'Renda Extra'!$B20) | C135: =IF(OR('Renda Extra'!$B20="",'Renda Extra'!$I20=""),"",'Renda Extra'!$I20) | D135: =IF(C135="","",C135-TODAY()) | E135: =IF(C135="","",D135+ROW()/100000)
A136: =IF('Renda Extra'!$B21="","","Renda Extra") | B136: =IF('Renda Extra'!$B21="","",'Renda Extra'!$B21) | C136: =IF(OR('Renda Extra'!$B21="",'Renda Extra'!$I21=""),"",'Renda Extra'!$I21) | D136: =IF(C136="","",C136-TODAY()) | E136: =IF(C136="","",D136+ROW()/100000)
... A164: =IF('Renda Extra'!$B49="","","Renda Extra") | B164: =IF('Renda Extra'!$B49="","",'Renda Extra'!$B49) | C164: =IF(OR('Renda Extra'!$B49="",'Renda Extra'!$I49=""),"",'Renda Extra'!$I49) | D164: =IF(C164="","",C164-TODAY()) | E164: =IF(C164="","",D164+ROW()/100000)
