Workbook

Sheet Início
A1: ROADMAP DE CURSOS & APRENDIZADO
A2: Sage Dreams · Calm & Natural — controle de pós-graduação, concursos, livros, cursos de IA e renda extra
B4: ABAS DA PLANILHA
B5: Dashboard | C5: Visão geral: totais, progresso médio, investimento, alertas de vencimento e gráficos.
B6: Roadmap | C6: Linha do tempo de 12 meses (Gantt) com barras por status e marcação do vencimento do acesso.
B7: Pós-graduação | C7: MBAs, especializações e extensões: instituição, modalidade, disciplinas, acesso e login.
B8: Concurso | C8: Cursos preparatórios: concurso-alvo, banca, data da prova, aulas concluídas e acesso.
B9: Livros | C9: Biblioteca: autor, formato, páginas lidas, nota e previsão de término.
B10: Cursos IA | C10: Cursos com foco em IA: ferramenta/foco, aulas concluídas, acesso e login.
B11: Renda Extra | C11: Cursos de renda extra: modelo de renda, meta e resultado mensal para medir o retorno.
B12: Listas | C12: Listas das setas (prioridade, modalidade, formato) e prazo do alerta de vencimento.
B14: COMO USAR
B15: Passo 1 | C15: Abra a aba da categoria e substitua a linha 8 (exemplo) pelo seu primeiro curso. Cada aba comporta 40 itens.
B16: Passo 2 | C16: Preencha instituição, datas (compra, início, término previsto e vencimento do acesso), valor e login/senha.
B17: Passo 3 | C17: Informe o total de aulas/disciplinas/páginas e atualize quantas você já concluiu: o % de andamento é calculado sozinho.
B18: Passo 4 | C18: Escolha Status e Prioridade pela seta da célula. Deixe o vencimento em branco para acessos vitalícios.
B19: Passo 5 | C19: Acompanhe tudo no Dashboard e no Roadmap. Nada a atualizar manualmente por lá.
B20: Passo 6 | C20: Precisa de mais de 40 itens? Copie uma linha inteira e use “Inserir células copiadas” ENTRE as linhas 8 e 47, para fórmulas e gráficos acompanharem.
B22: LEGENDA DE CORES
B23: Célula branca | C23: Campo para preencher.
B24: Célula cinza-areia | C24: Fórmula automática — não edite nem apague (ID, dias p/ vencer, situação do acesso, % andamento).
B25: Concluído | C25: Status concluído · barra do Roadmap em verde-claro.
B26: Em andamento | C26: Status em andamento · barra do Roadmap em verde-sálvia.
B27: Vence em breve | C27: Acesso com vencimento dentro do prazo de alerta (padrão 30 dias, editável em Listas).
B28: Vencido | C28: Acesso expirado — priorize ou renove.
B30: IMPORTANTE
B31: • Não edite as células cinza-areia: elas alimentam o Dashboard e o Roadmap.
B32: • Segurança: planilha não é cofre. Prefira um gerenciador de senhas e use a coluna Senha só como lembrete; não compartilhe este arquivo.
B33: • As linhas de exemplo (linha 8 de cada aba) entram nos totais até serem substituídas ou apagadas.
B34: • Premissa: o alerta de vencimento usa 30 dias como padrão — ajuste em Listas > G4.

Sheet Dashboard
A1: DASHBOARD · ROADMAP DE APRENDIZADO
A2: Visão geral de todas as categorias — atualiza automaticamente | K2: ← Voltar ao Início
B4: Total de itens | D4: Em andamento | F4: Concluídos | H4: Investimento total | J4: Progresso médio | L4: Acessos a vencer
B5: =C14 -> 5 | D5: =E14 -> 5 | F5: =F14 -> 0 | H5: =H14 -> 14933.9 | J5: =I14 -> 0.24944444 | L5: =J14 -> 0
B6: Hoje: | C6: =TODAY() -> 46298
B7: Resumo por categoria
B8: Categoria | C8: Itens | D8: Não iniciado | E8: Em andamento | F8: Concluído | G8: Pausado | H8: Investimento (R$) | I8: % médio | J8: A vencer | K8: Vencidos
B9: Pós-graduação | C9: =COUNTA('Pós-graduação'!B8:B47) -> 1 | D9: =COUNTIF('Pós-graduação'!O8:O47,D$8) -> 0 | E9: =COUNTIF('Pós-graduação'!O8:O47,E$8) -> 1 | F9: =COUNTIF('Pós-graduação'!O8:O47,F$8) -> 0 | G9: =COUNTIF('Pós-graduação'!O8:O47,G$8) -> 0 | H9: =SUM('Pós-graduação'!F8:F47) -> 12600 | I9: =IFERROR(AVERAGE('Pós-graduação'!N8:N47),0) -> 0.1 | J9: =COUNTIF('Pós-graduação'!K8:K47,"Vence em breve") -> 0 | K9: =COUNTIF('Pós-graduação'!K8:K47,"Vencido") -> 0
B10: Concurso | C10: =COUNTA(Concurso!B8:B47) -> 1 | D10: =COUNTIF(Concurso!Q8:Q47,D$8) -> 0 | E10: =COUNTIF(Concurso!Q8:Q47,E$8) -> 1 | F10: =COUNTIF(Concurso!Q8:Q47,F$8) -> 0 | G10: =COUNTIF(Concurso!Q8:Q47,G$8) -> 0 | H10: =SUM(Concurso!H8:H47) -> 1490 | I10: =IFERROR(AVERAGE(Concurso!P8:P47),0) -> 0.25 | J10: =COUNTIF(Concurso!M8:M47,"Vence em breve") -> 0 | K10: =COUNTIF(Concurso!M8:M47,"Vencido") -> 0
B11: Livros | C11: =COUNTA(Livros!B8:B47) -> 1 | D11: =COUNTIF(Livros!N8:N47,D$8) -> 0 | E11: =COUNTIF(Livros!N8:N47,E$8) -> 1 | F11: =COUNTIF(Livros!N8:N47,F$8) -> 0 | G11: =COUNTIF(Livros!N8:N47,G$8) -> 0 | H11: =SUM(Livros!H8:H47) -> 49.9 | I11: =IFERROR(AVERAGE(Livros!M8:M47),0) -> 0.375 | J11: — | K11: —
B12: Cursos IA | C12: =COUNTA('Cursos IA'!B8:B47) -> 1 | D12: =COUNTIF('Cursos IA'!O8:O47,D$8) -> 0 | E12: =COUNTIF('Cursos IA'!O8:O47,E$8) -> 1 | F12: =COUNTIF('Cursos IA'!O8:O47,F$8) -> 0 | G12: =COUNTIF('Cursos IA'!O8:O47,G$8) -> 0 | H12: =SUM('Cursos IA'!F8:F47) -> 497 | I12: =IFERROR(AVERAGE('Cursos IA'!N8:N47),0) -> 0.3 | J12: =COUNTIF('Cursos IA'!K8:K47,"Vence em breve") -> 0 | K12: =COUNTIF('Cursos IA'!K8:K47,"Vencido") -> 0
B13: Renda Extra | C13: =COUNTA('Renda Extra'!B8:B47) -> 1 | D13: =COUNTIF('Renda Extra'!O8:O47,D$8) -> 0 | E13: =COUNTIF('Renda Extra'!O8:O47,E$8) -> 1 | F13: =COUNTIF('Renda Extra'!O8:O47,F$8) -> 0 | G13: =COUNTIF('Renda Extra'!O8:O47,G$8) -> 0 | H13: =SUM('Renda Extra'!F8:F47) -> 297 | I13: =IFERROR(AVERAGE('Renda Extra'!N8:N47),0) -> 0.22222222 | J13: =COUNTIF('Renda Extra'!K8:K47,"Vence em breve") -> 0 | K13: =COUNTIF('Renda Extra'!K8:K47,"Vencido") -> 0
B14: TOTAL | C14: =SUM(C9:C13) -> 5 | D14: =SUM(D9:D13) -> 0 | E14: =SUM(E9:E13) -> 5 | F14: =SUM(F9:F13) -> 0 | G14: =SUM(G9:G13) -> 0 | H14: =SUM(H9:H13) -> 14933.9 | I14: =IFERROR(SUMPRODUCT(C9:C13,I9:I13)/C14,0) -> 0.24944444 | J14: =SUM(J9:J13) -> 0 | K14: =SUM(K9:K13) -> 0
B52: Os alertas “A vencer” usam o prazo definido na aba Listas (célula G4). Livros não têm vencimento de acesso.

Sheet Roadmap
A1: ROADMAP · LINHA DO TEMPO
A2: Barras = início → término previsto (cor pelo status) · ▼ = mês do vencimento do acesso | Q2: ← Voltar ao Início
A4: Mês inicial: | B4: 46296 | C4: ← altere para deslocar a janela de 12 meses. Mostra os 12 primeiros itens de cada aba.
A6: Categoria | B6: Item | C6: Status | D6: Início | E6: Término | F6: Vence acesso | G6: % Andam. | H6: =$B$4 -> 46296 | I6: =EDATE(H6,1) -> 46327 | J6: =EDATE(I6,1) -> 46357 | K6: =EDATE(J6,1) -> 46388 | L6: =EDATE(K6,1) -> 46419 | M6: =EDATE(L6,1) -> 46447 | N6: =EDATE(M6,1) -> 46478 | O6: =EDATE(N6,1) -> 46508 | P6: =EDATE(O6,1) -> 46539 | ... S6: =EDATE(R6,1) -> 46631
A7: PÓS-GRADUAÇÃO
A8: =IF($B8="","","Pós-graduação") -> Pós-graduação | B8: =IF('Pós-graduação'!B8="","",'Pós-graduação'!B8) -> MBA em Inteligência Artificial (exemplo) | C8: =IF($B8="","",IF('Pós-graduação'!O8="","",'Pós-graduação'!O8)) -> Em andamento | D8: =IF($B8="","",IF('Pós-graduação'!G8="","",'Pós-graduação'!G8)) -> 46266 | E8: =IF($B8="","",IF('Pós-graduação'!H8<>"",'Pós-graduação'!H8,IF('Pós-graduação'!I8<>"",'Pós-graduação'!I8,""))) -> 46813 | F8: =IF($B8="","",IF('Pós-graduação'!I8="","",'Pós-graduação'!I8)) -> 46997 | G8: =IF($B8="","",'Pós-graduação'!N8) -> 0.1 | H8: =IF(OR($B8="",$F8=""),"",IF(AND($F8>=H$6,$F8<EDATE(H$6,1)),"▼","")) | I8: =IF(OR($B8="",$F8=""),"",IF(AND($F8>=I$6,$F8<EDATE(I$6,1)),"▼","")) | J8: =IF(OR($B8="",$F8=""),"",IF(AND($F8>=J$6,$F8<EDATE(J$6,1)),"▼","")) | K8: =IF(OR($B8="",$F8=""),"",IF(AND($F8>=K$6,$F8<EDATE(K$6,1)),"▼","")) | L8: =IF(OR($B8="",$F8=""),"",IF(AND($F8>=L$6,$F8<EDATE(L$6,1)),"▼","")) | M8: =IF(OR($B8="",$F8=""),"",IF(AND($F8>=M$6,$F8<EDATE(M$6,1)),"▼","")) | N8: =IF(OR($B8="",$F8=""),"",IF(AND($F8>=N$6,$F8<EDATE(N$6,1)),"▼","")) | O8: =IF(OR($B8="",$F8=""),"",IF(AND($F8>=O$6,$F8<EDATE(O$6,1)),"▼","")) | ... S8: =IF(OR($B8="",$F8=""),"",IF(AND($F8>=S$6,$F8<EDATE(S$6,1)),"▼",""))
A9: =IF($B9="","","Pós-graduação") | B9: =IF('Pós-graduação'!B9="","",'Pós-graduação'!B9) | C9: =IF($B9="","",IF('Pós-graduação'!O9="","",'Pós-graduação'!O9)) | D9: =IF($B9="","",IF('Pós-graduação'!G9="","",'Pós-graduação'!G9)) | E9: =IF($B9="","",IF('Pós-graduação'!H9<>"",'Pós-graduação'!H9,IF('Pós-graduação'!I9<>"",'Pós-graduação'!I9,""))) | F9: =IF($B9="","",IF('Pós-graduação'!I9="","",'Pós-graduação'!I9)) | G9: =IF($B9="","",'Pós-graduação'!N9) | H9: =IF(OR($B9="",$F9=""),"",IF(AND($F9>=H$6,$F9<EDATE(H$6,1)),"▼","")) | I9: =IF(OR($B9="",$F9=""),"",IF(AND($F9>=I$6,$F9<EDATE(I$6,1)),"▼","")) | J9: =IF(OR($B9="",$F9=""),"",IF(AND($F9>=J$6,$F9<EDATE(J$6,1)),"▼","")) | K9: =IF(OR($B9="",$F9=""),"",IF(AND($F9>=K$6,$F9<EDATE(K$6,1)),"▼","")) | L9: =IF(OR($B9="",$F9=""),"",IF(AND($F9>=L$6,$F9<EDATE(L$6,1)),"▼","")) | M9: =IF(OR($B9="",$F9=""),"",IF(AND($F9>=M$6,$F9<EDATE(M$6,1)),"▼","")) | N9: =IF(OR($B9="",$F9=""),"",IF(AND($F9>=N$6,$F9<EDATE(N$6,1)),"▼","")) | O9: =IF(OR($B9="",$F9=""),"",IF(AND($F9>=O$6,$F9<EDATE(O$6,1)),"▼","")) | ... S9: =IF(OR($B9="",$F9=""),"",IF(AND($F9>=S$6,$F9<EDATE(S$6,1)),"▼",""))
A10: =IF($B10="","","Pós-graduação") | B10: =IF('Pós-graduação'!B10="","",'Pós-graduação'!B10) | C10: =IF($B10="","",IF('Pós-graduação'!O10="","",'Pós-graduação'!O10)) | D10: =IF($B10="","",IF('Pós-graduação'!G10="","",'Pós-graduação'!G10)) | E10: =IF($B10="","",IF('Pós-graduação'!H10<>"",'Pós-graduação'!H10,IF('Pós-graduação'!I10<>"",'Pós-graduação'!I10,""))) | F10: =IF($B10="","",IF('Pós-graduação'!I10="","",'Pós-graduação'!I10)) | G10: =IF($B10="","",'Pós-graduação'!N10) | H10: =IF(OR($B10="",$F10=""),"",IF(AND($F10>=H$6,$F10<EDATE(H$6,1)),"▼","")) | I10: =IF(OR($B10="",$F10=""),"",IF(AND($F10>=I$6,$F10<EDATE(I$6,1)),"▼","")) | J10: =IF(OR($B10="",$F10=""),"",IF(AND($F10>=J$6,$F10<EDATE(J$6,1)),"▼","")) | K10: =IF(OR($B10="",$F10=""),"",IF(AND($F10>=K$6,$F10<EDATE(K$6,1)),"▼","")) | L10: =IF(OR($B10="",$F10=""),"",IF(AND($F10>=L$6,$F10<EDATE(L$6,1)),"▼","")) | M10: =IF(OR($B10="",$F10=""),"",IF(AND($F10>=M$6,$F10<EDATE(M$6,1)),"▼","")) | N10: =IF(OR($B10="",$F10=""),"",IF(AND($F10>=N$6,$F10<EDATE(N$6,1)),"▼","")) | O10: =IF(OR($B10="",$F10=""),"",IF(AND($F10>=O$6,$F10<EDATE(O$6,1)),"▼","")) | ... S10: =IF(OR($B10="",$F10=""),"",IF(AND($F10>=S$6,$F10<EDATE(S$6,1)),"▼",""))
A11: =IF($B11="","","Pós-graduação") | B11: =IF('Pós-graduação'!B11="","",'Pós-graduação'!B11) | C11: =IF($B11="","",IF('Pós-graduação'!O11="","",'Pós-graduação'!O11)) | D11: =IF($B11="","",IF('Pós-graduação'!G11="","",'Pós-graduação'!G11)) | E11: =IF($B11="","",IF('Pós-graduação'!H11<>"",'Pós-graduação'!H11,IF('Pós-graduação'!I11<>"",'Pós-graduação'!I11,""))) | F11: =IF($B11="","",IF('Pós-graduação'!I11="","",'Pós-graduação'!I11)) | G11: =IF($B11="","",'Pós-graduação'!N11) | H11: =IF(OR($B11="",$F11=""),"",IF(AND($F11>=H$6,$F11<EDATE(H$6,1)),"▼","")) | I11: =IF(OR($B11="",$F11=""),"",IF(AND($F11>=I$6,$F11<EDATE(I$6,1)),"▼","")) | J11: =IF(OR($B11="",$F11=""),"",IF(AND($F11>=J$6,$F11<EDATE(J$6,1)),"▼","")) | K11: =IF(OR($B11="",$F11=""),"",IF(AND($F11>=K$6,$F11<EDATE(K$6,1)),"▼","")) | L11: =IF(OR($B11="",$F11=""),"",IF(AND($F11>=L$6,$F11<EDATE(L$6,1)),"▼","")) | M11: =IF(OR($B11="",$F11=""),"",IF(AND($F11>=M$6,$F11<EDATE(M$6,1)),"▼","")) | N11: =IF(OR($B11="",$F11=""),"",IF(AND($F11>=N$6,$F11<EDATE(N$6,1)),"▼","")) | O11: =IF(OR($B11="",$F11=""),"",IF(AND($F11>=O$6,$F11<EDATE(O$6,1)),"▼","")) | ... S11: =IF(OR($B11="",$F11=""),"",IF(AND($F11>=S$6,$F11<EDATE(S$6,1)),"▼",""))
A12: =IF($B12="","","Pós-graduação") | B12: =IF('Pós-graduação'!B12="","",'Pós-graduação'!B12) | C12: =IF($B12="","",IF('Pós-graduação'!O12="","",'Pós-graduação'!O12)) | D12: =IF($B12="","",IF('Pós-graduação'!G12="","",'Pós-graduação'!G12)) | E12: =IF($B12="","",IF('Pós-graduação'!H12<>"",'Pós-graduação'!H12,IF('Pós-graduação'!I12<>"",'Pós-graduação'!I12,""))) | F12: =IF($B12="","",IF('Pós-graduação'!I12="","",'Pós-graduação'!I12)) | G12: =IF($B12="","",'Pós-graduação'!N12) | H12: =IF(OR($B12="",$F12=""),"",IF(AND($F12>=H$6,$F12<EDATE(H$6,1)),"▼","")) | I12: =IF(OR($B12="",$F12=""),"",IF(AND($F12>=I$6,$F12<EDATE(I$6,1)),"▼","")) | J12: =IF(OR($B12="",$F12=""),"",IF(AND($F12>=J$6,$F12<EDATE(J$6,1)),"▼","")) | K12: =IF(OR($B12="",$F12=""),"",IF(AND($F12>=K$6,$F12<EDATE(K$6,1)),"▼","")) | L12: =IF(OR($B12="",$F12=""),"",IF(AND($F12>=L$6,$F12<EDATE(L$6,1)),"▼","")) | M12: =IF(OR($B12="",$F12=""),"",IF(AND($F12>=M$6,$F12<EDATE(M$6,1)),"▼","")) | N12: =IF(OR($B12="",$F12=""),"",IF(AND($F12>=N$6,$F12<EDATE(N$6,1)),"▼","")) | O12: =IF(OR($B12="",$F12=""),"",IF(AND($F12>=O$6,$F12<EDATE(O$6,1)),"▼","")) | ... S12: =IF(OR($B12="",$F12=""),"",IF(AND($F12>=S$6,$F12<EDATE(S$6,1)),"▼",""))
A13: =IF($B13="","","Pós-graduação") | B13: =IF('Pós-graduação'!B13="","",'Pós-graduação'!B13) | C13: =IF($B13="","",IF('Pós-graduação'!O13="","",'Pós-graduação'!O13)) | D13: =IF($B13="","",IF('Pós-graduação'!G13="","",'Pós-graduação'!G13)) | E13: =IF($B13="","",IF('Pós-graduação'!H13<>"",'Pós-graduação'!H13,IF('Pós-graduação'!I13<>"",'Pós-graduação'!I13,""))) | F13: =IF($B13="","",IF('Pós-graduação'!I13="","",'Pós-graduação'!I13)) | G13: =IF($B13="","",'Pós-graduação'!N13) | H13: =IF(OR($B13="",$F13=""),"",IF(AND($F13>=H$6,$F13<EDATE(H$6,1)),"▼","")) | I13: =IF(OR($B13="",$F13=""),"",IF(AND($F13>=I$6,$F13<EDATE(I$6,1)),"▼","")) | J13: =IF(OR($B13="",$F13=""),"",IF(AND($F13>=J$6,$F13<EDATE(J$6,1)),"▼","")) | K13: =IF(OR($B13="",$F13=""),"",IF(AND($F13>=K$6,$F13<EDATE(K$6,1)),"▼","")) | L13: =IF(OR($B13="",$F13=""),"",IF(AND($F13>=L$6,$F13<EDATE(L$6,1)),"▼","")) | M13: =IF(OR($B13="",$F13=""),"",IF(AND($F13>=M$6,$F13<EDATE(M$6,1)),"▼","")) | N13: =IF(OR($B13="",$F13=""),"",IF(AND($F13>=N$6,$F13<EDATE(N$6,1)),"▼","")) | O13: =IF(OR($B13="",$F13=""),"",IF(AND($F13>=O$6,$F13<EDATE(O$6,1)),"▼","")) | ... S13: =IF(OR($B13="",$F13=""),"",IF(AND($F13>=S$6,$F13<EDATE(S$6,1)),"▼",""))
A14: =IF($B14="","","Pós-graduação") | B14: =IF('Pós-graduação'!B14="","",'Pós-graduação'!B14) | C14: =IF($B14="","",IF('Pós-graduação'!O14="","",'Pós-graduação'!O14)) | D14: =IF($B14="","",IF('Pós-graduação'!G14="","",'Pós-graduação'!G14)) | E14: =IF($B14="","",IF('Pós-graduação'!H14<>"",'Pós-graduação'!H14,IF('Pós-graduação'!I14<>"",'Pós-graduação'!I14,""))) | F14: =IF($B14="","",IF('Pós-graduação'!I14="","",'Pós-graduação'!I14)) | G14: =IF($B14="","",'Pós-graduação'!N14) | H14: =IF(OR($B14="",$F14=""),"",IF(AND($F14>=H$6,$F14<EDATE(H$6,1)),"▼","")) | I14: =IF(OR($B14="",$F14=""),"",IF(AND($F14>=I$6,$F14<EDATE(I$6,1)),"▼","")) | J14: =IF(OR($B14="",$F14=""),"",IF(AND($F14>=J$6,$F14<EDATE(J$6,1)),"▼","")) | K14: =IF(OR($B14="",$F14=""),"",IF(AND($F14>=K$6,$F14<EDATE(K$6,1)),"▼","")) | L14: =IF(OR($B14="",$F14=""),"",IF(AND($F14>=L$6,$F14<EDATE(L$6,1)),"▼","")) | M14: =IF(OR($B14="",$F14=""),"",IF(AND($F14>=M$6,$F14<EDATE(M$6,1)),"▼","")) | N14: =IF(OR($B14="",$F14=""),"",IF(AND($F14>=N$6,$F14<EDATE(N$6,1)),"▼","")) | O14: =IF(OR($B14="",$F14=""),"",IF(AND($F14>=O$6,$F14<EDATE(O$6,1)),"▼","")) | ... S14: =IF(OR($B14="",$F14=""),"",IF(AND($F14>=S$6,$F14<EDATE(S$6,1)),"▼",""))
A15: =IF($B15="","","Pós-graduação") | B15: =IF('Pós-graduação'!B15="","",'Pós-graduação'!B15) | C15: =IF($B15="","",IF('Pós-graduação'!O15="","",'Pós-graduação'!O15)) | D15: =IF($B15="","",IF('Pós-graduação'!G15="","",'Pós-graduação'!G15)) | E15: =IF($B15="","",IF('Pós-graduação'!H15<>"",'Pós-graduação'!H15,IF('Pós-graduação'!I15<>"",'Pós-graduação'!I15,""))) | F15: =IF($B15="","",IF('Pós-graduação'!I15="","",'Pós-graduação'!I15)) | G15: =IF($B15="","",'Pós-graduação'!N15) | H15: =IF(OR($B15="",$F15=""),"",IF(AND($F15>=H$6,$F15<EDATE(H$6,1)),"▼","")) | I15: =IF(OR($B15="",$F15=""),"",IF(AND($F15>=I$6,$F15<EDATE(I$6,1)),"▼","")) | J15: =IF(OR($B15="",$F15=""),"",IF(AND($F15>=J$6,$F15<EDATE(J$6,1)),"▼","")) | K15: =IF(OR($B15="",$F15=""),"",IF(AND($F15>=K$6,$F15<EDATE(K$6,1)),"▼","")) | L15: =IF(OR($B15="",$F15=""),"",IF(AND($F15>=L$6,$F15<EDATE(L$6,1)),"▼","")) | M15: =IF(OR($B15="",$F15=""),"",IF(AND($F15>=M$6,$F15<EDATE(M$6,1)),"▼","")) | N15: =IF(OR($B15="",$F15=""),"",IF(AND($F15>=N$6,$F15<EDATE(N$6,1)),"▼","")) | O15: =IF(OR($B15="",$F15=""),"",IF(AND($F15>=O$6,$F15<EDATE(O$6,1)),"▼","")) | ... S15: =IF(OR($B15="",$F15=""),"",IF(AND($F15>=S$6,$F15<EDATE(S$6,1)),"▼",""))
A16: =IF($B16="","","Pós-graduação") | B16: =IF('Pós-graduação'!B16="","",'Pós-graduação'!B16) | C16: =IF($B16="","",IF('Pós-graduação'!O16="","",'Pós-graduação'!O16)) | D16: =IF($B16="","",IF('Pós-graduação'!G16="","",'Pós-graduação'!G16)) | E16: =IF($B16="","",IF('Pós-graduação'!H16<>"",'Pós-graduação'!H16,IF('Pós-graduação'!I16<>"",'Pós-graduação'!I16,""))) | F16: =IF($B16="","",IF('Pós-graduação'!I16="","",'Pós-graduação'!I16)) | G16: =IF($B16="","",'Pós-graduação'!N16) | H16: =IF(OR($B16="",$F16=""),"",IF(AND($F16>=H$6,$F16<EDATE(H$6,1)),"▼","")) | I16: =IF(OR($B16="",$F16=""),"",IF(AND($F16>=I$6,$F16<EDATE(I$6,1)),"▼","")) | J16: =IF(OR($B16="",$F16=""),"",IF(AND($F16>=J$6,$F16<EDATE(J$6,1)),"▼","")) | K16: =IF(OR($B16="",$F16=""),"",IF(AND($F16>=K$6,$F16<EDATE(K$6,1)),"▼","")) | L16: =IF(OR($B16="",$F16=""),"",IF(AND($F16>=L$6,$F16<EDATE(L$6,1)),"▼","")) | M16: =IF(OR($B16="",$F16=""),"",IF(AND($F16>=M$6,$F16<EDATE(M$6,1)),"▼","")) | N16: =IF(OR($B16="",$F16=""),"",IF(AND($F16>=N$6,$F16<EDATE(N$6,1)),"▼","")) | O16: =IF(OR($B16="",$F16=""),"",IF(AND($F16>=O$6,$F16<EDATE(O$6,1)),"▼","")) | ... S16: =IF(OR($B16="",$F16=""),"",IF(AND($F16>=S$6,$F16<EDATE(S$6,1)),"▼",""))
A17: =IF($B17="","","Pós-graduação") | B17: =IF('Pós-graduação'!B17="","",'Pós-graduação'!B17) | C17: =IF($B17="","",IF('Pós-graduação'!O17="","",'Pós-graduação'!O17)) | D17: =IF($B17="","",IF('Pós-graduação'!G17="","",'Pós-graduação'!G17)) | E17: =IF($B17="","",IF('Pós-graduação'!H17<>"",'Pós-graduação'!H17,IF('Pós-graduação'!I17<>"",'Pós-graduação'!I17,""))) | F17: =IF($B17="","",IF('Pós-graduação'!I17="","",'Pós-graduação'!I17)) | G17: =IF($B17="","",'Pós-graduação'!N17) | H17: =IF(OR($B17="",$F17=""),"",IF(AND($F17>=H$6,$F17<EDATE(H$6,1)),"▼","")) | I17: =IF(OR($B17="",$F17=""),"",IF(AND($F17>=I$6,$F17<EDATE(I$6,1)),"▼","")) | J17: =IF(OR($B17="",$F17=""),"",IF(AND($F17>=J$6,$F17<EDATE(J$6,1)),"▼","")) | K17: =IF(OR($B17="",$F17=""),"",IF(AND($F17>=K$6,$F17<EDATE(K$6,1)),"▼","")) | L17: =IF(OR($B17="",$F17=""),"",IF(AND($F17>=L$6,$F17<EDATE(L$6,1)),"▼","")) | M17: =IF(OR($B17="",$F17=""),"",IF(AND($F17>=M$6,$F17<EDATE(M$6,1)),"▼","")) | N17: =IF(OR($B17="",$F17=""),"",IF(AND($F17>=N$6,$F17<EDATE(N$6,1)),"▼","")) | O17: =IF(OR($B17="",$F17=""),"",IF(AND($F17>=O$6,$F17<EDATE(O$6,1)),"▼","")) | ... S17: =IF(OR($B17="",$F17=""),"",IF(AND($F17>=S$6,$F17<EDATE(S$6,1)),"▼",""))
A18: =IF($B18="","","Pós-graduação") | B18: =IF('Pós-graduação'!B18="","",'Pós-graduação'!B18) | C18: =IF($B18="","",IF('Pós-graduação'!O18="","",'Pós-graduação'!O18)) | D18: =IF($B18="","",IF('Pós-graduação'!G18="","",'Pós-graduação'!G18)) | E18: =IF($B18="","",IF('Pós-graduação'!H18<>"",'Pós-graduação'!H18,IF('Pós-graduação'!I18<>"",'Pós-graduação'!I18,""))) | F18: =IF($B18="","",IF('Pós-graduação'!I18="","",'Pós-graduação'!I18)) | G18: =IF($B18="","",'Pós-graduação'!N18) | H18: =IF(OR($B18="",$F18=""),"",IF(AND($F18>=H$6,$F18<EDATE(H$6,1)),"▼","")) | I18: =IF(OR($B18="",$F18=""),"",IF(AND($F18>=I$6,$F18<EDATE(I$6,1)),"▼","")) | J18: =IF(OR($B18="",$F18=""),"",IF(AND($F18>=J$6,$F18<EDATE(J$6,1)),"▼","")) | K18: =IF(OR($B18="",$F18=""),"",IF(AND($F18>=K$6,$F18<EDATE(K$6,1)),"▼","")) | L18: =IF(OR($B18="",$F18=""),"",IF(AND($F18>=L$6,$F18<EDATE(L$6,1)),"▼","")) | M18: =IF(OR($B18="",$F18=""),"",IF(AND($F18>=M$6,$F18<EDATE(M$6,1)),"▼","")) | N18: =IF(OR($B18="",$F18=""),"",IF(AND($F18>=N$6,$F18<EDATE(N$6,1)),"▼","")) | O18: =IF(OR($B18="",$F18=""),"",IF(AND($F18>=O$6,$F18<EDATE(O$6,1)),"▼","")) | ... S18: =IF(OR($B18="",$F18=""),"",IF(AND($F18>=S$6,$F18<EDATE(S$6,1)),"▼",""))
A19: =IF($B19="","","Pós-graduação") | B19: =IF('Pós-graduação'!B19="","",'Pós-graduação'!B19) | C19: =IF($B19="","",IF('Pós-graduação'!O19="","",'Pós-graduação'!O19)) | D19: =IF($B19="","",IF('Pós-graduação'!G19="","",'Pós-graduação'!G19)) | E19: =IF($B19="","",IF('Pós-graduação'!H19<>"",'Pós-graduação'!H19,IF('Pós-graduação'!I19<>"",'Pós-graduação'!I19,""))) | F19: =IF($B19="","",IF('Pós-graduação'!I19="","",'Pós-graduação'!I19)) | G19: =IF($B19="","",'Pós-graduação'!N19) | H19: =IF(OR($B19="",$F19=""),"",IF(AND($F19>=H$6,$F19<EDATE(H$6,1)),"▼","")) | I19: =IF(OR($B19="",$F19=""),"",IF(AND($F19>=I$6,$F19<EDATE(I$6,1)),"▼","")) | J19: =IF(OR($B19="",$F19=""),"",IF(AND($F19>=J$6,$F19<EDATE(J$6,1)),"▼","")) | K19: =IF(OR($B19="",$F19=""),"",IF(AND($F19>=K$6,$F19<EDATE(K$6,1)),"▼","")) | L19: =IF(OR($B19="",$F19=""),"",IF(AND($F19>=L$6,$F19<EDATE(L$6,1)),"▼","")) | M19: =IF(OR($B19="",$F19=""),"",IF(AND($F19>=M$6,$F19<EDATE(M$6,1)),"▼","")) | N19: =IF(OR($B19="",$F19=""),"",IF(AND($F19>=N$6,$F19<EDATE(N$6,1)),"▼","")) | O19: =IF(OR($B19="",$F19=""),"",IF(AND($F19>=O$6,$F19<EDATE(O$6,1)),"▼","")) | ... S19: =IF(OR($B19="",$F19=""),"",IF(AND($F19>=S$6,$F19<EDATE(S$6,1)),"▼",""))
A20: CONCURSO
A21: =IF($B21="","","Concurso") -> Concurso | B21: =IF(Concurso!B8="","",Concurso!B8) -> Curso Preparatório Completo (exemplo) | C21: =IF($B21="","",IF(Concurso!Q8="","",Concurso!Q8)) -> Em andamento | D21: =IF($B21="","",IF(Concurso!I8="","",Concurso!I8)) -> 46280 | E21: =IF($B21="","",IF(Concurso!J8<>"",Concurso!J8,IF(Concurso!K8<>"",Concurso!K8,""))) -> 46446 | F21: =IF($B21="","",IF(Concurso!K8="","",Concurso!K8)) -> 46568 | G21: =IF($B21="","",Concurso!P8) -> 0.25 | H21: =IF(OR($B21="",$F21=""),"",IF(AND($F21>=H$6,$F21<EDATE(H$6,1)),"▼","")) | I21: =IF(OR($B21="",$F21=""),"",IF(AND($F21>=I$6,$F21<EDATE(I$6,1)),"▼","")) | J21: =IF(OR($B21="",$F21=""),"",IF(AND($F21>=J$6,$F21<EDATE(J$6,1)),"▼","")) | K21: =IF(OR($B21="",$F21=""),"",IF(AND($F21>=K$6,$F21<EDATE(K$6,1)),"▼","")) | L21: =IF(OR($B21="",$F21=""),"",IF(AND($F21>=L$6,$F21<EDATE(L$6,1)),"▼","")) | M21: =IF(OR($B21="",$F21=""),"",IF(AND($F21>=M$6,$F21<EDATE(M$6,1)),"▼","")) | N21: =IF(OR($B21="",$F21=""),"",IF(AND($F21>=N$6,$F21<EDATE(N$6,1)),"▼","")) | O21: =IF(OR($B21="",$F21=""),"",IF(AND($F21>=O$6,$F21<EDATE(O$6,1)),"▼","")) | ... S21: =IF(OR($B21="",$F21=""),"",IF(AND($F21>=S$6,$F21<EDATE(S$6,1)),"▼",""))
A22: =IF($B22="","","Concurso") | B22: =IF(Concurso!B9="","",Concurso!B9) | C22: =IF($B22="","",IF(Concurso!Q9="","",Concurso!Q9)) | D22: =IF($B22="","",IF(Concurso!I9="","",Concurso!I9)) | E22: =IF($B22="","",IF(Concurso!J9<>"",Concurso!J9,IF(Concurso!K9<>"",Concurso!K9,""))) | F22: =IF($B22="","",IF(Concurso!K9="","",Concurso!K9)) | G22: =IF($B22="","",Concurso!P9) | H22: =IF(OR($B22="",$F22=""),"",IF(AND($F22>=H$6,$F22<EDATE(H$6,1)),"▼","")) | I22: =IF(OR($B22="",$F22=""),"",IF(AND($F22>=I$6,$F22<EDATE(I$6,1)),"▼","")) | J22: =IF(OR($B22="",$F22=""),"",IF(AND($F22>=J$6,$F22<EDATE(J$6,1)),"▼","")) | K22: =IF(OR($B22="",$F22=""),"",IF(AND($F22>=K$6,$F22<EDATE(K$6,1)),"▼","")) | L22: =IF(OR($B22="",$F22=""),"",IF(AND($F22>=L$6,$F22<EDATE(L$6,1)),"▼","")) | M22: =IF(OR($B22="",$F22=""),"",IF(AND($F22>=M$6,$F22<EDATE(M$6,1)),"▼","")) | N22: =IF(OR($B22="",$F22=""),"",IF(AND($F22>=N$6,$F22<EDATE(N$6,1)),"▼","")) | O22: =IF(OR($B22="",$F22=""),"",IF(AND($F22>=O$6,$F22<EDATE(O$6,1)),"▼","")) | ... S22: =IF(OR($B22="",$F22=""),"",IF(AND($F22>=S$6,$F22<EDATE(S$6,1)),"▼",""))
A23: =IF($B23="","","Concurso") | B23: =IF(Concurso!B10="","",Concurso!B10) | C23: =IF($B23="","",IF(Concurso!Q10="","",Concurso!Q10)) | D23: =IF($B23="","",IF(Concurso!I10="","",Concurso!I10)) | E23: =IF($B23="","",IF(Concurso!J10<>"",Concurso!J10,IF(Concurso!K10<>"",Concurso!K10,""))) | F23: =IF($B23="","",IF(Concurso!K10="","",Concurso!K10)) | G23: =IF($B23="","",Concurso!P10) | H23: =IF(OR($B23="",$F23=""),"",IF(AND($F23>=H$6,$F23<EDATE(H$6,1)),"▼","")) | I23: =IF(OR($B23="",$F23=""),"",IF(AND($F23>=I$6,$F23<EDATE(I$6,1)),"▼","")) | J23: =IF(OR($B23="",$F23=""),"",IF(AND($F23>=J$6,$F23<EDATE(J$6,1)),"▼","")) | K23: =IF(OR($B23="",$F23=""),"",IF(AND($F23>=K$6,$F23<EDATE(K$6,1)),"▼","")) | L23: =IF(OR($B23="",$F23=""),"",IF(AND($F23>=L$6,$F23<EDATE(L$6,1)),"▼","")) | M23: =IF(OR($B23="",$F23=""),"",IF(AND($F23>=M$6,$F23<EDATE(M$6,1)),"▼","")) | N23: =IF(OR($B23="",$F23=""),"",IF(AND($F23>=N$6,$F23<EDATE(N$6,1)),"▼","")) | O23: =IF(OR($B23="",$F23=""),"",IF(AND($F23>=O$6,$F23<EDATE(O$6,1)),"▼","")) | ... S23: =IF(OR($B23="",$F23=""),"",IF(AND($F23>=S$6,$F23<EDATE(S$6,1)),"▼",""))
A24: =IF($B24="","","Concurso") | B24: =IF(Concurso!B11="","",Concurso!B11) | C24: =IF($B24="","",IF(Concurso!Q11="","",Concurso!Q11)) | D24: =IF($B24="","",IF(Concurso!I11="","",Concurso!I11)) | E24: =IF($B24="","",IF(Concurso!J11<>"",Concurso!J11,IF(Concurso!K11<>"",Concurso!K11,""))) | F24: =IF($B24="","",IF(Concurso!K11="","",Concurso!K11)) | G24: =IF($B24="","",Concurso!P11) | H24: =IF(OR($B24="",$F24=""),"",IF(AND($F24>=H$6,$F24<EDATE(H$6,1)),"▼","")) | I24: =IF(OR($B24="",$F24=""),"",IF(AND($F24>=I$6,$F24<EDATE(I$6,1)),"▼","")) | J24: =IF(OR($B24="",$F24=""),"",IF(AND($F24>=J$6,$F24<EDATE(J$6,1)),"▼","")) | K24: =IF(OR($B24="",$F24=""),"",IF(AND($F24>=K$6,$F24<EDATE(K$6,1)),"▼","")) | L24: =IF(OR($B24="",$F24=""),"",IF(AND($F24>=L$6,$F24<EDATE(L$6,1)),"▼","")) | M24: =IF(OR($B24="",$F24=""),"",IF(AND($F24>=M$6,$F24<EDATE(M$6,1)),"▼","")) | N24: =IF(OR($B24="",$F24=""),"",IF(AND($F24>=N$6,$F24<EDATE(N$6,1)),"▼","")) | O24: =IF(OR($B24="",$F24=""),"",IF(AND($F24>=O$6,$F24<EDATE(O$6,1)),"▼","")) | ... S24: =IF(OR($B24="",$F24=""),"",IF(AND($F24>=S$6,$F24<EDATE(S$6,1)),"▼",""))
A25: =IF($B25="","","Concurso") | B25: =IF(Concurso!B12="","",Concurso!B12) | C25: =IF($B25="","",IF(Concurso!Q12="","",Concurso!Q12)) | D25: =IF($B25="","",IF(Concurso!I12="","",Concurso!I12)) | E25: =IF($B25="","",IF(Concurso!J12<>"",Concurso!J12,IF(Concurso!K12<>"",Concurso!K12,""))) | F25: =IF($B25="","",IF(Concurso!K12="","",Concurso!K12)) | G25: =IF($B25="","",Concurso!P12) | H25: =IF(OR($B25="",$F25=""),"",IF(AND($F25>=H$6,$F25<EDATE(H$6,1)),"▼","")) | I25: =IF(OR($B25="",$F25=""),"",IF(AND($F25>=I$6,$F25<EDATE(I$6,1)),"▼","")) | J25: =IF(OR($B25="",$F25=""),"",IF(AND($F25>=J$6,$F25<EDATE(J$6,1)),"▼","")) | K25: =IF(OR($B25="",$F25=""),"",IF(AND($F25>=K$6,$F25<EDATE(K$6,1)),"▼","")) | L25: =IF(OR($B25="",$F25=""),"",IF(AND($F25>=L$6,$F25<EDATE(L$6,1)),"▼","")) | M25: =IF(OR($B25="",$F25=""),"",IF(AND($F25>=M$6,$F25<EDATE(M$6,1)),"▼","")) | N25: =IF(OR($B25="",$F25=""),"",IF(AND($F25>=N$6,$F25<EDATE(N$6,1)),"▼","")) | O25: =IF(OR($B25="",$F25=""),"",IF(AND($F25>=O$6,$F25<EDATE(O$6,1)),"▼","")) | ... S25: =IF(OR($B25="",$F25=""),"",IF(AND($F25>=S$6,$F25<EDATE(S$6,1)),"▼",""))
A26: =IF($B26="","","Concurso") | B26: =IF(Concurso!B13="","",Concurso!B13) | C26: =IF($B26="","",IF(Concurso!Q13="","",Concurso!Q13)) | D26: =IF($B26="","",IF(Concurso!I13="","",Concurso!I13)) | E26: =IF($B26="","",IF(Concurso!J13<>"",Concurso!J13,IF(Concurso!K13<>"",Concurso!K13,""))) | F26: =IF($B26="","",IF(Concurso!K13="","",Concurso!K13)) | G26: =IF($B26="","",Concurso!P13) | H26: =IF(OR($B26="",$F26=""),"",IF(AND($F26>=H$6,$F26<EDATE(H$6,1)),"▼","")) | I26: =IF(OR($B26="",$F26=""),"",IF(AND($F26>=I$6,$F26<EDATE(I$6,1)),"▼","")) | J26: =IF(OR($B26="",$F26=""),"",IF(AND($F26>=J$6,$F26<EDATE(J$6,1)),"▼","")) | K26: =IF(OR($B26="",$F26=""),"",IF(AND($F26>=K$6,$F26<EDATE(K$6,1)),"▼","")) | L26: =IF(OR($B26="",$F26=""),"",IF(AND($F26>=L$6,$F26<EDATE(L$6,1)),"▼","")) | M26: =IF(OR($B26="",$F26=""),"",IF(AND($F26>=M$6,$F26<EDATE(M$6,1)),"▼","")) | N26: =IF(OR($B26="",$F26=""),"",IF(AND($F26>=N$6,$F26<EDATE(N$6,1)),"▼","")) | O26: =IF(OR($B26="",$F26=""),"",IF(AND($F26>=O$6,$F26<EDATE(O$6,1)),"▼","")) | ... S26: =IF(OR($B26="",$F26=""),"",IF(AND($F26>=S$6,$F26<EDATE(S$6,1)),"▼",""))
A27: =IF($B27="","","Concurso") | B27: =IF(Concurso!B14="","",Concurso!B14) | C27: =IF($B27="","",IF(Concurso!Q14="","",Concurso!Q14)) | D27: =IF($B27="","",IF(Concurso!I14="","",Concurso!I14)) | E27: =IF($B27="","",IF(Concurso!J14<>"",Concurso!J14,IF(Concurso!K14<>"",Concurso!K14,""))) | F27: =IF($B27="","",IF(Concurso!K14="","",Concurso!K14)) | G27: =IF($B27="","",Concurso!P14) | H27: =IF(OR($B27="",$F27=""),"",IF(AND($F27>=H$6,$F27<EDATE(H$6,1)),"▼","")) | I27: =IF(OR($B27="",$F27=""),"",IF(AND($F27>=I$6,$F27<EDATE(I$6,1)),"▼","")) | J27: =IF(OR($B27="",$F27=""),"",IF(AND($F27>=J$6,$F27<EDATE(J$6,1)),"▼","")) | K27: =IF(OR($B27="",$F27=""),"",IF(AND($F27>=K$6,$F27<EDATE(K$6,1)),"▼","")) | L27: =IF(OR($B27="",$F27=""),"",IF(AND($F27>=L$6,$F27<EDATE(L$6,1)),"▼","")) | M27: =IF(OR($B27="",$F27=""),"",IF(AND($F27>=M$6,$F27<EDATE(M$6,1)),"▼","")) | N27: =IF(OR($B27="",$F27=""),"",IF(AND($F27>=N$6,$F27<EDATE(N$6,1)),"▼","")) | O27: =IF(OR($B27="",$F27=""),"",IF(AND($F27>=O$6,$F27<EDATE(O$6,1)),"▼","")) | ... S27: =IF(OR($B27="",$F27=""),"",IF(AND($F27>=S$6,$F27<EDATE(S$6,1)),"▼",""))
A28: =IF($B28="","","Concurso") | B28: =IF(Concurso!B15="","",Concurso!B15) | C28: =IF($B28="","",IF(Concurso!Q15="","",Concurso!Q15)) | D28: =IF($B28="","",IF(Concurso!I15="","",Concurso!I15)) | E28: =IF($B28="","",IF(Concurso!J15<>"",Concurso!J15,IF(Concurso!K15<>"",Concurso!K15,""))) | F28: =IF($B28="","",IF(Concurso!K15="","",Concurso!K15)) | G28: =IF($B28="","",Concurso!P15) | H28: =IF(OR($B28="",$F28=""),"",IF(AND($F28>=H$6,$F28<EDATE(H$6,1)),"▼","")) | I28: =IF(OR($B28="",$F28=""),"",IF(AND($F28>=I$6,$F28<EDATE(I$6,1)),"▼","")) | J28: =IF(OR($B28="",$F28=""),"",IF(AND($F28>=J$6,$F28<EDATE(J$6,1)),"▼","")) | K28: =IF(OR($B28="",$F28=""),"",IF(AND($F28>=K$6,$F28<EDATE(K$6,1)),"▼","")) | L28: =IF(OR($B28="",$F28=""),"",IF(AND($F28>=L$6,$F28<EDATE(L$6,1)),"▼","")) | M28: =IF(OR($B28="",$F28=""),"",IF(AND($F28>=M$6,$F28<EDATE(M$6,1)),"▼","")) | N28: =IF(OR($B28="",$F28=""),"",IF(AND($F28>=N$6,$F28<EDATE(N$6,1)),"▼","")) | O28: =IF(OR($B28="",$F28=""),"",IF(AND($F28>=O$6,$F28<EDATE(O$6,1)),"▼","")) | ... S28: =IF(OR($B28="",$F28=""),"",IF(AND($F28>=S$6,$F28<EDATE(S$6,1)),"▼",""))
A29: =IF($B29="","","Concurso") | B29: =IF(Concurso!B16="","",Concurso!B16) | C29: =IF($B29="","",IF(Concurso!Q16="","",Concurso!Q16)) | D29: =IF($B29="","",IF(Concurso!I16="","",Concurso!I16)) | E29: =IF($B29="","",IF(Concurso!J16<>"",Concurso!J16,IF(Concurso!K16<>"",Concurso!K16,""))) | F29: =IF($B29="","",IF(Concurso!K16="","",Concurso!K16)) | G29: =IF($B29="","",Concurso!P16) | H29: =IF(OR($B29="",$F29=""),"",IF(AND($F29>=H$6,$F29<EDATE(H$6,1)),"▼","")) | I29: =IF(OR($B29="",$F29=""),"",IF(AND($F29>=I$6,$F29<EDATE(I$6,1)),"▼","")) | J29: =IF(OR($B29="",$F29=""),"",IF(AND($F29>=J$6,$F29<EDATE(J$6,1)),"▼","")) | K29: =IF(OR($B29="",$F29=""),"",IF(AND($F29>=K$6,$F29<EDATE(K$6,1)),"▼","")) | L29: =IF(OR($B29="",$F29=""),"",IF(AND($F29>=L$6,$F29<EDATE(L$6,1)),"▼","")) | M29: =IF(OR($B29="",$F29=""),"",IF(AND($F29>=M$6,$F29<EDATE(M$6,1)),"▼","")) | N29: =IF(OR($B29="",$F29=""),"",IF(AND($F29>=N$6,$F29<EDATE(N$6,1)),"▼","")) | O29: =IF(OR($B29="",$F29=""),"",IF(AND($F29>=O$6,$F29<EDATE(O$6,1)),"▼","")) | ... S29: =IF(OR($B29="",$F29=""),"",IF(AND($F29>=S$6,$F29<EDATE(S$6,1)),"▼",""))
A30: =IF($B30="","","Concurso") | B30: =IF(Concurso!B17="","",Concurso!B17) | C30: =IF($B30="","",IF(Concurso!Q17="","",Concurso!Q17)) | D30: =IF($B30="","",IF(Concurso!I17="","",Concurso!I17)) | E30: =IF($B30="","",IF(Concurso!J17<>"",Concurso!J17,IF(Concurso!K17<>"",Concurso!K17,""))) | F30: =IF($B30="","",IF(Concurso!K17="","",Concurso!K17)) | G30: =IF($B30="","",Concurso!P17) | H30: =IF(OR($B30="",$F30=""),"",IF(AND($F30>=H$6,$F30<EDATE(H$6,1)),"▼","")) | I30: =IF(OR($B30="",$F30=""),"",IF(AND($F30>=I$6,$F30<EDATE(I$6,1)),"▼","")) | J30: =IF(OR($B30="",$F30=""),"",IF(AND($F30>=J$6,$F30<EDATE(J$6,1)),"▼","")) | K30: =IF(OR($B30="",$F30=""),"",IF(AND($F30>=K$6,$F30<EDATE(K$6,1)),"▼","")) | L30: =IF(OR($B30="",$F30=""),"",IF(AND($F30>=L$6,$F30<EDATE(L$6,1)),"▼","")) | M30: =IF(OR($B30="",$F30=""),"",IF(AND($F30>=M$6,$F30<EDATE(M$6,1)),"▼","")) | N30: =IF(OR($B30="",$F30=""),"",IF(AND($F30>=N$6,$F30<EDATE(N$6,1)),"▼","")) | O30: =IF(OR($B30="",$F30=""),"",IF(AND($F30>=O$6,$F30<EDATE(O$6,1)),"▼","")) | ... S30: =IF(OR($B30="",$F30=""),"",IF(AND($F30>=S$6,$F30<EDATE(S$6,1)),"▼",""))
A31: =IF($B31="","","Concurso") | B31: =IF(Concurso!B18="","",Concurso!B18) | C31: =IF($B31="","",IF(Concurso!Q18="","",Concurso!Q18)) | D31: =IF($B31="","",IF(Concurso!I18="","",Concurso!I18)) | E31: =IF($B31="","",IF(Concurso!J18<>"",Concurso!J18,IF(Concurso!K18<>"",Concurso!K18,""))) | F31: =IF($B31="","",IF(Concurso!K18="","",Concurso!K18)) | G31: =IF($B31="","",Concurso!P18) | H31: =IF(OR($B31="",$F31=""),"",IF(AND($F31>=H$6,$F31<EDATE(H$6,1)),"▼","")) | I31: =IF(OR($B31="",$F31=""),"",IF(AND($F31>=I$6,$F31<EDATE(I$6,1)),"▼","")) | J31: =IF(OR($B31="",$F31=""),"",IF(AND($F31>=J$6,$F31<EDATE(J$6,1)),"▼","")) | K31: =IF(OR($B31="",$F31=""),"",IF(AND($F31>=K$6,$F31<EDATE(K$6,1)),"▼","")) | L31: =IF(OR($B31="",$F31=""),"",IF(AND($F31>=L$6,$F31<EDATE(L$6,1)),"▼","")) | M31: =IF(OR($B31="",$F31=""),"",IF(AND($F31>=M$6,$F31<EDATE(M$6,1)),"▼","")) | N31: =IF(OR($B31="",$F31=""),"",IF(AND($F31>=N$6,$F31<EDATE(N$6,1)),"▼","")) | O31: =IF(OR($B31="",$F31=""),"",IF(AND($F31>=O$6,$F31<EDATE(O$6,1)),"▼","")) | ... S31: =IF(OR($B31="",$F31=""),"",IF(AND($F31>=S$6,$F31<EDATE(S$6,1)),"▼",""))
A32: =IF($B32="","","Concurso") | B32: =IF(Concurso!B19="","",Concurso!B19) | C32: =IF($B32="","",IF(Concurso!Q19="","",Concurso!Q19)) | D32: =IF($B32="","",IF(Concurso!I19="","",Concurso!I19)) | E32: =IF($B32="","",IF(Concurso!J19<>"",Concurso!J19,IF(Concurso!K19<>"",Concurso!K19,""))) | F32: =IF($B32="","",IF(Concurso!K19="","",Concurso!K19)) | G32: =IF($B32="","",Concurso!P19) | H32: =IF(OR($B32="",$F32=""),"",IF(AND($F32>=H$6,$F32<EDATE(H$6,1)),"▼","")) | I32: =IF(OR($B32="",$F32=""),"",IF(AND($F32>=I$6,$F32<EDATE(I$6,1)),"▼","")) | J32: =IF(OR($B32="",$F32=""),"",IF(AND($F32>=J$6,$F32<EDATE(J$6,1)),"▼","")) | K32: =IF(OR($B32="",$F32=""),"",IF(AND($F32>=K$6,$F32<EDATE(K$6,1)),"▼","")) | L32: =IF(OR($B32="",$F32=""),"",IF(AND($F32>=L$6,$F32<EDATE(L$6,1)),"▼","")) | M32: =IF(OR($B32="",$F32=""),"",IF(AND($F32>=M$6,$F32<EDATE(M$6,1)),"▼","")) | N32: =IF(OR($B32="",$F32=""),"",IF(AND($F32>=N$6,$F32<EDATE(N$6,1)),"▼","")) | O32: =IF(OR($B32="",$F32=""),"",IF(AND($F32>=O$6,$F32<EDATE(O$6,1)),"▼","")) | ... S32: =IF(OR($B32="",$F32=""),"",IF(AND($F32>=S$6,$F32<EDATE(S$6,1)),"▼",""))
A33: LIVROS
A34: =IF($B34="","","Livros") -> Livros | B34: =IF(Livros!B8="","",Livros!B8) -> Hábitos Atômicos (exemplo) | C34: =IF($B34="","",IF(Livros!N8="","",Livros!N8)) -> Em andamento | D34: =IF($B34="","",IF(Livros!I8="","",Livros!I8)) -> 46290 | E34: =IF($B34="","",IF(Livros!J8="","",Livros!J8)) -> 46341 | F34: ="" | G34: =IF($B34="","",Livros!M8) -> 0.375 | H34: =IF(OR($B34="",$F34=""),"",IF(AND($F34>=H$6,$F34<EDATE(H$6,1)),"▼","")) | I34: =IF(OR($B34="",$F34=""),"",IF(AND($F34>=I$6,$F34<EDATE(I$6,1)),"▼","")) | J34: =IF(OR($B34="",$F34=""),"",IF(AND($F34>=J$6,$F34<EDATE(J$6,1)),"▼","")) | K34: =IF(OR($B34="",$F34=""),"",IF(AND($F34>=K$6,$F34<EDATE(K$6,1)),"▼","")) | L34: =IF(OR($B34="",$F34=""),"",IF(AND($F34>=L$6,$F34<EDATE(L$6,1)),"▼","")) | M34: =IF(OR($B34="",$F34=""),"",IF(AND($F34>=M$6,$F34<EDATE(M$6,1)),"▼","")) | N34: =IF(OR($B34="",$F34=""),"",IF(AND($F34>=N$6,$F34<EDATE(N$6,1)),"▼","")) | O34: =IF(OR($B34="",$F34=""),"",IF(AND($F34>=O$6,$F34<EDATE(O$6,1)),"▼","")) | ... S34: =IF(OR($B34="",$F34=""),"",IF(AND($F34>=S$6,$F34<EDATE(S$6,1)),"▼",""))
A35: =IF($B35="","","Livros") | B35: =IF(Livros!B9="","",Livros!B9) | C35: =IF($B35="","",IF(Livros!N9="","",Livros!N9)) | D35: =IF($B35="","",IF(Livros!I9="","",Livros!I9)) | E35: =IF($B35="","",IF(Livros!J9="","",Livros!J9)) | F35: ="" | G35: =IF($B35="","",Livros!M9) | H35: =IF(OR($B35="",$F35=""),"",IF(AND($F35>=H$6,$F35<EDATE(H$6,1)),"▼","")) | I35: =IF(OR($B35="",$F35=""),"",IF(AND($F35>=I$6,$F35<EDATE(I$6,1)),"▼","")) | J35: =IF(OR($B35="",$F35=""),"",IF(AND($F35>=J$6,$F35<EDATE(J$6,1)),"▼","")) | K35: =IF(OR($B35="",$F35=""),"",IF(AND($F35>=K$6,$F35<EDATE(K$6,1)),"▼","")) | L35: =IF(OR($B35="",$F35=""),"",IF(AND($F35>=L$6,$F35<EDATE(L$6,1)),"▼","")) | M35: =IF(OR($B35="",$F35=""),"",IF(AND($F35>=M$6,$F35<EDATE(M$6,1)),"▼","")) | N35: =IF(OR($B35="",$F35=""),"",IF(AND($F35>=N$6,$F35<EDATE(N$6,1)),"▼","")) | O35: =IF(OR($B35="",$F35=""),"",IF(AND($F35>=O$6,$F35<EDATE(O$6,1)),"▼","")) | ... S35: =IF(OR($B35="",$F35=""),"",IF(AND($F35>=S$6,$F35<EDATE(S$6,1)),"▼",""))
A36: =IF($B36="","","Livros") | B36: =IF(Livros!B10="","",Livros!B10) | C36: =IF($B36="","",IF(Livros!N10="","",Livros!N10)) | D36: =IF($B36="","",IF(Livros!I10="","",Livros!I10)) | E36: =IF($B36="","",IF(Livros!J10="","",Livros!J10)) | F36: ="" | G36: =IF($B36="","",Livros!M10) | H36: =IF(OR($B36="",$F36=""),"",IF(AND($F36>=H$6,$F36<EDATE(H$6,1)),"▼","")) | I36: =IF(OR($B36="",$F36=""),"",IF(AND($F36>=I$6,$F36<EDATE(I$6,1)),"▼","")) | J36: =IF(OR($B36="",$F36=""),"",IF(AND($F36>=J$6,$F36<EDATE(J$6,1)),"▼","")) | K36: =IF(OR($B36="",$F36=""),"",IF(AND($F36>=K$6,$F36<EDATE(K$6,1)),"▼","")) | L36: =IF(OR($B36="",$F36=""),"",IF(AND($F36>=L$6,$F36<EDATE(L$6,1)),"▼","")) | M36: =IF(OR($B36="",$F36=""),"",IF(AND($F36>=M$6,$F36<EDATE(M$6,1)),"▼","")) | N36: =IF(OR($B36="",$F36=""),"",IF(AND($F36>=N$6,$F36<EDATE(N$6,1)),"▼","")) | O36: =IF(OR($B36="",$F36=""),"",IF(AND($F36>=O$6,$F36<EDATE(O$6,1)),"▼","")) | ... S36: =IF(OR($B36="",$F36=""),"",IF(AND($F36>=S$6,$F36<EDATE(S$6,1)),"▼",""))
A37: =IF($B37="","","Livros") | B37: =IF(Livros!B11="","",Livros!B11) | C37: =IF($B37="","",IF(Livros!N11="","",Livros!N11)) | D37: =IF($B37="","",IF(Livros!I11="","",Livros!I11)) | E37: =IF($B37="","",IF(Livros!J11="","",Livros!J11)) | F37: ="" | G37: =IF($B37="","",Livros!M11) | H37: =IF(OR($B37="",$F37=""),"",IF(AND($F37>=H$6,$F37<EDATE(H$6,1)),"▼","")) | I37: =IF(OR($B37="",$F37=""),"",IF(AND($F37>=I$6,$F37<EDATE(I$6,1)),"▼","")) | J37: =IF(OR($B37="",$F37=""),"",IF(AND($F37>=J$6,$F37<EDATE(J$6,1)),"▼","")) | K37: =IF(OR($B37="",$F37=""),"",IF(AND($F37>=K$6,$F37<EDATE(K$6,1)),"▼","")) | L37: =IF(OR($B37="",$F37=""),"",IF(AND($F37>=L$6,$F37<EDATE(L$6,1)),"▼","")) | M37: =IF(OR($B37="",$F37=""),"",IF(AND($F37>=M$6,$F37<EDATE(M$6,1)),"▼","")) | N37: =IF(OR($B37="",$F37=""),"",IF(AND($F37>=N$6,$F37<EDATE(N$6,1)),"▼","")) | O37: =IF(OR($B37="",$F37=""),"",IF(AND($F37>=O$6,$F37<EDATE(O$6,1)),"▼","")) | ... S37: =IF(OR($B37="",$F37=""),"",IF(AND($F37>=S$6,$F37<EDATE(S$6,1)),"▼",""))
A38: =IF($B38="","","Livros") | B38: =IF(Livros!B12="","",Livros!B12) | C38: =IF($B38="","",IF(Livros!N12="","",Livros!N12)) | D38: =IF($B38="","",IF(Livros!I12="","",Livros!I12)) | E38: =IF($B38="","",IF(Livros!J12="","",Livros!J12)) | F38: ="" | G38: =IF($B38="","",Livros!M12) | H38: =IF(OR($B38="",$F38=""),"",IF(AND($F38>=H$6,$F38<EDATE(H$6,1)),"▼","")) | I38: =IF(OR($B38="",$F38=""),"",IF(AND($F38>=I$6,$F38<EDATE(I$6,1)),"▼","")) | J38: =IF(OR($B38="",$F38=""),"",IF(AND($F38>=J$6,$F38<EDATE(J$6,1)),"▼","")) | K38: =IF(OR($B38="",$F38=""),"",IF(AND($F38>=K$6,$F38<EDATE(K$6,1)),"▼","")) | L38: =IF(OR($B38="",$F38=""),"",IF(AND($F38>=L$6,$F38<EDATE(L$6,1)),"▼","")) | M38: =IF(OR($B38="",$F38=""),"",IF(AND($F38>=M$6,$F38<EDATE(M$6,1)),"▼","")) | N38: =IF(OR($B38="",$F38=""),"",IF(AND($F38>=N$6,$F38<EDATE(N$6,1)),"▼","")) | O38: =IF(OR($B38="",$F38=""),"",IF(AND($F38>=O$6,$F38<EDATE(O$6,1)),"▼","")) | ... S38: =IF(OR($B38="",$F38=""),"",IF(AND($F38>=S$6,$F38<EDATE(S$6,1)),"▼",""))
A39: =IF($B39="","","Livros") | B39: =IF(Livros!B13="","",Livros!B13) | C39: =IF($B39="","",IF(Livros!N13="","",Livros!N13)) | D39: =IF($B39="","",IF(Livros!I13="","",Livros!I13)) | E39: =IF($B39="","",IF(Livros!J13="","",Livros!J13)) | F39: ="" | G39: =IF($B39="","",Livros!M13) | H39: =IF(OR($B39="",$F39=""),"",IF(AND($F39>=H$6,$F39<EDATE(H$6,1)),"▼","")) | I39: =IF(OR($B39="",$F39=""),"",IF(AND($F39>=I$6,$F39<EDATE(I$6,1)),"▼","")) | J39: =IF(OR($B39="",$F39=""),"",IF(AND($F39>=J$6,$F39<EDATE(J$6,1)),"▼","")) | K39: =IF(OR($B39="",$F39=""),"",IF(AND($F39>=K$6,$F39<EDATE(K$6,1)),"▼","")) | L39: =IF(OR($B39="",$F39=""),"",IF(AND($F39>=L$6,$F39<EDATE(L$6,1)),"▼","")) | M39: =IF(OR($B39="",$F39=""),"",IF(AND($F39>=M$6,$F39<EDATE(M$6,1)),"▼","")) | N39: =IF(OR($B39="",$F39=""),"",IF(AND($F39>=N$6,$F39<EDATE(N$6,1)),"▼","")) | O39: =IF(OR($B39="",$F39=""),"",IF(AND($F39>=O$6,$F39<EDATE(O$6,1)),"▼","")) | ... S39: =IF(OR($B39="",$F39=""),"",IF(AND($F39>=S$6,$F39<EDATE(S$6,1)),"▼",""))
A40: =IF($B40="","","Livros") | B40: =IF(Livros!B14="","",Livros!B14) | C40: =IF($B40="","",IF(Livros!N14="","",Livros!N14)) | D40: =IF($B40="","",IF(Livros!I14="","",Livros!I14)) | E40: =IF($B40="","",IF(Livros!J14="","",Livros!J14)) | F40: ="" | G40: =IF($B40="","",Livros!M14) | H40: =IF(OR($B40="",$F40=""),"",IF(AND($F40>=H$6,$F40<EDATE(H$6,1)),"▼","")) | I40: =IF(OR($B40="",$F40=""),"",IF(AND($F40>=I$6,$F40<EDATE(I$6,1)),"▼","")) | J40: =IF(OR($B40="",$F40=""),"",IF(AND($F40>=J$6,$F40<EDATE(J$6,1)),"▼","")) | K40: =IF(OR($B40="",$F40=""),"",IF(AND($F40>=K$6,$F40<EDATE(K$6,1)),"▼","")) | L40: =IF(OR($B40="",$F40=""),"",IF(AND($F40>=L$6,$F40<EDATE(L$6,1)),"▼","")) | M40: =IF(OR($B40="",$F40=""),"",IF(AND($F40>=M$6,$F40<EDATE(M$6,1)),"▼","")) | N40: =IF(OR($B40="",$F40=""),"",IF(AND($F40>=N$6,$F40<EDATE(N$6,1)),"▼","")) | O40: =IF(OR($B40="",$F40=""),"",IF(AND($F40>=O$6,$F40<EDATE(O$6,1)),"▼","")) | ... S40: =IF(OR($B40="",$F40=""),"",IF(AND($F40>=S$6,$F40<EDATE(S$6,1)),"▼",""))
A41: =IF($B41="","","Livros") | B41: =IF(Livros!B15="","",Livros!B15) | C41: =IF($B41="","",IF(Livros!N15="","",Livros!N15)) | D41: =IF($B41="","",IF(Livros!I15="","",Livros!I15)) | E41: =IF($B41="","",IF(Livros!J15="","",Livros!J15)) | F41: ="" | G41: =IF($B41="","",Livros!M15) | H41: =IF(OR($B41="",$F41=""),"",IF(AND($F41>=H$6,$F41<EDATE(H$6,1)),"▼","")) | I41: =IF(OR($B41="",$F41=""),"",IF(AND($F41>=I$6,$F41<EDATE(I$6,1)),"▼","")) | J41: =IF(OR($B41="",$F41=""),"",IF(AND($F41>=J$6,$F41<EDATE(J$6,1)),"▼","")) | K41: =IF(OR($B41="",$F41=""),"",IF(AND($F41>=K$6,$F41<EDATE(K$6,1)),"▼","")) | L41: =IF(OR($B41="",$F41=""),"",IF(AND($F41>=L$6,$F41<EDATE(L$6,1)),"▼","")) | M41: =IF(OR($B41="",$F41=""),"",IF(AND($F41>=M$6,$F41<EDATE(M$6,1)),"▼","")) | N41: =IF(OR($B41="",$F41=""),"",IF(AND($F41>=N$6,$F41<EDATE(N$6,1)),"▼","")) | O41: =IF(OR($B41="",$F41=""),"",IF(AND($F41>=O$6,$F41<EDATE(O$6,1)),"▼","")) | ... S41: =IF(OR($B41="",$F41=""),"",IF(AND($F41>=S$6,$F41<EDATE(S$6,1)),"▼",""))
A42: =IF($B42="","","Livros") | B42: =IF(Livros!B16="","",Livros!B16) | C42: =IF($B42="","",IF(Livros!N16="","",Livros!N16)) | D42: =IF($B42="","",IF(Livros!I16="","",Livros!I16)) | E42: =IF($B42="","",IF(Livros!J16="","",Livros!J16)) | F42: ="" | G42: =IF($B42="","",Livros!M16) | H42: =IF(OR($B42="",$F42=""),"",IF(AND($F42>=H$6,$F42<EDATE(H$6,1)),"▼","")) | I42: =IF(OR($B42="",$F42=""),"",IF(AND($F42>=I$6,$F42<EDATE(I$6,1)),"▼","")) | J42: =IF(OR($B42="",$F42=""),"",IF(AND($F42>=J$6,$F42<EDATE(J$6,1)),"▼","")) | K42: =IF(OR($B42="",$F42=""),"",IF(AND($F42>=K$6,$F42<EDATE(K$6,1)),"▼","")) | L42: =IF(OR($B42="",$F42=""),"",IF(AND($F42>=L$6,$F42<EDATE(L$6,1)),"▼","")) | M42: =IF(OR($B42="",$F42=""),"",IF(AND($F42>=M$6,$F42<EDATE(M$6,1)),"▼","")) | N42: =IF(OR($B42="",$F42=""),"",IF(AND($F42>=N$6,$F42<EDATE(N$6,1)),"▼","")) | O42: =IF(OR($B42="",$F42=""),"",IF(AND($F42>=O$6,$F42<EDATE(O$6,1)),"▼","")) | ... S42: =IF(OR($B42="",$F42=""),"",IF(AND($F42>=S$6,$F42<EDATE(S$6,1)),"▼",""))
A43: =IF($B43="","","Livros") | B43: =IF(Livros!B17="","",Livros!B17) | C43: =IF($B43="","",IF(Livros!N17="","",Livros!N17)) | D43: =IF($B43="","",IF(Livros!I17="","",Livros!I17)) | E43: =IF($B43="","",IF(Livros!J17="","",Livros!J17)) | F43: ="" | G43: =IF($B43="","",Livros!M17) | H43: =IF(OR($B43="",$F43=""),"",IF(AND($F43>=H$6,$F43<EDATE(H$6,1)),"▼","")) | I43: =IF(OR($B43="",$F43=""),"",IF(AND($F43>=I$6,$F43<EDATE(I$6,1)),"▼","")) | J43: =IF(OR($B43="",$F43=""),"",IF(AND($F43>=J$6,$F43<EDATE(J$6,1)),"▼","")) | K43: =IF(OR($B43="",$F43=""),"",IF(AND($F43>=K$6,$F43<EDATE(K$6,1)),"▼","")) | L43: =IF(OR($B43="",$F43=""),"",IF(AND($F43>=L$6,$F43<EDATE(L$6,1)),"▼","")) | M43: =IF(OR($B43="",$F43=""),"",IF(AND($F43>=M$6,$F43<EDATE(M$6,1)),"▼","")) | N43: =IF(OR($B43="",$F43=""),"",IF(AND($F43>=N$6,$F43<EDATE(N$6,1)),"▼","")) | O43: =IF(OR($B43="",$F43=""),"",IF(AND($F43>=O$6,$F43<EDATE(O$6,1)),"▼","")) | ... S43: =IF(OR($B43="",$F43=""),"",IF(AND($F43>=S$6,$F43<EDATE(S$6,1)),"▼",""))
A44: =IF($B44="","","Livros") | B44: =IF(Livros!B18="","",Livros!B18) | C44: =IF($B44="","",IF(Livros!N18="","",Livros!N18)) | D44: =IF($B44="","",IF(Livros!I18="","",Livros!I18)) | E44: =IF($B44="","",IF(Livros!J18="","",Livros!J18)) | F44: ="" | G44: =IF($B44="","",Livros!M18) | H44: =IF(OR($B44="",$F44=""),"",IF(AND($F44>=H$6,$F44<EDATE(H$6,1)),"▼","")) | I44: =IF(OR($B44="",$F44=""),"",IF(AND($F44>=I$6,$F44<EDATE(I$6,1)),"▼","")) | J44: =IF(OR($B44="",$F44=""),"",IF(AND($F44>=J$6,$F44<EDATE(J$6,1)),"▼","")) | K44: =IF(OR($B44="",$F44=""),"",IF(AND($F44>=K$6,$F44<EDATE(K$6,1)),"▼","")) | L44: =IF(OR($B44="",$F44=""),"",IF(AND($F44>=L$6,$F44<EDATE(L$6,1)),"▼","")) | M44: =IF(OR($B44="",$F44=""),"",IF(AND($F44>=M$6,$F44<EDATE(M$6,1)),"▼","")) | N44: =IF(OR($B44="",$F44=""),"",IF(AND($F44>=N$6,$F44<EDATE(N$6,1)),"▼","")) | O44: =IF(OR($B44="",$F44=""),"",IF(AND($F44>=O$6,$F44<EDATE(O$6,1)),"▼","")) | ... S44: =IF(OR($B44="",$F44=""),"",IF(AND($F44>=S$6,$F44<EDATE(S$6,1)),"▼",""))
A45: =IF($B45="","","Livros") | B45: =IF(Livros!B19="","",Livros!B19) | C45: =IF($B45="","",IF(Livros!N19="","",Livros!N19)) | D45: =IF($B45="","",IF(Livros!I19="","",Livros!I19)) | E45: =IF($B45="","",IF(Livros!J19="","",Livros!J19)) | F45: ="" | G45: =IF($B45="","",Livros!M19) | H45: =IF(OR($B45="",$F45=""),"",IF(AND($F45>=H$6,$F45<EDATE(H$6,1)),"▼","")) | I45: =IF(OR($B45="",$F45=""),"",IF(AND($F45>=I$6,$F45<EDATE(I$6,1)),"▼","")) | J45: =IF(OR($B45="",$F45=""),"",IF(AND($F45>=J$6,$F45<EDATE(J$6,1)),"▼","")) | K45: =IF(OR($B45="",$F45=""),"",IF(AND($F45>=K$6,$F45<EDATE(K$6,1)),"▼","")) | L45: =IF(OR($B45="",$F45=""),"",IF(AND($F45>=L$6,$F45<EDATE(L$6,1)),"▼","")) | M45: =IF(OR($B45="",$F45=""),"",IF(AND($F45>=M$6,$F45<EDATE(M$6,1)),"▼","")) | N45: =IF(OR($B45="",$F45=""),"",IF(AND($F45>=N$6,$F45<EDATE(N$6,1)),"▼","")) | O45: =IF(OR($B45="",$F45=""),"",IF(AND($F45>=O$6,$F45<EDATE(O$6,1)),"▼","")) | ... S45: =IF(OR($B45="",$F45=""),"",IF(AND($F45>=S$6,$F45<EDATE(S$6,1)),"▼",""))
A46: CURSOS IA
A47: =IF($B47="","","Cursos IA") -> Cursos IA | B47: =IF('Cursos IA'!B8="","",'Cursos IA'!B8) -> Agentes de IA na Prática (exemplo) | C47: =IF($B47="","",IF('Cursos IA'!O8="","",'Cursos IA'!O8)) -> Em andamento | D47: =IF($B47="","",IF('Cursos IA'!G8="","",'Cursos IA'!G8)) -> 46285 | E47: =IF($B47="","",IF('Cursos IA'!H8<>"",'Cursos IA'!H8,IF('Cursos IA'!I8<>"",'Cursos IA'!I8,""))) -> 46376 | F47: =IF($B47="","",IF('Cursos IA'!I8="","",'Cursos IA'!I8)) -> 46642 | G47: =IF($B47="","",'Cursos IA'!N8) -> 0.3 | H47: =IF(OR($B47="",$F47=""),"",IF(AND($F47>=H$6,$F47<EDATE(H$6,1)),"▼","")) | I47: =IF(OR($B47="",$F47=""),"",IF(AND($F47>=I$6,$F47<EDATE(I$6,1)),"▼","")) | J47: =IF(OR($B47="",$F47=""),"",IF(AND($F47>=J$6,$F47<EDATE(J$6,1)),"▼","")) | K47: =IF(OR($B47="",$F47=""),"",IF(AND($F47>=K$6,$F47<EDATE(K$6,1)),"▼","")) | L47: =IF(OR($B47="",$F47=""),"",IF(AND($F47>=L$6,$F47<EDATE(L$6,1)),"▼","")) | M47: =IF(OR($B47="",$F47=""),"",IF(AND($F47>=M$6,$F47<EDATE(M$6,1)),"▼","")) | N47: =IF(OR($B47="",$F47=""),"",IF(AND($F47>=N$6,$F47<EDATE(N$6,1)),"▼","")) | O47: =IF(OR($B47="",$F47=""),"",IF(AND($F47>=O$6,$F47<EDATE(O$6,1)),"▼","")) | ... S47: =IF(OR($B47="",$F47=""),"",IF(AND($F47>=S$6,$F47<EDATE(S$6,1)),"▼","")) -> ▼
A48: =IF($B48="","","Cursos IA") | B48: =IF('Cursos IA'!B9="","",'Cursos IA'!B9) | C48: =IF($B48="","",IF('Cursos IA'!O9="","",'Cursos IA'!O9)) | D48: =IF($B48="","",IF('Cursos IA'!G9="","",'Cursos IA'!G9)) | E48: =IF($B48="","",IF('Cursos IA'!H9<>"",'Cursos IA'!H9,IF('Cursos IA'!I9<>"",'Cursos IA'!I9,""))) | F48: =IF($B48="","",IF('Cursos IA'!I9="","",'Cursos IA'!I9)) | G48: =IF($B48="","",'Cursos IA'!N9) | H48: =IF(OR($B48="",$F48=""),"",IF(AND($F48>=H$6,$F48<EDATE(H$6,1)),"▼","")) | I48: =IF(OR($B48="",$F48=""),"",IF(AND($F48>=I$6,$F48<EDATE(I$6,1)),"▼","")) | J48: =IF(OR($B48="",$F48=""),"",IF(AND($F48>=J$6,$F48<EDATE(J$6,1)),"▼","")) | K48: =IF(OR($B48="",$F48=""),"",IF(AND($F48>=K$6,$F48<EDATE(K$6,1)),"▼","")) | L48: =IF(OR($B48="",$F48=""),"",IF(AND($F48>=L$6,$F48<EDATE(L$6,1)),"▼","")) | M48: =IF(OR($B48="",$F48=""),"",IF(AND($F48>=M$6,$F48<EDATE(M$6,1)),"▼","")) | N48: =IF(OR($B48="",$F48=""),"",IF(AND($F48>=N$6,$F48<EDATE(N$6,1)),"▼","")) | O48: =IF(OR($B48="",$F48=""),"",IF(AND($F48>=O$6,$F48<EDATE(O$6,1)),"▼","")) | ... S48: =IF(OR($B48="",$F48=""),"",IF(AND($F48>=S$6,$F48<EDATE(S$6,1)),"▼",""))
A49: =IF($B49="","","Cursos IA") | B49: =IF('Cursos IA'!B10="","",'Cursos IA'!B10) | C49: =IF($B49="","",IF('Cursos IA'!O10="","",'Cursos IA'!O10)) | D49: =IF($B49="","",IF('Cursos IA'!G10="","",'Cursos IA'!G10)) | E49: =IF($B49="","",IF('Cursos IA'!H10<>"",'Cursos IA'!H10,IF('Cursos IA'!I10<>"",'Cursos IA'!I10,""))) | F49: =IF($B49="","",IF('Cursos IA'!I10="","",'Cursos IA'!I10)) | G49: =IF($B49="","",'Cursos IA'!N10) | H49: =IF(OR($B49="",$F49=""),"",IF(AND($F49>=H$6,$F49<EDATE(H$6,1)),"▼","")) | I49: =IF(OR($B49="",$F49=""),"",IF(AND($F49>=I$6,$F49<EDATE(I$6,1)),"▼","")) | J49: =IF(OR($B49="",$F49=""),"",IF(AND($F49>=J$6,$F49<EDATE(J$6,1)),"▼","")) | K49: =IF(OR($B49="",$F49=""),"",IF(AND($F49>=K$6,$F49<EDATE(K$6,1)),"▼","")) | L49: =IF(OR($B49="",$F49=""),"",IF(AND($F49>=L$6,$F49<EDATE(L$6,1)),"▼","")) | M49: =IF(OR($B49="",$F49=""),"",IF(AND($F49>=M$6,$F49<EDATE(M$6,1)),"▼","")) | N49: =IF(OR($B49="",$F49=""),"",IF(AND($F49>=N$6,$F49<EDATE(N$6,1)),"▼","")) | O49: =IF(OR($B49="",$F49=""),"",IF(AND($F49>=O$6,$F49<EDATE(O$6,1)),"▼","")) | ... S49: =IF(OR($B49="",$F49=""),"",IF(AND($F49>=S$6,$F49<EDATE(S$6,1)),"▼",""))
A50: =IF($B50="","","Cursos IA") | B50: =IF('Cursos IA'!B11="","",'Cursos IA'!B11) | C50: =IF($B50="","",IF('Cursos IA'!O11="","",'Cursos IA'!O11)) | D50: =IF($B50="","",IF('Cursos IA'!G11="","",'Cursos IA'!G11)) | E50: =IF($B50="","",IF('Cursos IA'!H11<>"",'Cursos IA'!H11,IF('Cursos IA'!I11<>"",'Cursos IA'!I11,""))) | F50: =IF($B50="","",IF('Cursos IA'!I11="","",'Cursos IA'!I11)) | G50: =IF($B50="","",'Cursos IA'!N11) | H50: =IF(OR($B50="",$F50=""),"",IF(AND($F50>=H$6,$F50<EDATE(H$6,1)),"▼","")) | I50: =IF(OR($B50="",$F50=""),"",IF(AND($F50>=I$6,$F50<EDATE(I$6,1)),"▼","")) | J50: =IF(OR($B50="",$F50=""),"",IF(AND($F50>=J$6,$F50<EDATE(J$6,1)),"▼","")) | K50: =IF(OR($B50="",$F50=""),"",IF(AND($F50>=K$6,$F50<EDATE(K$6,1)),"▼","")) | L50: =IF(OR($B50="",$F50=""),"",IF(AND($F50>=L$6,$F50<EDATE(L$6,1)),"▼","")) | M50: =IF(OR($B50="",$F50=""),"",IF(AND($F50>=M$6,$F50<EDATE(M$6,1)),"▼","")) | N50: =IF(OR($B50="",$F50=""),"",IF(AND($F50>=N$6,$F50<EDATE(N$6,1)),"▼","")) | O50: =IF(OR($B50="",$F50=""),"",IF(AND($F50>=O$6,$F50<EDATE(O$6,1)),"▼","")) | ... S50: =IF(OR($B50="",$F50=""),"",IF(AND($F50>=S$6,$F50<EDATE(S$6,1)),"▼",""))
A51: =IF($B51="","","Cursos IA") | B51: =IF('Cursos IA'!B12="","",'Cursos IA'!B12) | C51: =IF($B51="","",IF('Cursos IA'!O12="","",'Cursos IA'!O12)) | D51: =IF($B51="","",IF('Cursos IA'!G12="","",'Cursos IA'!G12)) | E51: =IF($B51="","",IF('Cursos IA'!H12<>"",'Cursos IA'!H12,IF('Cursos IA'!I12<>"",'Cursos IA'!I12,""))) | F51: =IF($B51="","",IF('Cursos IA'!I12="","",'Cursos IA'!I12)) | G51: =IF($B51="","",'Cursos IA'!N12) | H51: =IF(OR($B51="",$F51=""),"",IF(AND($F51>=H$6,$F51<EDATE(H$6,1)),"▼","")) | I51: =IF(OR($B51="",$F51=""),"",IF(AND($F51>=I$6,$F51<EDATE(I$6,1)),"▼","")) | J51: =IF(OR($B51="",$F51=""),"",IF(AND($F51>=J$6,$F51<EDATE(J$6,1)),"▼","")) | K51: =IF(OR($B51="",$F51=""),"",IF(AND($F51>=K$6,$F51<EDATE(K$6,1)),"▼","")) | L51: =IF(OR($B51="",$F51=""),"",IF(AND($F51>=L$6,$F51<EDATE(L$6,1)),"▼","")) | M51: =IF(OR($B51="",$F51=""),"",IF(AND($F51>=M$6,$F51<EDATE(M$6,1)),"▼","")) | N51: =IF(OR($B51="",$F51=""),"",IF(AND($F51>=N$6,$F51<EDATE(N$6,1)),"▼","")) | O51: =IF(OR($B51="",$F51=""),"",IF(AND($F51>=O$6,$F51<EDATE(O$6,1)),"▼","")) | ... S51: =IF(OR($B51="",$F51=""),"",IF(AND($F51>=S$6,$F51<EDATE(S$6,1)),"▼",""))
A52: =IF($B52="","","Cursos IA") | B52: =IF('Cursos IA'!B13="","",'Cursos IA'!B13) | C52: =IF($B52="","",IF('Cursos IA'!O13="","",'Cursos IA'!O13)) | D52: =IF($B52="","",IF('Cursos IA'!G13="","",'Cursos IA'!G13)) | E52: =IF($B52="","",IF('Cursos IA'!H13<>"",'Cursos IA'!H13,IF('Cursos IA'!I13<>"",'Cursos IA'!I13,""))) | F52: =IF($B52="","",IF('Cursos IA'!I13="","",'Cursos IA'!I13)) | G52: =IF($B52="","",'Cursos IA'!N13) | H52: =IF(OR($B52="",$F52=""),"",IF(AND($F52>=H$6,$F52<EDATE(H$6,1)),"▼","")) | I52: =IF(OR($B52="",$F52=""),"",IF(AND($F52>=I$6,$F52<EDATE(I$6,1)),"▼","")) | J52: =IF(OR($B52="",$F52=""),"",IF(AND($F52>=J$6,$F52<EDATE(J$6,1)),"▼","")) | K52: =IF(OR($B52="",$F52=""),"",IF(AND($F52>=K$6,$F52<EDATE(K$6,1)),"▼","")) | L52: =IF(OR($B52="",$F52=""),"",IF(AND($F52>=L$6,$F52<EDATE(L$6,1)),"▼","")) | M52: =IF(OR($B52="",$F52=""),"",IF(AND($F52>=M$6,$F52<EDATE(M$6,1)),"▼","")) | N52: =IF(OR($B52="",$F52=""),"",IF(AND($F52>=N$6,$F52<EDATE(N$6,1)),"▼","")) | O52: =IF(OR($B52="",$F52=""),"",IF(AND($F52>=O$6,$F52<EDATE(O$6,1)),"▼","")) | ... S52: =IF(OR($B52="",$F52=""),"",IF(AND($F52>=S$6,$F52<EDATE(S$6,1)),"▼",""))
A53: =IF($B53="","","Cursos IA") | B53: =IF('Cursos IA'!B14="","",'Cursos IA'!B14) | C53: =IF($B53="","",IF('Cursos IA'!O14="","",'Cursos IA'!O14)) | D53: =IF($B53="","",IF('Cursos IA'!G14="","",'Cursos IA'!G14)) | E53: =IF($B53="","",IF('Cursos IA'!H14<>"",'Cursos IA'!H14,IF('Cursos IA'!I14<>"",'Cursos IA'!I14,""))) | F53: =IF($B53="","",IF('Cursos IA'!I14="","",'Cursos IA'!I14)) | G53: =IF($B53="","",'Cursos IA'!N14) | H53: =IF(OR($B53="",$F53=""),"",IF(AND($F53>=H$6,$F53<EDATE(H$6,1)),"▼","")) | I53: =IF(OR($B53="",$F53=""),"",IF(AND($F53>=I$6,$F53<EDATE(I$6,1)),"▼","")) | J53: =IF(OR($B53="",$F53=""),"",IF(AND($F53>=J$6,$F53<EDATE(J$6,1)),"▼","")) | K53: =IF(OR($B53="",$F53=""),"",IF(AND($F53>=K$6,$F53<EDATE(K$6,1)),"▼","")) | L53: =IF(OR($B53="",$F53=""),"",IF(AND($F53>=L$6,$F53<EDATE(L$6,1)),"▼","")) | M53: =IF(OR($B53="",$F53=""),"",IF(AND($F53>=M$6,$F53<EDATE(M$6,1)),"▼","")) | N53: =IF(OR($B53="",$F53=""),"",IF(AND($F53>=N$6,$F53<EDATE(N$6,1)),"▼","")) | O53: =IF(OR($B53="",$F53=""),"",IF(AND($F53>=O$6,$F53<EDATE(O$6,1)),"▼","")) | ... S53: =IF(OR($B53="",$F53=""),"",IF(AND($F53>=S$6,$F53<EDATE(S$6,1)),"▼",""))
A54: =IF($B54="","","Cursos IA") | B54: =IF('Cursos IA'!B15="","",'Cursos IA'!B15) | C54: =IF($B54="","",IF('Cursos IA'!O15="","",'Cursos IA'!O15)) | D54: =IF($B54="","",IF('Cursos IA'!G15="","",'Cursos IA'!G15)) | E54: =IF($B54="","",IF('Cursos IA'!H15<>"",'Cursos IA'!H15,IF('Cursos IA'!I15<>"",'Cursos IA'!I15,""))) | F54: =IF($B54="","",IF('Cursos IA'!I15="","",'Cursos IA'!I15)) | G54: =IF($B54="","",'Cursos IA'!N15) | H54: =IF(OR($B54="",$F54=""),"",IF(AND($F54>=H$6,$F54<EDATE(H$6,1)),"▼","")) | I54: =IF(OR($B54="",$F54=""),"",IF(AND($F54>=I$6,$F54<EDATE(I$6,1)),"▼","")) | J54: =IF(OR($B54="",$F54=""),"",IF(AND($F54>=J$6,$F54<EDATE(J$6,1)),"▼","")) | K54: =IF(OR($B54="",$F54=""),"",IF(AND($F54>=K$6,$F54<EDATE(K$6,1)),"▼","")) | L54: =IF(OR($B54="",$F54=""),"",IF(AND($F54>=L$6,$F54<EDATE(L$6,1)),"▼","")) | M54: =IF(OR($B54="",$F54=""),"",IF(AND($F54>=M$6,$F54<EDATE(M$6,1)),"▼","")) | N54: =IF(OR($B54="",$F54=""),"",IF(AND($F54>=N$6,$F54<EDATE(N$6,1)),"▼","")) | O54: =IF(OR($B54="",$F54=""),"",IF(AND($F54>=O$6,$F54<EDATE(O$6,1)),"▼","")) | ... S54: =IF(OR($B54="",$F54=""),"",IF(AND($F54>=S$6,$F54<EDATE(S$6,1)),"▼",""))
A55: =IF($B55="","","Cursos IA") | B55: =IF('Cursos IA'!B16="","",'Cursos IA'!B16) | C55: =IF($B55="","",IF('Cursos IA'!O16="","",'Cursos IA'!O16)) | D55: =IF($B55="","",IF('Cursos IA'!G16="","",'Cursos IA'!G16)) | E55: =IF($B55="","",IF('Cursos IA'!H16<>"",'Cursos IA'!H16,IF('Cursos IA'!I16<>"",'Cursos IA'!I16,""))) | F55: =IF($B55="","",IF('Cursos IA'!I16="","",'Cursos IA'!I16)) | G55: =IF($B55="","",'Cursos IA'!N16) | H55: =IF(OR($B55="",$F55=""),"",IF(AND($F55>=H$6,$F55<EDATE(H$6,1)),"▼","")) | I55: =IF(OR($B55="",$F55=""),"",IF(AND($F55>=I$6,$F55<EDATE(I$6,1)),"▼","")) | J55: =IF(OR($B55="",$F55=""),"",IF(AND($F55>=J$6,$F55<EDATE(J$6,1)),"▼","")) | K55: =IF(OR($B55="",$F55=""),"",IF(AND($F55>=K$6,$F55<EDATE(K$6,1)),"▼","")) | L55: =IF(OR($B55="",$F55=""),"",IF(AND($F55>=L$6,$F55<EDATE(L$6,1)),"▼","")) | M55: =IF(OR($B55="",$F55=""),"",IF(AND($F55>=M$6,$F55<EDATE(M$6,1)),"▼","")) | N55: =IF(OR($B55="",$F55=""),"",IF(AND($F55>=N$6,$F55<EDATE(N$6,1)),"▼","")) | O55: =IF(OR($B55="",$F55=""),"",IF(AND($F55>=O$6,$F55<EDATE(O$6,1)),"▼","")) | ... S55: =IF(OR($B55="",$F55=""),"",IF(AND($F55>=S$6,$F55<EDATE(S$6,1)),"▼",""))
A56: =IF($B56="","","Cursos IA") | B56: =IF('Cursos IA'!B17="","",'Cursos IA'!B17) | C56: =IF($B56="","",IF('Cursos IA'!O17="","",'Cursos IA'!O17)) | D56: =IF($B56="","",IF('Cursos IA'!G17="","",'Cursos IA'!G17)) | E56: =IF($B56="","",IF('Cursos IA'!H17<>"",'Cursos IA'!H17,IF('Cursos IA'!I17<>"",'Cursos IA'!I17,""))) | F56: =IF($B56="","",IF('Cursos IA'!I17="","",'Cursos IA'!I17)) | G56: =IF($B56="","",'Cursos IA'!N17) | H56: =IF(OR($B56="",$F56=""),"",IF(AND($F56>=H$6,$F56<EDATE(H$6,1)),"▼","")) | I56: =IF(OR($B56="",$F56=""),"",IF(AND($F56>=I$6,$F56<EDATE(I$6,1)),"▼","")) | J56: =IF(OR($B56="",$F56=""),"",IF(AND($F56>=J$6,$F56<EDATE(J$6,1)),"▼","")) | K56: =IF(OR($B56="",$F56=""),"",IF(AND($F56>=K$6,$F56<EDATE(K$6,1)),"▼","")) | L56: =IF(OR($B56="",$F56=""),"",IF(AND($F56>=L$6,$F56<EDATE(L$6,1)),"▼","")) | M56: =IF(OR($B56="",$F56=""),"",IF(AND($F56>=M$6,$F56<EDATE(M$6,1)),"▼","")) | N56: =IF(OR($B56="",$F56=""),"",IF(AND($F56>=N$6,$F56<EDATE(N$6,1)),"▼","")) | O56: =IF(OR($B56="",$F56=""),"",IF(AND($F56>=O$6,$F56<EDATE(O$6,1)),"▼","")) | ... S56: =IF(OR($B56="",$F56=""),"",IF(AND($F56>=S$6,$F56<EDATE(S$6,1)),"▼",""))
A57: =IF($B57="","","Cursos IA") | B57: =IF('Cursos IA'!B18="","",'Cursos IA'!B18) | C57: =IF($B57="","",IF('Cursos IA'!O18="","",'Cursos IA'!O18)) | D57: =IF($B57="","",IF('Cursos IA'!G18="","",'Cursos IA'!G18)) | E57: =IF($B57="","",IF('Cursos IA'!H18<>"",'Cursos IA'!H18,IF('Cursos IA'!I18<>"",'Cursos IA'!I18,""))) | F57: =IF($B57="","",IF('Cursos IA'!I18="","",'Cursos IA'!I18)) | G57: =IF($B57="","",'Cursos IA'!N18) | H57: =IF(OR($B57="",$F57=""),"",IF(AND($F57>=H$6,$F57<EDATE(H$6,1)),"▼","")) | I57: =IF(OR($B57="",$F57=""),"",IF(AND($F57>=I$6,$F57<EDATE(I$6,1)),"▼","")) | J57: =IF(OR($B57="",$F57=""),"",IF(AND($F57>=J$6,$F57<EDATE(J$6,1)),"▼","")) | K57: =IF(OR($B57="",$F57=""),"",IF(AND($F57>=K$6,$F57<EDATE(K$6,1)),"▼","")) | L57: =IF(OR($B57="",$F57=""),"",IF(AND($F57>=L$6,$F57<EDATE(L$6,1)),"▼","")) | M57: =IF(OR($B57="",$F57=""),"",IF(AND($F57>=M$6,$F57<EDATE(M$6,1)),"▼","")) | N57: =IF(OR($B57="",$F57=""),"",IF(AND($F57>=N$6,$F57<EDATE(N$6,1)),"▼","")) | O57: =IF(OR($B57="",$F57=""),"",IF(AND($F57>=O$6,$F57<EDATE(O$6,1)),"▼","")) | ... S57: =IF(OR($B57="",$F57=""),"",IF(AND($F57>=S$6,$F57<EDATE(S$6,1)),"▼",""))
A58: =IF($B58="","","Cursos IA") | B58: =IF('Cursos IA'!B19="","",'Cursos IA'!B19) | C58: =IF($B58="","",IF('Cursos IA'!O19="","",'Cursos IA'!O19)) | D58: =IF($B58="","",IF('Cursos IA'!G19="","",'Cursos IA'!G19)) | E58: =IF($B58="","",IF('Cursos IA'!H19<>"",'Cursos IA'!H19,IF('Cursos IA'!I19<>"",'Cursos IA'!I19,""))) | F58: =IF($B58="","",IF('Cursos IA'!I19="","",'Cursos IA'!I19)) | G58: =IF($B58="","",'Cursos IA'!N19) | H58: =IF(OR($B58="",$F58=""),"",IF(AND($F58>=H$6,$F58<EDATE(H$6,1)),"▼","")) | I58: =IF(OR($B58="",$F58=""),"",IF(AND($F58>=I$6,$F58<EDATE(I$6,1)),"▼","")) | J58: =IF(OR($B58="",$F58=""),"",IF(AND($F58>=J$6,$F58<EDATE(J$6,1)),"▼","")) | K58: =IF(OR($B58="",$F58=""),"",IF(AND($F58>=K$6,$F58<EDATE(K$6,1)),"▼","")) | L58: =IF(OR($B58="",$F58=""),"",IF(AND($F58>=L$6,$F58<EDATE(L$6,1)),"▼","")) | M58: =IF(OR($B58="",$F58=""),"",IF(AND($F58>=M$6,$F58<EDATE(M$6,1)),"▼","")) | N58: =IF(OR($B58="",$F58=""),"",IF(AND($F58>=N$6,$F58<EDATE(N$6,1)),"▼","")) | O58: =IF(OR($B58="",$F58=""),"",IF(AND($F58>=O$6,$F58<EDATE(O$6,1)),"▼","")) | ... S58: =IF(OR($B58="",$F58=""),"",IF(AND($F58>=S$6,$F58<EDATE(S$6,1)),"▼",""))
A59: RENDA EXTRA
A60: =IF($B60="","","Renda Extra") -> Renda Extra | B60: =IF('Renda Extra'!B8="","",'Renda Extra'!B8) -> Marketing de Afiliados do Zero (exemplo) | C60: =IF($B60="","",IF('Renda Extra'!O8="","",'Renda Extra'!O8)) -> Em andamento | D60: =IF($B60="","",IF('Renda Extra'!G8="","",'Renda Extra'!G8)) -> 46268 | E60: =IF($B60="","",IF('Renda Extra'!H8<>"",'Renda Extra'!H8,IF('Renda Extra'!I8<>"",'Renda Extra'!I8,""))) -> 46356 | F60: =IF($B60="","",IF('Renda Extra'!I8="","",'Renda Extra'!I8)) -> 46631 | G60: =IF($B60="","",'Renda Extra'!N8) -> 0.22222222 | H60: =IF(OR($B60="",$F60=""),"",IF(AND($F60>=H$6,$F60<EDATE(H$6,1)),"▼","")) | I60: =IF(OR($B60="",$F60=""),"",IF(AND($F60>=I$6,$F60<EDATE(I$6,1)),"▼","")) | J60: =IF(OR($B60="",$F60=""),"",IF(AND($F60>=J$6,$F60<EDATE(J$6,1)),"▼","")) | K60: =IF(OR($B60="",$F60=""),"",IF(AND($F60>=K$6,$F60<EDATE(K$6,1)),"▼","")) | L60: =IF(OR($B60="",$F60=""),"",IF(AND($F60>=L$6,$F60<EDATE(L$6,1)),"▼","")) | M60: =IF(OR($B60="",$F60=""),"",IF(AND($F60>=M$6,$F60<EDATE(M$6,1)),"▼","")) | N60: =IF(OR($B60="",$F60=""),"",IF(AND($F60>=N$6,$F60<EDATE(N$6,1)),"▼","")) | O60: =IF(OR($B60="",$F60=""),"",IF(AND($F60>=O$6,$F60<EDATE(O$6,1)),"▼","")) | ... S60: =IF(OR($B60="",$F60=""),"",IF(AND($F60>=S$6,$F60<EDATE(S$6,1)),"▼","")) -> ▼
A61: =IF($B61="","","Renda Extra") | B61: =IF('Renda Extra'!B9="","",'Renda Extra'!B9) | C61: =IF($B61="","",IF('Renda Extra'!O9="","",'Renda Extra'!O9)) | D61: =IF($B61="","",IF('Renda Extra'!G9="","",'Renda Extra'!G9)) | E61: =IF($B61="","",IF('Renda Extra'!H9<>"",'Renda Extra'!H9,IF('Renda Extra'!I9<>"",'Renda Extra'!I9,""))) | F61: =IF($B61="","",IF('Renda Extra'!I9="","",'Renda Extra'!I9)) | G61: =IF($B61="","",'Renda Extra'!N9) | H61: =IF(OR($B61="",$F61=""),"",IF(AND($F61>=H$6,$F61<EDATE(H$6,1)),"▼","")) | I61: =IF(OR($B61="",$F61=""),"",IF(AND($F61>=I$6,$F61<EDATE(I$6,1)),"▼","")) | J61: =IF(OR($B61="",$F61=""),"",IF(AND($F61>=J$6,$F61<EDATE(J$6,1)),"▼","")) | K61: =IF(OR($B61="",$F61=""),"",IF(AND($F61>=K$6,$F61<EDATE(K$6,1)),"▼","")) | L61: =IF(OR($B61="",$F61=""),"",IF(AND($F61>=L$6,$F61<EDATE(L$6,1)),"▼","")) | M61: =IF(OR($B61="",$F61=""),"",IF(AND($F61>=M$6,$F61<EDATE(M$6,1)),"▼","")) | N61: =IF(OR($B61="",$F61=""),"",IF(AND($F61>=N$6,$F61<EDATE(N$6,1)),"▼","")) | O61: =IF(OR($B61="",$F61=""),"",IF(AND($F61>=O$6,$F61<EDATE(O$6,1)),"▼","")) | ... S61: =IF(OR($B61="",$F61=""),"",IF(AND($F61>=S$6,$F61<EDATE(S$6,1)),"▼",""))
A62: =IF($B62="","","Renda Extra") | B62: =IF('Renda Extra'!B10="","",'Renda Extra'!B10) | C62: =IF($B62="","",IF('Renda Extra'!O10="","",'Renda Extra'!O10)) | D62: =IF($B62="","",IF('Renda Extra'!G10="","",'Renda Extra'!G10)) | E62: =IF($B62="","",IF('Renda Extra'!H10<>"",'Renda Extra'!H10,IF('Renda Extra'!I10<>"",'Renda Extra'!I10,""))) | F62: =IF($B62="","",IF('Renda Extra'!I10="","",'Renda Extra'!I10)) | G62: =IF($B62="","",'Renda Extra'!N10) | H62: =IF(OR($B62="",$F62=""),"",IF(AND($F62>=H$6,$F62<EDATE(H$6,1)),"▼","")) | I62: =IF(OR($B62="",$F62=""),"",IF(AND($F62>=I$6,$F62<EDATE(I$6,1)),"▼","")) | J62: =IF(OR($B62="",$F62=""),"",IF(AND($F62>=J$6,$F62<EDATE(J$6,1)),"▼","")) | K62: =IF(OR($B62="",$F62=""),"",IF(AND($F62>=K$6,$F62<EDATE(K$6,1)),"▼","")) | L62: =IF(OR($B62="",$F62=""),"",IF(AND($F62>=L$6,$F62<EDATE(L$6,1)),"▼","")) | M62: =IF(OR($B62="",$F62=""),"",IF(AND($F62>=M$6,$F62<EDATE(M$6,1)),"▼","")) | N62: =IF(OR($B62="",$F62=""),"",IF(AND($F62>=N$6,$F62<EDATE(N$6,1)),"▼","")) | O62: =IF(OR($B62="",$F62=""),"",IF(AND($F62>=O$6,$F62<EDATE(O$6,1)),"▼","")) | ... S62: =IF(OR($B62="",$F62=""),"",IF(AND($F62>=S$6,$F62<EDATE(S$6,1)),"▼",""))
A63: =IF($B63="","","Renda Extra") | B63: =IF('Renda Extra'!B11="","",'Renda Extra'!B11) | C63: =IF($B63="","",IF('Renda Extra'!O11="","",'Renda Extra'!O11)) | D63: =IF($B63="","",IF('Renda Extra'!G11="","",'Renda Extra'!G11)) | E63: =IF($B63="","",IF('Renda Extra'!H11<>"",'Renda Extra'!H11,IF('Renda Extra'!I11<>"",'Renda Extra'!I11,""))) | F63: =IF($B63="","",IF('Renda Extra'!I11="","",'Renda Extra'!I11)) | G63: =IF($B63="","",'Renda Extra'!N11) | H63: =IF(OR($B63="",$F63=""),"",IF(AND($F63>=H$6,$F63<EDATE(H$6,1)),"▼","")) | I63: =IF(OR($B63="",$F63=""),"",IF(AND($F63>=I$6,$F63<EDATE(I$6,1)),"▼","")) | J63: =IF(OR($B63="",$F63=""),"",IF(AND($F63>=J$6,$F63<EDATE(J$6,1)),"▼","")) | K63: =IF(OR($B63="",$F63=""),"",IF(AND($F63>=K$6,$F63<EDATE(K$6,1)),"▼","")) | L63: =IF(OR($B63="",$F63=""),"",IF(AND($F63>=L$6,$F63<EDATE(L$6,1)),"▼","")) | M63: =IF(OR($B63="",$F63=""),"",IF(AND($F63>=M$6,$F63<EDATE(M$6,1)),"▼","")) | N63: =IF(OR($B63="",$F63=""),"",IF(AND($F63>=N$6,$F63<EDATE(N$6,1)),"▼","")) | O63: =IF(OR($B63="",$F63=""),"",IF(AND($F63>=O$6,$F63<EDATE(O$6,1)),"▼","")) | ... S63: =IF(OR($B63="",$F63=""),"",IF(AND($F63>=S$6,$F63<EDATE(S$6,1)),"▼",""))
A64: =IF($B64="","","Renda Extra") | B64: =IF('Renda Extra'!B12="","",'Renda Extra'!B12) | C64: =IF($B64="","",IF('Renda Extra'!O12="","",'Renda Extra'!O12)) | D64: =IF($B64="","",IF('Renda Extra'!G12="","",'Renda Extra'!G12)) | E64: =IF($B64="","",IF('Renda Extra'!H12<>"",'Renda Extra'!H12,IF('Renda Extra'!I12<>"",'Renda Extra'!I12,""))) | F64: =IF($B64="","",IF('Renda Extra'!I12="","",'Renda Extra'!I12)) | G64: =IF($B64="","",'Renda Extra'!N12) | H64: =IF(OR($B64="",$F64=""),"",IF(AND($F64>=H$6,$F64<EDATE(H$6,1)),"▼","")) | I64: =IF(OR($B64="",$F64=""),"",IF(AND($F64>=I$6,$F64<EDATE(I$6,1)),"▼","")) | J64: =IF(OR($B64="",$F64=""),"",IF(AND($F64>=J$6,$F64<EDATE(J$6,1)),"▼","")) | K64: =IF(OR($B64="",$F64=""),"",IF(AND($F64>=K$6,$F64<EDATE(K$6,1)),"▼","")) | L64: =IF(OR($B64="",$F64=""),"",IF(AND($F64>=L$6,$F64<EDATE(L$6,1)),"▼","")) | M64: =IF(OR($B64="",$F64=""),"",IF(AND($F64>=M$6,$F64<EDATE(M$6,1)),"▼","")) | N64: =IF(OR($B64="",$F64=""),"",IF(AND($F64>=N$6,$F64<EDATE(N$6,1)),"▼","")) | O64: =IF(OR($B64="",$F64=""),"",IF(AND($F64>=O$6,$F64<EDATE(O$6,1)),"▼","")) | ... S64: =IF(OR($B64="",$F64=""),"",IF(AND($F64>=S$6,$F64<EDATE(S$6,1)),"▼",""))
A65: =IF($B65="","","Renda Extra") | B65: =IF('Renda Extra'!B13="","",'Renda Extra'!B13) | C65: =IF($B65="","",IF('Renda Extra'!O13="","",'Renda Extra'!O13)) | D65: =IF($B65="","",IF('Renda Extra'!G13="","",'Renda Extra'!G13)) | E65: =IF($B65="","",IF('Renda Extra'!H13<>"",'Renda Extra'!H13,IF('Renda Extra'!I13<>"",'Renda Extra'!I13,""))) | F65: =IF($B65="","",IF('Renda Extra'!I13="","",'Renda Extra'!I13)) | G65: =IF($B65="","",'Renda Extra'!N13) | H65: =IF(OR($B65="",$F65=""),"",IF(AND($F65>=H$6,$F65<EDATE(H$6,1)),"▼","")) | I65: =IF(OR($B65="",$F65=""),"",IF(AND($F65>=I$6,$F65<EDATE(I$6,1)),"▼","")) | J65: =IF(OR($B65="",$F65=""),"",IF(AND($F65>=J$6,$F65<EDATE(J$6,1)),"▼","")) | K65: =IF(OR($B65="",$F65=""),"",IF(AND($F65>=K$6,$F65<EDATE(K$6,1)),"▼","")) | L65: =IF(OR($B65="",$F65=""),"",IF(AND($F65>=L$6,$F65<EDATE(L$6,1)),"▼","")) | M65: =IF(OR($B65="",$F65=""),"",IF(AND($F65>=M$6,$F65<EDATE(M$6,1)),"▼","")) | N65: =IF(OR($B65="",$F65=""),"",IF(AND($F65>=N$6,$F65<EDATE(N$6,1)),"▼","")) | O65: =IF(OR($B65="",$F65=""),"",IF(AND($F65>=O$6,$F65<EDATE(O$6,1)),"▼","")) | ... S65: =IF(OR($B65="",$F65=""),"",IF(AND($F65>=S$6,$F65<EDATE(S$6,1)),"▼",""))
A66: =IF($B66="","","Renda Extra") | B66: =IF('Renda Extra'!B14="","",'Renda Extra'!B14) | C66: =IF($B66="","",IF('Renda Extra'!O14="","",'Renda Extra'!O14)) | D66: =IF($B66="","",IF('Renda Extra'!G14="","",'Renda Extra'!G14)) | E66: =IF($B66="","",IF('Renda Extra'!H14<>"",'Renda Extra'!H14,IF('Renda Extra'!I14<>"",'Renda Extra'!I14,""))) | F66: =IF($B66="","",IF('Renda Extra'!I14="","",'Renda Extra'!I14)) | G66: =IF($B66="","",'Renda Extra'!N14) | H66: =IF(OR($B66="",$F66=""),"",IF(AND($F66>=H$6,$F66<EDATE(H$6,1)),"▼","")) | I66: =IF(OR($B66="",$F66=""),"",IF(AND($F66>=I$6,$F66<EDATE(I$6,1)),"▼","")) | J66: =IF(OR($B66="",$F66=""),"",IF(AND($F66>=J$6,$F66<EDATE(J$6,1)),"▼","")) | K66: =IF(OR($B66="",$F66=""),"",IF(AND($F66>=K$6,$F66<EDATE(K$6,1)),"▼","")) | L66: =IF(OR($B66="",$F66=""),"",IF(AND($F66>=L$6,$F66<EDATE(L$6,1)),"▼","")) | M66: =IF(OR($B66="",$F66=""),"",IF(AND($F66>=M$6,$F66<EDATE(M$6,1)),"▼","")) | N66: =IF(OR($B66="",$F66=""),"",IF(AND($F66>=N$6,$F66<EDATE(N$6,1)),"▼","")) | O66: =IF(OR($B66="",$F66=""),"",IF(AND($F66>=O$6,$F66<EDATE(O$6,1)),"▼","")) | ... S66: =IF(OR($B66="",$F66=""),"",IF(AND($F66>=S$6,$F66<EDATE(S$6,1)),"▼",""))
A67: =IF($B67="","","Renda Extra") | B67: =IF('Renda Extra'!B15="","",'Renda Extra'!B15) | C67: =IF($B67="","",IF('Renda Extra'!O15="","",'Renda Extra'!O15)) | D67: =IF($B67="","",IF('Renda Extra'!G15="","",'Renda Extra'!G15)) | E67: =IF($B67="","",IF('Renda Extra'!H15<>"",'Renda Extra'!H15,IF('Renda Extra'!I15<>"",'Renda Extra'!I15,""))) | F67: =IF($B67="","",IF('Renda Extra'!I15="","",'Renda Extra'!I15)) | G67: =IF($B67="","",'Renda Extra'!N15) | H67: =IF(OR($B67="",$F67=""),"",IF(AND($F67>=H$6,$F67<EDATE(H$6,1)),"▼","")) | I67: =IF(OR($B67="",$F67=""),"",IF(AND($F67>=I$6,$F67<EDATE(I$6,1)),"▼","")) | J67: =IF(OR($B67="",$F67=""),"",IF(AND($F67>=J$6,$F67<EDATE(J$6,1)),"▼","")) | K67: =IF(OR($B67="",$F67=""),"",IF(AND($F67>=K$6,$F67<EDATE(K$6,1)),"▼","")) | L67: =IF(OR($B67="",$F67=""),"",IF(AND($F67>=L$6,$F67<EDATE(L$6,1)),"▼","")) | M67: =IF(OR($B67="",$F67=""),"",IF(AND($F67>=M$6,$F67<EDATE(M$6,1)),"▼","")) | N67: =IF(OR($B67="",$F67=""),"",IF(AND($F67>=N$6,$F67<EDATE(N$6,1)),"▼","")) | O67: =IF(OR($B67="",$F67=""),"",IF(AND($F67>=O$6,$F67<EDATE(O$6,1)),"▼","")) | ... S67: =IF(OR($B67="",$F67=""),"",IF(AND($F67>=S$6,$F67<EDATE(S$6,1)),"▼",""))
A68: =IF($B68="","","Renda Extra") | B68: =IF('Renda Extra'!B16="","",'Renda Extra'!B16) | C68: =IF($B68="","",IF('Renda Extra'!O16="","",'Renda Extra'!O16)) | D68: =IF($B68="","",IF('Renda Extra'!G16="","",'Renda Extra'!G16)) | E68: =IF($B68="","",IF('Renda Extra'!H16<>"",'Renda Extra'!H16,IF('Renda Extra'!I16<>"",'Renda Extra'!I16,""))) | F68: =IF($B68="","",IF('Renda Extra'!I16="","",'Renda Extra'!I16)) | G68: =IF($B68="","",'Renda Extra'!N16) | H68: =IF(OR($B68="",$F68=""),"",IF(AND($F68>=H$6,$F68<EDATE(H$6,1)),"▼","")) | I68: =IF(OR($B68="",$F68=""),"",IF(AND($F68>=I$6,$F68<EDATE(I$6,1)),"▼","")) | J68: =IF(OR($B68="",$F68=""),"",IF(AND($F68>=J$6,$F68<EDATE(J$6,1)),"▼","")) | K68: =IF(OR($B68="",$F68=""),"",IF(AND($F68>=K$6,$F68<EDATE(K$6,1)),"▼","")) | L68: =IF(OR($B68="",$F68=""),"",IF(AND($F68>=L$6,$F68<EDATE(L$6,1)),"▼","")) | M68: =IF(OR($B68="",$F68=""),"",IF(AND($F68>=M$6,$F68<EDATE(M$6,1)),"▼","")) | N68: =IF(OR($B68="",$F68=""),"",IF(AND($F68>=N$6,$F68<EDATE(N$6,1)),"▼","")) | O68: =IF(OR($B68="",$F68=""),"",IF(AND($F68>=O$6,$F68<EDATE(O$6,1)),"▼","")) | ... S68: =IF(OR($B68="",$F68=""),"",IF(AND($F68>=S$6,$F68<EDATE(S$6,1)),"▼",""))
A69: =IF($B69="","","Renda Extra") | B69: =IF('Renda Extra'!B17="","",'Renda Extra'!B17) | C69: =IF($B69="","",IF('Renda Extra'!O17="","",'Renda Extra'!O17)) | D69: =IF($B69="","",IF('Renda Extra'!G17="","",'Renda Extra'!G17)) | E69: =IF($B69="","",IF('Renda Extra'!H17<>"",'Renda Extra'!H17,IF('Renda Extra'!I17<>"",'Renda Extra'!I17,""))) | F69: =IF($B69="","",IF('Renda Extra'!I17="","",'Renda Extra'!I17)) | G69: =IF($B69="","",'Renda Extra'!N17) | H69: =IF(OR($B69="",$F69=""),"",IF(AND($F69>=H$6,$F69<EDATE(H$6,1)),"▼","")) | I69: =IF(OR($B69="",$F69=""),"",IF(AND($F69>=I$6,$F69<EDATE(I$6,1)),"▼","")) | J69: =IF(OR($B69="",$F69=""),"",IF(AND($F69>=J$6,$F69<EDATE(J$6,1)),"▼","")) | K69: =IF(OR($B69="",$F69=""),"",IF(AND($F69>=K$6,$F69<EDATE(K$6,1)),"▼","")) | L69: =IF(OR($B69="",$F69=""),"",IF(AND($F69>=L$6,$F69<EDATE(L$6,1)),"▼","")) | M69: =IF(OR($B69="",$F69=""),"",IF(AND($F69>=M$6,$F69<EDATE(M$6,1)),"▼","")) | N69: =IF(OR($B69="",$F69=""),"",IF(AND($F69>=N$6,$F69<EDATE(N$6,1)),"▼","")) | O69: =IF(OR($B69="",$F69=""),"",IF(AND($F69>=O$6,$F69<EDATE(O$6,1)),"▼","")) | ... S69: =IF(OR($B69="",$F69=""),"",IF(AND($F69>=S$6,$F69<EDATE(S$6,1)),"▼",""))
A70: =IF($B70="","","Renda Extra") | B70: =IF('Renda Extra'!B18="","",'Renda Extra'!B18) | C70: =IF($B70="","",IF('Renda Extra'!O18="","",'Renda Extra'!O18)) | D70: =IF($B70="","",IF('Renda Extra'!G18="","",'Renda Extra'!G18)) | E70: =IF($B70="","",IF('Renda Extra'!H18<>"",'Renda Extra'!H18,IF('Renda Extra'!I18<>"",'Renda Extra'!I18,""))) | F70: =IF($B70="","",IF('Renda Extra'!I18="","",'Renda Extra'!I18)) | G70: =IF($B70="","",'Renda Extra'!N18) | H70: =IF(OR($B70="",$F70=""),"",IF(AND($F70>=H$6,$F70<EDATE(H$6,1)),"▼","")) | I70: =IF(OR($B70="",$F70=""),"",IF(AND($F70>=I$6,$F70<EDATE(I$6,1)),"▼","")) | J70: =IF(OR($B70="",$F70=""),"",IF(AND($F70>=J$6,$F70<EDATE(J$6,1)),"▼","")) | K70: =IF(OR($B70="",$F70=""),"",IF(AND($F70>=K$6,$F70<EDATE(K$6,1)),"▼","")) | L70: =IF(OR($B70="",$F70=""),"",IF(AND($F70>=L$6,$F70<EDATE(L$6,1)),"▼","")) | M70: =IF(OR($B70="",$F70=""),"",IF(AND($F70>=M$6,$F70<EDATE(M$6,1)),"▼","")) | N70: =IF(OR($B70="",$F70=""),"",IF(AND($F70>=N$6,$F70<EDATE(N$6,1)),"▼","")) | O70: =IF(OR($B70="",$F70=""),"",IF(AND($F70>=O$6,$F70<EDATE(O$6,1)),"▼","")) | ... S70: =IF(OR($B70="",$F70=""),"",IF(AND($F70>=S$6,$F70<EDATE(S$6,1)),"▼",""))
A71: =IF($B71="","","Renda Extra") | B71: =IF('Renda Extra'!B19="","",'Renda Extra'!B19) | C71: =IF($B71="","",IF('Renda Extra'!O19="","",'Renda Extra'!O19)) | D71: =IF($B71="","",IF('Renda Extra'!G19="","",'Renda Extra'!G19)) | E71: =IF($B71="","",IF('Renda Extra'!H19<>"",'Renda Extra'!H19,IF('Renda Extra'!I19<>"",'Renda Extra'!I19,""))) | F71: =IF($B71="","",IF('Renda Extra'!I19="","",'Renda Extra'!I19)) | G71: =IF($B71="","",'Renda Extra'!N19) | H71: =IF(OR($B71="",$F71=""),"",IF(AND($F71>=H$6,$F71<EDATE(H$6,1)),"▼","")) | I71: =IF(OR($B71="",$F71=""),"",IF(AND($F71>=I$6,$F71<EDATE(I$6,1)),"▼","")) | J71: =IF(OR($B71="",$F71=""),"",IF(AND($F71>=J$6,$F71<EDATE(J$6,1)),"▼","")) | K71: =IF(OR($B71="",$F71=""),"",IF(AND($F71>=K$6,$F71<EDATE(K$6,1)),"▼","")) | L71: =IF(OR($B71="",$F71=""),"",IF(AND($F71>=L$6,$F71<EDATE(L$6,1)),"▼","")) | M71: =IF(OR($B71="",$F71=""),"",IF(AND($F71>=M$6,$F71<EDATE(M$6,1)),"▼","")) | N71: =IF(OR($B71="",$F71=""),"",IF(AND($F71>=N$6,$F71<EDATE(N$6,1)),"▼","")) | O71: =IF(OR($B71="",$F71=""),"",IF(AND($F71>=O$6,$F71<EDATE(O$6,1)),"▼","")) | ... S71: =IF(OR($B71="",$F71=""),"",IF(AND($F71>=S$6,$F71<EDATE(S$6,1)),"▼",""))

Sheet Pós-graduação
A1: PÓS-GRADUAÇÃO
A2: MBAs, especializações, mestrado e extensões · acompanhe disciplinas, acesso e investimento | R2: ← Voltar ao Início
B4: Itens | D4: Em andamento | F4: Concluídos | H4: Investido | J4: Progresso médio | L4: Acessos a vencer
B5: =COUNTA(B8:B47) -> 1 | D5: =COUNTIF(O8:O47,"Em andamento") -> 1 | F5: =COUNTIF(O8:O47,"Concluído") -> 0 | H5: =SUM(F8:F47) -> 12600 | J5: =IFERROR(AVERAGE(N8:N47),0) -> 0.1 | L5: =COUNTIF(K8:K47,"Vence em breve") -> 0
A6: Células cinza = automáticas (não edite) · Linha 8 = exemplo: substitua ou apague · Escolha Status e Prioridade na seta da célula
A7: ID | B7: Curso / Pós-graduação | C7: Instituição | D7: Modalidade | E7: Data da compra | F7: Valor pago (R$) | G7: Data de início | H7: Término previsto | I7: Vencimento do acesso | J7: Dias p/ vencer | K7: Situação do acesso | L7: Disciplinas (total) | M7: Disciplinas concluídas | N7: % Andamento | O7: Status | P7: Prioridade | Q7: Login | R7: Senha | S7: Link de acesso | T7: Observações
A8: =IF($B8="","","PG-"&TEXT(ROW()-7,"00")) -> PG-01 | B8: MBA em Inteligência Artificial (exemplo) | C8: Universidade Exemplo | D8: EAD | E8: 46244 | F8: 12600 | G8: 46266 | H8: 46813 | I8: 46997 | J8: =IF(OR($B8="",$I8=""),"",$I8-TODAY()) -> 699 | K8: =IF($B8="","",IF($I8="","Vitalício / sem prazo",IF($J8<0,"Vencido",IF($J8<=Listas!$G$4,"Vence em breve","Ativo")))) -> Ativo | L8: 20 | M8: 2 | N8: =IF($B8="","",IF(N($L8)=0,0,MIN(1,N($M8)/$L8))) -> 0.1 | O8: Em andamento | P8: Alta | Q8: seu.email@exemplo.com | R8: (guarde no gerenciador de senhas) | S8: https://portal.exemplo.com | T8: Linha de exemplo — substitua pelos seus dados.
A9: =IF($B9="","","PG-"&TEXT(ROW()-7,"00")) | J9: =IF(OR($B9="",$I9=""),"",$I9-TODAY()) | K9: =IF($B9="","",IF($I9="","Vitalício / sem prazo",IF($J9<0,"Vencido",IF($J9<=Listas!$G$4,"Vence em breve","Ativo")))) | N9: =IF($B9="","",IF(N($L9)=0,0,MIN(1,N($M9)/$L9)))
A10: =IF($B10="","","PG-"&TEXT(ROW()-7,"00")) | J10: =IF(OR($B10="",$I10=""),"",$I10-TODAY()) | K10: =IF($B10="","",IF($I10="","Vitalício / sem prazo",IF($J10<0,"Vencido",IF($J10<=Listas!$G$4,"Vence em breve","Ativo")))) | N10: =IF($B10="","",IF(N($L10)=0,0,MIN(1,N($M10)/$L10)))
A11: =IF($B11="","","PG-"&TEXT(ROW()-7,"00")) | J11: =IF(OR($B11="",$I11=""),"",$I11-TODAY()) | K11: =IF($B11="","",IF($I11="","Vitalício / sem prazo",IF($J11<0,"Vencido",IF($J11<=Listas!$G$4,"Vence em breve","Ativo")))) | N11: =IF($B11="","",IF(N($L11)=0,0,MIN(1,N($M11)/$L11)))
A12: =IF($B12="","","PG-"&TEXT(ROW()-7,"00")) | J12: =IF(OR($B12="",$I12=""),"",$I12-TODAY()) | K12: =IF($B12="","",IF($I12="","Vitalício / sem prazo",IF($J12<0,"Vencido",IF($J12<=Listas!$G$4,"Vence em breve","Ativo")))) | N12: =IF($B12="","",IF(N($L12)=0,0,MIN(1,N($M12)/$L12)))
A13: =IF($B13="","","PG-"&TEXT(ROW()-7,"00")) | J13: =IF(OR($B13="",$I13=""),"",$I13-TODAY()) | K13: =IF($B13="","",IF($I13="","Vitalício / sem prazo",IF($J13<0,"Vencido",IF($J13<=Listas!$G$4,"Vence em breve","Ativo")))) | N13: =IF($B13="","",IF(N($L13)=0,0,MIN(1,N($M13)/$L13)))
A14: =IF($B14="","","PG-"&TEXT(ROW()-7,"00")) | J14: =IF(OR($B14="",$I14=""),"",$I14-TODAY()) | K14: =IF($B14="","",IF($I14="","Vitalício / sem prazo",IF($J14<0,"Vencido",IF($J14<=Listas!$G$4,"Vence em breve","Ativo")))) | N14: =IF($B14="","",IF(N($L14)=0,0,MIN(1,N($M14)/$L14)))
A15: =IF($B15="","","PG-"&TEXT(ROW()-7,"00")) | J15: =IF(OR($B15="",$I15=""),"",$I15-TODAY()) | K15: =IF($B15="","",IF($I15="","Vitalício / sem prazo",IF($J15<0,"Vencido",IF($J15<=Listas!$G$4,"Vence em breve","Ativo")))) | N15: =IF($B15="","",IF(N($L15)=0,0,MIN(1,N($M15)/$L15)))
A16: =IF($B16="","","PG-"&TEXT(ROW()-7,"00")) | J16: =IF(OR($B16="",$I16=""),"",$I16-TODAY()) | K16: =IF($B16="","",IF($I16="","Vitalício / sem prazo",IF($J16<0,"Vencido",IF($J16<=Listas!$G$4,"Vence em breve","Ativo")))) | N16: =IF($B16="","",IF(N($L16)=0,0,MIN(1,N($M16)/$L16)))
A17: =IF($B17="","","PG-"&TEXT(ROW()-7,"00")) | J17: =IF(OR($B17="",$I17=""),"",$I17-TODAY()) | K17: =IF($B17="","",IF($I17="","Vitalício / sem prazo",IF($J17<0,"Vencido",IF($J17<=Listas!$G$4,"Vence em breve","Ativo")))) | N17: =IF($B17="","",IF(N($L17)=0,0,MIN(1,N($M17)/$L17)))
A18: =IF($B18="","","PG-"&TEXT(ROW()-7,"00")) | J18: =IF(OR($B18="",$I18=""),"",$I18-TODAY()) | K18: =IF($B18="","",IF($I18="","Vitalício / sem prazo",IF($J18<0,"Vencido",IF($J18<=Listas!$G$4,"Vence em breve","Ativo")))) | N18: =IF($B18="","",IF(N($L18)=0,0,MIN(1,N($M18)/$L18)))
A19: =IF($B19="","","PG-"&TEXT(ROW()-7,"00")) | J19: =IF(OR($B19="",$I19=""),"",$I19-TODAY()) | K19: =IF($B19="","",IF($I19="","Vitalício / sem prazo",IF($J19<0,"Vencido",IF($J19<=Listas!$G$4,"Vence em breve","Ativo")))) | N19: =IF($B19="","",IF(N($L19)=0,0,MIN(1,N($M19)/$L19)))
A20: =IF($B20="","","PG-"&TEXT(ROW()-7,"00")) | J20: =IF(OR($B20="",$I20=""),"",$I20-TODAY()) | K20: =IF($B20="","",IF($I20="","Vitalício / sem prazo",IF($J20<0,"Vencido",IF($J20<=Listas!$G$4,"Vence em breve","Ativo")))) | N20: =IF($B20="","",IF(N($L20)=0,0,MIN(1,N($M20)/$L20)))
... A47: =IF($B47="","","PG-"&TEXT(ROW()-7,"00")) | J47: =IF(OR($B47="",$I47=""),"",$I47-TODAY()) | K47: =IF($B47="","",IF($I47="","Vitalício / sem prazo",IF($J47<0,"Vencido",IF($J47<=Listas!$G$4,"Vence em breve","Ativo")))) | N47: =IF($B47="","",IF(N($L47)=0,0,MIN(1,N($M47)/$L47)))

Sheet Concurso
A1: CONCURSOS PÚBLICOS
A2: Cursos preparatórios, bancos de questões e materiais · vincule cada curso ao concurso-alvo | T2: ← Voltar ao Início
B4: Itens | D4: Em andamento | F4: Concluídos | H4: Investido | J4: Progresso médio | L4: Acessos a vencer
B5: =COUNTA(B8:B47) -> 1 | D5: =COUNTIF(Q8:Q47,"Em andamento") -> 1 | F5: =COUNTIF(Q8:Q47,"Concluído") -> 0 | H5: =SUM(H8:H47) -> 1490 | J5: =IFERROR(AVERAGE(P8:P47),0) -> 0.25 | L5: =COUNTIF(M8:M47,"Vence em breve") -> 0
A6: Células cinza = automáticas (não edite) · Linha 8 = exemplo: substitua ou apague · Escolha Status e Prioridade na seta da célula
A7: ID | B7: Curso / Material | C7: Plataforma / Instituição | D7: Concurso / Cargo alvo | E7: Banca | F7: Data da prova | G7: Data da compra | H7: Valor pago (R$) | I7: Data de início | J7: Término previsto | K7: Vencimento do acesso | L7: Dias p/ vencer | M7: Situação do acesso | N7: Aulas / Tópicos (total) | O7: Aulas / Tópicos concluídos | P7: % Andamento | Q7: Status | R7: Prioridade | S7: Login | T7: Senha | U7: Link de acesso | V7: Observações
A8: =IF($B8="","","CO-"&TEXT(ROW()-7,"00")) -> CO-01 | B8: Curso Preparatório Completo (exemplo) | C8: Plataforma Exemplo | D8: Analista — Órgão Exemplo | E8: CEBRASPE | F8: 46460 | G8: 46270 | H8: 1490 | I8: 46280 | J8: 46446 | K8: 46568 | L8: =IF(OR($B8="",$K8=""),"",$K8-TODAY()) -> 270 | M8: =IF($B8="","",IF($K8="","Vitalício / sem prazo",IF($L8<0,"Vencido",IF($L8<=Listas!$G$4,"Vence em breve","Ativo")))) -> Ativo | N8: 180 | O8: 45 | P8: =IF($B8="","",IF(N($N8)=0,0,MIN(1,N($O8)/$N8))) -> 0.25 | Q8: Em andamento | R8: Alta | S8: seu.email@exemplo.com | T8: (guarde no gerenciador de senhas) | U8: https://plataforma.exemplo.com | V8: Linha de exemplo — substitua pelos seus dados.
A9: =IF($B9="","","CO-"&TEXT(ROW()-7,"00")) | L9: =IF(OR($B9="",$K9=""),"",$K9-TODAY()) | M9: =IF($B9="","",IF($K9="","Vitalício / sem prazo",IF($L9<0,"Vencido",IF($L9<=Listas!$G$4,"Vence em breve","Ativo")))) | P9: =IF($B9="","",IF(N($N9)=0,0,MIN(1,N($O9)/$N9)))
A10: =IF($B10="","","CO-"&TEXT(ROW()-7,"00")) | L10: =IF(OR($B10="",$K10=""),"",$K10-TODAY()) | M10: =IF($B10="","",IF($K10="","Vitalício / sem prazo",IF($L10<0,"Vencido",IF($L10<=Listas!$G$4,"Vence em breve","Ativo")))) | P10: =IF($B10="","",IF(N($N10)=0,0,MIN(1,N($O10)/$N10)))
A11: =IF($B11="","","CO-"&TEXT(ROW()-7,"00")) | L11: =IF(OR($B11="",$K11=""),"",$K11-TODAY()) | M11: =IF($B11="","",IF($K11="","Vitalício / sem prazo",IF($L11<0,"Vencido",IF($L11<=Listas!$G$4,"Vence em breve","Ativo")))) | P11: =IF($B11="","",IF(N($N11)=0,0,MIN(1,N($O11)/$N11)))
A12: =IF($B12="","","CO-"&TEXT(ROW()-7,"00")) | L12: =IF(OR($B12="",$K12=""),"",$K12-TODAY()) | M12: =IF($B12="","",IF($K12="","Vitalício / sem prazo",IF($L12<0,"Vencido",IF($L12<=Listas!$G$4,"Vence em breve","Ativo")))) | P12: =IF($B12="","",IF(N($N12)=0,0,MIN(1,N($O12)/$N12)))
A13: =IF($B13="","","CO-"&TEXT(ROW()-7,"00")) | L13: =IF(OR($B13="",$K13=""),"",$K13-TODAY()) | M13: =IF($B13="","",IF($K13="","Vitalício / sem prazo",IF($L13<0,"Vencido",IF($L13<=Listas!$G$4,"Vence em breve","Ativo")))) | P13: =IF($B13="","",IF(N($N13)=0,0,MIN(1,N($O13)/$N13)))
A14: =IF($B14="","","CO-"&TEXT(ROW()-7,"00")) | L14: =IF(OR($B14="",$K14=""),"",$K14-TODAY()) | M14: =IF($B14="","",IF($K14="","Vitalício / sem prazo",IF($L14<0,"Vencido",IF($L14<=Listas!$G$4,"Vence em breve","Ativo")))) | P14: =IF($B14="","",IF(N($N14)=0,0,MIN(1,N($O14)/$N14)))
A15: =IF($B15="","","CO-"&TEXT(ROW()-7,"00")) | L15: =IF(OR($B15="",$K15=""),"",$K15-TODAY()) | M15: =IF($B15="","",IF($K15="","Vitalício / sem prazo",IF($L15<0,"Vencido",IF($L15<=Listas!$G$4,"Vence em breve","Ativo")))) | P15: =IF($B15="","",IF(N($N15)=0,0,MIN(1,N($O15)/$N15)))
A16: =IF($B16="","","CO-"&TEXT(ROW()-7,"00")) | L16: =IF(OR($B16="",$K16=""),"",$K16-TODAY()) | M16: =IF($B16="","",IF($K16="","Vitalício / sem prazo",IF($L16<0,"Vencido",IF($L16<=Listas!$G$4,"Vence em breve","Ativo")))) | P16: =IF($B16="","",IF(N($N16)=0,0,MIN(1,N($O16)/$N16)))
A17: =IF($B17="","","CO-"&TEXT(ROW()-7,"00")) | L17: =IF(OR($B17="",$K17=""),"",$K17-TODAY()) | M17: =IF($B17="","",IF($K17="","Vitalício / sem prazo",IF($L17<0,"Vencido",IF($L17<=Listas!$G$4,"Vence em breve","Ativo")))) | P17: =IF($B17="","",IF(N($N17)=0,0,MIN(1,N($O17)/$N17)))
A18: =IF($B18="","","CO-"&TEXT(ROW()-7,"00")) | L18: =IF(OR($B18="",$K18=""),"",$K18-TODAY()) | M18: =IF($B18="","",IF($K18="","Vitalício / sem prazo",IF($L18<0,"Vencido",IF($L18<=Listas!$G$4,"Vence em breve","Ativo")))) | P18: =IF($B18="","",IF(N($N18)=0,0,MIN(1,N($O18)/$N18)))
A19: =IF($B19="","","CO-"&TEXT(ROW()-7,"00")) | L19: =IF(OR($B19="",$K19=""),"",$K19-TODAY()) | M19: =IF($B19="","",IF($K19="","Vitalício / sem prazo",IF($L19<0,"Vencido",IF($L19<=Listas!$G$4,"Vence em breve","Ativo")))) | P19: =IF($B19="","",IF(N($N19)=0,0,MIN(1,N($O19)/$N19)))
A20: =IF($B20="","","CO-"&TEXT(ROW()-7,"00")) | L20: =IF(OR($B20="",$K20=""),"",$K20-TODAY()) | M20: =IF($B20="","",IF($K20="","Vitalício / sem prazo",IF($L20<0,"Vencido",IF($L20<=Listas!$G$4,"Vence em breve","Ativo")))) | P20: =IF($B20="","",IF(N($N20)=0,0,MIN(1,N($O20)/$N20)))
... A47: =IF($B47="","","CO-"&TEXT(ROW()-7,"00")) | L47: =IF(OR($B47="",$K47=""),"",$K47-TODAY()) | M47: =IF($B47="","",IF($K47="","Vitalício / sem prazo",IF($L47<0,"Vencido",IF($L47<=Listas!$G$4,"Vence em breve","Ativo")))) | P47: =IF($B47="","",IF(N($N47)=0,0,MIN(1,N($O47)/$N47)))

Sheet Livros
A1: LIVROS
A2: Biblioteca de leitura · páginas lidas, formato, nota e previsão de término | P2: ← Voltar ao Início
B4: Itens | D4: Em andamento | F4: Concluídos | H4: Investido | J4: Progresso médio | L4: Páginas lidas
B5: =COUNTA(B8:B47) -> 1 | D5: =COUNTIF(N8:N47,"Em andamento") -> 1 | F5: =COUNTIF(N8:N47,"Concluído") -> 0 | H5: =SUM(H8:H47) -> 49.9 | J5: =IFERROR(AVERAGE(M8:M47),0) -> 0.375 | L5: =SUM(L8:L47) -> 120
A6: Células cinza = automáticas (não edite) · Linha 8 = exemplo: substitua ou apague · Escolha Status e Prioridade na seta da célula
A7: ID | B7: Título | C7: Autor(a) | D7: Tema / Categoria | E7: Editora / Loja | F7: Formato | G7: Data da compra | H7: Valor pago (R$) | I7: Data de início | J7: Término previsto | K7: Páginas (total) | L7: Páginas lidas | M7: % Andamento | N7: Status | O7: Prioridade | P7: Nota (1–5) | Q7: Link / Onde está | R7: Observações
A8: =IF($B8="","","LV-"&TEXT(ROW()-7,"00")) -> LV-01 | B8: Hábitos Atômicos (exemplo) | C8: James Clear | D8: Produtividade | E8: Livraria Exemplo | F8: Físico | G8: 46285 | H8: 49.9 | I8: 46290 | J8: 46341 | K8: 320 | L8: 120 | M8: =IF($B8="","",IF(N($K8)=0,0,MIN(1,N($L8)/$K8))) -> 0.375 | N8: Em andamento | O8: Média | Q8: Estante — prateleira 2 | R8: Linha de exemplo — substitua pelos seus dados.
A9: =IF($B9="","","LV-"&TEXT(ROW()-7,"00")) | M9: =IF($B9="","",IF(N($K9)=0,0,MIN(1,N($L9)/$K9)))
A10: =IF($B10="","","LV-"&TEXT(ROW()-7,"00")) | M10: =IF($B10="","",IF(N($K10)=0,0,MIN(1,N($L10)/$K10)))
A11: =IF($B11="","","LV-"&TEXT(ROW()-7,"00")) | M11: =IF($B11="","",IF(N($K11)=0,0,MIN(1,N($L11)/$K11)))
A12: =IF($B12="","","LV-"&TEXT(ROW()-7,"00")) | M12: =IF($B12="","",IF(N($K12)=0,0,MIN(1,N($L12)/$K12)))
A13: =IF($B13="","","LV-"&TEXT(ROW()-7,"00")) | M13: =IF($B13="","",IF(N($K13)=0,0,MIN(1,N($L13)/$K13)))
A14: =IF($B14="","","LV-"&TEXT(ROW()-7,"00")) | M14: =IF($B14="","",IF(N($K14)=0,0,MIN(1,N($L14)/$K14)))
A15: =IF($B15="","","LV-"&TEXT(ROW()-7,"00")) | M15: =IF($B15="","",IF(N($K15)=0,0,MIN(1,N($L15)/$K15)))
A16: =IF($B16="","","LV-"&TEXT(ROW()-7,"00")) | M16: =IF($B16="","",IF(N($K16)=0,0,MIN(1,N($L16)/$K16)))
A17: =IF($B17="","","LV-"&TEXT(ROW()-7,"00")) | M17: =IF($B17="","",IF(N($K17)=0,0,MIN(1,N($L17)/$K17)))
A18: =IF($B18="","","LV-"&TEXT(ROW()-7,"00")) | M18: =IF($B18="","",IF(N($K18)=0,0,MIN(1,N($L18)/$K18)))
A19: =IF($B19="","","LV-"&TEXT(ROW()-7,"00")) | M19: =IF($B19="","",IF(N($K19)=0,0,MIN(1,N($L19)/$K19)))
A20: =IF($B20="","","LV-"&TEXT(ROW()-7,"00")) | M20: =IF($B20="","",IF(N($K20)=0,0,MIN(1,N($L20)/$K20)))
... A47: =IF($B47="","","LV-"&TEXT(ROW()-7,"00")) | M47: =IF($B47="","",IF(N($K47)=0,0,MIN(1,N($L47)/$K47)))

Sheet Cursos IA
A1: CURSOS · FOCO EM IA
A2: Inteligência artificial, agentes, automação e ferramentas · do aprendizado à aplicação | R2: ← Voltar ao Início
B4: Itens | D4: Em andamento | F4: Concluídos | H4: Investido | J4: Progresso médio | L4: Acessos a vencer
B5: =COUNTA(B8:B47) -> 1 | D5: =COUNTIF(O8:O47,"Em andamento") -> 1 | F5: =COUNTIF(O8:O47,"Concluído") -> 0 | H5: =SUM(F8:F47) -> 497 | J5: =IFERROR(AVERAGE(N8:N47),0) -> 0.3 | L5: =COUNTIF(K8:K47,"Vence em breve") -> 0
A6: Células cinza = automáticas (não edite) · Linha 8 = exemplo: substitua ou apague · Escolha Status e Prioridade na seta da célula
A7: ID | B7: Curso | C7: Instituição / Plataforma | D7: Foco / Ferramenta | E7: Data da compra | F7: Valor pago (R$) | G7: Data de início | H7: Término previsto | I7: Vencimento do acesso | J7: Dias p/ vencer | K7: Situação do acesso | L7: Aulas (total) | M7: Aulas concluídas | N7: % Andamento | O7: Status | P7: Prioridade | Q7: Login | R7: Senha | S7: Link de acesso | T7: Observações
A8: =IF($B8="","","IA-"&TEXT(ROW()-7,"00")) -> IA-01 | B8: Agentes de IA na Prática (exemplo) | C8: Plataforma Exemplo | D8: Agentes · automação | E8: 46277 | F8: 497 | G8: 46285 | H8: 46376 | I8: 46642 | J8: =IF(OR($B8="",$I8=""),"",$I8-TODAY()) -> 344 | K8: =IF($B8="","",IF($I8="","Vitalício / sem prazo",IF($J8<0,"Vencido",IF($J8<=Listas!$G$4,"Vence em breve","Ativo")))) -> Ativo | L8: 60 | M8: 18 | N8: =IF($B8="","",IF(N($L8)=0,0,MIN(1,N($M8)/$L8))) -> 0.3 | O8: Em andamento | P8: Alta | Q8: seu.email@exemplo.com | R8: (guarde no gerenciador de senhas) | S8: https://plataforma.exemplo.com | T8: Linha de exemplo — substitua pelos seus dados.
A9: =IF($B9="","","IA-"&TEXT(ROW()-7,"00")) | J9: =IF(OR($B9="",$I9=""),"",$I9-TODAY()) | K9: =IF($B9="","",IF($I9="","Vitalício / sem prazo",IF($J9<0,"Vencido",IF($J9<=Listas!$G$4,"Vence em breve","Ativo")))) | N9: =IF($B9="","",IF(N($L9)=0,0,MIN(1,N($M9)/$L9)))
A10: =IF($B10="","","IA-"&TEXT(ROW()-7,"00")) | J10: =IF(OR($B10="",$I10=""),"",$I10-TODAY()) | K10: =IF($B10="","",IF($I10="","Vitalício / sem prazo",IF($J10<0,"Vencido",IF($J10<=Listas!$G$4,"Vence em breve","Ativo")))) | N10: =IF($B10="","",IF(N($L10)=0,0,MIN(1,N($M10)/$L10)))
A11: =IF($B11="","","IA-"&TEXT(ROW()-7,"00")) | J11: =IF(OR($B11="",$I11=""),"",$I11-TODAY()) | K11: =IF($B11="","",IF($I11="","Vitalício / sem prazo",IF($J11<0,"Vencido",IF($J11<=Listas!$G$4,"Vence em breve","Ativo")))) | N11: =IF($B11="","",IF(N($L11)=0,0,MIN(1,N($M11)/$L11)))
A12: =IF($B12="","","IA-"&TEXT(ROW()-7,"00")) | J12: =IF(OR($B12="",$I12=""),"",$I12-TODAY()) | K12: =IF($B12="","",IF($I12="","Vitalício / sem prazo",IF($J12<0,"Vencido",IF($J12<=Listas!$G$4,"Vence em breve","Ativo")))) | N12: =IF($B12="","",IF(N($L12)=0,0,MIN(1,N($M12)/$L12)))
A13: =IF($B13="","","IA-"&TEXT(ROW()-7,"00")) | J13: =IF(OR($B13="",$I13=""),"",$I13-TODAY()) | K13: =IF($B13="","",IF($I13="","Vitalício / sem prazo",IF($J13<0,"Vencido",IF($J13<=Listas!$G$4,"Vence em breve","Ativo")))) | N13: =IF($B13="","",IF(N($L13)=0,0,MIN(1,N($M13)/$L13)))
A14: =IF($B14="","","IA-"&TEXT(ROW()-7,"00")) | J14: =IF(OR($B14="",$I14=""),"",$I14-TODAY()) | K14: =IF($B14="","",IF($I14="","Vitalício / sem prazo",IF($J14<0,"Vencido",IF($J14<=Listas!$G$4,"Vence em breve","Ativo")))) | N14: =IF($B14="","",IF(N($L14)=0,0,MIN(1,N($M14)/$L14)))
A15: =IF($B15="","","IA-"&TEXT(ROW()-7,"00")) | J15: =IF(OR($B15="",$I15=""),"",$I15-TODAY()) | K15: =IF($B15="","",IF($I15="","Vitalício / sem prazo",IF($J15<0,"Vencido",IF($J15<=Listas!$G$4,"Vence em breve","Ativo")))) | N15: =IF($B15="","",IF(N($L15)=0,0,MIN(1,N($M15)/$L15)))
A16: =IF($B16="","","IA-"&TEXT(ROW()-7,"00")) | J16: =IF(OR($B16="",$I16=""),"",$I16-TODAY()) | K16: =IF($B16="","",IF($I16="","Vitalício / sem prazo",IF($J16<0,"Vencido",IF($J16<=Listas!$G$4,"Vence em breve","Ativo")))) | N16: =IF($B16="","",IF(N($L16)=0,0,MIN(1,N($M16)/$L16)))
A17: =IF($B17="","","IA-"&TEXT(ROW()-7,"00")) | J17: =IF(OR($B17="",$I17=""),"",$I17-TODAY()) | K17: =IF($B17="","",IF($I17="","Vitalício / sem prazo",IF($J17<0,"Vencido",IF($J17<=Listas!$G$4,"Vence em breve","Ativo")))) | N17: =IF($B17="","",IF(N($L17)=0,0,MIN(1,N($M17)/$L17)))
A18: =IF($B18="","","IA-"&TEXT(ROW()-7,"00")) | J18: =IF(OR($B18="",$I18=""),"",$I18-TODAY()) | K18: =IF($B18="","",IF($I18="","Vitalício / sem prazo",IF($J18<0,"Vencido",IF($J18<=Listas!$G$4,"Vence em breve","Ativo")))) | N18: =IF($B18="","",IF(N($L18)=0,0,MIN(1,N($M18)/$L18)))
A19: =IF($B19="","","IA-"&TEXT(ROW()-7,"00")) | J19: =IF(OR($B19="",$I19=""),"",$I19-TODAY()) | K19: =IF($B19="","",IF($I19="","Vitalício / sem prazo",IF($J19<0,"Vencido",IF($J19<=Listas!$G$4,"Vence em breve","Ativo")))) | N19: =IF($B19="","",IF(N($L19)=0,0,MIN(1,N($M19)/$L19)))
A20: =IF($B20="","","IA-"&TEXT(ROW()-7,"00")) | J20: =IF(OR($B20="",$I20=""),"",$I20-TODAY()) | K20: =IF($B20="","",IF($I20="","Vitalício / sem prazo",IF($J20<0,"Vencido",IF($J20<=Listas!$G$4,"Vence em breve","Ativo")))) | N20: =IF($B20="","",IF(N($L20)=0,0,MIN(1,N($M20)/$L20)))
... A47: =IF($B47="","","IA-"&TEXT(ROW()-7,"00")) | J47: =IF(OR($B47="",$I47=""),"",$I47-TODAY()) | K47: =IF($B47="","",IF($I47="","Vitalício / sem prazo",IF($J47<0,"Vencido",IF($J47<=Listas!$G$4,"Vence em breve","Ativo")))) | N47: =IF($B47="","",IF(N($L47)=0,0,MIN(1,N($M47)/$L47)))

Sheet Renda Extra
A1: CURSOS · FOCO EM RENDA EXTRA
A2: Afiliados, freelas, infoprodutos e negócios digitais · acompanhe aprendizado e retorno financeiro | T2: ← Voltar ao Início
B4: Itens | D4: Em andamento | F4: Concluídos | H4: Investido | J4: Progresso médio | L4: Resultado/mês atual
B5: =COUNTA(B8:B47) -> 1 | D5: =COUNTIF(O8:O47,"Em andamento") -> 1 | F5: =COUNTIF(O8:O47,"Concluído") -> 0 | H5: =SUM(F8:F47) -> 297 | J5: =IFERROR(AVERAGE(N8:N47),0) -> 0.22222222 | L5: =SUM(R8:R47) -> 0
A6: Células cinza = automáticas (não edite) · Linha 8 = exemplo: substitua ou apague · Escolha Status e Prioridade na seta da célula
A7: ID | B7: Curso | C7: Instituição / Plataforma | D7: Modelo de renda | E7: Data da compra | F7: Valor pago (R$) | G7: Data de início | H7: Término previsto | I7: Vencimento do acesso | J7: Dias p/ vencer | K7: Situação do acesso | L7: Aulas (total) | M7: Aulas concluídas | N7: % Andamento | O7: Status | P7: Prioridade | Q7: Meta de ganho/mês (R$) | R7: Resultado atual/mês (R$) | S7: Login | T7: Senha | U7: Link de acesso | V7: Observações
A8: =IF($B8="","","RE-"&TEXT(ROW()-7,"00")) -> RE-01 | B8: Marketing de Afiliados do Zero (exemplo) | C8: Plataforma Exemplo | D8: Afiliados | E8: 46266 | F8: 297 | G8: 46268 | H8: 46356 | I8: 46631 | J8: =IF(OR($B8="",$I8=""),"",$I8-TODAY()) -> 333 | K8: =IF($B8="","",IF($I8="","Vitalício / sem prazo",IF($J8<0,"Vencido",IF($J8<=Listas!$G$4,"Vence em breve","Ativo")))) -> Ativo | L8: 45 | M8: 10 | N8: =IF($B8="","",IF(N($L8)=0,0,MIN(1,N($M8)/$L8))) -> 0.22222222 | O8: Em andamento | P8: Média | Q8: 1500 | R8: 0 | S8: seu.email@exemplo.com | T8: (guarde no gerenciador de senhas) | U8: https://plataforma.exemplo.com | V8: Linha de exemplo — substitua pelos seus dados.
A9: =IF($B9="","","RE-"&TEXT(ROW()-7,"00")) | J9: =IF(OR($B9="",$I9=""),"",$I9-TODAY()) | K9: =IF($B9="","",IF($I9="","Vitalício / sem prazo",IF($J9<0,"Vencido",IF($J9<=Listas!$G$4,"Vence em breve","Ativo")))) | N9: =IF($B9="","",IF(N($L9)=0,0,MIN(1,N($M9)/$L9)))
A10: =IF($B10="","","RE-"&TEXT(ROW()-7,"00")) | J10: =IF(OR($B10="",$I10=""),"",$I10-TODAY()) | K10: =IF($B10="","",IF($I10="","Vitalício / sem prazo",IF($J10<0,"Vencido",IF($J10<=Listas!$G$4,"Vence em breve","Ativo")))) | N10: =IF($B10="","",IF(N($L10)=0,0,MIN(1,N($M10)/$L10)))
A11: =IF($B11="","","RE-"&TEXT(ROW()-7,"00")) | J11: =IF(OR($B11="",$I11=""),"",$I11-TODAY()) | K11: =IF($B11="","",IF($I11="","Vitalício / sem prazo",IF($J11<0,"Vencido",IF($J11<=Listas!$G$4,"Vence em breve","Ativo")))) | N11: =IF($B11="","",IF(N($L11)=0,0,MIN(1,N($M11)/$L11)))
A12: =IF($B12="","","RE-"&TEXT(ROW()-7,"00")) | J12: =IF(OR($B12="",$I12=""),"",$I12-TODAY()) | K12: =IF($B12="","",IF($I12="","Vitalício / sem prazo",IF($J12<0,"Vencido",IF($J12<=Listas!$G$4,"Vence em breve","Ativo")))) | N12: =IF($B12="","",IF(N($L12)=0,0,MIN(1,N($M12)/$L12)))
A13: =IF($B13="","","RE-"&TEXT(ROW()-7,"00")) | J13: =IF(OR($B13="",$I13=""),"",$I13-TODAY()) | K13: =IF($B13="","",IF($I13="","Vitalício / sem prazo",IF($J13<0,"Vencido",IF($J13<=Listas!$G$4,"Vence em breve","Ativo")))) | N13: =IF($B13="","",IF(N($L13)=0,0,MIN(1,N($M13)/$L13)))
A14: =IF($B14="","","RE-"&TEXT(ROW()-7,"00")) | J14: =IF(OR($B14="",$I14=""),"",$I14-TODAY()) | K14: =IF($B14="","",IF($I14="","Vitalício / sem prazo",IF($J14<0,"Vencido",IF($J14<=Listas!$G$4,"Vence em breve","Ativo")))) | N14: =IF($B14="","",IF(N($L14)=0,0,MIN(1,N($M14)/$L14)))
A15: =IF($B15="","","RE-"&TEXT(ROW()-7,"00")) | J15: =IF(OR($B15="",$I15=""),"",$I15-TODAY()) | K15: =IF($B15="","",IF($I15="","Vitalício / sem prazo",IF($J15<0,"Vencido",IF($J15<=Listas!$G$4,"Vence em breve","Ativo")))) | N15: =IF($B15="","",IF(N($L15)=0,0,MIN(1,N($M15)/$L15)))
A16: =IF($B16="","","RE-"&TEXT(ROW()-7,"00")) | J16: =IF(OR($B16="",$I16=""),"",$I16-TODAY()) | K16: =IF($B16="","",IF($I16="","Vitalício / sem prazo",IF($J16<0,"Vencido",IF($J16<=Listas!$G$4,"Vence em breve","Ativo")))) | N16: =IF($B16="","",IF(N($L16)=0,0,MIN(1,N($M16)/$L16)))
A17: =IF($B17="","","RE-"&TEXT(ROW()-7,"00")) | J17: =IF(OR($B17="",$I17=""),"",$I17-TODAY()) | K17: =IF($B17="","",IF($I17="","Vitalício / sem prazo",IF($J17<0,"Vencido",IF($J17<=Listas!$G$4,"Vence em breve","Ativo")))) | N17: =IF($B17="","",IF(N($L17)=0,0,MIN(1,N($M17)/$L17)))
A18: =IF($B18="","","RE-"&TEXT(ROW()-7,"00")) | J18: =IF(OR($B18="",$I18=""),"",$I18-TODAY()) | K18: =IF($B18="","",IF($I18="","Vitalício / sem prazo",IF($J18<0,"Vencido",IF($J18<=Listas!$G$4,"Vence em breve","Ativo")))) | N18: =IF($B18="","",IF(N($L18)=0,0,MIN(1,N($M18)/$L18)))
A19: =IF($B19="","","RE-"&TEXT(ROW()-7,"00")) | J19: =IF(OR($B19="",$I19=""),"",$I19-TODAY()) | K19: =IF($B19="","",IF($I19="","Vitalício / sem prazo",IF($J19<0,"Vencido",IF($J19<=Listas!$G$4,"Vence em breve","Ativo")))) | N19: =IF($B19="","",IF(N($L19)=0,0,MIN(1,N($M19)/$L19)))
A20: =IF($B20="","","RE-"&TEXT(ROW()-7,"00")) | J20: =IF(OR($B20="",$I20=""),"",$I20-TODAY()) | K20: =IF($B20="","",IF($I20="","Vitalício / sem prazo",IF($J20<0,"Vencido",IF($J20<=Listas!$G$4,"Vence em breve","Ativo")))) | N20: =IF($B20="","",IF(N($L20)=0,0,MIN(1,N($M20)/$L20)))
... A47: =IF($B47="","","RE-"&TEXT(ROW()-7,"00")) | J47: =IF(OR($B47="",$I47=""),"",$I47-TODAY()) | K47: =IF($B47="","",IF($I47="","Vitalício / sem prazo",IF($J47<0,"Vencido",IF($J47<=Listas!$G$4,"Vence em breve","Ativo")))) | N47: =IF($B47="","",IF(N($L47)=0,0,MIN(1,N($M47)/$L47)))

Sheet Listas
A1: LISTAS E CONFIGURAÇÕES
A2: Edite as listas das setas (Prioridade, Modalidade, Formato) e o prazo de alerta. Não renomeie os 4 Status. | F2: ← Voltar ao Início
A3: Status | B3: Prioridade | C3: Modalidade | D3: Formato (livros) | G3: Alerta de vencimento (dias)
A4: Não iniciado | B4: Alta | C4: EAD | D4: Físico | G4: 30
A5: Em andamento | B5: Média | C5: Presencial | D5: E-book | G5: Acessos que vencem em até este nº de dias aparecem como “Vence em breve”.
A6: Concluído | B6: Baixa | C6: Híbrido | D6: Audiobook
A7: Pausado | D7: PDF
A9: Premissa: o prazo de alerta de 30 dias é um valor padrão sugerido (editável na célula G4).
