Workbook

Sheet Leia-me
B2: ROADMAP DE CURSOS & APRENDIZADO
B4: Planilha dos seus dados · gerada em 03/10/2026, 23:55:56
B6: Como usar
B7: 1) Edite as linhas das abas de categoria (Pós-graduação, Concurso, Livros, Cursos IA e Renda Extra), do Radar de Aquisições, do Diário de Estudo e do Plano de Estudos. Cada aba já tem linhas em branco formatadas para você acrescentar itens.
B8: 2) Use as listas suspensas (setinha na célula) para Status, Prioridade, Certificado, Formato, Categoria do livro, Gênero, Repetição e Dia da semana. Datas no formato dd/mm/aaaa.
B9: 3) As colunas cinza-claro (Saldo a pagar e % andamento) são calculadas sozinhas: não precisa digitar nada nelas.
B10: 4) Não apague a coluna “ID interno” das linhas que já existem: é ela que permite atualizar em vez de duplicar. Em linhas novas, deixe em branco.
B11: 5) Para atualizar o app: no app, toque em “⬆ Enviar planilha” e escolha este arquivo. Você escolhe entre mesclar (mantém tudo e atualiza) ou substituir.
B12: 6) A aba “Resumo” mostra os totais por categoria. A aba “Listas” alimenta as listas suspensas: não altere. Senhas e chaves não são exportadas.

Sheet Resumo
B2: RESUMO POR CATEGORIA
B4: Categoria | C4: Itens | D4: Valor total (R$) | E4: Já pago (R$) | F4: Saldo a pagar (R$) | G4: Progresso médio
B5: Pós-graduação | C5: =COUNTA('Pós-graduação'!$A$2:$A$42) -> 1 | D5: =SUM('Pós-graduação'!$E$2:$E$42) -> 12600 | E5: =C5-E5 -> 1400 | F5: =SUM('Pós-graduação'!$H$2:$H$42) -> 11200 | G5: =IFERROR(AVERAGE('Pós-graduação'!$N$2:$N$42),"") -> 0.1
B6: Concurso | C6: =COUNTA('Concurso'!$A$2:$A$42) -> 1 | D6: =SUM('Concurso'!$G$2:$G$42) -> 1490 | E6: =C6-E6 -> 149 | F6: =SUM('Concurso'!$J$2:$J$42) -> 1341 | G6: =IFERROR(AVERAGE('Concurso'!$P$2:$P$42),"") -> 0.25
B7: Livros | C7: =COUNTA('Livros'!$A$2:$A$42) -> 1 | D7: =SUM('Livros'!$K$2:$K$42) -> 49.9 | E7: =C7-E7 -> 49.9 | F7: =SUM('Livros'!$N$2:$N$42) -> 0 | G7: =IFERROR(AVERAGE('Livros'!$S$2:$S$42),"") -> 0.375
B8: Cursos IA | C8: =COUNTA('Cursos IA'!$A$2:$A$42) -> 1 | D8: =SUM('Cursos IA'!$E$2:$E$42) -> 497 | E8: =C8-E8 -> 41.42 | F8: =SUM('Cursos IA'!$H$2:$H$42) -> 455.58 | G8: =IFERROR(AVERAGE('Cursos IA'!$N$2:$N$42),"") -> 0.3
B9: Renda Extra | C9: =COUNTA('Renda Extra'!$A$2:$A$42) -> 1 | D9: =SUM('Renda Extra'!$H$2:$H$42) -> 297 | E9: =C9-E9 -> 99 | F9: =SUM('Renda Extra'!$K$2:$K$42) -> 198 | G9: =IFERROR(AVERAGE('Renda Extra'!$Q$2:$Q$42),"") -> 0.22222222
B10: TOTAL | C10: =SUM(C5:C9) -> 5 | D10: =SUM(D5:D9) -> 14933.9 | E10: =SUM(E5:E9) -> 1739.32 | F10: =SUM(F5:F9) -> 13194.58
B12: Os números desta aba se atualizam sozinhos quando você edita as outras abas.

Sheet Pós-graduação
A1: Curso / Pós-graduação | B1: Instituição | C1: Modalidade | D1: Data da compra | E1: Valor total (R$) | F1: Quantidade de parcelas | G1: Parcelas pagas | H1: Saldo a pagar (R$) | I1: Data de início | J1: Término previsto | K1: Vencimento do acesso | L1: Disciplinas (total) | M1: Disciplinas concluídas | N1: % andamento | O1: Status | P1: Prioridade | Q1: Certificado | R1: Login | S1: Link de acesso | T1: Observações | U1: ID interno
A2: MBA em Inteligência Artificial (exemplo) | B2: Universidade Exemplo | C2: EAD | D2: 46244 | E2: 12600 | F2: 18 | G2: 2 | H2: =IF(N(E2)>0,ROUND(E2-IF(N(F2)>0,ROUND(E2*MIN(N(G2),N(F2))/N(F2),2),E2),2),"") -> 11200 | I2: 46266 | J2: 46818 | K2: 46998 | L2: 20 | M2: 2 | N2: =IF(N(L2)>0,MIN(1,N(M2)/N(L2)),"") -> 0.1 | O2: Em andamento | P2: Alta | Q2: Não emitido | R2: seu.email@exemplo.com | S2: https://portal.exemplo.com | U2: yzz4hc2
H3: =IF(N(E3)>0,ROUND(E3-IF(N(F3)>0,ROUND(E3*MIN(N(G3),N(F3))/N(F3),2),E3),2),"") | N3: =IF(N(L3)>0,MIN(1,N(M3)/N(L3)),"")
H4: =IF(N(E4)>0,ROUND(E4-IF(N(F4)>0,ROUND(E4*MIN(N(G4),N(F4))/N(F4),2),E4),2),"") | N4: =IF(N(L4)>0,MIN(1,N(M4)/N(L4)),"")
H5: =IF(N(E5)>0,ROUND(E5-IF(N(F5)>0,ROUND(E5*MIN(N(G5),N(F5))/N(F5),2),E5),2),"") | N5: =IF(N(L5)>0,MIN(1,N(M5)/N(L5)),"")
H6: =IF(N(E6)>0,ROUND(E6-IF(N(F6)>0,ROUND(E6*MIN(N(G6),N(F6))/N(F6),2),E6),2),"") | N6: =IF(N(L6)>0,MIN(1,N(M6)/N(L6)),"")
H7: =IF(N(E7)>0,ROUND(E7-IF(N(F7)>0,ROUND(E7*MIN(N(G7),N(F7))/N(F7),2),E7),2),"") | N7: =IF(N(L7)>0,MIN(1,N(M7)/N(L7)),"")
H8: =IF(N(E8)>0,ROUND(E8-IF(N(F8)>0,ROUND(E8*MIN(N(G8),N(F8))/N(F8),2),E8),2),"") | N8: =IF(N(L8)>0,MIN(1,N(M8)/N(L8)),"")
H9: =IF(N(E9)>0,ROUND(E9-IF(N(F9)>0,ROUND(E9*MIN(N(G9),N(F9))/N(F9),2),E9),2),"") | N9: =IF(N(L9)>0,MIN(1,N(M9)/N(L9)),"")
H10: =IF(N(E10)>0,ROUND(E10-IF(N(F10)>0,ROUND(E10*MIN(N(G10),N(F10))/N(F10),2),E10),2),"") | N10: =IF(N(L10)>0,MIN(1,N(M10)/N(L10)),"")
H11: =IF(N(E11)>0,ROUND(E11-IF(N(F11)>0,ROUND(E11*MIN(N(G11),N(F11))/N(F11),2),E11),2),"") | N11: =IF(N(L11)>0,MIN(1,N(M11)/N(L11)),"")
H12: =IF(N(E12)>0,ROUND(E12-IF(N(F12)>0,ROUND(E12*MIN(N(G12),N(F12))/N(F12),2),E12),2),"") | N12: =IF(N(L12)>0,MIN(1,N(M12)/N(L12)),"")
H13: =IF(N(E13)>0,ROUND(E13-IF(N(F13)>0,ROUND(E13*MIN(N(G13),N(F13))/N(F13),2),E13),2),"") | N13: =IF(N(L13)>0,MIN(1,N(M13)/N(L13)),"")
H14: =IF(N(E14)>0,ROUND(E14-IF(N(F14)>0,ROUND(E14*MIN(N(G14),N(F14))/N(F14),2),E14),2),"") | N14: =IF(N(L14)>0,MIN(1,N(M14)/N(L14)),"")
... H42: =IF(N(E42)>0,ROUND(E42-IF(N(F42)>0,ROUND(E42*MIN(N(G42),N(F42))/N(F42),2),E42),2),"") | N42: =IF(N(L42)>0,MIN(1,N(M42)/N(L42)),"")

Sheet Concurso
A1: Curso / Material | B1: Plataforma / Instituição | C1: Concurso / Cargo alvo | D1: Banca | E1: Data da prova | F1: Data da compra | G1: Valor total (R$) | H1: Quantidade de parcelas | I1: Parcelas pagas | J1: Saldo a pagar (R$) | K1: Data de início | L1: Término previsto | M1: Vencimento do acesso | N1: Aulas / tópicos (total) | O1: Aulas / Tópicos concluídos | P1: % andamento | Q1: Status | R1: Prioridade | S1: Certificado | T1: Login | U1: Link de acesso | V1: Observações | W1: ID interno
A2: Curso Preparatório Completo (exemplo) | B2: Plataforma Exemplo | C2: Analista — Órgão Exemplo | D2: CEBRASPE | E2: 46458 | F2: 46270 | G2: 1490 | H2: 10 | I2: 1 | J2: =IF(N(G2)>0,ROUND(G2-IF(N(H2)>0,ROUND(G2*MIN(N(I2),N(H2))/N(H2),2),G2),2),"") -> 1341 | K2: 46280 | L2: 46448 | M2: 46568 | N2: 180 | O2: 45 | P2: =IF(N(N2)>0,MIN(1,N(O2)/N(N2)),"") -> 0.25 | Q2: Em andamento | R2: Alta | S2: Não se aplica | T2: seu.email@exemplo.com | W2: kooutn6
J3: =IF(N(G3)>0,ROUND(G3-IF(N(H3)>0,ROUND(G3*MIN(N(I3),N(H3))/N(H3),2),G3),2),"") | P3: =IF(N(N3)>0,MIN(1,N(O3)/N(N3)),"")
J4: =IF(N(G4)>0,ROUND(G4-IF(N(H4)>0,ROUND(G4*MIN(N(I4),N(H4))/N(H4),2),G4),2),"") | P4: =IF(N(N4)>0,MIN(1,N(O4)/N(N4)),"")
J5: =IF(N(G5)>0,ROUND(G5-IF(N(H5)>0,ROUND(G5*MIN(N(I5),N(H5))/N(H5),2),G5),2),"") | P5: =IF(N(N5)>0,MIN(1,N(O5)/N(N5)),"")
J6: =IF(N(G6)>0,ROUND(G6-IF(N(H6)>0,ROUND(G6*MIN(N(I6),N(H6))/N(H6),2),G6),2),"") | P6: =IF(N(N6)>0,MIN(1,N(O6)/N(N6)),"")
J7: =IF(N(G7)>0,ROUND(G7-IF(N(H7)>0,ROUND(G7*MIN(N(I7),N(H7))/N(H7),2),G7),2),"") | P7: =IF(N(N7)>0,MIN(1,N(O7)/N(N7)),"")
J8: =IF(N(G8)>0,ROUND(G8-IF(N(H8)>0,ROUND(G8*MIN(N(I8),N(H8))/N(H8),2),G8),2),"") | P8: =IF(N(N8)>0,MIN(1,N(O8)/N(N8)),"")
J9: =IF(N(G9)>0,ROUND(G9-IF(N(H9)>0,ROUND(G9*MIN(N(I9),N(H9))/N(H9),2),G9),2),"") | P9: =IF(N(N9)>0,MIN(1,N(O9)/N(N9)),"")
J10: =IF(N(G10)>0,ROUND(G10-IF(N(H10)>0,ROUND(G10*MIN(N(I10),N(H10))/N(H10),2),G10),2),"") | P10: =IF(N(N10)>0,MIN(1,N(O10)/N(N10)),"")
J11: =IF(N(G11)>0,ROUND(G11-IF(N(H11)>0,ROUND(G11*MIN(N(I11),N(H11))/N(H11),2),G11),2),"") | P11: =IF(N(N11)>0,MIN(1,N(O11)/N(N11)),"")
J12: =IF(N(G12)>0,ROUND(G12-IF(N(H12)>0,ROUND(G12*MIN(N(I12),N(H12))/N(H12),2),G12),2),"") | P12: =IF(N(N12)>0,MIN(1,N(O12)/N(N12)),"")
J13: =IF(N(G13)>0,ROUND(G13-IF(N(H13)>0,ROUND(G13*MIN(N(I13),N(H13))/N(H13),2),G13),2),"") | P13: =IF(N(N13)>0,MIN(1,N(O13)/N(N13)),"")
J14: =IF(N(G14)>0,ROUND(G14-IF(N(H14)>0,ROUND(G14*MIN(N(I14),N(H14))/N(H14),2),G14),2),"") | P14: =IF(N(N14)>0,MIN(1,N(O14)/N(N14)),"")
... J42: =IF(N(G42)>0,ROUND(G42-IF(N(H42)>0,ROUND(G42*MIN(N(I42),N(H42))/N(H42),2),G42),2),"") | P42: =IF(N(N42)>0,MIN(1,N(O42)/N(N42)),"")

Sheet Livros
A1: Título | B1: Autor(a) | C1: Edição (nº ou ano) | D1: Editora | E1: Categoria do livro | F1: Gênero | G1: Tema / assunto | H1: Formato | I1: Nota (1–5) | J1: Data da compra | K1: Valor total (R$) | L1: Quantidade de parcelas | M1: Parcelas pagas | N1: Saldo a pagar (R$) | O1: Data de início | P1: Término previsto | Q1: Páginas (total) | R1: Páginas lidas | S1: % andamento | T1: Status | U1: Prioridade | V1: Link de acesso | W1: Observações | X1: ID interno
A2: Hábitos Atômicos (exemplo) | B2: James Clear | C2: 1 | D2: Editora Exemplo | E2: Não ficção | F2: Desenvolvimento pessoal | G2: Produtividade | H2: Físico | J2: 46285 | K2: 49.9 | N2: =IF(N(K2)>0,ROUND(K2-IF(N(L2)>0,ROUND(K2*MIN(N(M2),N(L2))/N(L2),2),K2),2),"") -> 0 | O2: 46290 | P2: 46341 | Q2: 320 | R2: 120 | S2: =IF(N(Q2)>0,MIN(1,N(R2)/N(Q2)),"") -> 0.375 | T2: Em andamento | U2: Média | X2: 9u2ne8g
N3: =IF(N(K3)>0,ROUND(K3-IF(N(L3)>0,ROUND(K3*MIN(N(M3),N(L3))/N(L3),2),K3),2),"") | S3: =IF(N(Q3)>0,MIN(1,N(R3)/N(Q3)),"")
N4: =IF(N(K4)>0,ROUND(K4-IF(N(L4)>0,ROUND(K4*MIN(N(M4),N(L4))/N(L4),2),K4),2),"") | S4: =IF(N(Q4)>0,MIN(1,N(R4)/N(Q4)),"")
N5: =IF(N(K5)>0,ROUND(K5-IF(N(L5)>0,ROUND(K5*MIN(N(M5),N(L5))/N(L5),2),K5),2),"") | S5: =IF(N(Q5)>0,MIN(1,N(R5)/N(Q5)),"")
N6: =IF(N(K6)>0,ROUND(K6-IF(N(L6)>0,ROUND(K6*MIN(N(M6),N(L6))/N(L6),2),K6),2),"") | S6: =IF(N(Q6)>0,MIN(1,N(R6)/N(Q6)),"")
N7: =IF(N(K7)>0,ROUND(K7-IF(N(L7)>0,ROUND(K7*MIN(N(M7),N(L7))/N(L7),2),K7),2),"") | S7: =IF(N(Q7)>0,MIN(1,N(R7)/N(Q7)),"")
N8: =IF(N(K8)>0,ROUND(K8-IF(N(L8)>0,ROUND(K8*MIN(N(M8),N(L8))/N(L8),2),K8),2),"") | S8: =IF(N(Q8)>0,MIN(1,N(R8)/N(Q8)),"")
N9: =IF(N(K9)>0,ROUND(K9-IF(N(L9)>0,ROUND(K9*MIN(N(M9),N(L9))/N(L9),2),K9),2),"") | S9: =IF(N(Q9)>0,MIN(1,N(R9)/N(Q9)),"")
N10: =IF(N(K10)>0,ROUND(K10-IF(N(L10)>0,ROUND(K10*MIN(N(M10),N(L10))/N(L10),2),K10),2),"") | S10: =IF(N(Q10)>0,MIN(1,N(R10)/N(Q10)),"")
N11: =IF(N(K11)>0,ROUND(K11-IF(N(L11)>0,ROUND(K11*MIN(N(M11),N(L11))/N(L11),2),K11),2),"") | S11: =IF(N(Q11)>0,MIN(1,N(R11)/N(Q11)),"")
N12: =IF(N(K12)>0,ROUND(K12-IF(N(L12)>0,ROUND(K12*MIN(N(M12),N(L12))/N(L12),2),K12),2),"") | S12: =IF(N(Q12)>0,MIN(1,N(R12)/N(Q12)),"")
N13: =IF(N(K13)>0,ROUND(K13-IF(N(L13)>0,ROUND(K13*MIN(N(M13),N(L13))/N(L13),2),K13),2),"") | S13: =IF(N(Q13)>0,MIN(1,N(R13)/N(Q13)),"")
N14: =IF(N(K14)>0,ROUND(K14-IF(N(L14)>0,ROUND(K14*MIN(N(M14),N(L14))/N(L14),2),K14),2),"") | S14: =IF(N(Q14)>0,MIN(1,N(R14)/N(Q14)),"")
... N42: =IF(N(K42)>0,ROUND(K42-IF(N(L42)>0,ROUND(K42*MIN(N(M42),N(L42))/N(L42),2),K42),2),"") | S42: =IF(N(Q42)>0,MIN(1,N(R42)/N(Q42)),"")

Sheet Cursos IA
A1: Curso | B1: Instituição / Plataforma | C1: Foco / Ferramenta | D1: Data da compra | E1: Valor total (R$) | F1: Quantidade de parcelas | G1: Parcelas pagas | H1: Saldo a pagar (R$) | I1: Data de início | J1: Término previsto | K1: Vencimento do acesso | L1: Aulas (total) | M1: Aulas concluídas | N1: % andamento | O1: Status | P1: Prioridade | Q1: Certificado | R1: Login | S1: Link de acesso | T1: Observações | U1: ID interno
A2: Agentes de IA na Prática (exemplo) | B2: Plataforma Exemplo | C2: Agentes · automação | D2: 46277 | E2: 497 | F2: 12 | G2: 1 | H2: =IF(N(E2)>0,ROUND(E2-IF(N(F2)>0,ROUND(E2*MIN(N(G2),N(F2))/N(F2),2),E2),2),"") -> 455.58 | I2: 46285 | J2: 46376 | K2: 46642 | L2: 60 | M2: 18 | N2: =IF(N(L2)>0,MIN(1,N(M2)/N(L2)),"") -> 0.3 | O2: Em andamento | P2: Alta | Q2: Não emitido | R2: seu.email@exemplo.com | U2: fopz0ig
H3: =IF(N(E3)>0,ROUND(E3-IF(N(F3)>0,ROUND(E3*MIN(N(G3),N(F3))/N(F3),2),E3),2),"") | N3: =IF(N(L3)>0,MIN(1,N(M3)/N(L3)),"")
H4: =IF(N(E4)>0,ROUND(E4-IF(N(F4)>0,ROUND(E4*MIN(N(G4),N(F4))/N(F4),2),E4),2),"") | N4: =IF(N(L4)>0,MIN(1,N(M4)/N(L4)),"")
H5: =IF(N(E5)>0,ROUND(E5-IF(N(F5)>0,ROUND(E5*MIN(N(G5),N(F5))/N(F5),2),E5),2),"") | N5: =IF(N(L5)>0,MIN(1,N(M5)/N(L5)),"")
H6: =IF(N(E6)>0,ROUND(E6-IF(N(F6)>0,ROUND(E6*MIN(N(G6),N(F6))/N(F6),2),E6),2),"") | N6: =IF(N(L6)>0,MIN(1,N(M6)/N(L6)),"")
H7: =IF(N(E7)>0,ROUND(E7-IF(N(F7)>0,ROUND(E7*MIN(N(G7),N(F7))/N(F7),2),E7),2),"") | N7: =IF(N(L7)>0,MIN(1,N(M7)/N(L7)),"")
H8: =IF(N(E8)>0,ROUND(E8-IF(N(F8)>0,ROUND(E8*MIN(N(G8),N(F8))/N(F8),2),E8),2),"") | N8: =IF(N(L8)>0,MIN(1,N(M8)/N(L8)),"")
H9: =IF(N(E9)>0,ROUND(E9-IF(N(F9)>0,ROUND(E9*MIN(N(G9),N(F9))/N(F9),2),E9),2),"") | N9: =IF(N(L9)>0,MIN(1,N(M9)/N(L9)),"")
H10: =IF(N(E10)>0,ROUND(E10-IF(N(F10)>0,ROUND(E10*MIN(N(G10),N(F10))/N(F10),2),E10),2),"") | N10: =IF(N(L10)>0,MIN(1,N(M10)/N(L10)),"")
H11: =IF(N(E11)>0,ROUND(E11-IF(N(F11)>0,ROUND(E11*MIN(N(G11),N(F11))/N(F11),2),E11),2),"") | N11: =IF(N(L11)>0,MIN(1,N(M11)/N(L11)),"")
H12: =IF(N(E12)>0,ROUND(E12-IF(N(F12)>0,ROUND(E12*MIN(N(G12),N(F12))/N(F12),2),E12),2),"") | N12: =IF(N(L12)>0,MIN(1,N(M12)/N(L12)),"")
H13: =IF(N(E13)>0,ROUND(E13-IF(N(F13)>0,ROUND(E13*MIN(N(G13),N(F13))/N(F13),2),E13),2),"") | N13: =IF(N(L13)>0,MIN(1,N(M13)/N(L13)),"")
H14: =IF(N(E14)>0,ROUND(E14-IF(N(F14)>0,ROUND(E14*MIN(N(G14),N(F14))/N(F14),2),E14),2),"") | N14: =IF(N(L14)>0,MIN(1,N(M14)/N(L14)),"")
... H42: =IF(N(E42)>0,ROUND(E42-IF(N(F42)>0,ROUND(E42*MIN(N(G42),N(F42))/N(F42),2),E42),2),"") | N42: =IF(N(L42)>0,MIN(1,N(M42)/N(L42)),"")

Sheet Renda Extra
A1: Curso | B1: Instituição / Plataforma | C1: Modelo de renda | D1: Meta de ganho/mês (R$) | E1: Resultado atual/mês (R$) | F1: Receita acumulada (R$) | G1: Data da compra | H1: Valor total (R$) | I1: Quantidade de parcelas | J1: Parcelas pagas | K1: Saldo a pagar (R$) | L1: Data de início | M1: Término previsto | N1: Vencimento do acesso | O1: Aulas (total) | P1: Aulas concluídas | Q1: % andamento | R1: Status | S1: Prioridade | T1: Certificado | U1: Login | V1: Link de acesso | W1: Observações | X1: ID interno
A2: Marketing de Afiliados do Zero (exemplo) | B2: Plataforma Exemplo | C2: Afiliados | D2: 1500 | E2: 120 | F2: 180 | G2: 46266 | H2: 297 | I2: 3 | J2: 1 | K2: =IF(N(H2)>0,ROUND(H2-IF(N(I2)>0,ROUND(H2*MIN(N(J2),N(I2))/N(I2),2),H2),2),"") -> 198 | L2: 46268 | M2: 46356 | N2: 46631 | O2: 45 | P2: 10 | Q2: =IF(N(O2)>0,MIN(1,N(P2)/N(O2)),"") -> 0.22222222 | R2: Em andamento | S2: Média | T2: Não emitido | U2: seu.email@exemplo.com | X2: f334ans
K3: =IF(N(H3)>0,ROUND(H3-IF(N(I3)>0,ROUND(H3*MIN(N(J3),N(I3))/N(I3),2),H3),2),"") | Q3: =IF(N(O3)>0,MIN(1,N(P3)/N(O3)),"")
K4: =IF(N(H4)>0,ROUND(H4-IF(N(I4)>0,ROUND(H4*MIN(N(J4),N(I4))/N(I4),2),H4),2),"") | Q4: =IF(N(O4)>0,MIN(1,N(P4)/N(O4)),"")
K5: =IF(N(H5)>0,ROUND(H5-IF(N(I5)>0,ROUND(H5*MIN(N(J5),N(I5))/N(I5),2),H5),2),"") | Q5: =IF(N(O5)>0,MIN(1,N(P5)/N(O5)),"")
K6: =IF(N(H6)>0,ROUND(H6-IF(N(I6)>0,ROUND(H6*MIN(N(J6),N(I6))/N(I6),2),H6),2),"") | Q6: =IF(N(O6)>0,MIN(1,N(P6)/N(O6)),"")
K7: =IF(N(H7)>0,ROUND(H7-IF(N(I7)>0,ROUND(H7*MIN(N(J7),N(I7))/N(I7),2),H7),2),"") | Q7: =IF(N(O7)>0,MIN(1,N(P7)/N(O7)),"")
K8: =IF(N(H8)>0,ROUND(H8-IF(N(I8)>0,ROUND(H8*MIN(N(J8),N(I8))/N(I8),2),H8),2),"") | Q8: =IF(N(O8)>0,MIN(1,N(P8)/N(O8)),"")
K9: =IF(N(H9)>0,ROUND(H9-IF(N(I9)>0,ROUND(H9*MIN(N(J9),N(I9))/N(I9),2),H9),2),"") | Q9: =IF(N(O9)>0,MIN(1,N(P9)/N(O9)),"")
K10: =IF(N(H10)>0,ROUND(H10-IF(N(I10)>0,ROUND(H10*MIN(N(J10),N(I10))/N(I10),2),H10),2),"") | Q10: =IF(N(O10)>0,MIN(1,N(P10)/N(O10)),"")
K11: =IF(N(H11)>0,ROUND(H11-IF(N(I11)>0,ROUND(H11*MIN(N(J11),N(I11))/N(I11),2),H11),2),"") | Q11: =IF(N(O11)>0,MIN(1,N(P11)/N(O11)),"")
K12: =IF(N(H12)>0,ROUND(H12-IF(N(I12)>0,ROUND(H12*MIN(N(J12),N(I12))/N(I12),2),H12),2),"") | Q12: =IF(N(O12)>0,MIN(1,N(P12)/N(O12)),"")
K13: =IF(N(H13)>0,ROUND(H13-IF(N(I13)>0,ROUND(H13*MIN(N(J13),N(I13))/N(I13),2),H13),2),"") | Q13: =IF(N(O13)>0,MIN(1,N(P13)/N(O13)),"")
K14: =IF(N(H14)>0,ROUND(H14-IF(N(I14)>0,ROUND(H14*MIN(N(J14),N(I14))/N(I14),2),H14),2),"") | Q14: =IF(N(O14)>0,MIN(1,N(P14)/N(O14)),"")
... K42: =IF(N(H42)>0,ROUND(H42-IF(N(I42)>0,ROUND(H42*MIN(N(J42),N(I42))/N(I42),2),H42),2),"") | Q42: =IF(N(O42)>0,MIN(1,N(P42)/N(O42)),"")

Sheet Radar de Aquisições
A1: Categoria | B1: Item | C1: Instituição / Editora / Loja | D1: Autor(a) | E1: Edição | F1: Categoria do livro | G1: Gênero | H1: Valor estimado (R$) | I1: Previsão de compra | J1: Prioridade | K1: Link | L1: Por que está no radar? | M1: ID interno
A2: Cursos IA | B2: Automação com n8n (exemplo) | C2: Plataforma Exemplo | H2: 397 | I2: 46358 | J2: Alta | L2: Complementa o curso de agentes | M2: bhp3dmg
A3: Livros | B3: Essencialismo (exemplo) | C3: Editora Exemplo | D3: Greg McKeown | E3: 1 | F3: Não ficção | G3: Desenvolvimento pessoal | H3: 54.9 | I3: 46328 | J3: Média | L3: Para foco e prioridades | M3: 2cz3bvb
A4: Pós-graduação | B4: Especialização em Data Analytics (exemplo) | C4: Universidade Exemplo | H4: 9800 | I4: 46538 | J4: Baixa | L4: Avaliar depois de concluir o MBA | M4: 3su0vur

Sheet Diário de Estudo
A1: Data | B1: Categoria | C1: Curso / Livro | D1: Horas | E1: Tema estudado | F1: Foco (1–5) | G1: ID interno
A2: 46296 | B2: Pós-graduação | C2: MBA em Inteligência Artificial (exemplo) | D2: 2 | E2: Introdução a machine learning | F2: 4 | G2: 7rnhezl
A3: 46297 | B3: Cursos IA | C3: Agentes de IA na Prática (exemplo) | D3: 1.5 | E3: Fluxos de automação | F3: 5 | G3: tmfhjjm
A4: 46298 | B4: Livros | C4: Hábitos Atômicos (exemplo) | D4: 1 | E4: Capítulos 5 a 7 | F4: 4 | G4: h4skb1d

Sheet Plano de Estudos
A1: Dia da semana | B1: Horário | C1: Duração (min) | D1: Curso / Livro | E1: Tarefa | F1: Meta (unidades) | G1: Repetição | H1: A partir de | I1: Até | J1: ID interno
A2: Seg | B2: 19:00 | C2: 60 | D2: MBA em Inteligência Artificial (exemplo) | E2: Assistir a aula da disciplina atual | G2: Semanal | H2: 46298 | J2: fzcdwfb
A3: Ter | B3: 19:00 | C3: 60 | D3: Agentes de IA na Prática (exemplo) | E3: Meta: ~2 aulas | G3: Semanal | H3: 46298 | J3: d6x9sqn
A4: Qua | B4: 19:00 | C4: 60 | D4: Curso Preparatório Completo (exemplo) | E4: Meta: ~2 aulas | G4: Semanal | H4: 46298 | J4: u64nf6q
A5: Qui | B5: 19:00 | C5: 60 | D5: MBA em Inteligência Artificial (exemplo) | E5: Leitura e exercícios | G5: Semanal | H5: 46298 | J5: qk4unhz
A6: Sex | B6: 19:00 | C6: 45 | D6: Marketing de Afiliados do Zero (exemplo) | E6: Meta: ~1 aula | G6: Semanal | H6: 46298 | J6: 8zmu4rq
A7: Sáb | B7: 09:00 | C7: 90 | D7: Curso Preparatório Completo (exemplo) | E7: Questões da banca | G7: Semanal | H7: 46298 | J7: m0eep5i
A8: Dom | B8: 17:00 | C8: 45 | D8: Hábitos Atômicos (exemplo) | E8: Ler ~20 páginas | G8: Semanal | H8: 46298 | J8: 30bsaci

Sheet Metas
A1: Categoria | B1: Meta mensal (h)
A2: Pós-graduação | B2: 20
A3: Concurso | B3: 20
A4: Livros | B4: 8
A5: Cursos IA | B5: 15
A6: Renda Extra | B6: 10

Sheet Configurações
A1: Configuração | B1: Valor
A2: Prazo de alerta de vencimento (dias) | B2: 30
A3: Cidade (previsão do tempo) | B3: Porto Alegre, RS

Sheet Listas
A1: Status | B1: Prioridade | C1: Certificado | D1: Formato | E1: Categoria do livro | F1: Gênero | G1: Repetição | H1: Dia da semana | I1: Categoria
A2: Não iniciado | B2: Alta | C2: Não emitido | D2: Físico | E2: Ficção | F2: Romance | G2: Semanal | H2: Seg | I2: Pós-graduação
A3: Em andamento | B3: Média | C3: Em emissão | D3: E-book | E3: Não ficção | F3: Fantasia | G3: Diário | H3: Ter | I3: Concurso
A4: Concluído | B4: Baixa | C4: Emitido | D4: Audiobook | E4: Literatura infantil e juvenil | F4: Ficção científica | G4: Quinzenal | H4: Qua | I4: Livros
A5: Pausado | C5: Não se aplica | D5: PDF | E5: Outros formatos/gêneros | F5: Terror | G5: Mensal | H5: Qui | I5: Cursos IA
F6: Suspense/Thriller | G6: Única | H6: Sex | I6: Renda Extra
F7: Mistério | H7: Sáb
F8: Aventura | H8: Dom
F9: Policial
F10: Ficção histórica
F11: Distopia
F12: Romance romântico
F13: Humor
F14: Biografia/Autobiografia
F15: História
F16: Filosofia
F17: Psicologia
F18: Ciência
F19: Política
F20: Negócios
... F35: Livros didáticos
